Workbook

Sheet Inputs
A1: SPUR Co-location Model — Preliminary Illustrative Run (2 configurations)
A2: Blue = hardcoded inputs. Green = pulled from Configurations tab. Yellow = scenario levers. $ in millions.
A4: SCENARIO LEVERS
A5: Configuration (1=Solar+BESS 100MW, 2=Wind+BESS 150MW) | B5: 1 | C5: Switches all green config parameters below
A6: Queue wait (mech. completion -> COD), years | B6: 4 | C6: Test 2/4/6/8 (LBNL Queued Up 2025: https://emp.lbl.gov/queues)
A7: ITC rate | B7: 0.3 | C7: 0% = OBBBA Scenario D (zero credit under EITHER credit type); 30% = full rate w/ PWA
A8: Credit type (1=ITC, 2=PTC) | B8: 1 | C8: Framework 2.3.5: run both per configuration; PTC path uses full depreciable basis (no ITC basis reduction)
A9: PTC rate ($/MWh, full rate w/ PWA) | B9: 15 | C9: $0.015/kWh, 10-yr duration (Framework 2.3.4; inflation adjustment omitted)
A10: CONFIGURATION PARAMETERS (from Configurations tab)
A11: Capacity (MW) | B11: =INDEX(Configurations!$B$4:$C$4,1,$B$5) -> 100
A12: Capacity factor | B12: =INDEX(Configurations!$B$5:$C$5,1,$B$5) -> 0.275
A13: Annual degradation | B13: =INDEX(Configurations!$B$6:$C$6,1,$B$5) -> 0.005
A14: Availability | B14: =INDEX(Configurations!$B$7:$C$7,1,$B$5) -> 0.98
A15: Electrical losses | B15: =INDEX(Configurations!$B$8:$C$8,1,$B$5) -> 0.025
A16: Total CAPEX ($mm) | B16: =INDEX(Configurations!$B$9:$C$9,1,$B$5) -> 197
A17: Qualified investment ($mm) | B17: =INDEX(Configurations!$B$10:$C$10,1,$B$5) -> 180
A18: Microgrid CAPEX ($mm) | B18: =INDEX(Configurations!$B$11:$C$11,1,$B$5) -> 12
A19: Fixed O&M, gen + BESS ($mm/yr) | B19: =INDEX(Configurations!$B$12:$C$12,1,$B$5) -> 3
A20: Land lease + insurance ($mm/yr) | B20: =INDEX(Configurations!$B$13:$C$13,1,$B$5) -> 1.088
A21: Microgrid O&M ($mm/yr) | B21: =INDEX(Configurations!$B$14:$C$14,1,$B$5) -> 0.75
A22: SHARED PARAMETERS
A23: BESS delivery loss (RTE approx.) | B23: 0.01 | C23: Annual approximation of round-trip losses
A24: Debt interest rate | B24: 0.055 | C24: Framework 2.3.1: 5-7% range
A25: Debt tenor (years) | B25: 20 | C25: Framework 2.3.1
A26: Target DSCR (debt sizing) | B26: 1.35 | C26: Framework 2.7
A27: Max leverage (% of total capital) | B27: 0.55 | C27: Framework 2.3.1: senior debt 50-55% of CAPEX; binds when DSCR-sized debt exceeds it (wind)
A28: Combined tax rate (fed + CA) | B28: 0.2984 | C28: 21% federal + 8.84% CA
A29: Tax equity pay rate (per $ benefit PV) | B29: 0.8 | C29: TE pays ~80c per $1 PV of ITC + MACRS shield
A30: MACRS PV discount rate | B30: 0.07 | C30: Assumption
A31: Grid hybrid PPA price ($/MWh) | B31: 72 | C31: LBNL Utility-Scale Solar (hybrid PPA levels): https://emp.lbl.gov/utility-scale-solar
A32: BTM PPA price ($/MWh) | B32: 60 | C32: ~17% discount, within 10-20% industry range (Framework 4.3)
A33: Asset management (% of revenue) | B33: 0.015 | C33: Framework 2.6
A34: Construction years | B34: 2 | C34: Framework 2.1
... A39: Developer cash share, post-flip | B39: 0.975 | C39: Framework 2.8.2

Sheet Capitalization
A1: Capitalization — debt = MIN(DSCR-sized, max leverage x capital); tax equity sized to ITC + MACRS shield
B3: Baseline | C3: Co-location
A4: Total capital required ($mm) | B4: =Inputs!$B$16 -> 197 | C4: =Inputs!$B$16+Inputs!$B$18 -> 209
A5: First grid-year net energy (MWh) | B5: =Inputs!$B$11*Inputs!$B$12*8760*Inputs!$B$14*(1-Inputs!$B$15) -> 230179.95 | C5: =Inputs!$B$11*Inputs!$B$12*8760*Inputs!$B$14*(1-Inputs!$B$15) -> 230179.95
A6: First grid-year revenue ($mm) | B6: =B5*Inputs!$B$31/1000000 -> 16.572956 | C6: =C5*Inputs!$B$31/1000000 -> 16.572956
A7: First grid-year OPEX ($mm) | B7: =Inputs!$B$19+Inputs!$B$20+Inputs!$B$33*B6 -> 4.3365943 | C7: =Inputs!$B$19+Inputs!$B$20+Inputs!$B$21+Inputs!$B$33*C6 -> 5.0865943
A8: First grid-year EBITDA ($mm) | B8: =B6-B7 -> 12.236362 | C8: =C6-C7 -> 11.486362
A9: Max debt service @ DSCR ($mm/yr) | B9: =B8/Inputs!$B$26 -> 9.0639719 | C9: =C8/Inputs!$B$26 -> 8.5084163
A10: DSCR-sized debt ($mm) | B10: =B9*(1-(1+Inputs!$B$24)^-Inputs!$B$25)/Inputs!$B$24 -> 108.31793 | C10: =C9*(1-(1+Inputs!$B$24)^-Inputs!$B$25)/Inputs!$B$24 -> 101.67883
A11: Senior debt after leverage cap ($mm) | B11: =MIN(B10,Inputs!$B$27*B4) -> 108.31793 | C11: =MIN(C10,Inputs!$B$27*C4) -> 101.67883
A12: Actual debt service ($mm/yr) | B12: =B11/((1-(1+Inputs!$B$24)^-Inputs!$B$25)/Inputs!$B$24) -> 9.0639719 | C12: =C11/((1-(1+Inputs!$B$24)^-Inputs!$B$25)/Inputs!$B$24) -> 8.5084163
A13: ITC amount ($mm) | B13: =IF(Inputs!$B$8=1,Inputs!$B$17*Inputs!$B$7,0) -> 54 | C13: =IF(Inputs!$B$8=1,Inputs!$B$17*Inputs!$B$7,0) -> 54
A14: PTC start year (calendar) | B14: =Inputs!$B$34+Inputs!$B$6+1 -> 7 | C14: =Inputs!$B$34+1 -> 3
A15: PTC stream PV ($mm) | B15: =IF(Inputs!$B$8=2,B5*Inputs!$B$9/1000000*(1-(1+Inputs!$B$30)^-10)/Inputs!$B$30/(1+Inputs!$B$30)^(B14-1),0) -> 0 | C15: =IF(Inputs!$B$8=2,C5*Inputs!$B$9/1000000*(1-(1+Inputs!$B$30)^-10)/Inputs!$B$30/(1+Inputs!$B$30)^(C14-1),0) -> 0
A16: Depreciable basis ($mm) | B16: =IF(Inputs!$B$8=1,Inputs!$B$17-0.5*B13,Inputs!$B$17) -> 153 | C16: =IF(Inputs!$B$8=1,Inputs!$B$17-0.5*C13,Inputs!$B$17) -> 153
A17: MACRS shield PV ($mm) | B17: =SUMPRODUCT($B$25:$B$30, B16*Inputs!$B$28/(1+Inputs!$B$30)^ROW(INDIRECT("1:6"))) -> 37.964505 | C17: =SUMPRODUCT($B$25:$B$30, C16*Inputs!$B$28/(1+Inputs!$B$30)^ROW(INDIRECT("1:6"))) -> 37.964505
A18: Tax equity contribution ($mm) | B18: =IF(Inputs!$B$7=0,0,Inputs!$B$29*(B13+B15+B17)) -> 73.571604 | C18: =IF(Inputs!$B$7=0,0,Inputs!$B$29*(C13+C15+C17)) -> 73.571604
A19: Developer equity ($mm) | B19: =B4-B11-B18 -> 15.110465 | C19: =C4-C11-C18 -> 33.749566
A21: PTC start assumption: baseline facility is not placed in service while idle (PTC begins at COD); co-location BTM operation
A22: is assumed to qualify as placed in service (PTC begins at mechanical completion). Open tax question — validate in practitioner interviews.
A24: MACRS 5-yr schedule (Framework 2.3.3)
A25: Year 1 | B25: 0.2
A26: Year 2 | B26: 0.32
A27: Year 3 | B27: 0.192
A28: Year 4 | B28: 0.1152
A29: Year 5 | B29: 0.1152
A30: Year 6 | B30: 0.0576

Sheet Configurations
A1: Configuration library — values feed Inputs via the selector
A3: Parameter | B3: 1: Solar+BESS 100MW | C3: 2: Wind+BESS 150MW | D3: Source / note
A4: Capacity (MW) | B4: 100 | C4: 150 | D4: Solar: Framework 2.2.1. Wind: 150 MW scale variant (user-specified)
A5: Capacity factor | B5: 0.275 | C5: 0.35 | D5: Solar: CA midpoint. Wind: upper end of Tehachapi 30-35% range (Framework 2.2.1; NREL ATB 2024: https://atb.nrel.gov/electricity/2024/technologies)
A6: Annual degradation | B6: 0.005 | C6: 0.002 | D6: Framework 2.5.2
A7: Availability | B7: 0.98 | C7: 0.96 | D7: Framework 2.5.2 (wind 95-97% midpoint)
A8: Electrical losses | B8: 0.025 | C8: 0.025 | D8: Framework 2.5.2
A9: Total CAPEX ($mm) | B9: 197 | C9: 321.4 | D9: Solar: Framework 2.2.3. Wind: $1,350/kW x150MW + BESS 75MW/300MWh @$1,250/kW + dev 4% + land $2 + intercon $100/kW (NREL ATB 2024 midpoints, framework 0.5x BESS ratio)
A10: Qualified investment ($mm) | B10: 180 | C10: 296.25 | D10: Generation + BESS only (Framework 2.2.4)
A11: Microgrid CAPEX ($mm) | B11: 12 | C11: 18 | D11: $120/kW midpoint of $50-150/kW range x capacity
A12: Fixed O&M, gen + BESS ($mm/yr) | B12: 3 | C12: 6.375 | D12: Solar $17.5/kW + BESS $25/kW; Wind $30/kW x150 + BESS $25/kW x75 (Framework 2.6)
A13: Land lease + insurance ($mm/yr) | B13: 1.088 | C13: 1.586 | D13: $0.3mm land + 0.4% of CAPEX insurance
A14: Microgrid O&M ($mm/yr) | B14: 0.75 | C14: 1.125 | D14: $7.5/kW-yr x capacity
A16: Caveat: wind at 35% CF likely favors PTC over ITC (Framework 2.3.5); this quick model runs ITC only — flag in discussion.

Sheet Baseline
A1: Baseline — annual cash flow waterfall ($mm)
A2: Developer levered IRR: | B2: =IRR(K5:K32) -> 0.038933368
A4: Year | B4: Phase | C4: Op yr | D4: Net energy (MWh) | E4: Revenue | F4: OPEX | G4: EBITDA | H4: Debt service | I4: Distributable cash | J4: Dev share | K4: Dev cash flow
A5: 0 | B5: =IF(A5=0,"Equity",IF(A5<=Inputs!$B$34,"Construction",IF(A5<=Inputs!$B$34+Inputs!$B$6,"Queue wait","Grid ops"))) -> Equity | C5: =IF(A5<=Inputs!$B$34,"",A5-Inputs!$B$34-1) | D5: =IF(A5<=Inputs!$B$34,0,Inputs!$B$11*Inputs!$B$12*8760*(1-Inputs!$B$13)^C5*Inputs!$B$14*(1-Inputs!$B$15)) -> 0 | E5: =IF(A5<=Inputs!$B$34,0,IF(A5<=Inputs!$B$34+Inputs!$B$6,0,D5*Inputs!$B$31/1000000)) -> 0 | F5: =IF(A5<=Inputs!$B$34,0,IF(A5<=Inputs!$B$34+Inputs!$B$6,Inputs!$B$20,Inputs!$B$19+Inputs!$B$20+Inputs!$B$33*E5)) -> 0 | G5: =E5-F5 -> 0 | H5: =IF(AND(A5>Inputs!$B$34,A5<=Inputs!$B$34+Inputs!$B$25),Capitalization!B$12,0) -> 0 | I5: =G5-H5 -> 0 | J5: =IF(A5<=Inputs!$B$34,"",IF(AND(A5<=Inputs!$B$36,Capitalization!B$18>0),Inputs!$B$38,Inputs!$B$39)) | K5: =IF(A5=0,-Capitalization!B$19,IF(A5<=Inputs!$B$34,0,I5*J5-IF(AND(A5=Inputs!$B$36,Capitalization!B$18>0),Inputs!$B$37,0))) -> -15.110465
A6: 1 | B6: =IF(A6=0,"Equity",IF(A6<=Inputs!$B$34,"Construction",IF(A6<=Inputs!$B$34+Inputs!$B$6,"Queue wait","Grid ops"))) -> Construction | C6: =IF(A6<=Inputs!$B$34,"",A6-Inputs!$B$34-1) | D6: =IF(A6<=Inputs!$B$34,0,Inputs!$B$11*Inputs!$B$12*8760*(1-Inputs!$B$13)^C6*Inputs!$B$14*(1-Inputs!$B$15)) -> 0 | E6: =IF(A6<=Inputs!$B$34,0,IF(A6<=Inputs!$B$34+Inputs!$B$6,0,D6*Inputs!$B$31/1000000)) -> 0 | F6: =IF(A6<=Inputs!$B$34,0,IF(A6<=Inputs!$B$34+Inputs!$B$6,Inputs!$B$20,Inputs!$B$19+Inputs!$B$20+Inputs!$B$33*E6)) -> 0 | G6: =E6-F6 -> 0 | H6: =IF(AND(A6>Inputs!$B$34,A6<=Inputs!$B$34+Inputs!$B$25),Capitalization!B$12,0) -> 0 | I6: =G6-H6 -> 0 | J6: =IF(A6<=Inputs!$B$34,"",IF(AND(A6<=Inputs!$B$36,Capitalization!B$18>0),Inputs!$B$38,Inputs!$B$39)) | K6: =IF(A6=0,-Capitalization!B$19,IF(A6<=Inputs!$B$34,0,I6*J6-IF(AND(A6=Inputs!$B$36,Capitalization!B$18>0),Inputs!$B$37,0))) -> 0
A7: 2 | B7: =IF(A7=0,"Equity",IF(A7<=Inputs!$B$34,"Construction",IF(A7<=Inputs!$B$34+Inputs!$B$6,"Queue wait","Grid ops"))) -> Construction | C7: =IF(A7<=Inputs!$B$34,"",A7-Inputs!$B$34-1) | D7: =IF(A7<=Inputs!$B$34,0,Inputs!$B$11*Inputs!$B$12*8760*(1-Inputs!$B$13)^C7*Inputs!$B$14*(1-Inputs!$B$15)) -> 0 | E7: =IF(A7<=Inputs!$B$34,0,IF(A7<=Inputs!$B$34+Inputs!$B$6,0,D7*Inputs!$B$31/1000000)) -> 0 | F7: =IF(A7<=Inputs!$B$34,0,IF(A7<=Inputs!$B$34+Inputs!$B$6,Inputs!$B$20,Inputs!$B$19+Inputs!$B$20+Inputs!$B$33*E7)) -> 0 | G7: =E7-F7 -> 0 | H7: =IF(AND(A7>Inputs!$B$34,A7<=Inputs!$B$34+Inputs!$B$25),Capitalization!B$12,0) -> 0 | I7: =G7-H7 -> 0 | J7: =IF(A7<=Inputs!$B$34,"",IF(AND(A7<=Inputs!$B$36,Capitalization!B$18>0),Inputs!$B$38,Inputs!$B$39)) | K7: =IF(A7=0,-Capitalization!B$19,IF(A7<=Inputs!$B$34,0,I7*J7-IF(AND(A7=Inputs!$B$36,Capitalization!B$18>0),Inputs!$B$37,0))) -> 0
A8: 3 | B8: =IF(A8=0,"Equity",IF(A8<=Inputs!$B$34,"Construction",IF(A8<=Inputs!$B$34+Inputs!$B$6,"Queue wait","Grid ops"))) -> Queue wait | C8: =IF(A8<=Inputs!$B$34,"",A8-Inputs!$B$34-1) -> 0 | D8: =IF(A8<=Inputs!$B$34,0,Inputs!$B$11*Inputs!$B$12*8760*(1-Inputs!$B$13)^C8*Inputs!$B$14*(1-Inputs!$B$15)) -> 230179.95 | E8: =IF(A8<=Inputs!$B$34,0,IF(A8<=Inputs!$B$34+Inputs!$B$6,0,D8*Inputs!$B$31/1000000)) -> 0 | F8: =IF(A8<=Inputs!$B$34,0,IF(A8<=Inputs!$B$34+Inputs!$B$6,Inputs!$B$20,Inputs!$B$19+Inputs!$B$20+Inputs!$B$33*E8)) -> 1.088 | G8: =E8-F8 -> -1.088 | H8: =IF(AND(A8>Inputs!$B$34,A8<=Inputs!$B$34+Inputs!$B$25),Capitalization!B$12,0) -> 9.0639719 | I8: =G8-H8 -> -10.151972 | J8: =IF(A8<=Inputs!$B$34,"",IF(AND(A8<=Inputs!$B$36,Capitalization!B$18>0),Inputs!$B$38,Inputs!$B$39)) -> 0.7 | K8: =IF(A8=0,-Capitalization!B$19,IF(A8<=Inputs!$B$34,0,I8*J8-IF(AND(A8=Inputs!$B$36,Capitalization!B$18>0),Inputs!$B$37,0))) -> -7.1063803
A9: 4 | B9: =IF(A9=0,"Equity",IF(A9<=Inputs!$B$34,"Construction",IF(A9<=Inputs!$B$34+Inputs!$B$6,"Queue wait","Grid ops"))) -> Queue wait | C9: =IF(A9<=Inputs!$B$34,"",A9-Inputs!$B$34-1) -> 1 | D9: =IF(A9<=Inputs!$B$34,0,Inputs!$B$11*Inputs!$B$12*8760*(1-Inputs!$B$13)^C9*Inputs!$B$14*(1-Inputs!$B$15)) -> 229029.05 | E9: =IF(A9<=Inputs!$B$34,0,IF(A9<=Inputs!$B$34+Inputs!$B$6,0,D9*Inputs!$B$31/1000000)) -> 0 | F9: =IF(A9<=Inputs!$B$34,0,IF(A9<=Inputs!$B$34+Inputs!$B$6,Inputs!$B$20,Inputs!$B$19+Inputs!$B$20+Inputs!$B$33*E9)) -> 1.088 | G9: =E9-F9 -> -1.088 | H9: =IF(AND(A9>Inputs!$B$34,A9<=Inputs!$B$34+Inputs!$B$25),Capitalization!B$12,0) -> 9.0639719 | I9: =G9-H9 -> -10.151972 | J9: =IF(A9<=Inputs!$B$34,"",IF(AND(A9<=Inputs!$B$36,Capitalization!B$18>0),Inputs!$B$38,Inputs!$B$39)) -> 0.7 | K9: =IF(A9=0,-Capitalization!B$19,IF(A9<=Inputs!$B$34,0,I9*J9-IF(AND(A9=Inputs!$B$36,Capitalization!B$18>0),Inputs!$B$37,0))) -> -7.1063803
A10: 5 | B10: =IF(A10=0,"Equity",IF(A10<=Inputs!$B$34,"Construction",IF(A10<=Inputs!$B$34+Inputs!$B$6,"Queue wait","Grid ops"))) -> Queue wait | C10: =IF(A10<=Inputs!$B$34,"",A10-Inputs!$B$34-1) -> 2 | D10: =IF(A10<=Inputs!$B$34,0,Inputs!$B$11*Inputs!$B$12*8760*(1-Inputs!$B$13)^C10*Inputs!$B$14*(1-Inputs!$B$15)) -> 227883.9 | E10: =IF(A10<=Inputs!$B$34,0,IF(A10<=Inputs!$B$34+Inputs!$B$6,0,D10*Inputs!$B$31/1000000)) -> 0 | F10: =IF(A10<=Inputs!$B$34,0,IF(A10<=Inputs!$B$34+Inputs!$B$6,Inputs!$B$20,Inputs!$B$19+Inputs!$B$20+Inputs!$B$33*E10)) -> 1.088 | G10: =E10-F10 -> -1.088 | H10: =IF(AND(A10>Inputs!$B$34,A10<=Inputs!$B$34+Inputs!$B$25),Capitalization!B$12,0) -> 9.0639719 | I10: =G10-H10 -> -10.151972 | J10: =IF(A10<=Inputs!$B$34,"",IF(AND(A10<=Inputs!$B$36,Capitalization!B$18>0),Inputs!$B$38,Inputs!$B$39)) -> 0.7 | K10: =IF(A10=0,-Capitalization!B$19,IF(A10<=Inputs!$B$34,0,I10*J10-IF(AND(A10=Inputs!$B$36,Capitalization!B$18>0),Inputs!$B$37,0))) -> -7.1063803
A11: 6 | B11: =IF(A11=0,"Equity",IF(A11<=Inputs!$B$34,"Construction",IF(A11<=Inputs!$B$34+Inputs!$B$6,"Queue wait","Grid ops"))) -> Queue wait | C11: =IF(A11<=Inputs!$B$34,"",A11-Inputs!$B$34-1) -> 3 | D11: =IF(A11<=Inputs!$B$34,0,Inputs!$B$11*Inputs!$B$12*8760*(1-Inputs!$B$13)^C11*Inputs!$B$14*(1-Inputs!$B$15)) -> 226744.49 | E11: =IF(A11<=Inputs!$B$34,0,IF(A11<=Inputs!$B$34+Inputs!$B$6,0,D11*Inputs!$B$31/1000000)) -> 0 | F11: =IF(A11<=Inputs!$B$34,0,IF(A11<=Inputs!$B$34+Inputs!$B$6,Inputs!$B$20,Inputs!$B$19+Inputs!$B$20+Inputs!$B$33*E11)) -> 1.088 | G11: =E11-F11 -> -1.088 | H11: =IF(AND(A11>Inputs!$B$34,A11<=Inputs!$B$34+Inputs!$B$25),Capitalization!B$12,0) -> 9.0639719 | I11: =G11-H11 -> -10.151972 | J11: =IF(A11<=Inputs!$B$34,"",IF(AND(A11<=Inputs!$B$36,Capitalization!B$18>0),Inputs!$B$38,Inputs!$B$39)) -> 0.7 | K11: =IF(A11=0,-Capitalization!B$19,IF(A11<=Inputs!$B$34,0,I11*J11-IF(AND(A11=Inputs!$B$36,Capitalization!B$18>0),Inputs!$B$37,0))) -> -7.1063803
A12: 7 | B12: =IF(A12=0,"Equity",IF(A12<=Inputs!$B$34,"Construction",IF(A12<=Inputs!$B$34+Inputs!$B$6,"Queue wait","Grid ops"))) -> Grid ops | C12: =IF(A12<=Inputs!$B$34,"",A12-Inputs!$B$34-1) -> 4 | D12: =IF(A12<=Inputs!$B$34,0,Inputs!$B$11*Inputs!$B$12*8760*(1-Inputs!$B$13)^C12*Inputs!$B$14*(1-Inputs!$B$15)) -> 225610.76 | E12: =IF(A12<=Inputs!$B$34,0,IF(A12<=Inputs!$B$34+Inputs!$B$6,0,D12*Inputs!$B$31/1000000)) -> 16.243975 | F12: =IF(A12<=Inputs!$B$34,0,IF(A12<=Inputs!$B$34+Inputs!$B$6,Inputs!$B$20,Inputs!$B$19+Inputs!$B$20+Inputs!$B$33*E12)) -> 4.3316596 | G12: =E12-F12 -> 11.912315 | H12: =IF(AND(A12>Inputs!$B$34,A12<=Inputs!$B$34+Inputs!$B$25),Capitalization!B$12,0) -> 9.0639719 | I12: =G12-H12 -> 2.8483434 | J12: =IF(A12<=Inputs!$B$34,"",IF(AND(A12<=Inputs!$B$36,Capitalization!B$18>0),Inputs!$B$38,Inputs!$B$39)) -> 0.7 | K12: =IF(A12=0,-Capitalization!B$19,IF(A12<=Inputs!$B$34,0,I12*J12-IF(AND(A12=Inputs!$B$36,Capitalization!B$18>0),Inputs!$B$37,0))) -> 1.9938404
A13: 8 | B13: =IF(A13=0,"Equity",IF(A13<=Inputs!$B$34,"Construction",IF(A13<=Inputs!$B$34+Inputs!$B$6,"Queue wait","Grid ops"))) -> Grid ops | C13: =IF(A13<=Inputs!$B$34,"",A13-Inputs!$B$34-1) -> 5 | D13: =IF(A13<=Inputs!$B$34,0,Inputs!$B$11*Inputs!$B$12*8760*(1-Inputs!$B$13)^C13*Inputs!$B$14*(1-Inputs!$B$15)) -> 224482.71 | E13: =IF(A13<=Inputs!$B$34,0,IF(A13<=Inputs!$B$34+Inputs!$B$6,0,D13*Inputs!$B$31/1000000)) -> 16.162755 | F13: =IF(A13<=Inputs!$B$34,0,IF(A13<=Inputs!$B$34+Inputs!$B$6,Inputs!$B$20,Inputs!$B$19+Inputs!$B$20+Inputs!$B$33*E13)) -> 4.3304413 | G13: =E13-F13 -> 11.832314 | H13: =IF(AND(A13>Inputs!$B$34,A13<=Inputs!$B$34+Inputs!$B$25),Capitalization!B$12,0) -> 9.0639719 | I13: =G13-H13 -> 2.7683418 | J13: =IF(A13<=Inputs!$B$34,"",IF(AND(A13<=Inputs!$B$36,Capitalization!B$18>0),Inputs!$B$38,Inputs!$B$39)) -> 0.7 | K13: =IF(A13=0,-Capitalization!B$19,IF(A13<=Inputs!$B$34,0,I13*J13-IF(AND(A13=Inputs!$B$36,Capitalization!B$18>0),Inputs!$B$37,0))) -> 0.93783929
A14: 9 | B14: =IF(A14=0,"Equity",IF(A14<=Inputs!$B$34,"Construction",IF(A14<=Inputs!$B$34+Inputs!$B$6,"Queue wait","Grid ops"))) -> Grid ops | C14: =IF(A14<=Inputs!$B$34,"",A14-Inputs!$B$34-1) -> 6 | D14: =IF(A14<=Inputs!$B$34,0,Inputs!$B$11*Inputs!$B$12*8760*(1-Inputs!$B$13)^C14*Inputs!$B$14*(1-Inputs!$B$15)) -> 223360.3 | E14: =IF(A14<=Inputs!$B$34,0,IF(A14<=Inputs!$B$34+Inputs!$B$6,0,D14*Inputs!$B$31/1000000)) -> 16.081941 | F14: =IF(A14<=Inputs!$B$34,0,IF(A14<=Inputs!$B$34+Inputs!$B$6,Inputs!$B$20,Inputs!$B$19+Inputs!$B$20+Inputs!$B$33*E14)) -> 4.3292291 | G14: =E14-F14 -> 11.752712 | H14: =IF(AND(A14>Inputs!$B$34,A14<=Inputs!$B$34+Inputs!$B$25),Capitalization!B$12,0) -> 9.0639719 | I14: =G14-H14 -> 2.6887403 | J14: =IF(A14<=Inputs!$B$34,"",IF(AND(A14<=Inputs!$B$36,Capitalization!B$18>0),Inputs!$B$38,Inputs!$B$39)) -> 0.975 | K14: =IF(A14=0,-Capitalization!B$19,IF(A14<=Inputs!$B$34,0,I14*J14-IF(AND(A14=Inputs!$B$36,Capitalization!B$18>0),Inputs!$B$37,0))) -> 2.6215218
A15: 10 | B15: =IF(A15=0,"Equity",IF(A15<=Inputs!$B$34,"Construction",IF(A15<=Inputs!$B$34+Inputs!$B$6,"Queue wait","Grid ops"))) -> Grid ops | C15: =IF(A15<=Inputs!$B$34,"",A15-Inputs!$B$34-1) -> 7 | D15: =IF(A15<=Inputs!$B$34,0,Inputs!$B$11*Inputs!$B$12*8760*(1-Inputs!$B$13)^C15*Inputs!$B$14*(1-Inputs!$B$15)) -> 222243.49 | E15: =IF(A15<=Inputs!$B$34,0,IF(A15<=Inputs!$B$34+Inputs!$B$6,0,D15*Inputs!$B$31/1000000)) -> 16.001532 | F15: =IF(A15<=Inputs!$B$34,0,IF(A15<=Inputs!$B$34+Inputs!$B$6,Inputs!$B$20,Inputs!$B$19+Inputs!$B$20+Inputs!$B$33*E15)) -> 4.328023 | G15: =E15-F15 -> 11.673509 | H15: =IF(AND(A15>Inputs!$B$34,A15<=Inputs!$B$34+Inputs!$B$25),Capitalization!B$12,0) -> 9.0639719 | I15: =G15-H15 -> 2.6095367 | J15: =IF(A15<=Inputs!$B$34,"",IF(AND(A15<=Inputs!$B$36,Capitalization!B$18>0),Inputs!$B$38,Inputs!$B$39)) -> 0.975 | K15: =IF(A15=0,-Capitalization!B$19,IF(A15<=Inputs!$B$34,0,I15*J15-IF(AND(A15=Inputs!$B$36,Capitalization!B$18>0),Inputs!$B$37,0))) -> 2.5442983
A16: 11 | B16: =IF(A16=0,"Equity",IF(A16<=Inputs!$B$34,"Construction",IF(A16<=Inputs!$B$34+Inputs!$B$6,"Queue wait","Grid ops"))) -> Grid ops | C16: =IF(A16<=Inputs!$B$34,"",A16-Inputs!$B$34-1) -> 8 | D16: =IF(A16<=Inputs!$B$34,0,Inputs!$B$11*Inputs!$B$12*8760*(1-Inputs!$B$13)^C16*Inputs!$B$14*(1-Inputs!$B$15)) -> 221132.28 | E16: =IF(A16<=Inputs!$B$34,0,IF(A16<=Inputs!$B$34+Inputs!$B$6,0,D16*Inputs!$B$31/1000000)) -> 15.921524 | F16: =IF(A16<=Inputs!$B$34,0,IF(A16<=Inputs!$B$34+Inputs!$B$6,Inputs!$B$20,Inputs!$B$19+Inputs!$B$20+Inputs!$B$33*E16)) -> 4.3268229 | G16: =E16-F16 -> 11.594701 | H16: =IF(AND(A16>Inputs!$B$34,A16<=Inputs!$B$34+Inputs!$B$25),Capitalization!B$12,0) -> 9.0639719 | I16: =G16-H16 -> 2.5307292 | J16: =IF(A16<=Inputs!$B$34,"",IF(AND(A16<=Inputs!$B$36,Capitalization!B$18>0),Inputs!$B$38,Inputs!$B$39)) -> 0.975 | K16: =IF(A16=0,-Capitalization!B$19,IF(A16<=Inputs!$B$34,0,I16*J16-IF(AND(A16=Inputs!$B$36,Capitalization!B$18>0),Inputs!$B$37,0))) -> 2.4674609
... A32: 27 | B32: =IF(A32=0,"Equity",IF(A32<=Inputs!$B$34,"Construction",IF(A32<=Inputs!$B$34+Inputs!$B$6,"Queue wait","Grid ops"))) -> Grid ops | C32: =IF(A32<=Inputs!$B$34,"",A32-Inputs!$B$34-1) -> 24 | D32: =IF(A32<=Inputs!$B$34,0,Inputs!$B$11*Inputs!$B$12*8760*(1-Inputs!$B$13)^C32*Inputs!$B$14*(1-Inputs!$B$15)) -> 204089.86 | E32: =IF(A32<=Inputs!$B$34,0,IF(A32<=Inputs!$B$34+Inputs!$B$6,0,D32*Inputs!$B$31/1000000)) -> 14.69447 | F32: =IF(A32<=Inputs!$B$34,0,IF(A32<=Inputs!$B$34+Inputs!$B$6,Inputs!$B$20,Inputs!$B$19+Inputs!$B$20+Inputs!$B$33*E32)) -> 4.308417 | G32: =E32-F32 -> 10.386053 | H32: =IF(AND(A32>Inputs!$B$34,A32<=Inputs!$B$34+Inputs!$B$25),Capitalization!B$12,0) -> 0 | I32: =G32-H32 -> 10.386053 | J32: =IF(A32<=Inputs!$B$34,"",IF(AND(A32<=Inputs!$B$36,Capitalization!B$18>0),Inputs!$B$38,Inputs!$B$39)) -> 0.975 | K32: =IF(A32=0,-Capitalization!B$19,IF(A32<=Inputs!$B$34,0,I32*J32-IF(AND(A32=Inputs!$B$36,Capitalization!B$18>0),Inputs!$B$37,0))) -> 10.126402

Sheet Co-location
A1: Co-location — annual cash flow waterfall ($mm)
A2: Developer levered IRR: | B2: =IRR(K5:K32) -> 0.042466888
A4: Year | B4: Phase | C4: Op yr | D4: Net energy (MWh) | E4: Revenue | F4: OPEX | G4: EBITDA | H4: Debt service | I4: Distributable cash | J4: Dev share | K4: Dev cash flow
A5: 0 | B5: =IF(A5=0,"Equity",IF(A5<=Inputs!$B$34,"Construction",IF(A5<=Inputs!$B$34+Inputs!$B$6,"Queue wait","Grid ops"))) -> Equity | C5: =IF(A5<=Inputs!$B$34,"",A5-Inputs!$B$34-1) | D5: =IF(A5<=Inputs!$B$34,0,Inputs!$B$11*Inputs!$B$12*8760*(1-Inputs!$B$13)^C5*Inputs!$B$14*(1-Inputs!$B$15)) -> 0 | E5: =IF(A5<=Inputs!$B$34,0,IF(A5<=Inputs!$B$34+Inputs!$B$6,D5*(1-Inputs!$B$23)*Inputs!$B$32/1000000,D5*Inputs!$B$31/1000000)) -> 0 | F5: =IF(A5<=Inputs!$B$34,0,Inputs!$B$19+Inputs!$B$20+Inputs!$B$21+Inputs!$B$33*E5) -> 0 | G5: =E5-F5 -> 0 | H5: =IF(AND(A5>Inputs!$B$34,A5<=Inputs!$B$34+Inputs!$B$25),Capitalization!C$12,0) -> 0 | I5: =G5-H5 -> 0 | J5: =IF(A5<=Inputs!$B$34,"",IF(AND(A5<=Inputs!$B$36,Capitalization!C$18>0),Inputs!$B$38,Inputs!$B$39)) | K5: =IF(A5=0,-Capitalization!C$19,IF(A5<=Inputs!$B$34,0,I5*J5-IF(AND(A5=Inputs!$B$36,Capitalization!C$18>0),Inputs!$B$37,0))) -> -33.749566
A6: 1 | B6: =IF(A6=0,"Equity",IF(A6<=Inputs!$B$34,"Construction",IF(A6<=Inputs!$B$34+Inputs!$B$6,"Queue wait","Grid ops"))) -> Construction | C6: =IF(A6<=Inputs!$B$34,"",A6-Inputs!$B$34-1) | D6: =IF(A6<=Inputs!$B$34,0,Inputs!$B$11*Inputs!$B$12*8760*(1-Inputs!$B$13)^C6*Inputs!$B$14*(1-Inputs!$B$15)) -> 0 | E6: =IF(A6<=Inputs!$B$34,0,IF(A6<=Inputs!$B$34+Inputs!$B$6,D6*(1-Inputs!$B$23)*Inputs!$B$32/1000000,D6*Inputs!$B$31/1000000)) -> 0 | F6: =IF(A6<=Inputs!$B$34,0,Inputs!$B$19+Inputs!$B$20+Inputs!$B$21+Inputs!$B$33*E6) -> 0 | G6: =E6-F6 -> 0 | H6: =IF(AND(A6>Inputs!$B$34,A6<=Inputs!$B$34+Inputs!$B$25),Capitalization!C$12,0) -> 0 | I6: =G6-H6 -> 0 | J6: =IF(A6<=Inputs!$B$34,"",IF(AND(A6<=Inputs!$B$36,Capitalization!C$18>0),Inputs!$B$38,Inputs!$B$39)) | K6: =IF(A6=0,-Capitalization!C$19,IF(A6<=Inputs!$B$34,0,I6*J6-IF(AND(A6=Inputs!$B$36,Capitalization!C$18>0),Inputs!$B$37,0))) -> 0
A7: 2 | B7: =IF(A7=0,"Equity",IF(A7<=Inputs!$B$34,"Construction",IF(A7<=Inputs!$B$34+Inputs!$B$6,"Queue wait","Grid ops"))) -> Construction | C7: =IF(A7<=Inputs!$B$34,"",A7-Inputs!$B$34-1) | D7: =IF(A7<=Inputs!$B$34,0,Inputs!$B$11*Inputs!$B$12*8760*(1-Inputs!$B$13)^C7*Inputs!$B$14*(1-Inputs!$B$15)) -> 0 | E7: =IF(A7<=Inputs!$B$34,0,IF(A7<=Inputs!$B$34+Inputs!$B$6,D7*(1-Inputs!$B$23)*Inputs!$B$32/1000000,D7*Inputs!$B$31/1000000)) -> 0 | F7: =IF(A7<=Inputs!$B$34,0,Inputs!$B$19+Inputs!$B$20+Inputs!$B$21+Inputs!$B$33*E7) -> 0 | G7: =E7-F7 -> 0 | H7: =IF(AND(A7>Inputs!$B$34,A7<=Inputs!$B$34+Inputs!$B$25),Capitalization!C$12,0) -> 0 | I7: =G7-H7 -> 0 | J7: =IF(A7<=Inputs!$B$34,"",IF(AND(A7<=Inputs!$B$36,Capitalization!C$18>0),Inputs!$B$38,Inputs!$B$39)) | K7: =IF(A7=0,-Capitalization!C$19,IF(A7<=Inputs!$B$34,0,I7*J7-IF(AND(A7=Inputs!$B$36,Capitalization!C$18>0),Inputs!$B$37,0))) -> 0
A8: 3 | B8: =IF(A8=0,"Equity",IF(A8<=Inputs!$B$34,"Construction",IF(A8<=Inputs!$B$34+Inputs!$B$6,"Queue wait","Grid ops"))) -> Queue wait | C8: =IF(A8<=Inputs!$B$34,"",A8-Inputs!$B$34-1) -> 0 | D8: =IF(A8<=Inputs!$B$34,0,Inputs!$B$11*Inputs!$B$12*8760*(1-Inputs!$B$13)^C8*Inputs!$B$14*(1-Inputs!$B$15)) -> 230179.95 | E8: =IF(A8<=Inputs!$B$34,0,IF(A8<=Inputs!$B$34+Inputs!$B$6,D8*(1-Inputs!$B$23)*Inputs!$B$32/1000000,D8*Inputs!$B$31/1000000)) -> 13.672689 | F8: =IF(A8<=Inputs!$B$34,0,Inputs!$B$19+Inputs!$B$20+Inputs!$B$21+Inputs!$B$33*E8) -> 5.0430903 | G8: =E8-F8 -> 8.6295987 | H8: =IF(AND(A8>Inputs!$B$34,A8<=Inputs!$B$34+Inputs!$B$25),Capitalization!C$12,0) -> 8.5084163 | I8: =G8-H8 -> 0.12118236 | J8: =IF(A8<=Inputs!$B$34,"",IF(AND(A8<=Inputs!$B$36,Capitalization!C$18>0),Inputs!$B$38,Inputs!$B$39)) -> 0.7 | K8: =IF(A8=0,-Capitalization!C$19,IF(A8<=Inputs!$B$34,0,I8*J8-IF(AND(A8=Inputs!$B$36,Capitalization!C$18>0),Inputs!$B$37,0))) -> 0.084827651
A9: 4 | B9: =IF(A9=0,"Equity",IF(A9<=Inputs!$B$34,"Construction",IF(A9<=Inputs!$B$34+Inputs!$B$6,"Queue wait","Grid ops"))) -> Queue wait | C9: =IF(A9<=Inputs!$B$34,"",A9-Inputs!$B$34-1) -> 1 | D9: =IF(A9<=Inputs!$B$34,0,Inputs!$B$11*Inputs!$B$12*8760*(1-Inputs!$B$13)^C9*Inputs!$B$14*(1-Inputs!$B$15)) -> 229029.05 | E9: =IF(A9<=Inputs!$B$34,0,IF(A9<=Inputs!$B$34+Inputs!$B$6,D9*(1-Inputs!$B$23)*Inputs!$B$32/1000000,D9*Inputs!$B$31/1000000)) -> 13.604326 | F9: =IF(A9<=Inputs!$B$34,0,Inputs!$B$19+Inputs!$B$20+Inputs!$B$21+Inputs!$B$33*E9) -> 5.0420649 | G9: =E9-F9 -> 8.5622607 | H9: =IF(AND(A9>Inputs!$B$34,A9<=Inputs!$B$34+Inputs!$B$25),Capitalization!C$12,0) -> 8.5084163 | I9: =G9-H9 -> 0.053844365 | J9: =IF(A9<=Inputs!$B$34,"",IF(AND(A9<=Inputs!$B$36,Capitalization!C$18>0),Inputs!$B$38,Inputs!$B$39)) -> 0.7 | K9: =IF(A9=0,-Capitalization!C$19,IF(A9<=Inputs!$B$34,0,I9*J9-IF(AND(A9=Inputs!$B$36,Capitalization!C$18>0),Inputs!$B$37,0))) -> 0.037691055
A10: 5 | B10: =IF(A10=0,"Equity",IF(A10<=Inputs!$B$34,"Construction",IF(A10<=Inputs!$B$34+Inputs!$B$6,"Queue wait","Grid ops"))) -> Queue wait | C10: =IF(A10<=Inputs!$B$34,"",A10-Inputs!$B$34-1) -> 2 | D10: =IF(A10<=Inputs!$B$34,0,Inputs!$B$11*Inputs!$B$12*8760*(1-Inputs!$B$13)^C10*Inputs!$B$14*(1-Inputs!$B$15)) -> 227883.9 | E10: =IF(A10<=Inputs!$B$34,0,IF(A10<=Inputs!$B$34+Inputs!$B$6,D10*(1-Inputs!$B$23)*Inputs!$B$32/1000000,D10*Inputs!$B$31/1000000)) -> 13.536304 | F10: =IF(A10<=Inputs!$B$34,0,Inputs!$B$19+Inputs!$B$20+Inputs!$B$21+Inputs!$B$33*E10) -> 5.0410446 | G10: =E10-F10 -> 8.4952594 | H10: =IF(AND(A10>Inputs!$B$34,A10<=Inputs!$B$34+Inputs!$B$25),Capitalization!C$12,0) -> 8.5084163 | I10: =G10-H10 -> -0.013156939 | J10: =IF(A10<=Inputs!$B$34,"",IF(AND(A10<=Inputs!$B$36,Capitalization!C$18>0),Inputs!$B$38,Inputs!$B$39)) -> 0.7 | K10: =IF(A10=0,-Capitalization!C$19,IF(A10<=Inputs!$B$34,0,I10*J10-IF(AND(A10=Inputs!$B$36,Capitalization!C$18>0),Inputs!$B$37,0))) -> -0.0092098571
A11: 6 | B11: =IF(A11=0,"Equity",IF(A11<=Inputs!$B$34,"Construction",IF(A11<=Inputs!$B$34+Inputs!$B$6,"Queue wait","Grid ops"))) -> Queue wait | C11: =IF(A11<=Inputs!$B$34,"",A11-Inputs!$B$34-1) -> 3 | D11: =IF(A11<=Inputs!$B$34,0,Inputs!$B$11*Inputs!$B$12*8760*(1-Inputs!$B$13)^C11*Inputs!$B$14*(1-Inputs!$B$15)) -> 226744.49 | E11: =IF(A11<=Inputs!$B$34,0,IF(A11<=Inputs!$B$34+Inputs!$B$6,D11*(1-Inputs!$B$23)*Inputs!$B$32/1000000,D11*Inputs!$B$31/1000000)) -> 13.468622 | F11: =IF(A11<=Inputs!$B$34,0,Inputs!$B$19+Inputs!$B$20+Inputs!$B$21+Inputs!$B$33*E11) -> 5.0400293 | G11: =E11-F11 -> 8.4285931 | H11: =IF(AND(A11>Inputs!$B$34,A11<=Inputs!$B$34+Inputs!$B$25),Capitalization!C$12,0) -> 8.5084163 | I11: =G11-H11 -> -0.079823236 | J11: =IF(A11<=Inputs!$B$34,"",IF(AND(A11<=Inputs!$B$36,Capitalization!C$18>0),Inputs!$B$38,Inputs!$B$39)) -> 0.7 | K11: =IF(A11=0,-Capitalization!C$19,IF(A11<=Inputs!$B$34,0,I11*J11-IF(AND(A11=Inputs!$B$36,Capitalization!C$18>0),Inputs!$B$37,0))) -> -0.055876265
A12: 7 | B12: =IF(A12=0,"Equity",IF(A12<=Inputs!$B$34,"Construction",IF(A12<=Inputs!$B$34+Inputs!$B$6,"Queue wait","Grid ops"))) -> Grid ops | C12: =IF(A12<=Inputs!$B$34,"",A12-Inputs!$B$34-1) -> 4 | D12: =IF(A12<=Inputs!$B$34,0,Inputs!$B$11*Inputs!$B$12*8760*(1-Inputs!$B$13)^C12*Inputs!$B$14*(1-Inputs!$B$15)) -> 225610.76 | E12: =IF(A12<=Inputs!$B$34,0,IF(A12<=Inputs!$B$34+Inputs!$B$6,D12*(1-Inputs!$B$23)*Inputs!$B$32/1000000,D12*Inputs!$B$31/1000000)) -> 16.243975 | F12: =IF(A12<=Inputs!$B$34,0,Inputs!$B$19+Inputs!$B$20+Inputs!$B$21+Inputs!$B$33*E12) -> 5.0816596 | G12: =E12-F12 -> 11.162315 | H12: =IF(AND(A12>Inputs!$B$34,A12<=Inputs!$B$34+Inputs!$B$25),Capitalization!C$12,0) -> 8.5084163 | I12: =G12-H12 -> 2.653899 | J12: =IF(A12<=Inputs!$B$34,"",IF(AND(A12<=Inputs!$B$36,Capitalization!C$18>0),Inputs!$B$38,Inputs!$B$39)) -> 0.7 | K12: =IF(A12=0,-Capitalization!C$19,IF(A12<=Inputs!$B$34,0,I12*J12-IF(AND(A12=Inputs!$B$36,Capitalization!C$18>0),Inputs!$B$37,0))) -> 1.8577293
A13: 8 | B13: =IF(A13=0,"Equity",IF(A13<=Inputs!$B$34,"Construction",IF(A13<=Inputs!$B$34+Inputs!$B$6,"Queue wait","Grid ops"))) -> Grid ops | C13: =IF(A13<=Inputs!$B$34,"",A13-Inputs!$B$34-1) -> 5 | D13: =IF(A13<=Inputs!$B$34,0,Inputs!$B$11*Inputs!$B$12*8760*(1-Inputs!$B$13)^C13*Inputs!$B$14*(1-Inputs!$B$15)) -> 224482.71 | E13: =IF(A13<=Inputs!$B$34,0,IF(A13<=Inputs!$B$34+Inputs!$B$6,D13*(1-Inputs!$B$23)*Inputs!$B$32/1000000,D13*Inputs!$B$31/1000000)) -> 16.162755 | F13: =IF(A13<=Inputs!$B$34,0,Inputs!$B$19+Inputs!$B$20+Inputs!$B$21+Inputs!$B$33*E13) -> 5.0804413 | G13: =E13-F13 -> 11.082314 | H13: =IF(AND(A13>Inputs!$B$34,A13<=Inputs!$B$34+Inputs!$B$25),Capitalization!C$12,0) -> 8.5084163 | I13: =G13-H13 -> 2.5738974 | J13: =IF(A13<=Inputs!$B$34,"",IF(AND(A13<=Inputs!$B$36,Capitalization!C$18>0),Inputs!$B$38,Inputs!$B$39)) -> 0.7 | K13: =IF(A13=0,-Capitalization!C$19,IF(A13<=Inputs!$B$34,0,I13*J13-IF(AND(A13=Inputs!$B$36,Capitalization!C$18>0),Inputs!$B$37,0))) -> 0.80172818
A14: 9 | B14: =IF(A14=0,"Equity",IF(A14<=Inputs!$B$34,"Construction",IF(A14<=Inputs!$B$34+Inputs!$B$6,"Queue wait","Grid ops"))) -> Grid ops | C14: =IF(A14<=Inputs!$B$34,"",A14-Inputs!$B$34-1) -> 6 | D14: =IF(A14<=Inputs!$B$34,0,Inputs!$B$11*Inputs!$B$12*8760*(1-Inputs!$B$13)^C14*Inputs!$B$14*(1-Inputs!$B$15)) -> 223360.3 | E14: =IF(A14<=Inputs!$B$34,0,IF(A14<=Inputs!$B$34+Inputs!$B$6,D14*(1-Inputs!$B$23)*Inputs!$B$32/1000000,D14*Inputs!$B$31/1000000)) -> 16.081941 | F14: =IF(A14<=Inputs!$B$34,0,Inputs!$B$19+Inputs!$B$20+Inputs!$B$21+Inputs!$B$33*E14) -> 5.0792291 | G14: =E14-F14 -> 11.002712 | H14: =IF(AND(A14>Inputs!$B$34,A14<=Inputs!$B$34+Inputs!$B$25),Capitalization!C$12,0) -> 8.5084163 | I14: =G14-H14 -> 2.4942958 | J14: =IF(A14<=Inputs!$B$34,"",IF(AND(A14<=Inputs!$B$36,Capitalization!C$18>0),Inputs!$B$38,Inputs!$B$39)) -> 0.975 | K14: =IF(A14=0,-Capitalization!C$19,IF(A14<=Inputs!$B$34,0,I14*J14-IF(AND(A14=Inputs!$B$36,Capitalization!C$18>0),Inputs!$B$37,0))) -> 2.4319384
A15: 10 | B15: =IF(A15=0,"Equity",IF(A15<=Inputs!$B$34,"Construction",IF(A15<=Inputs!$B$34+Inputs!$B$6,"Queue wait","Grid ops"))) -> Grid ops | C15: =IF(A15<=Inputs!$B$34,"",A15-Inputs!$B$34-1) -> 7 | D15: =IF(A15<=Inputs!$B$34,0,Inputs!$B$11*Inputs!$B$12*8760*(1-Inputs!$B$13)^C15*Inputs!$B$14*(1-Inputs!$B$15)) -> 222243.49 | E15: =IF(A15<=Inputs!$B$34,0,IF(A15<=Inputs!$B$34+Inputs!$B$6,D15*(1-Inputs!$B$23)*Inputs!$B$32/1000000,D15*Inputs!$B$31/1000000)) -> 16.001532 | F15: =IF(A15<=Inputs!$B$34,0,Inputs!$B$19+Inputs!$B$20+Inputs!$B$21+Inputs!$B$33*E15) -> 5.078023 | G15: =E15-F15 -> 10.923509 | H15: =IF(AND(A15>Inputs!$B$34,A15<=Inputs!$B$34+Inputs!$B$25),Capitalization!C$12,0) -> 8.5084163 | I15: =G15-H15 -> 2.4150923 | J15: =IF(A15<=Inputs!$B$34,"",IF(AND(A15<=Inputs!$B$36,Capitalization!C$18>0),Inputs!$B$38,Inputs!$B$39)) -> 0.975 | K15: =IF(A15=0,-Capitalization!C$19,IF(A15<=Inputs!$B$34,0,I15*J15-IF(AND(A15=Inputs!$B$36,Capitalization!C$18>0),Inputs!$B$37,0))) -> 2.354715
A16: 11 | B16: =IF(A16=0,"Equity",IF(A16<=Inputs!$B$34,"Construction",IF(A16<=Inputs!$B$34+Inputs!$B$6,"Queue wait","Grid ops"))) -> Grid ops | C16: =IF(A16<=Inputs!$B$34,"",A16-Inputs!$B$34-1) -> 8 | D16: =IF(A16<=Inputs!$B$34,0,Inputs!$B$11*Inputs!$B$12*8760*(1-Inputs!$B$13)^C16*Inputs!$B$14*(1-Inputs!$B$15)) -> 221132.28 | E16: =IF(A16<=Inputs!$B$34,0,IF(A16<=Inputs!$B$34+Inputs!$B$6,D16*(1-Inputs!$B$23)*Inputs!$B$32/1000000,D16*Inputs!$B$31/1000000)) -> 15.921524 | F16: =IF(A16<=Inputs!$B$34,0,Inputs!$B$19+Inputs!$B$20+Inputs!$B$21+Inputs!$B$33*E16) -> 5.0768229 | G16: =E16-F16 -> 10.844701 | H16: =IF(AND(A16>Inputs!$B$34,A16<=Inputs!$B$34+Inputs!$B$25),Capitalization!C$12,0) -> 8.5084163 | I16: =G16-H16 -> 2.3362847 | J16: =IF(A16<=Inputs!$B$34,"",IF(AND(A16<=Inputs!$B$36,Capitalization!C$18>0),Inputs!$B$38,Inputs!$B$39)) -> 0.975 | K16: =IF(A16=0,-Capitalization!C$19,IF(A16<=Inputs!$B$34,0,I16*J16-IF(AND(A16=Inputs!$B$36,Capitalization!C$18>0),Inputs!$B$37,0))) -> 2.2778776
... A32: 27 | B32: =IF(A32=0,"Equity",IF(A32<=Inputs!$B$34,"Construction",IF(A32<=Inputs!$B$34+Inputs!$B$6,"Queue wait","Grid ops"))) -> Grid ops | C32: =IF(A32<=Inputs!$B$34,"",A32-Inputs!$B$34-1) -> 24 | D32: =IF(A32<=Inputs!$B$34,0,Inputs!$B$11*Inputs!$B$12*8760*(1-Inputs!$B$13)^C32*Inputs!$B$14*(1-Inputs!$B$15)) -> 204089.86 | E32: =IF(A32<=Inputs!$B$34,0,IF(A32<=Inputs!$B$34+Inputs!$B$6,D32*(1-Inputs!$B$23)*Inputs!$B$32/1000000,D32*Inputs!$B$31/1000000)) -> 14.69447 | F32: =IF(A32<=Inputs!$B$34,0,Inputs!$B$19+Inputs!$B$20+Inputs!$B$21+Inputs!$B$33*E32) -> 5.058417 | G32: =E32-F32 -> 9.6360529 | H32: =IF(AND(A32>Inputs!$B$34,A32<=Inputs!$B$34+Inputs!$B$25),Capitalization!C$12,0) -> 0 | I32: =G32-H32 -> 9.6360529 | J32: =IF(A32<=Inputs!$B$34,"",IF(AND(A32<=Inputs!$B$36,Capitalization!C$18>0),Inputs!$B$38,Inputs!$B$39)) -> 0.975 | K32: =IF(A32=0,-Capitalization!C$19,IF(A32<=Inputs!$B$34,0,I32*J32-IF(AND(A32=Inputs!$B$36,Capitalization!C$18>0),Inputs!$B$37,0))) -> 9.3951516

Sheet Results
A1: Results
A3: Live scenario (change yellow cells on Inputs tab):
A4: Configuration | B4: =IF(Inputs!$B$5=1,"Solar+BESS 100MW","Wind+BESS 150MW") -> Solar+BESS 100MW
A5: Queue wait (yrs) | B5: =Inputs!$B$6 -> 4
A6: ITC rate | B6: =Inputs!$B$7 -> 0.3
A7: Credit type | B7: =IF(Inputs!$B$8=1,"ITC","PTC") -> ITC
A8: Baseline developer levered IRR | B8: =Baseline!B2 -> 0.038933368
A9: Co-location developer levered IRR | B9: ='Co-location'!B2 -> 0.042466888
A10: Delta IRR (co-location - baseline), pp | B10: =('Co-location'!B2-Baseline!B2)*100 -> 0.35335193
A11: Scenario sweep — Solar+BESS 100MW (same model re-run per combination; reproduce via Inputs)
A12: ITC | B12: Queue (yrs) | C12: Baseline IRR | D12: Co-location IRR | E12: Delta (pp)
A13: 0.3 | B13: 2 | C13: 0.0675 | D13: 0.0477 | E13: -1.98
A14: 0.3 | B14: 4 | C14: 0.0389 | D14: 0.0425 | E14: 0.35
A15: 0.3 | B15: 6 | C15: 0.0193 | D15: 0.0379 | E15: 1.87
A16: 0.3 | B16: 8 | C16: -0.002 | D16: 0.0323 | E16: 3.43
A17: 0 | B17: 2 | C17: -0.0084 | D17: -0.0114 | E17: -0.31
A18: 0 | B18: 4 | C18: -0.0201 | D18: -0.0141 | E18: 0.6
A19: 0 | B19: 6 | C19: -0.0305 | D19: -0.0167 | E19: 1.38
A20: 0 | B20: 8 | C20: -0.0405 | D20: -0.0193 | E20: 2.11
A22: Scenario sweep — Wind+BESS 150MW (same model re-run per combination; reproduce via Inputs)
A23: ITC | B23: Queue (yrs) | C23: Baseline IRR | D23: Co-location IRR | E23: Delta (pp)
A24: 0.3 | B24: 2 | C24: 0.1092 | D24: 0.1075 | E24: -0.18
A25: 0.3 | B25: 4 | C25: 0.0734 | D25: 0.0976 | E25: 2.42
A26: 0.3 | B26: 6 | C26: 0.0499 | D26: 0.0898 | E26: 4
A27: 0.3 | B27: 8 | C27: 0.0254 | D27: 0.0811 | E27: 5.56
A28: 0 | B28: 2 | C28: 0.0149 | D28: 0.0116 | E28: -0.33
A29: 0 | B29: 4 | C29: 0.0015 | D29: 0.0082 | E29: 0.68
A30: 0 | B30: 6 | C30: -0.0102 | D30: 0.005 | E30: 1.52
A31: 0 | B31: 8 | C31: -0.0209 | D31: 0.0019 | E31: 2.28
A33: Takeaways: breakeven Q* ~3.5 yrs (solar) vs ~2.2 yrs (wind, 30% ITC); higher CF monetizes more energy per queue year, so wind reaches
A34: the H1 3-6pp band (+5.6pp at 8 yrs). Wind quick-run uses ITC only; PTC likely optimal at 35% CF (Framework 2.3.5) — a to-do, not a result.
