Workbook

Sheet Inputs
A1: Model 3 - Data Center Electricity Cost Model - INPUTS
A2: Blue = hardcoded input. Yellow = PLACEHOLDER pending sourced data. Column D = source.
A3: SEC 1: DATA CENTER LOAD
A4: DC nameplate load | B4: 100 | C4: MW | D4: Scenario setting (user; central case of 50/100/200 MW matrix)
A5: DC load factor | B5: 0.9 | C5: frac | D5: PLACEHOLDER - AI DC annualized utilization; to be sourced (lit. / Chien interview). Typical claim 85-95%.
A6: Hours per year | B6: 8760 | C6: hrs | D6: Constant
A7: Annual DC demand | B7: =B4*B5*B6 -> 788400 | C7: MWh/yr | D7: Calc: nameplate x LF x 8760
A8: SEC 2: GENERATION SUPPLY (from Model 2 configs)
A9: Solar net capacity factor | B9: 0.26 | C9: frac | D9: PLACEHOLDER - Model 2 SolarBase net of degradation/availability/losses (gross CF 25-30%, NREL ATB 2024, https://atb.nrel.gov/electricity/2024/technologies)
A10: Wind net capacity factor | B10: 0.33 | C10: frac | D10: PLACEHOLDER - Model 2 WindBase net (gross 30-35%, NREL ATB 2024)
A11: Geothermal net capacity factor | B11: 0.87 | C11: frac | D11: PLACEHOLDER - Model 2 GeoBase net (gross 90%+, NREL ATB 2024)
A12: Solar capacity | B12: 100 | C12: MW | D12: Model 2 configuration
A13: Wind capacity | B13: 150 | C13: MW | D13: Model 2 configuration
A14: Geothermal capacity | B14: 100 | C14: MW | D14: Model 2 configuration
A15: BESS round-trip efficiency | B15: 0.875 | C15: frac | D15: Framework Sec 2.5.3 (85-90%); applied to shifted energy share - simplified: coverage treated as energy-balance bound, hourly dispatch pending
A16: SEC 3: PRICES - SOURCED
A17: CAISO HV Transmission Access Charge (TAC) | B17: 15.5751 | C17: $/MWh | D17: CAISO, High Voltage Access Charge Rates effective Jan 1 2026, https://www.caiso.com/documents/high-voltage-access-charge-rates-effective-jan-01-2026.pdf
A18: RA capacity price (system, wtd avg) | B18: 25.19 | C18: $/kW-mo | D18: CPUC, 2025 LCR-RCM calculation (Q1-Q4 2024 contracts, 2025-26 delivery), https://www.cpuc.ca.gov/-/media/cpuc-website/divisions/energy-division/documents/resource-adequacy-homepage/resource-adequacy-compliance-materials/lcr-rcm-2025.pdf
A19: Planning reserve margin (PRM) | B19: 0.18 | C19: frac | D19: CPUC D.25-06-048 (June 2025), Slice-of-Day framework, https://www.cpuc.ca.gov/-/media/cpuc-website/divisions/energy-division/documents/resource-adequacy-homepage/oga-fact-sheet-on-track-3-decision-final.pdf
A20: Utility bundled all-in rate (Structure A) | B20: 236.91 | C20: $/MWh | D20: PG&E Schedule B-20 Primary, total electricity cost $0.23691/kWh, rates as of Mar 1 2026, PG&E-3CE Joint Rate Comparison, https://www.pge.com/assets/pge/docs/account/alternate-energy-providers/3ce-rcc.pdf. Note: transmission-voltage (B-20 T) would be somewhat lower; treat as upper reference.
A21: EIA-861 CA industrial avg (cross-check) | B21: 215.3 | C21: $/MWh | D21: EIA-861 2024, California industrial average retail price (prior extraction; re-verify at https://www.eia.gov/electricity/data/eia861/)
A22: Non-bypassable charges (NBC: PCIA/PPP/ND/wildfire) | B22: 23 | C22: $/MWh | D22: PLACEHOLDER - anchored to PG&E PCIA/FF line ~$0.023/kWh in PG&E joint rate comparisons (see B-20 rows, same PG&E PDFs); decompose properly from PG&E/SCE tariff sheets
A23: SEC 4: PRICES - PLACEHOLDERS (pending Model 1 / Model 4)
A24: Grid PPA energy price (Structure B) | B24: 70 | C24: $/MWh | D24: PLACEHOLDER - market comparable needed (LevelTen CAISO index or similar); do NOT reuse project LCOE (circularity)
A25: BTM PPA price (Structure C) | B25: 62 | C25: $/MWh | D25: PLACEHOLDER - Model 4 output pending; currently midpoint assumption from Model 2
A26: Ancillary services + CAISO GMC | B26: 1.5 | C26: $/MWh | D26: PLACEHOLDER - CAISO GMC ~$0.4-0.5 + AS; source from CAISO market charges schedule
A27: Scheduling coordinator fee | B27: 0.5 | C27: $/MWh | D27: PLACEHOLDER
A28: Shaping / imbalance cost | B28: 7 | C28: $/MWh | D28: PLACEHOLDER - as-generated renewable vs flat load mismatch; source from hourly dispatch model when built
A29: Microgrid service fee (paid by DC) | B29: 3.5 | C29: $/MWh | D29: Framework Sec 3.2 range $2-5/MWh. ALLOCATION ASSUMPTION: microgrid CAPEX sits in Model 2 project CAPEX; DC pays service fee only - no double count
A30: Backup power cost (diesel, Phase 1) | B30: 300 | C30: $/MWh | D30: PLACEHOLDER - CA diesel gen fuel+O&M+permits; source needed (e.g., Lazard LCOE+ gas peaking as proxy, CARB permit constraints)
A31: Standby charge (Phase 2, grid backup) | B31: 5 | C31: $/MWh | D31: PLACEHOLDER - CPUC standby/departing-load tariff (e.g., PG&E Schedule S); convert $/kW-mo to $/MWh once sourced

Sheet Coverage
A1: Energy-Balance Coverage by Configuration
A2: Coverage = min(1, annual net generation / annual DC demand). Energy-balance upper bound: BESS shifts timing but cannot create energy. Hourly dispatch (pending) will only lower these.
B4: Solar+BESS | C4: Wind+BESS | D4: Geo+BESS
A5: Capacity (MW) | B5: =Inputs!B12 -> 100 | C5: =Inputs!B13 -> 150 | D5: =Inputs!B14 -> 100
A6: Net capacity factor | B6: =Inputs!B9 -> 0.26 | C6: =Inputs!B10 -> 0.33 | D6: =Inputs!B11 -> 0.87
A7: Annual net generation (MWh) | B7: =B5*B6*Inputs!$B$6 -> 227760 | C7: =C5*C6*Inputs!$B$6 -> 433620 | D7: =D5*D6*Inputs!$B$6 -> 762120
A8: Annual DC demand (MWh) | B8: =Inputs!$B$7 -> 788400 | C8: =Inputs!$B$7 -> 788400 | D8: =Inputs!$B$7 -> 788400
A9: Coverage ratio (capped at 100%) | B9: =MIN(1,B7/B8) -> 0.28888889 | C9: =MIN(1,C7/C8) -> 0.55 | D9: =MIN(1,D7/D8) -> 0.96666667
A10: Uncovered share (backup/grid) | B10: =1-B9 -> 0.71111111 | C10: =1-C9 -> 0.45 | D10: =1-D9 -> 0.033333333

Sheet StructA_B
A1: Structure A: Utility Tariff (bundled, all-in)
A3: All-in delivered cost ($/MWh) | B3: =Inputs!B20 -> 236.91 | C3: PG&E B-20 Primary, Mar 2026. Upper reference; transmission voltage would be lower.
A4: Cross-check: EIA-861 CA industrial avg | B4: =Inputs!B21 -> 215.3
A7: Structure B: Sleeved Grid PPA (all-in delivered)
A8: VPPA treated as sensitivity (see note row 20). Sleeved = physical delivery via grid at transmission voltage.
A10: PPA energy price | B10: =Inputs!B24 -> 70 | C10: Placeholder pending market comp
A11: CAISO TAC (HV) | B11: =Inputs!B17 -> 15.5751 | C11: Sourced - CAISO Jan 2026
A12: Non-bypassable charges | B12: =Inputs!B22 -> 23 | C12: Placeholder range
A13: Resource Adequacy | B13: =Inputs!B4*1000*(1+Inputs!B19)*Inputs!B18*12/Inputs!B7 -> 45.242314 | C13: Calc: nameplate kW x (1+PRM) x $/kW-mo x 12 / annual MWh. Price and PRM sourced.
A14: Ancillary + GMC | B14: =Inputs!B26 -> 1.5 | C14: Placeholder
A15: Scheduling coordinator | B15: =Inputs!B27 -> 0.5 | C15: Placeholder
A16: Shaping / imbalance | B16: =Inputs!B28 -> 7 | C16: Placeholder
A17: Structure B all-in ($/MWh) | B17: =SUM(B10:B16) -> 162.81741
A19: KEY FINDING
A20: RA capacity cost alone adds ~$45/MWh to a flat 100 MW load. Structure B all-in far exceeds the framework's $60-90/MWh estimate, resolving the Model 3 internal inconsistency in the direction of a WIDER negotiation zone.
A22: VPPA sensitivity: VPPA cost = Structure A retail cost + (PPA price - hub LMP settlement). Requires Model 1 LMP; deferred.

Sheet StructC
A1: Structure C: BTM Co-location (all-in $/MWh to the DC)
A2: Phase 1 = islanded (queue wait): backup fills uncovered share. Phase 2 = grid-connected: grid supply fills uncovered share.
B4: Solar+BESS | C4: Wind+BESS | D4: Geo+BESS
A5: Coverage ratio | B5: =Coverage!B9 -> 0.28888889 | C5: =Coverage!C9 -> 0.55 | D5: =Coverage!D9 -> 0.96666667
A7: PHASE 1 (islanded, queue-wait window)
A8: BTM energy component | B8: =B5*Inputs!$B$25 -> 17.911111 | C8: =C5*Inputs!$B$25 -> 34.1 | D8: =D5*Inputs!$B$25 -> 59.933333
A9: Backup component (uncovered x diesel) | B9: =(1-B5)*Inputs!$B$30 -> 213.33333 | C9: =(1-C5)*Inputs!$B$30 -> 135 | D9: =(1-D5)*Inputs!$B$30 -> 10
A10: Microgrid service fee | B10: =Inputs!$B$29 -> 3.5 | C10: =Inputs!$B$29 -> 3.5 | D10: =Inputs!$B$29 -> 3.5
A11: Phase 1 all-in ($/MWh) | B11: =SUM(B8:B10) -> 234.74444 | C11: =SUM(C8:C10) -> 172.6 | D11: =SUM(D8:D10) -> 73.433333
A13: PHASE 2 (grid-connected, post-COD)
A14: BTM energy component | B14: =B5*Inputs!$B$25 -> 17.911111 | C14: =C5*Inputs!$B$25 -> 34.1 | D14: =D5*Inputs!$B$25 -> 59.933333
A15: Grid supplemental (uncovered x [PPA+TAC+NBC]) | B15: =(1-B5)*(Inputs!$B$24+Inputs!$B$17+Inputs!$B$22) -> 77.20896 | C15: =(1-C5)*(Inputs!$B$24+Inputs!$B$17+Inputs!$B$22) -> 48.858795 | D15: =(1-D5)*(Inputs!$B$24+Inputs!$B$17+Inputs!$B$22) -> 3.61917
A16: Standby charge | B16: =Inputs!$B$31 -> 5 | C16: =Inputs!$B$31 -> 5 | D16: =Inputs!$B$31 -> 5
A17: Microgrid service fee | B17: =Inputs!$B$29 -> 3.5 | C17: =Inputs!$B$29 -> 3.5 | D17: =Inputs!$B$29 -> 3.5
A18: Phase 2 all-in ($/MWh) | B18: =SUM(B14:B17) -> 103.62007 | C18: =SUM(C14:C17) -> 91.458795 | D18: =SUM(D14:D17) -> 72.052503
A20: Note: Phase 2 grid supplemental assumes RA embedded in supplemental supply price is NOT separately charged (conservative low); alternative adds pro-rata RA - test in sensitivity.

Sheet Results
A1: Model 3 Results - Effective Delivered Cost and H2 Test
B3: Solar+BESS | C3: Wind+BESS | D3: Geo+BESS
A4: Structure A - utility tariff ($/MWh) | B4: =StructA_B!$B$3 -> 236.91 | C4: =StructA_B!$B$3 -> 236.91 | D4: =StructA_B!$B$3 -> 236.91
A5: Structure B - sleeved grid PPA all-in ($/MWh) | B5: =StructA_B!$B$17 -> 162.81741 | C5: =StructA_B!$B$17 -> 162.81741 | D5: =StructA_B!$B$17 -> 162.81741
A6: Structure C - Phase 1 islanded ($/MWh) | B6: =StructC!B11 -> 234.74444 | C6: =StructC!C11 -> 172.6 | D6: =StructC!D11 -> 73.433333
A7: Structure C - Phase 2 grid-connected ($/MWh) | B7: =StructC!B18 -> 103.62007 | C7: =StructC!C18 -> 91.458795 | D7: =StructC!D18 -> 72.052503
A9: H2 TEST - dual denominator
A10: Savings, P1 vs B all-in: (B-C1)/B | B10: =(B5-B6)/B5 -> -0.44176498 | C10: =(C5-C6)/C5 -> -0.060083171 | D10: =(D5-D6)/D5 -> 0.54898354
A11: Savings, P2 vs B all-in: (B-C2)/B | B11: =(B5-B7)/B5 -> 0.36358115 | C11: =(C5-C7)/C5 -> 0.43827387 | D11: =(D5-D7)/D5 -> 0.55746439
A12: Savings, P1 vs B PPA price only | B12: =(Inputs!$B$24-B6)/Inputs!$B$24 -> -2.3534921 | C12: =(Inputs!$B$24-C6)/Inputs!$B$24 -> -1.4657143 | D12: =(Inputs!$B$24-D6)/Inputs!$B$24 -> -0.049047619
A13: Savings, P2 vs B PPA price only | B13: =(Inputs!$B$24-B7)/Inputs!$B$24 -> -0.48028673 | C13: =(Inputs!$B$24-C7)/Inputs!$B$24 -> -0.30655421 | D13: =(Inputs!$B$24-D7)/Inputs!$B$24 -> -0.029321476
A14: H2 (20-35%) met on all-in basis, Phase 1? | B14: =IF(B10>=0.2,"YES","NO") -> NO | C14: =IF(C10>=0.2,"YES","NO") -> NO | D14: =IF(D10>=0.2,"YES","NO") -> YES
A16: READING
A17: The vs-PPA-price-only rows will show negative 'savings' for low-coverage configs (solar) because backup cost dominates - this is why the all-in denominator is the meaningful H2 test.
