Workbook

Sheet Inputs
A1: SPUR Preliminary Co-location Model v7 — per-configuration tabs
A2: Three yellow levers apply to ALL configurations simultaneously (keeps cross-config comparison consistent). Blue = editable. $ in millions.
A4: SCENARIO LEVERS (GLOBAL)
A5: Queue wait (mech. completion -> COD), years | B5: 4 | C5: Test 2/4/6/8 (LBNL Queued Up 2025: https://emp.lbl.gov/queues)
A6: ITC rate | B6: 0.3 | C6: 0% = OBBBA Scenario D (zero credit under EITHER credit type); 30% = full rate w/ PWA
A7: Credit type (1=ITC, 2=PTC) | B7: 1 | C7: Framework 2.3.5: run both; PTC uses full depreciable basis
A8: SHARED PARAMETERS
A9: PTC rate ($/MWh, full rate w/ PWA) | B9: 15 | C9: $0.015/kWh, 10-yr duration (Framework 2.3.4; inflation adjustment omitted)
A10: BESS delivery loss (RTE approx.) | B10: 0.01 | C10: Annual approximation of round-trip losses
A11: Debt interest rate | B11: 0.055 | C11: Framework 2.3.1: 5-7% range
A12: Debt tenor (years) | B12: 20 | C12: Framework 2.3.1
A13: Target DSCR (debt sizing) | B13: 1.35 | C13: Framework 2.7
A14: Max leverage (% of total capital) | B14: 0.55 | C14: Framework 2.3.1: 50-55%; binds when DSCR-sized debt exceeds it (wind, geothermal)
A15: Combined tax rate (fed + CA) | B15: 0.2984 | C15: 21% federal + 8.84% CA
A16: Tax equity pay rate (per $ benefit PV) | B16: 0.8 | C16: TE pays ~80c per $1 PV of ITC + PTC + MACRS shield
A17: MACRS PV discount rate | B17: 0.07 | C17: Assumption
A18: Grid hybrid PPA price ($/MWh) | B18: 72 | C18: LBNL Utility-Scale Solar (hybrid PPA levels): https://emp.lbl.gov/utility-scale-solar
A19: BTM PPA price ($/MWh) | B19: 60 | C19: ~17% discount, within 10-20% industry range (Framework 4.3)
A20: Asset management (% of revenue) | B20: 0.015 | C20: Framework 2.6
... A26: Developer cash share, post-flip | B26: 0.975 | C26: Framework 2.8.2

Sheet Configurations
A1: Configuration library — each parameter feeds its configuration's tabs directly
A3: Parameter | B3: Solar+BESS 100MW | C3: Wind+BESS 150MW | D3: Geothermal+BESS 100MW | E3: Source / note
A4: Capacity (MW) | B4: 100 | C4: 150 | D4: 100 | E4: Solar/Geothermal: Framework 2.2.1. Wind: 150 MW scale variant (user-specified)
A5: Capacity factor | B5: 0.275 | C5: 0.35 | D5: 0.9 | E5: Solar: CA midpoint. Wind: upper Tehachapi 30-35%. Geothermal: 90%+ Salton Sea/Imperial Valley (NREL ATB 2024: https://atb.nrel.gov/electricity/2024/technologies)
A6: Annual degradation | B6: 0.005 | C6: 0.002 | D6: 0 | E6: Framework 2.5.2 (geothermal ~0%)
A7: Availability | B7: 0.98 | C7: 0.96 | D7: 0.95 | E7: Framework 2.5.2
A8: Electrical losses | B8: 0.025 | C8: 0.025 | D8: 0.025 | E8: Framework 2.5.2
A9: Total CAPEX ($mm) | B9: 197 | C9: 321.4 | D9: 568.25 | E9: Solar: Framework 2.2.3. Wind: $1,350/kW x150 + BESS 75MW/300MWh @$1,250/kW + dev 4% + land + intercon. Geothermal: $5,000/kW x100 + BESS 25MW/50MWh + dev 4% + land + intercon (NREL ATB 2024 midpoints)
A10: Qualified investment ($mm) | B10: 180 | C10: 296.25 | D10: 531.25 | E10: Generation + BESS only (Framework 2.2.4)
A11: Microgrid CAPEX ($mm) | B11: 12 | C11: 18 | D11: 12 | E11: $120/kW midpoint of $50-150/kW x capacity
A12: Fixed O&M, gen + BESS ($mm/yr) | B12: 3 | C12: 6.375 | D12: 4.625 | E12: Framework 2.6 midpoints per configuration
A13: Land lease + insurance ($mm/yr) | B13: 1.088 | C13: 1.586 | D13: 2.573 | E13: $0.3mm land + 0.4% of CAPEX insurance
A14: Microgrid O&M ($mm/yr) | B14: 0.75 | C14: 1.125 | D14: 0.75 | E14: $7.5/kW-yr x capacity
A15: Operating life (years) | B15: 25 | C15: 25 | D15: 30 | E15: Framework 2.1: 25 yrs solar/wind, 30 yrs geothermal
A18: Notes: (1) Model finds ITC > PTC for all three configurations at these parameters — for geothermal this contradicts Framework 2.3.5's
A19: expectation; sensitive to the omitted PTC inflation adjustment and the 7% discount on the PTC stream. (2) Geothermal faces no near-term
A20: OBBBA deadline (phaseout from 2034), so the 0% ITC scenario is a stress test rather than a live policy risk for that configuration.

Sheet Capitalization
A1: Capitalization — debt = MIN(DSCR-sized, max leverage x capital); tax equity sized to ITC/PTC + MACRS shield
B3: Solar Base | C3: Solar Coloc | D3: Wind Base | E3: Wind Coloc | F3: Geo Base | G3: Geo Coloc
A4: Total capital required ($mm) | B4: =Configurations!$B$9 -> 197 | C4: =Configurations!$B$9+Configurations!$B$11 -> 209 | D4: =Configurations!$C$9 -> 321.4 | E4: =Configurations!$C$9+Configurations!$C$11 -> 339.4 | F4: =Configurations!$D$9 -> 568.25 | G4: =Configurations!$D$9+Configurations!$D$11 -> 580.25
A5: First grid-year net energy (MWh) | B5: =Configurations!$B$4*Configurations!$B$5*8760*Configurations!$B$7*(1-Configurations!$B$8) -> 230179.95 | C5: =Configurations!$B$4*Configurations!$B$5*8760*Configurations!$B$7*(1-Configurations!$B$8) -> 230179.95 | D5: =Configurations!$C$4*Configurations!$C$5*8760*Configurations!$C$7*(1-Configurations!$C$8) -> 430466.4 | E5: =Configurations!$C$4*Configurations!$C$5*8760*Configurations!$C$7*(1-Configurations!$C$8) -> 430466.4 | F5: =Configurations!$D$4*Configurations!$D$5*8760*Configurations!$D$7*(1-Configurations!$D$8) -> 730255.5 | G5: =Configurations!$D$4*Configurations!$D$5*8760*Configurations!$D$7*(1-Configurations!$D$8) -> 730255.5
A6: First grid-year revenue ($mm) | B6: =B5*Inputs!$B$18/1000000 -> 16.572956 | C6: =C5*Inputs!$B$18/1000000 -> 16.572956 | D6: =D5*Inputs!$B$18/1000000 -> 30.993581 | E6: =E5*Inputs!$B$18/1000000 -> 30.993581 | F6: =F5*Inputs!$B$18/1000000 -> 52.578396 | G6: =G5*Inputs!$B$18/1000000 -> 52.578396
A7: First grid-year OPEX ($mm) | B7: =Configurations!$B$12+Configurations!$B$13+Inputs!$B$20*B6 -> 4.3365943 | C7: =Configurations!$B$12+Configurations!$B$13+Configurations!$B$14+Inputs!$B$20*C6 -> 5.0865943 | D7: =Configurations!$C$12+Configurations!$C$13+Inputs!$B$20*D6 -> 8.4259037 | E7: =Configurations!$C$12+Configurations!$C$13+Configurations!$C$14+Inputs!$B$20*E6 -> 9.5509037 | F7: =Configurations!$D$12+Configurations!$D$13+Inputs!$B$20*F6 -> 7.9866759 | G7: =Configurations!$D$12+Configurations!$D$13+Configurations!$D$14+Inputs!$B$20*G6 -> 8.7366759
A8: First grid-year EBITDA ($mm) | B8: =B6-B7 -> 12.236362 | C8: =C6-C7 -> 11.486362 | D8: =D6-D7 -> 22.567677 | E8: =E6-E7 -> 21.442677 | F8: =F6-F7 -> 44.59172 | G8: =G6-G7 -> 43.84172
A9: Max debt service @ DSCR ($mm/yr) | B9: =B8/Inputs!$B$13 -> 9.0639719 | C9: =C8/Inputs!$B$13 -> 8.5084163 | D9: =D8/Inputs!$B$13 -> 16.716798 | E9: =E8/Inputs!$B$13 -> 15.883465 | F9: =F8/Inputs!$B$13 -> 33.030904 | G9: =G8/Inputs!$B$13 -> 32.475348
A10: DSCR-sized debt ($mm) | B10: =B9*(1-(1+Inputs!$B$11)^-Inputs!$B$12)/Inputs!$B$11 -> 108.31793 | C10: =C9*(1-(1+Inputs!$B$11)^-Inputs!$B$12)/Inputs!$B$11 -> 101.67883 | D10: =D9*(1-(1+Inputs!$B$11)^-Inputs!$B$12)/Inputs!$B$11 -> 199.77213 | E10: =E9*(1-(1+Inputs!$B$11)^-Inputs!$B$12)/Inputs!$B$11 -> 189.81348 | F10: =F9*(1-(1+Inputs!$B$11)^-Inputs!$B$12)/Inputs!$B$11 -> 394.73193 | G10: =G9*(1-(1+Inputs!$B$11)^-Inputs!$B$12)/Inputs!$B$11 -> 388.09283
A11: Senior debt after leverage cap ($mm) | B11: =MIN(B10,Inputs!$B$14*B4) -> 108.31793 | C11: =MIN(C10,Inputs!$B$14*C4) -> 101.67883 | D11: =MIN(D10,Inputs!$B$14*D4) -> 176.77 | E11: =MIN(E10,Inputs!$B$14*E4) -> 186.67 | F11: =MIN(F10,Inputs!$B$14*F4) -> 312.5375 | G11: =MIN(G10,Inputs!$B$14*G4) -> 319.1375
A12: Actual debt service ($mm/yr) | B12: =B11/((1-(1+Inputs!$B$11)^-Inputs!$B$12)/Inputs!$B$11) -> 9.0639719 | C12: =C11/((1-(1+Inputs!$B$11)^-Inputs!$B$12)/Inputs!$B$11) -> 8.5084163 | D12: =D11/((1-(1+Inputs!$B$11)^-Inputs!$B$12)/Inputs!$B$11) -> 14.791995 | E12: =E11/((1-(1+Inputs!$B$11)^-Inputs!$B$12)/Inputs!$B$11) -> 15.620421 | F12: =F11/((1-(1+Inputs!$B$11)^-Inputs!$B$12)/Inputs!$B$11) -> 26.152929 | G12: =G11/((1-(1+Inputs!$B$11)^-Inputs!$B$12)/Inputs!$B$11) -> 26.705212
A13: ITC amount ($mm) | B13: =IF(Inputs!$B$7=1,Configurations!$B$10*Inputs!$B$6,0) -> 54 | C13: =IF(Inputs!$B$7=1,Configurations!$B$10*Inputs!$B$6,0) -> 54 | D13: =IF(Inputs!$B$7=1,Configurations!$C$10*Inputs!$B$6,0) -> 88.875 | E13: =IF(Inputs!$B$7=1,Configurations!$C$10*Inputs!$B$6,0) -> 88.875 | F13: =IF(Inputs!$B$7=1,Configurations!$D$10*Inputs!$B$6,0) -> 159.375 | G13: =IF(Inputs!$B$7=1,Configurations!$D$10*Inputs!$B$6,0) -> 159.375
A14: PTC start year (calendar) | B14: =Inputs!$B$21+Inputs!$B$5+1 -> 7 | C14: =Inputs!$B$21+1 -> 3 | D14: =Inputs!$B$21+Inputs!$B$5+1 -> 7 | E14: =Inputs!$B$21+1 -> 3 | F14: =Inputs!$B$21+Inputs!$B$5+1 -> 7 | G14: =Inputs!$B$21+1 -> 3
A15: PTC stream PV ($mm) | B15: =IF(Inputs!$B$7=2,B5*Inputs!$B$9/1000000*(1-(1+Inputs!$B$17)^-10)/Inputs!$B$17/(1+Inputs!$B$17)^(B14-1),0) -> 0 | C15: =IF(Inputs!$B$7=2,C5*Inputs!$B$9/1000000*(1-(1+Inputs!$B$17)^-10)/Inputs!$B$17/(1+Inputs!$B$17)^(C14-1),0) -> 0 | D15: =IF(Inputs!$B$7=2,D5*Inputs!$B$9/1000000*(1-(1+Inputs!$B$17)^-10)/Inputs!$B$17/(1+Inputs!$B$17)^(D14-1),0) -> 0 | E15: =IF(Inputs!$B$7=2,E5*Inputs!$B$9/1000000*(1-(1+Inputs!$B$17)^-10)/Inputs!$B$17/(1+Inputs!$B$17)^(E14-1),0) -> 0 | F15: =IF(Inputs!$B$7=2,F5*Inputs!$B$9/1000000*(1-(1+Inputs!$B$17)^-10)/Inputs!$B$17/(1+Inputs!$B$17)^(F14-1),0) -> 0 | G15: =IF(Inputs!$B$7=2,G5*Inputs!$B$9/1000000*(1-(1+Inputs!$B$17)^-10)/Inputs!$B$17/(1+Inputs!$B$17)^(G14-1),0) -> 0
A16: Depreciable basis ($mm) | B16: =IF(Inputs!$B$7=1,Configurations!$B$10-0.5*B13,Configurations!$B$10) -> 153 | C16: =IF(Inputs!$B$7=1,Configurations!$B$10-0.5*C13,Configurations!$B$10) -> 153 | D16: =IF(Inputs!$B$7=1,Configurations!$C$10-0.5*D13,Configurations!$C$10) -> 251.8125 | E16: =IF(Inputs!$B$7=1,Configurations!$C$10-0.5*E13,Configurations!$C$10) -> 251.8125 | F16: =IF(Inputs!$B$7=1,Configurations!$D$10-0.5*F13,Configurations!$D$10) -> 451.5625 | G16: =IF(Inputs!$B$7=1,Configurations!$D$10-0.5*G13,Configurations!$D$10) -> 451.5625
A17: MACRS shield PV ($mm) | B17: =SUMPRODUCT($B$25:$B$30,B16*Inputs!$B$15/(1+Inputs!$B$17)^ROW(INDIRECT("1:6"))) -> 37.964505 | C17: =SUMPRODUCT($B$25:$B$30,C16*Inputs!$B$15/(1+Inputs!$B$17)^ROW(INDIRECT("1:6"))) -> 37.964505 | D17: =SUMPRODUCT($B$25:$B$30,D16*Inputs!$B$15/(1+Inputs!$B$17)^ROW(INDIRECT("1:6"))) -> 62.483248 | E17: =SUMPRODUCT($B$25:$B$30,E16*Inputs!$B$15/(1+Inputs!$B$17)^ROW(INDIRECT("1:6"))) -> 62.483248 | F17: =SUMPRODUCT($B$25:$B$30,F16*Inputs!$B$15/(1+Inputs!$B$17)^ROW(INDIRECT("1:6"))) -> 112.04802 | G17: =SUMPRODUCT($B$25:$B$30,G16*Inputs!$B$15/(1+Inputs!$B$17)^ROW(INDIRECT("1:6"))) -> 112.04802
A18: Tax equity contribution ($mm) | B18: =IF(Inputs!$B$6=0,0,Inputs!$B$16*(B13+B15+B17)) -> 73.571604 | C18: =IF(Inputs!$B$6=0,0,Inputs!$B$16*(C13+C15+C17)) -> 73.571604 | D18: =IF(Inputs!$B$6=0,0,Inputs!$B$16*(D13+D15+D17)) -> 121.0866 | E18: =IF(Inputs!$B$6=0,0,Inputs!$B$16*(E13+E15+E17)) -> 121.0866 | F18: =IF(Inputs!$B$6=0,0,Inputs!$B$16*(F13+F15+F17)) -> 217.13841 | G18: =IF(Inputs!$B$6=0,0,Inputs!$B$16*(G13+G15+G17)) -> 217.13841
A19: Developer equity ($mm) | B19: =B4-B11-B18 -> 15.110465 | C19: =C4-C11-C18 -> 33.749566 | D19: =D4-D11-D18 -> 23.543402 | E19: =E4-E11-E18 -> 31.643402 | F19: =F4-F11-F18 -> 38.574086 | G19: =G4-G11-G18 -> 43.974086
A21: PTC start assumption: baseline is not placed in service while idle (PTC begins at COD); co-location BTM operation is assumed
A22: to qualify as placed in service (PTC begins at mechanical completion). Open tax question — validate in practitioner interviews.
A24: MACRS 5-yr schedule (Framework 2.3.3)
A25: Year 1 | B25: 0.2
A26: Year 2 | B26: 0.32
A27: Year 3 | B27: 0.192
A28: Year 4 | B28: 0.1152
A29: Year 5 | B29: 0.1152
A30: Year 6 | B30: 0.0576

Sheet SolarBase
A1: SolarBase — annual cash flow waterfall ($mm)
A2: Developer levered IRR: | B2: =IRR(K5:K37) -> 0.040713705 | C2: Unlevered (project) IRR: | D2: =IRR(M5:M37) -> 0.0091238666 | E2: NPV of dev cash @ discount rate ($mm): | F2: =K5+NPV(Inputs!$B$24,K6:K37) -> -15.39658
A4: Year | B4: Phase | C4: Op yr | D4: Net energy (MWh) | E4: Revenue | F4: OPEX | G4: EBITDA | H4: Debt service | I4: Distributable cash | J4: Dev share | K4: Dev cash flow | L4: DSCR | M4: Project CF (unlevered)
A5: 0 | B5: =IF(A5=0,"Equity",IF(A5<=Inputs!$B$21,"Construction",IF(A5<=Inputs!$B$21+Inputs!$B$5,"Queue wait",IF(A5<=Inputs!$B$21+Configurations!$B$15,"Grid ops","—")))) -> Equity | C5: =IF(A5<=Inputs!$B$21,"",A5-Inputs!$B$21-1) | D5: =IF(OR(A5<=Inputs!$B$21,A5>Inputs!$B$21+Configurations!$B$15),0,Configurations!$B$4*Configurations!$B$5*8760*(1-Configurations!$B$6)^C5*Configurations!$B$7*(1-Configurations!$B$8)) -> 0 | E5: =IF(OR(A5<=Inputs!$B$21,A5>Inputs!$B$21+Configurations!$B$15),0,IF(A5<=Inputs!$B$21+Inputs!$B$5,0,D5*Inputs!$B$18/1000000)) -> 0 | F5: =IF(OR(A5<=Inputs!$B$21,A5>Inputs!$B$21+Configurations!$B$15),0,IF(A5<=Inputs!$B$21+Inputs!$B$5,Configurations!$B$13,Configurations!$B$12+Configurations!$B$13+Inputs!$B$20*E5)) -> 0 | G5: =E5-F5 -> 0 | H5: =IF(AND(A5>Inputs!$B$21,A5<=Inputs!$B$21+Inputs!$B$12),Capitalization!B$12,0) -> 0 | I5: =G5-H5 -> 0 | J5: =IF(A5<=Inputs!$B$21,"",IF(AND(A5<=Inputs!$B$22,Capitalization!B$18>0),Inputs!$B$25,Inputs!$B$26)) | K5: =IF(A5=0,-Capitalization!B$19,IF(A5<=Inputs!$B$21,0,I5*J5-IF(AND(A5=Inputs!$B$22,Capitalization!B$18>0),Inputs!$B$23,0))) -> -15.110465 | L5: =IF(H5>0,G5/H5,"") | M5: =IF(A5=0,-Capitalization!B$4,IF(A5<=Inputs!$B$21,0,G5)) -> -197
A6: 1 | B6: =IF(A6=0,"Equity",IF(A6<=Inputs!$B$21,"Construction",IF(A6<=Inputs!$B$21+Inputs!$B$5,"Queue wait",IF(A6<=Inputs!$B$21+Configurations!$B$15,"Grid ops","—")))) -> Construction | C6: =IF(A6<=Inputs!$B$21,"",A6-Inputs!$B$21-1) | D6: =IF(OR(A6<=Inputs!$B$21,A6>Inputs!$B$21+Configurations!$B$15),0,Configurations!$B$4*Configurations!$B$5*8760*(1-Configurations!$B$6)^C6*Configurations!$B$7*(1-Configurations!$B$8)) -> 0 | E6: =IF(OR(A6<=Inputs!$B$21,A6>Inputs!$B$21+Configurations!$B$15),0,IF(A6<=Inputs!$B$21+Inputs!$B$5,0,D6*Inputs!$B$18/1000000)) -> 0 | F6: =IF(OR(A6<=Inputs!$B$21,A6>Inputs!$B$21+Configurations!$B$15),0,IF(A6<=Inputs!$B$21+Inputs!$B$5,Configurations!$B$13,Configurations!$B$12+Configurations!$B$13+Inputs!$B$20*E6)) -> 0 | G6: =E6-F6 -> 0 | H6: =IF(AND(A6>Inputs!$B$21,A6<=Inputs!$B$21+Inputs!$B$12),Capitalization!B$12,0) -> 0 | I6: =G6-H6 -> 0 | J6: =IF(A6<=Inputs!$B$21,"",IF(AND(A6<=Inputs!$B$22,Capitalization!B$18>0),Inputs!$B$25,Inputs!$B$26)) | K6: =IF(A6=0,-Capitalization!B$19,IF(A6<=Inputs!$B$21,0,I6*J6-IF(AND(A6=Inputs!$B$22,Capitalization!B$18>0),Inputs!$B$23,0))) -> 0 | L6: =IF(H6>0,G6/H6,"") | M6: =IF(A6=0,-Capitalization!B$4,IF(A6<=Inputs!$B$21,0,G6)) -> 0
A7: 2 | B7: =IF(A7=0,"Equity",IF(A7<=Inputs!$B$21,"Construction",IF(A7<=Inputs!$B$21+Inputs!$B$5,"Queue wait",IF(A7<=Inputs!$B$21+Configurations!$B$15,"Grid ops","—")))) -> Construction | C7: =IF(A7<=Inputs!$B$21,"",A7-Inputs!$B$21-1) | D7: =IF(OR(A7<=Inputs!$B$21,A7>Inputs!$B$21+Configurations!$B$15),0,Configurations!$B$4*Configurations!$B$5*8760*(1-Configurations!$B$6)^C7*Configurations!$B$7*(1-Configurations!$B$8)) -> 0 | E7: =IF(OR(A7<=Inputs!$B$21,A7>Inputs!$B$21+Configurations!$B$15),0,IF(A7<=Inputs!$B$21+Inputs!$B$5,0,D7*Inputs!$B$18/1000000)) -> 0 | F7: =IF(OR(A7<=Inputs!$B$21,A7>Inputs!$B$21+Configurations!$B$15),0,IF(A7<=Inputs!$B$21+Inputs!$B$5,Configurations!$B$13,Configurations!$B$12+Configurations!$B$13+Inputs!$B$20*E7)) -> 0 | G7: =E7-F7 -> 0 | H7: =IF(AND(A7>Inputs!$B$21,A7<=Inputs!$B$21+Inputs!$B$12),Capitalization!B$12,0) -> 0 | I7: =G7-H7 -> 0 | J7: =IF(A7<=Inputs!$B$21,"",IF(AND(A7<=Inputs!$B$22,Capitalization!B$18>0),Inputs!$B$25,Inputs!$B$26)) | K7: =IF(A7=0,-Capitalization!B$19,IF(A7<=Inputs!$B$21,0,I7*J7-IF(AND(A7=Inputs!$B$22,Capitalization!B$18>0),Inputs!$B$23,0))) -> 0 | L7: =IF(H7>0,G7/H7,"") | M7: =IF(A7=0,-Capitalization!B$4,IF(A7<=Inputs!$B$21,0,G7)) -> 0
A8: 3 | B8: =IF(A8=0,"Equity",IF(A8<=Inputs!$B$21,"Construction",IF(A8<=Inputs!$B$21+Inputs!$B$5,"Queue wait",IF(A8<=Inputs!$B$21+Configurations!$B$15,"Grid ops","—")))) -> Queue wait | C8: =IF(A8<=Inputs!$B$21,"",A8-Inputs!$B$21-1) -> 0 | D8: =IF(OR(A8<=Inputs!$B$21,A8>Inputs!$B$21+Configurations!$B$15),0,Configurations!$B$4*Configurations!$B$5*8760*(1-Configurations!$B$6)^C8*Configurations!$B$7*(1-Configurations!$B$8)) -> 230179.95 | E8: =IF(OR(A8<=Inputs!$B$21,A8>Inputs!$B$21+Configurations!$B$15),0,IF(A8<=Inputs!$B$21+Inputs!$B$5,0,D8*Inputs!$B$18/1000000)) -> 0 | F8: =IF(OR(A8<=Inputs!$B$21,A8>Inputs!$B$21+Configurations!$B$15),0,IF(A8<=Inputs!$B$21+Inputs!$B$5,Configurations!$B$13,Configurations!$B$12+Configurations!$B$13+Inputs!$B$20*E8)) -> 1.088 | G8: =E8-F8 -> -1.088 | H8: =IF(AND(A8>Inputs!$B$21,A8<=Inputs!$B$21+Inputs!$B$12),Capitalization!B$12,0) -> 9.0639719 | I8: =G8-H8 -> -10.151972 | J8: =IF(A8<=Inputs!$B$21,"",IF(AND(A8<=Inputs!$B$22,Capitalization!B$18>0),Inputs!$B$25,Inputs!$B$26)) -> 0.7 | K8: =IF(A8=0,-Capitalization!B$19,IF(A8<=Inputs!$B$21,0,I8*J8-IF(AND(A8=Inputs!$B$22,Capitalization!B$18>0),Inputs!$B$23,0))) -> -7.1063803 | L8: =IF(H8>0,G8/H8,"") -> -0.12003568 | M8: =IF(A8=0,-Capitalization!B$4,IF(A8<=Inputs!$B$21,0,G8)) -> -1.088
A9: 4 | B9: =IF(A9=0,"Equity",IF(A9<=Inputs!$B$21,"Construction",IF(A9<=Inputs!$B$21+Inputs!$B$5,"Queue wait",IF(A9<=Inputs!$B$21+Configurations!$B$15,"Grid ops","—")))) -> Queue wait | C9: =IF(A9<=Inputs!$B$21,"",A9-Inputs!$B$21-1) -> 1 | D9: =IF(OR(A9<=Inputs!$B$21,A9>Inputs!$B$21+Configurations!$B$15),0,Configurations!$B$4*Configurations!$B$5*8760*(1-Configurations!$B$6)^C9*Configurations!$B$7*(1-Configurations!$B$8)) -> 229029.05 | E9: =IF(OR(A9<=Inputs!$B$21,A9>Inputs!$B$21+Configurations!$B$15),0,IF(A9<=Inputs!$B$21+Inputs!$B$5,0,D9*Inputs!$B$18/1000000)) -> 0 | F9: =IF(OR(A9<=Inputs!$B$21,A9>Inputs!$B$21+Configurations!$B$15),0,IF(A9<=Inputs!$B$21+Inputs!$B$5,Configurations!$B$13,Configurations!$B$12+Configurations!$B$13+Inputs!$B$20*E9)) -> 1.088 | G9: =E9-F9 -> -1.088 | H9: =IF(AND(A9>Inputs!$B$21,A9<=Inputs!$B$21+Inputs!$B$12),Capitalization!B$12,0) -> 9.0639719 | I9: =G9-H9 -> -10.151972 | J9: =IF(A9<=Inputs!$B$21,"",IF(AND(A9<=Inputs!$B$22,Capitalization!B$18>0),Inputs!$B$25,Inputs!$B$26)) -> 0.7 | K9: =IF(A9=0,-Capitalization!B$19,IF(A9<=Inputs!$B$21,0,I9*J9-IF(AND(A9=Inputs!$B$22,Capitalization!B$18>0),Inputs!$B$23,0))) -> -7.1063803 | L9: =IF(H9>0,G9/H9,"") -> -0.12003568 | M9: =IF(A9=0,-Capitalization!B$4,IF(A9<=Inputs!$B$21,0,G9)) -> -1.088
A10: 5 | B10: =IF(A10=0,"Equity",IF(A10<=Inputs!$B$21,"Construction",IF(A10<=Inputs!$B$21+Inputs!$B$5,"Queue wait",IF(A10<=Inputs!$B$21+Configurations!$B$15,"Grid ops","—")))) -> Queue wait | C10: =IF(A10<=Inputs!$B$21,"",A10-Inputs!$B$21-1) -> 2 | D10: =IF(OR(A10<=Inputs!$B$21,A10>Inputs!$B$21+Configurations!$B$15),0,Configurations!$B$4*Configurations!$B$5*8760*(1-Configurations!$B$6)^C10*Configurations!$B$7*(1-Configurations!$B$8)) -> 227883.9 | E10: =IF(OR(A10<=Inputs!$B$21,A10>Inputs!$B$21+Configurations!$B$15),0,IF(A10<=Inputs!$B$21+Inputs!$B$5,0,D10*Inputs!$B$18/1000000)) -> 0 | F10: =IF(OR(A10<=Inputs!$B$21,A10>Inputs!$B$21+Configurations!$B$15),0,IF(A10<=Inputs!$B$21+Inputs!$B$5,Configurations!$B$13,Configurations!$B$12+Configurations!$B$13+Inputs!$B$20*E10)) -> 1.088 | G10: =E10-F10 -> -1.088 | H10: =IF(AND(A10>Inputs!$B$21,A10<=Inputs!$B$21+Inputs!$B$12),Capitalization!B$12,0) -> 9.0639719 | I10: =G10-H10 -> -10.151972 | J10: =IF(A10<=Inputs!$B$21,"",IF(AND(A10<=Inputs!$B$22,Capitalization!B$18>0),Inputs!$B$25,Inputs!$B$26)) -> 0.7 | K10: =IF(A10=0,-Capitalization!B$19,IF(A10<=Inputs!$B$21,0,I10*J10-IF(AND(A10=Inputs!$B$22,Capitalization!B$18>0),Inputs!$B$23,0))) -> -7.1063803 | L10: =IF(H10>0,G10/H10,"") -> -0.12003568 | M10: =IF(A10=0,-Capitalization!B$4,IF(A10<=Inputs!$B$21,0,G10)) -> -1.088
A11: 6 | B11: =IF(A11=0,"Equity",IF(A11<=Inputs!$B$21,"Construction",IF(A11<=Inputs!$B$21+Inputs!$B$5,"Queue wait",IF(A11<=Inputs!$B$21+Configurations!$B$15,"Grid ops","—")))) -> Queue wait | C11: =IF(A11<=Inputs!$B$21,"",A11-Inputs!$B$21-1) -> 3 | D11: =IF(OR(A11<=Inputs!$B$21,A11>Inputs!$B$21+Configurations!$B$15),0,Configurations!$B$4*Configurations!$B$5*8760*(1-Configurations!$B$6)^C11*Configurations!$B$7*(1-Configurations!$B$8)) -> 226744.49 | E11: =IF(OR(A11<=Inputs!$B$21,A11>Inputs!$B$21+Configurations!$B$15),0,IF(A11<=Inputs!$B$21+Inputs!$B$5,0,D11*Inputs!$B$18/1000000)) -> 0 | F11: =IF(OR(A11<=Inputs!$B$21,A11>Inputs!$B$21+Configurations!$B$15),0,IF(A11<=Inputs!$B$21+Inputs!$B$5,Configurations!$B$13,Configurations!$B$12+Configurations!$B$13+Inputs!$B$20*E11)) -> 1.088 | G11: =E11-F11 -> -1.088 | H11: =IF(AND(A11>Inputs!$B$21,A11<=Inputs!$B$21+Inputs!$B$12),Capitalization!B$12,0) -> 9.0639719 | I11: =G11-H11 -> -10.151972 | J11: =IF(A11<=Inputs!$B$21,"",IF(AND(A11<=Inputs!$B$22,Capitalization!B$18>0),Inputs!$B$25,Inputs!$B$26)) -> 0.7 | K11: =IF(A11=0,-Capitalization!B$19,IF(A11<=Inputs!$B$21,0,I11*J11-IF(AND(A11=Inputs!$B$22,Capitalization!B$18>0),Inputs!$B$23,0))) -> -8.1063803 | L11: =IF(H11>0,G11/H11,"") -> -0.12003568 | M11: =IF(A11=0,-Capitalization!B$4,IF(A11<=Inputs!$B$21,0,G11)) -> -1.088
A12: 7 | B12: =IF(A12=0,"Equity",IF(A12<=Inputs!$B$21,"Construction",IF(A12<=Inputs!$B$21+Inputs!$B$5,"Queue wait",IF(A12<=Inputs!$B$21+Configurations!$B$15,"Grid ops","—")))) -> Grid ops | C12: =IF(A12<=Inputs!$B$21,"",A12-Inputs!$B$21-1) -> 4 | D12: =IF(OR(A12<=Inputs!$B$21,A12>Inputs!$B$21+Configurations!$B$15),0,Configurations!$B$4*Configurations!$B$5*8760*(1-Configurations!$B$6)^C12*Configurations!$B$7*(1-Configurations!$B$8)) -> 225610.76 | E12: =IF(OR(A12<=Inputs!$B$21,A12>Inputs!$B$21+Configurations!$B$15),0,IF(A12<=Inputs!$B$21+Inputs!$B$5,0,D12*Inputs!$B$18/1000000)) -> 16.243975 | F12: =IF(OR(A12<=Inputs!$B$21,A12>Inputs!$B$21+Configurations!$B$15),0,IF(A12<=Inputs!$B$21+Inputs!$B$5,Configurations!$B$13,Configurations!$B$12+Configurations!$B$13+Inputs!$B$20*E12)) -> 4.3316596 | G12: =E12-F12 -> 11.912315 | H12: =IF(AND(A12>Inputs!$B$21,A12<=Inputs!$B$21+Inputs!$B$12),Capitalization!B$12,0) -> 9.0639719 | I12: =G12-H12 -> 2.8483434 | J12: =IF(A12<=Inputs!$B$21,"",IF(AND(A12<=Inputs!$B$22,Capitalization!B$18>0),Inputs!$B$25,Inputs!$B$26)) -> 0.975 | K12: =IF(A12=0,-Capitalization!B$19,IF(A12<=Inputs!$B$21,0,I12*J12-IF(AND(A12=Inputs!$B$22,Capitalization!B$18>0),Inputs!$B$23,0))) -> 2.7771348 | L12: =IF(H12>0,G12/H12,"") -> 1.3142489 | M12: =IF(A12=0,-Capitalization!B$4,IF(A12<=Inputs!$B$21,0,G12)) -> 11.912315
A13: 8 | B13: =IF(A13=0,"Equity",IF(A13<=Inputs!$B$21,"Construction",IF(A13<=Inputs!$B$21+Inputs!$B$5,"Queue wait",IF(A13<=Inputs!$B$21+Configurations!$B$15,"Grid ops","—")))) -> Grid ops | C13: =IF(A13<=Inputs!$B$21,"",A13-Inputs!$B$21-1) -> 5 | D13: =IF(OR(A13<=Inputs!$B$21,A13>Inputs!$B$21+Configurations!$B$15),0,Configurations!$B$4*Configurations!$B$5*8760*(1-Configurations!$B$6)^C13*Configurations!$B$7*(1-Configurations!$B$8)) -> 224482.71 | E13: =IF(OR(A13<=Inputs!$B$21,A13>Inputs!$B$21+Configurations!$B$15),0,IF(A13<=Inputs!$B$21+Inputs!$B$5,0,D13*Inputs!$B$18/1000000)) -> 16.162755 | F13: =IF(OR(A13<=Inputs!$B$21,A13>Inputs!$B$21+Configurations!$B$15),0,IF(A13<=Inputs!$B$21+Inputs!$B$5,Configurations!$B$13,Configurations!$B$12+Configurations!$B$13+Inputs!$B$20*E13)) -> 4.3304413 | G13: =E13-F13 -> 11.832314 | H13: =IF(AND(A13>Inputs!$B$21,A13<=Inputs!$B$21+Inputs!$B$12),Capitalization!B$12,0) -> 9.0639719 | I13: =G13-H13 -> 2.7683418 | J13: =IF(A13<=Inputs!$B$21,"",IF(AND(A13<=Inputs!$B$22,Capitalization!B$18>0),Inputs!$B$25,Inputs!$B$26)) -> 0.975 | K13: =IF(A13=0,-Capitalization!B$19,IF(A13<=Inputs!$B$21,0,I13*J13-IF(AND(A13=Inputs!$B$22,Capitalization!B$18>0),Inputs!$B$23,0))) -> 2.6991333 | L13: =IF(H13>0,G13/H13,"") -> 1.3054226 | M13: =IF(A13=0,-Capitalization!B$4,IF(A13<=Inputs!$B$21,0,G13)) -> 11.832314
A14: 9 | B14: =IF(A14=0,"Equity",IF(A14<=Inputs!$B$21,"Construction",IF(A14<=Inputs!$B$21+Inputs!$B$5,"Queue wait",IF(A14<=Inputs!$B$21+Configurations!$B$15,"Grid ops","—")))) -> Grid ops | C14: =IF(A14<=Inputs!$B$21,"",A14-Inputs!$B$21-1) -> 6 | D14: =IF(OR(A14<=Inputs!$B$21,A14>Inputs!$B$21+Configurations!$B$15),0,Configurations!$B$4*Configurations!$B$5*8760*(1-Configurations!$B$6)^C14*Configurations!$B$7*(1-Configurations!$B$8)) -> 223360.3 | E14: =IF(OR(A14<=Inputs!$B$21,A14>Inputs!$B$21+Configurations!$B$15),0,IF(A14<=Inputs!$B$21+Inputs!$B$5,0,D14*Inputs!$B$18/1000000)) -> 16.081941 | F14: =IF(OR(A14<=Inputs!$B$21,A14>Inputs!$B$21+Configurations!$B$15),0,IF(A14<=Inputs!$B$21+Inputs!$B$5,Configurations!$B$13,Configurations!$B$12+Configurations!$B$13+Inputs!$B$20*E14)) -> 4.3292291 | G14: =E14-F14 -> 11.752712 | H14: =IF(AND(A14>Inputs!$B$21,A14<=Inputs!$B$21+Inputs!$B$12),Capitalization!B$12,0) -> 9.0639719 | I14: =G14-H14 -> 2.6887403 | J14: =IF(A14<=Inputs!$B$21,"",IF(AND(A14<=Inputs!$B$22,Capitalization!B$18>0),Inputs!$B$25,Inputs!$B$26)) -> 0.975 | K14: =IF(A14=0,-Capitalization!B$19,IF(A14<=Inputs!$B$21,0,I14*J14-IF(AND(A14=Inputs!$B$22,Capitalization!B$18>0),Inputs!$B$23,0))) -> 2.6215218 | L14: =IF(H14>0,G14/H14,"") -> 1.2966404 | M14: =IF(A14=0,-Capitalization!B$4,IF(A14<=Inputs!$B$21,0,G14)) -> 11.752712
A15: 10 | B15: =IF(A15=0,"Equity",IF(A15<=Inputs!$B$21,"Construction",IF(A15<=Inputs!$B$21+Inputs!$B$5,"Queue wait",IF(A15<=Inputs!$B$21+Configurations!$B$15,"Grid ops","—")))) -> Grid ops | C15: =IF(A15<=Inputs!$B$21,"",A15-Inputs!$B$21-1) -> 7 | D15: =IF(OR(A15<=Inputs!$B$21,A15>Inputs!$B$21+Configurations!$B$15),0,Configurations!$B$4*Configurations!$B$5*8760*(1-Configurations!$B$6)^C15*Configurations!$B$7*(1-Configurations!$B$8)) -> 222243.49 | E15: =IF(OR(A15<=Inputs!$B$21,A15>Inputs!$B$21+Configurations!$B$15),0,IF(A15<=Inputs!$B$21+Inputs!$B$5,0,D15*Inputs!$B$18/1000000)) -> 16.001532 | F15: =IF(OR(A15<=Inputs!$B$21,A15>Inputs!$B$21+Configurations!$B$15),0,IF(A15<=Inputs!$B$21+Inputs!$B$5,Configurations!$B$13,Configurations!$B$12+Configurations!$B$13+Inputs!$B$20*E15)) -> 4.328023 | G15: =E15-F15 -> 11.673509 | H15: =IF(AND(A15>Inputs!$B$21,A15<=Inputs!$B$21+Inputs!$B$12),Capitalization!B$12,0) -> 9.0639719 | I15: =G15-H15 -> 2.6095367 | J15: =IF(A15<=Inputs!$B$21,"",IF(AND(A15<=Inputs!$B$22,Capitalization!B$18>0),Inputs!$B$25,Inputs!$B$26)) -> 0.975 | K15: =IF(A15=0,-Capitalization!B$19,IF(A15<=Inputs!$B$21,0,I15*J15-IF(AND(A15=Inputs!$B$22,Capitalization!B$18>0),Inputs!$B$23,0))) -> 2.5442983 | L15: =IF(H15>0,G15/H15,"") -> 1.2879021 | M15: =IF(A15=0,-Capitalization!B$4,IF(A15<=Inputs!$B$21,0,G15)) -> 11.673509
A16: 11 | B16: =IF(A16=0,"Equity",IF(A16<=Inputs!$B$21,"Construction",IF(A16<=Inputs!$B$21+Inputs!$B$5,"Queue wait",IF(A16<=Inputs!$B$21+Configurations!$B$15,"Grid ops","—")))) -> Grid ops | C16: =IF(A16<=Inputs!$B$21,"",A16-Inputs!$B$21-1) -> 8 | D16: =IF(OR(A16<=Inputs!$B$21,A16>Inputs!$B$21+Configurations!$B$15),0,Configurations!$B$4*Configurations!$B$5*8760*(1-Configurations!$B$6)^C16*Configurations!$B$7*(1-Configurations!$B$8)) -> 221132.28 | E16: =IF(OR(A16<=Inputs!$B$21,A16>Inputs!$B$21+Configurations!$B$15),0,IF(A16<=Inputs!$B$21+Inputs!$B$5,0,D16*Inputs!$B$18/1000000)) -> 15.921524 | F16: =IF(OR(A16<=Inputs!$B$21,A16>Inputs!$B$21+Configurations!$B$15),0,IF(A16<=Inputs!$B$21+Inputs!$B$5,Configurations!$B$13,Configurations!$B$12+Configurations!$B$13+Inputs!$B$20*E16)) -> 4.3268229 | G16: =E16-F16 -> 11.594701 | H16: =IF(AND(A16>Inputs!$B$21,A16<=Inputs!$B$21+Inputs!$B$12),Capitalization!B$12,0) -> 9.0639719 | I16: =G16-H16 -> 2.5307292 | J16: =IF(A16<=Inputs!$B$21,"",IF(AND(A16<=Inputs!$B$22,Capitalization!B$18>0),Inputs!$B$25,Inputs!$B$26)) -> 0.975 | K16: =IF(A16=0,-Capitalization!B$19,IF(A16<=Inputs!$B$21,0,I16*J16-IF(AND(A16=Inputs!$B$22,Capitalization!B$18>0),Inputs!$B$23,0))) -> 2.4674609 | L16: =IF(H16>0,G16/H16,"") -> 1.2792075 | M16: =IF(A16=0,-Capitalization!B$4,IF(A16<=Inputs!$B$21,0,G16)) -> 11.594701
... A37: 32 | B37: =IF(A37=0,"Equity",IF(A37<=Inputs!$B$21,"Construction",IF(A37<=Inputs!$B$21+Inputs!$B$5,"Queue wait",IF(A37<=Inputs!$B$21+Configurations!$B$15,"Grid ops","—")))) -> — | C37: =IF(A37<=Inputs!$B$21,"",A37-Inputs!$B$21-1) -> 29 | D37: =IF(OR(A37<=Inputs!$B$21,A37>Inputs!$B$21+Configurations!$B$15),0,Configurations!$B$4*Configurations!$B$5*8760*(1-Configurations!$B$6)^C37*Configurations!$B$7*(1-Configurations!$B$8)) -> 0 | E37: =IF(OR(A37<=Inputs!$B$21,A37>Inputs!$B$21+Configurations!$B$15),0,IF(A37<=Inputs!$B$21+Inputs!$B$5,0,D37*Inputs!$B$18/1000000)) -> 0 | F37: =IF(OR(A37<=Inputs!$B$21,A37>Inputs!$B$21+Configurations!$B$15),0,IF(A37<=Inputs!$B$21+Inputs!$B$5,Configurations!$B$13,Configurations!$B$12+Configurations!$B$13+Inputs!$B$20*E37)) -> 0 | G37: =E37-F37 -> 0 | H37: =IF(AND(A37>Inputs!$B$21,A37<=Inputs!$B$21+Inputs!$B$12),Capitalization!B$12,0) -> 0 | I37: =G37-H37 -> 0 | J37: =IF(A37<=Inputs!$B$21,"",IF(AND(A37<=Inputs!$B$22,Capitalization!B$18>0),Inputs!$B$25,Inputs!$B$26)) -> 0.975 | K37: =IF(A37=0,-Capitalization!B$19,IF(A37<=Inputs!$B$21,0,I37*J37-IF(AND(A37=Inputs!$B$22,Capitalization!B$18>0),Inputs!$B$23,0))) -> 0 | L37: =IF(H37>0,G37/H37,"") | M37: =IF(A37=0,-Capitalization!B$4,IF(A37<=Inputs!$B$21,0,G37)) -> 0

Sheet SolarColoc
A1: SolarColoc — annual cash flow waterfall ($mm)
A2: Developer levered IRR: | B2: =IRR(K5:K37) -> 0.044070577 | C2: Unlevered (project) IRR: | D2: =IRR(M5:M37) -> 0.012821957 | E2: NPV of dev cash @ discount rate ($mm): | F2: =K5+NPV(Inputs!$B$24,K6:K37) -> -15.39725
A4: Year | B4: Phase | C4: Op yr | D4: Net energy (MWh) | E4: Revenue | F4: OPEX | G4: EBITDA | H4: Debt service | I4: Distributable cash | J4: Dev share | K4: Dev cash flow | L4: DSCR | M4: Project CF (unlevered)
A5: 0 | B5: =IF(A5=0,"Equity",IF(A5<=Inputs!$B$21,"Construction",IF(A5<=Inputs!$B$21+Inputs!$B$5,"Queue wait",IF(A5<=Inputs!$B$21+Configurations!$B$15,"Grid ops","—")))) -> Equity | C5: =IF(A5<=Inputs!$B$21,"",A5-Inputs!$B$21-1) | D5: =IF(OR(A5<=Inputs!$B$21,A5>Inputs!$B$21+Configurations!$B$15),0,Configurations!$B$4*Configurations!$B$5*8760*(1-Configurations!$B$6)^C5*Configurations!$B$7*(1-Configurations!$B$8)) -> 0 | E5: =IF(OR(A5<=Inputs!$B$21,A5>Inputs!$B$21+Configurations!$B$15),0,IF(A5<=Inputs!$B$21+Inputs!$B$5,D5*(1-Inputs!$B$10)*Inputs!$B$19/1000000,D5*Inputs!$B$18/1000000)) -> 0 | F5: =IF(OR(A5<=Inputs!$B$21,A5>Inputs!$B$21+Configurations!$B$15),0,Configurations!$B$12+Configurations!$B$13+Configurations!$B$14+Inputs!$B$20*E5) -> 0 | G5: =E5-F5 -> 0 | H5: =IF(AND(A5>Inputs!$B$21,A5<=Inputs!$B$21+Inputs!$B$12),Capitalization!C$12,0) -> 0 | I5: =G5-H5 -> 0 | J5: =IF(A5<=Inputs!$B$21,"",IF(AND(A5<=Inputs!$B$22,Capitalization!C$18>0),Inputs!$B$25,Inputs!$B$26)) | K5: =IF(A5=0,-Capitalization!C$19,IF(A5<=Inputs!$B$21,0,I5*J5-IF(AND(A5=Inputs!$B$22,Capitalization!C$18>0),Inputs!$B$23,0))) -> -33.749566 | L5: =IF(H5>0,G5/H5,"") | M5: =IF(A5=0,-Capitalization!C$4,IF(A5<=Inputs!$B$21,0,G5)) -> -209
A6: 1 | B6: =IF(A6=0,"Equity",IF(A6<=Inputs!$B$21,"Construction",IF(A6<=Inputs!$B$21+Inputs!$B$5,"Queue wait",IF(A6<=Inputs!$B$21+Configurations!$B$15,"Grid ops","—")))) -> Construction | C6: =IF(A6<=Inputs!$B$21,"",A6-Inputs!$B$21-1) | D6: =IF(OR(A6<=Inputs!$B$21,A6>Inputs!$B$21+Configurations!$B$15),0,Configurations!$B$4*Configurations!$B$5*8760*(1-Configurations!$B$6)^C6*Configurations!$B$7*(1-Configurations!$B$8)) -> 0 | E6: =IF(OR(A6<=Inputs!$B$21,A6>Inputs!$B$21+Configurations!$B$15),0,IF(A6<=Inputs!$B$21+Inputs!$B$5,D6*(1-Inputs!$B$10)*Inputs!$B$19/1000000,D6*Inputs!$B$18/1000000)) -> 0 | F6: =IF(OR(A6<=Inputs!$B$21,A6>Inputs!$B$21+Configurations!$B$15),0,Configurations!$B$12+Configurations!$B$13+Configurations!$B$14+Inputs!$B$20*E6) -> 0 | G6: =E6-F6 -> 0 | H6: =IF(AND(A6>Inputs!$B$21,A6<=Inputs!$B$21+Inputs!$B$12),Capitalization!C$12,0) -> 0 | I6: =G6-H6 -> 0 | J6: =IF(A6<=Inputs!$B$21,"",IF(AND(A6<=Inputs!$B$22,Capitalization!C$18>0),Inputs!$B$25,Inputs!$B$26)) | K6: =IF(A6=0,-Capitalization!C$19,IF(A6<=Inputs!$B$21,0,I6*J6-IF(AND(A6=Inputs!$B$22,Capitalization!C$18>0),Inputs!$B$23,0))) -> 0 | L6: =IF(H6>0,G6/H6,"") | M6: =IF(A6=0,-Capitalization!C$4,IF(A6<=Inputs!$B$21,0,G6)) -> 0
A7: 2 | B7: =IF(A7=0,"Equity",IF(A7<=Inputs!$B$21,"Construction",IF(A7<=Inputs!$B$21+Inputs!$B$5,"Queue wait",IF(A7<=Inputs!$B$21+Configurations!$B$15,"Grid ops","—")))) -> Construction | C7: =IF(A7<=Inputs!$B$21,"",A7-Inputs!$B$21-1) | D7: =IF(OR(A7<=Inputs!$B$21,A7>Inputs!$B$21+Configurations!$B$15),0,Configurations!$B$4*Configurations!$B$5*8760*(1-Configurations!$B$6)^C7*Configurations!$B$7*(1-Configurations!$B$8)) -> 0 | E7: =IF(OR(A7<=Inputs!$B$21,A7>Inputs!$B$21+Configurations!$B$15),0,IF(A7<=Inputs!$B$21+Inputs!$B$5,D7*(1-Inputs!$B$10)*Inputs!$B$19/1000000,D7*Inputs!$B$18/1000000)) -> 0 | F7: =IF(OR(A7<=Inputs!$B$21,A7>Inputs!$B$21+Configurations!$B$15),0,Configurations!$B$12+Configurations!$B$13+Configurations!$B$14+Inputs!$B$20*E7) -> 0 | G7: =E7-F7 -> 0 | H7: =IF(AND(A7>Inputs!$B$21,A7<=Inputs!$B$21+Inputs!$B$12),Capitalization!C$12,0) -> 0 | I7: =G7-H7 -> 0 | J7: =IF(A7<=Inputs!$B$21,"",IF(AND(A7<=Inputs!$B$22,Capitalization!C$18>0),Inputs!$B$25,Inputs!$B$26)) | K7: =IF(A7=0,-Capitalization!C$19,IF(A7<=Inputs!$B$21,0,I7*J7-IF(AND(A7=Inputs!$B$22,Capitalization!C$18>0),Inputs!$B$23,0))) -> 0 | L7: =IF(H7>0,G7/H7,"") | M7: =IF(A7=0,-Capitalization!C$4,IF(A7<=Inputs!$B$21,0,G7)) -> 0
A8: 3 | B8: =IF(A8=0,"Equity",IF(A8<=Inputs!$B$21,"Construction",IF(A8<=Inputs!$B$21+Inputs!$B$5,"Queue wait",IF(A8<=Inputs!$B$21+Configurations!$B$15,"Grid ops","—")))) -> Queue wait | C8: =IF(A8<=Inputs!$B$21,"",A8-Inputs!$B$21-1) -> 0 | D8: =IF(OR(A8<=Inputs!$B$21,A8>Inputs!$B$21+Configurations!$B$15),0,Configurations!$B$4*Configurations!$B$5*8760*(1-Configurations!$B$6)^C8*Configurations!$B$7*(1-Configurations!$B$8)) -> 230179.95 | E8: =IF(OR(A8<=Inputs!$B$21,A8>Inputs!$B$21+Configurations!$B$15),0,IF(A8<=Inputs!$B$21+Inputs!$B$5,D8*(1-Inputs!$B$10)*Inputs!$B$19/1000000,D8*Inputs!$B$18/1000000)) -> 13.672689 | F8: =IF(OR(A8<=Inputs!$B$21,A8>Inputs!$B$21+Configurations!$B$15),0,Configurations!$B$12+Configurations!$B$13+Configurations!$B$14+Inputs!$B$20*E8) -> 5.0430903 | G8: =E8-F8 -> 8.6295987 | H8: =IF(AND(A8>Inputs!$B$21,A8<=Inputs!$B$21+Inputs!$B$12),Capitalization!C$12,0) -> 8.5084163 | I8: =G8-H8 -> 0.12118236 | J8: =IF(A8<=Inputs!$B$21,"",IF(AND(A8<=Inputs!$B$22,Capitalization!C$18>0),Inputs!$B$25,Inputs!$B$26)) -> 0.7 | K8: =IF(A8=0,-Capitalization!C$19,IF(A8<=Inputs!$B$21,0,I8*J8-IF(AND(A8=Inputs!$B$22,Capitalization!C$18>0),Inputs!$B$23,0))) -> 0.084827651 | L8: =IF(H8>0,G8/H8,"") -> 1.0142426 | M8: =IF(A8=0,-Capitalization!C$4,IF(A8<=Inputs!$B$21,0,G8)) -> 8.6295987
A9: 4 | B9: =IF(A9=0,"Equity",IF(A9<=Inputs!$B$21,"Construction",IF(A9<=Inputs!$B$21+Inputs!$B$5,"Queue wait",IF(A9<=Inputs!$B$21+Configurations!$B$15,"Grid ops","—")))) -> Queue wait | C9: =IF(A9<=Inputs!$B$21,"",A9-Inputs!$B$21-1) -> 1 | D9: =IF(OR(A9<=Inputs!$B$21,A9>Inputs!$B$21+Configurations!$B$15),0,Configurations!$B$4*Configurations!$B$5*8760*(1-Configurations!$B$6)^C9*Configurations!$B$7*(1-Configurations!$B$8)) -> 229029.05 | E9: =IF(OR(A9<=Inputs!$B$21,A9>Inputs!$B$21+Configurations!$B$15),0,IF(A9<=Inputs!$B$21+Inputs!$B$5,D9*(1-Inputs!$B$10)*Inputs!$B$19/1000000,D9*Inputs!$B$18/1000000)) -> 13.604326 | F9: =IF(OR(A9<=Inputs!$B$21,A9>Inputs!$B$21+Configurations!$B$15),0,Configurations!$B$12+Configurations!$B$13+Configurations!$B$14+Inputs!$B$20*E9) -> 5.0420649 | G9: =E9-F9 -> 8.5622607 | H9: =IF(AND(A9>Inputs!$B$21,A9<=Inputs!$B$21+Inputs!$B$12),Capitalization!C$12,0) -> 8.5084163 | I9: =G9-H9 -> 0.053844365 | J9: =IF(A9<=Inputs!$B$21,"",IF(AND(A9<=Inputs!$B$22,Capitalization!C$18>0),Inputs!$B$25,Inputs!$B$26)) -> 0.7 | K9: =IF(A9=0,-Capitalization!C$19,IF(A9<=Inputs!$B$21,0,I9*J9-IF(AND(A9=Inputs!$B$22,Capitalization!C$18>0),Inputs!$B$23,0))) -> 0.037691055 | L9: =IF(H9>0,G9/H9,"") -> 1.0063284 | M9: =IF(A9=0,-Capitalization!C$4,IF(A9<=Inputs!$B$21,0,G9)) -> 8.5622607
A10: 5 | B10: =IF(A10=0,"Equity",IF(A10<=Inputs!$B$21,"Construction",IF(A10<=Inputs!$B$21+Inputs!$B$5,"Queue wait",IF(A10<=Inputs!$B$21+Configurations!$B$15,"Grid ops","—")))) -> Queue wait | C10: =IF(A10<=Inputs!$B$21,"",A10-Inputs!$B$21-1) -> 2 | D10: =IF(OR(A10<=Inputs!$B$21,A10>Inputs!$B$21+Configurations!$B$15),0,Configurations!$B$4*Configurations!$B$5*8760*(1-Configurations!$B$6)^C10*Configurations!$B$7*(1-Configurations!$B$8)) -> 227883.9 | E10: =IF(OR(A10<=Inputs!$B$21,A10>Inputs!$B$21+Configurations!$B$15),0,IF(A10<=Inputs!$B$21+Inputs!$B$5,D10*(1-Inputs!$B$10)*Inputs!$B$19/1000000,D10*Inputs!$B$18/1000000)) -> 13.536304 | F10: =IF(OR(A10<=Inputs!$B$21,A10>Inputs!$B$21+Configurations!$B$15),0,Configurations!$B$12+Configurations!$B$13+Configurations!$B$14+Inputs!$B$20*E10) -> 5.0410446 | G10: =E10-F10 -> 8.4952594 | H10: =IF(AND(A10>Inputs!$B$21,A10<=Inputs!$B$21+Inputs!$B$12),Capitalization!C$12,0) -> 8.5084163 | I10: =G10-H10 -> -0.013156939 | J10: =IF(A10<=Inputs!$B$21,"",IF(AND(A10<=Inputs!$B$22,Capitalization!C$18>0),Inputs!$B$25,Inputs!$B$26)) -> 0.7 | K10: =IF(A10=0,-Capitalization!C$19,IF(A10<=Inputs!$B$21,0,I10*J10-IF(AND(A10=Inputs!$B$22,Capitalization!C$18>0),Inputs!$B$23,0))) -> -0.0092098571 | L10: =IF(H10>0,G10/H10,"") -> 0.99845366 | M10: =IF(A10=0,-Capitalization!C$4,IF(A10<=Inputs!$B$21,0,G10)) -> 8.4952594
A11: 6 | B11: =IF(A11=0,"Equity",IF(A11<=Inputs!$B$21,"Construction",IF(A11<=Inputs!$B$21+Inputs!$B$5,"Queue wait",IF(A11<=Inputs!$B$21+Configurations!$B$15,"Grid ops","—")))) -> Queue wait | C11: =IF(A11<=Inputs!$B$21,"",A11-Inputs!$B$21-1) -> 3 | D11: =IF(OR(A11<=Inputs!$B$21,A11>Inputs!$B$21+Configurations!$B$15),0,Configurations!$B$4*Configurations!$B$5*8760*(1-Configurations!$B$6)^C11*Configurations!$B$7*(1-Configurations!$B$8)) -> 226744.49 | E11: =IF(OR(A11<=Inputs!$B$21,A11>Inputs!$B$21+Configurations!$B$15),0,IF(A11<=Inputs!$B$21+Inputs!$B$5,D11*(1-Inputs!$B$10)*Inputs!$B$19/1000000,D11*Inputs!$B$18/1000000)) -> 13.468622 | F11: =IF(OR(A11<=Inputs!$B$21,A11>Inputs!$B$21+Configurations!$B$15),0,Configurations!$B$12+Configurations!$B$13+Configurations!$B$14+Inputs!$B$20*E11) -> 5.0400293 | G11: =E11-F11 -> 8.4285931 | H11: =IF(AND(A11>Inputs!$B$21,A11<=Inputs!$B$21+Inputs!$B$12),Capitalization!C$12,0) -> 8.5084163 | I11: =G11-H11 -> -0.079823236 | J11: =IF(A11<=Inputs!$B$21,"",IF(AND(A11<=Inputs!$B$22,Capitalization!C$18>0),Inputs!$B$25,Inputs!$B$26)) -> 0.7 | K11: =IF(A11=0,-Capitalization!C$19,IF(A11<=Inputs!$B$21,0,I11*J11-IF(AND(A11=Inputs!$B$22,Capitalization!C$18>0),Inputs!$B$23,0))) -> -1.0558763 | L11: =IF(H11>0,G11/H11,"") -> 0.99061832 | M11: =IF(A11=0,-Capitalization!C$4,IF(A11<=Inputs!$B$21,0,G11)) -> 8.4285931
A12: 7 | B12: =IF(A12=0,"Equity",IF(A12<=Inputs!$B$21,"Construction",IF(A12<=Inputs!$B$21+Inputs!$B$5,"Queue wait",IF(A12<=Inputs!$B$21+Configurations!$B$15,"Grid ops","—")))) -> Grid ops | C12: =IF(A12<=Inputs!$B$21,"",A12-Inputs!$B$21-1) -> 4 | D12: =IF(OR(A12<=Inputs!$B$21,A12>Inputs!$B$21+Configurations!$B$15),0,Configurations!$B$4*Configurations!$B$5*8760*(1-Configurations!$B$6)^C12*Configurations!$B$7*(1-Configurations!$B$8)) -> 225610.76 | E12: =IF(OR(A12<=Inputs!$B$21,A12>Inputs!$B$21+Configurations!$B$15),0,IF(A12<=Inputs!$B$21+Inputs!$B$5,D12*(1-Inputs!$B$10)*Inputs!$B$19/1000000,D12*Inputs!$B$18/1000000)) -> 16.243975 | F12: =IF(OR(A12<=Inputs!$B$21,A12>Inputs!$B$21+Configurations!$B$15),0,Configurations!$B$12+Configurations!$B$13+Configurations!$B$14+Inputs!$B$20*E12) -> 5.0816596 | G12: =E12-F12 -> 11.162315 | H12: =IF(AND(A12>Inputs!$B$21,A12<=Inputs!$B$21+Inputs!$B$12),Capitalization!C$12,0) -> 8.5084163 | I12: =G12-H12 -> 2.653899 | J12: =IF(A12<=Inputs!$B$21,"",IF(AND(A12<=Inputs!$B$22,Capitalization!C$18>0),Inputs!$B$25,Inputs!$B$26)) -> 0.975 | K12: =IF(A12=0,-Capitalization!C$19,IF(A12<=Inputs!$B$21,0,I12*J12-IF(AND(A12=Inputs!$B$22,Capitalization!C$18>0),Inputs!$B$23,0))) -> 2.5875515 | L12: =IF(H12>0,G12/H12,"") -> 1.3119146 | M12: =IF(A12=0,-Capitalization!C$4,IF(A12<=Inputs!$B$21,0,G12)) -> 11.162315
A13: 8 | B13: =IF(A13=0,"Equity",IF(A13<=Inputs!$B$21,"Construction",IF(A13<=Inputs!$B$21+Inputs!$B$5,"Queue wait",IF(A13<=Inputs!$B$21+Configurations!$B$15,"Grid ops","—")))) -> Grid ops | C13: =IF(A13<=Inputs!$B$21,"",A13-Inputs!$B$21-1) -> 5 | D13: =IF(OR(A13<=Inputs!$B$21,A13>Inputs!$B$21+Configurations!$B$15),0,Configurations!$B$4*Configurations!$B$5*8760*(1-Configurations!$B$6)^C13*Configurations!$B$7*(1-Configurations!$B$8)) -> 224482.71 | E13: =IF(OR(A13<=Inputs!$B$21,A13>Inputs!$B$21+Configurations!$B$15),0,IF(A13<=Inputs!$B$21+Inputs!$B$5,D13*(1-Inputs!$B$10)*Inputs!$B$19/1000000,D13*Inputs!$B$18/1000000)) -> 16.162755 | F13: =IF(OR(A13<=Inputs!$B$21,A13>Inputs!$B$21+Configurations!$B$15),0,Configurations!$B$12+Configurations!$B$13+Configurations!$B$14+Inputs!$B$20*E13) -> 5.0804413 | G13: =E13-F13 -> 11.082314 | H13: =IF(AND(A13>Inputs!$B$21,A13<=Inputs!$B$21+Inputs!$B$12),Capitalization!C$12,0) -> 8.5084163 | I13: =G13-H13 -> 2.5738974 | J13: =IF(A13<=Inputs!$B$21,"",IF(AND(A13<=Inputs!$B$22,Capitalization!C$18>0),Inputs!$B$25,Inputs!$B$26)) -> 0.975 | K13: =IF(A13=0,-Capitalization!C$19,IF(A13<=Inputs!$B$21,0,I13*J13-IF(AND(A13=Inputs!$B$22,Capitalization!C$18>0),Inputs!$B$23,0))) -> 2.50955 | L13: =IF(H13>0,G13/H13,"") -> 1.3025119 | M13: =IF(A13=0,-Capitalization!C$4,IF(A13<=Inputs!$B$21,0,G13)) -> 11.082314
A14: 9 | B14: =IF(A14=0,"Equity",IF(A14<=Inputs!$B$21,"Construction",IF(A14<=Inputs!$B$21+Inputs!$B$5,"Queue wait",IF(A14<=Inputs!$B$21+Configurations!$B$15,"Grid ops","—")))) -> Grid ops | C14: =IF(A14<=Inputs!$B$21,"",A14-Inputs!$B$21-1) -> 6 | D14: =IF(OR(A14<=Inputs!$B$21,A14>Inputs!$B$21+Configurations!$B$15),0,Configurations!$B$4*Configurations!$B$5*8760*(1-Configurations!$B$6)^C14*Configurations!$B$7*(1-Configurations!$B$8)) -> 223360.3 | E14: =IF(OR(A14<=Inputs!$B$21,A14>Inputs!$B$21+Configurations!$B$15),0,IF(A14<=Inputs!$B$21+Inputs!$B$5,D14*(1-Inputs!$B$10)*Inputs!$B$19/1000000,D14*Inputs!$B$18/1000000)) -> 16.081941 | F14: =IF(OR(A14<=Inputs!$B$21,A14>Inputs!$B$21+Configurations!$B$15),0,Configurations!$B$12+Configurations!$B$13+Configurations!$B$14+Inputs!$B$20*E14) -> 5.0792291 | G14: =E14-F14 -> 11.002712 | H14: =IF(AND(A14>Inputs!$B$21,A14<=Inputs!$B$21+Inputs!$B$12),Capitalization!C$12,0) -> 8.5084163 | I14: =G14-H14 -> 2.4942958 | J14: =IF(A14<=Inputs!$B$21,"",IF(AND(A14<=Inputs!$B$22,Capitalization!C$18>0),Inputs!$B$25,Inputs!$B$26)) -> 0.975 | K14: =IF(A14=0,-Capitalization!C$19,IF(A14<=Inputs!$B$21,0,I14*J14-IF(AND(A14=Inputs!$B$22,Capitalization!C$18>0),Inputs!$B$23,0))) -> 2.4319384 | L14: =IF(H14>0,G14/H14,"") -> 1.2931563 | M14: =IF(A14=0,-Capitalization!C$4,IF(A14<=Inputs!$B$21,0,G14)) -> 11.002712
A15: 10 | B15: =IF(A15=0,"Equity",IF(A15<=Inputs!$B$21,"Construction",IF(A15<=Inputs!$B$21+Inputs!$B$5,"Queue wait",IF(A15<=Inputs!$B$21+Configurations!$B$15,"Grid ops","—")))) -> Grid ops | C15: =IF(A15<=Inputs!$B$21,"",A15-Inputs!$B$21-1) -> 7 | D15: =IF(OR(A15<=Inputs!$B$21,A15>Inputs!$B$21+Configurations!$B$15),0,Configurations!$B$4*Configurations!$B$5*8760*(1-Configurations!$B$6)^C15*Configurations!$B$7*(1-Configurations!$B$8)) -> 222243.49 | E15: =IF(OR(A15<=Inputs!$B$21,A15>Inputs!$B$21+Configurations!$B$15),0,IF(A15<=Inputs!$B$21+Inputs!$B$5,D15*(1-Inputs!$B$10)*Inputs!$B$19/1000000,D15*Inputs!$B$18/1000000)) -> 16.001532 | F15: =IF(OR(A15<=Inputs!$B$21,A15>Inputs!$B$21+Configurations!$B$15),0,Configurations!$B$12+Configurations!$B$13+Configurations!$B$14+Inputs!$B$20*E15) -> 5.078023 | G15: =E15-F15 -> 10.923509 | H15: =IF(AND(A15>Inputs!$B$21,A15<=Inputs!$B$21+Inputs!$B$12),Capitalization!C$12,0) -> 8.5084163 | I15: =G15-H15 -> 2.4150923 | J15: =IF(A15<=Inputs!$B$21,"",IF(AND(A15<=Inputs!$B$22,Capitalization!C$18>0),Inputs!$B$25,Inputs!$B$26)) -> 0.975 | K15: =IF(A15=0,-Capitalization!C$19,IF(A15<=Inputs!$B$21,0,I15*J15-IF(AND(A15=Inputs!$B$22,Capitalization!C$18>0),Inputs!$B$23,0))) -> 2.354715 | L15: =IF(H15>0,G15/H15,"") -> 1.2838474 | M15: =IF(A15=0,-Capitalization!C$4,IF(A15<=Inputs!$B$21,0,G15)) -> 10.923509
A16: 11 | B16: =IF(A16=0,"Equity",IF(A16<=Inputs!$B$21,"Construction",IF(A16<=Inputs!$B$21+Inputs!$B$5,"Queue wait",IF(A16<=Inputs!$B$21+Configurations!$B$15,"Grid ops","—")))) -> Grid ops | C16: =IF(A16<=Inputs!$B$21,"",A16-Inputs!$B$21-1) -> 8 | D16: =IF(OR(A16<=Inputs!$B$21,A16>Inputs!$B$21+Configurations!$B$15),0,Configurations!$B$4*Configurations!$B$5*8760*(1-Configurations!$B$6)^C16*Configurations!$B$7*(1-Configurations!$B$8)) -> 221132.28 | E16: =IF(OR(A16<=Inputs!$B$21,A16>Inputs!$B$21+Configurations!$B$15),0,IF(A16<=Inputs!$B$21+Inputs!$B$5,D16*(1-Inputs!$B$10)*Inputs!$B$19/1000000,D16*Inputs!$B$18/1000000)) -> 15.921524 | F16: =IF(OR(A16<=Inputs!$B$21,A16>Inputs!$B$21+Configurations!$B$15),0,Configurations!$B$12+Configurations!$B$13+Configurations!$B$14+Inputs!$B$20*E16) -> 5.0768229 | G16: =E16-F16 -> 10.844701 | H16: =IF(AND(A16>Inputs!$B$21,A16<=Inputs!$B$21+Inputs!$B$12),Capitalization!C$12,0) -> 8.5084163 | I16: =G16-H16 -> 2.3362847 | J16: =IF(A16<=Inputs!$B$21,"",IF(AND(A16<=Inputs!$B$22,Capitalization!C$18>0),Inputs!$B$25,Inputs!$B$26)) -> 0.975 | K16: =IF(A16=0,-Capitalization!C$19,IF(A16<=Inputs!$B$21,0,I16*J16-IF(AND(A16=Inputs!$B$22,Capitalization!C$18>0),Inputs!$B$23,0))) -> 2.2778776 | L16: =IF(H16>0,G16/H16,"") -> 1.2745851 | M16: =IF(A16=0,-Capitalization!C$4,IF(A16<=Inputs!$B$21,0,G16)) -> 10.844701
... A37: 32 | B37: =IF(A37=0,"Equity",IF(A37<=Inputs!$B$21,"Construction",IF(A37<=Inputs!$B$21+Inputs!$B$5,"Queue wait",IF(A37<=Inputs!$B$21+Configurations!$B$15,"Grid ops","—")))) -> — | C37: =IF(A37<=Inputs!$B$21,"",A37-Inputs!$B$21-1) -> 29 | D37: =IF(OR(A37<=Inputs!$B$21,A37>Inputs!$B$21+Configurations!$B$15),0,Configurations!$B$4*Configurations!$B$5*8760*(1-Configurations!$B$6)^C37*Configurations!$B$7*(1-Configurations!$B$8)) -> 0 | E37: =IF(OR(A37<=Inputs!$B$21,A37>Inputs!$B$21+Configurations!$B$15),0,IF(A37<=Inputs!$B$21+Inputs!$B$5,D37*(1-Inputs!$B$10)*Inputs!$B$19/1000000,D37*Inputs!$B$18/1000000)) -> 0 | F37: =IF(OR(A37<=Inputs!$B$21,A37>Inputs!$B$21+Configurations!$B$15),0,Configurations!$B$12+Configurations!$B$13+Configurations!$B$14+Inputs!$B$20*E37) -> 0 | G37: =E37-F37 -> 0 | H37: =IF(AND(A37>Inputs!$B$21,A37<=Inputs!$B$21+Inputs!$B$12),Capitalization!C$12,0) -> 0 | I37: =G37-H37 -> 0 | J37: =IF(A37<=Inputs!$B$21,"",IF(AND(A37<=Inputs!$B$22,Capitalization!C$18>0),Inputs!$B$25,Inputs!$B$26)) -> 0.975 | K37: =IF(A37=0,-Capitalization!C$19,IF(A37<=Inputs!$B$21,0,I37*J37-IF(AND(A37=Inputs!$B$22,Capitalization!C$18>0),Inputs!$B$23,0))) -> 0 | L37: =IF(H37>0,G37/H37,"") | M37: =IF(A37=0,-Capitalization!C$4,IF(A37<=Inputs!$B$21,0,G37)) -> 0

Sheet WindBase
A1: WindBase — annual cash flow waterfall ($mm)
A2: Developer levered IRR: | B2: =IRR(K5:K37) -> 0.076471682 | C2: Unlevered (project) IRR: | D2: =IRR(M5:M37) -> 0.02031468 | E2: NPV of dev cash @ discount rate ($mm): | F2: =K5+NPV(Inputs!$B$24,K6:K37) -> -2.4701198
A4: Year | B4: Phase | C4: Op yr | D4: Net energy (MWh) | E4: Revenue | F4: OPEX | G4: EBITDA | H4: Debt service | I4: Distributable cash | J4: Dev share | K4: Dev cash flow | L4: DSCR | M4: Project CF (unlevered)
A5: 0 | B5: =IF(A5=0,"Equity",IF(A5<=Inputs!$B$21,"Construction",IF(A5<=Inputs!$B$21+Inputs!$B$5,"Queue wait",IF(A5<=Inputs!$B$21+Configurations!$C$15,"Grid ops","—")))) -> Equity | C5: =IF(A5<=Inputs!$B$21,"",A5-Inputs!$B$21-1) | D5: =IF(OR(A5<=Inputs!$B$21,A5>Inputs!$B$21+Configurations!$C$15),0,Configurations!$C$4*Configurations!$C$5*8760*(1-Configurations!$C$6)^C5*Configurations!$C$7*(1-Configurations!$C$8)) -> 0 | E5: =IF(OR(A5<=Inputs!$B$21,A5>Inputs!$B$21+Configurations!$C$15),0,IF(A5<=Inputs!$B$21+Inputs!$B$5,0,D5*Inputs!$B$18/1000000)) -> 0 | F5: =IF(OR(A5<=Inputs!$B$21,A5>Inputs!$B$21+Configurations!$C$15),0,IF(A5<=Inputs!$B$21+Inputs!$B$5,Configurations!$C$13,Configurations!$C$12+Configurations!$C$13+Inputs!$B$20*E5)) -> 0 | G5: =E5-F5 -> 0 | H5: =IF(AND(A5>Inputs!$B$21,A5<=Inputs!$B$21+Inputs!$B$12),Capitalization!D$12,0) -> 0 | I5: =G5-H5 -> 0 | J5: =IF(A5<=Inputs!$B$21,"",IF(AND(A5<=Inputs!$B$22,Capitalization!D$18>0),Inputs!$B$25,Inputs!$B$26)) | K5: =IF(A5=0,-Capitalization!D$19,IF(A5<=Inputs!$B$21,0,I5*J5-IF(AND(A5=Inputs!$B$22,Capitalization!D$18>0),Inputs!$B$23,0))) -> -23.543402 | L5: =IF(H5>0,G5/H5,"") | M5: =IF(A5=0,-Capitalization!D$4,IF(A5<=Inputs!$B$21,0,G5)) -> -321.4
A6: 1 | B6: =IF(A6=0,"Equity",IF(A6<=Inputs!$B$21,"Construction",IF(A6<=Inputs!$B$21+Inputs!$B$5,"Queue wait",IF(A6<=Inputs!$B$21+Configurations!$C$15,"Grid ops","—")))) -> Construction | C6: =IF(A6<=Inputs!$B$21,"",A6-Inputs!$B$21-1) | D6: =IF(OR(A6<=Inputs!$B$21,A6>Inputs!$B$21+Configurations!$C$15),0,Configurations!$C$4*Configurations!$C$5*8760*(1-Configurations!$C$6)^C6*Configurations!$C$7*(1-Configurations!$C$8)) -> 0 | E6: =IF(OR(A6<=Inputs!$B$21,A6>Inputs!$B$21+Configurations!$C$15),0,IF(A6<=Inputs!$B$21+Inputs!$B$5,0,D6*Inputs!$B$18/1000000)) -> 0 | F6: =IF(OR(A6<=Inputs!$B$21,A6>Inputs!$B$21+Configurations!$C$15),0,IF(A6<=Inputs!$B$21+Inputs!$B$5,Configurations!$C$13,Configurations!$C$12+Configurations!$C$13+Inputs!$B$20*E6)) -> 0 | G6: =E6-F6 -> 0 | H6: =IF(AND(A6>Inputs!$B$21,A6<=Inputs!$B$21+Inputs!$B$12),Capitalization!D$12,0) -> 0 | I6: =G6-H6 -> 0 | J6: =IF(A6<=Inputs!$B$21,"",IF(AND(A6<=Inputs!$B$22,Capitalization!D$18>0),Inputs!$B$25,Inputs!$B$26)) | K6: =IF(A6=0,-Capitalization!D$19,IF(A6<=Inputs!$B$21,0,I6*J6-IF(AND(A6=Inputs!$B$22,Capitalization!D$18>0),Inputs!$B$23,0))) -> 0 | L6: =IF(H6>0,G6/H6,"") | M6: =IF(A6=0,-Capitalization!D$4,IF(A6<=Inputs!$B$21,0,G6)) -> 0
A7: 2 | B7: =IF(A7=0,"Equity",IF(A7<=Inputs!$B$21,"Construction",IF(A7<=Inputs!$B$21+Inputs!$B$5,"Queue wait",IF(A7<=Inputs!$B$21+Configurations!$C$15,"Grid ops","—")))) -> Construction | C7: =IF(A7<=Inputs!$B$21,"",A7-Inputs!$B$21-1) | D7: =IF(OR(A7<=Inputs!$B$21,A7>Inputs!$B$21+Configurations!$C$15),0,Configurations!$C$4*Configurations!$C$5*8760*(1-Configurations!$C$6)^C7*Configurations!$C$7*(1-Configurations!$C$8)) -> 0 | E7: =IF(OR(A7<=Inputs!$B$21,A7>Inputs!$B$21+Configurations!$C$15),0,IF(A7<=Inputs!$B$21+Inputs!$B$5,0,D7*Inputs!$B$18/1000000)) -> 0 | F7: =IF(OR(A7<=Inputs!$B$21,A7>Inputs!$B$21+Configurations!$C$15),0,IF(A7<=Inputs!$B$21+Inputs!$B$5,Configurations!$C$13,Configurations!$C$12+Configurations!$C$13+Inputs!$B$20*E7)) -> 0 | G7: =E7-F7 -> 0 | H7: =IF(AND(A7>Inputs!$B$21,A7<=Inputs!$B$21+Inputs!$B$12),Capitalization!D$12,0) -> 0 | I7: =G7-H7 -> 0 | J7: =IF(A7<=Inputs!$B$21,"",IF(AND(A7<=Inputs!$B$22,Capitalization!D$18>0),Inputs!$B$25,Inputs!$B$26)) | K7: =IF(A7=0,-Capitalization!D$19,IF(A7<=Inputs!$B$21,0,I7*J7-IF(AND(A7=Inputs!$B$22,Capitalization!D$18>0),Inputs!$B$23,0))) -> 0 | L7: =IF(H7>0,G7/H7,"") | M7: =IF(A7=0,-Capitalization!D$4,IF(A7<=Inputs!$B$21,0,G7)) -> 0
A8: 3 | B8: =IF(A8=0,"Equity",IF(A8<=Inputs!$B$21,"Construction",IF(A8<=Inputs!$B$21+Inputs!$B$5,"Queue wait",IF(A8<=Inputs!$B$21+Configurations!$C$15,"Grid ops","—")))) -> Queue wait | C8: =IF(A8<=Inputs!$B$21,"",A8-Inputs!$B$21-1) -> 0 | D8: =IF(OR(A8<=Inputs!$B$21,A8>Inputs!$B$21+Configurations!$C$15),0,Configurations!$C$4*Configurations!$C$5*8760*(1-Configurations!$C$6)^C8*Configurations!$C$7*(1-Configurations!$C$8)) -> 430466.4 | E8: =IF(OR(A8<=Inputs!$B$21,A8>Inputs!$B$21+Configurations!$C$15),0,IF(A8<=Inputs!$B$21+Inputs!$B$5,0,D8*Inputs!$B$18/1000000)) -> 0 | F8: =IF(OR(A8<=Inputs!$B$21,A8>Inputs!$B$21+Configurations!$C$15),0,IF(A8<=Inputs!$B$21+Inputs!$B$5,Configurations!$C$13,Configurations!$C$12+Configurations!$C$13+Inputs!$B$20*E8)) -> 1.586 | G8: =E8-F8 -> -1.586 | H8: =IF(AND(A8>Inputs!$B$21,A8<=Inputs!$B$21+Inputs!$B$12),Capitalization!D$12,0) -> 14.791995 | I8: =G8-H8 -> -16.377995 | J8: =IF(A8<=Inputs!$B$21,"",IF(AND(A8<=Inputs!$B$22,Capitalization!D$18>0),Inputs!$B$25,Inputs!$B$26)) -> 0.7 | K8: =IF(A8=0,-Capitalization!D$19,IF(A8<=Inputs!$B$21,0,I8*J8-IF(AND(A8=Inputs!$B$22,Capitalization!D$18>0),Inputs!$B$23,0))) -> -11.464597 | L8: =IF(H8>0,G8/H8,"") -> -0.10722015 | M8: =IF(A8=0,-Capitalization!D$4,IF(A8<=Inputs!$B$21,0,G8)) -> -1.586
A9: 4 | B9: =IF(A9=0,"Equity",IF(A9<=Inputs!$B$21,"Construction",IF(A9<=Inputs!$B$21+Inputs!$B$5,"Queue wait",IF(A9<=Inputs!$B$21+Configurations!$C$15,"Grid ops","—")))) -> Queue wait | C9: =IF(A9<=Inputs!$B$21,"",A9-Inputs!$B$21-1) -> 1 | D9: =IF(OR(A9<=Inputs!$B$21,A9>Inputs!$B$21+Configurations!$C$15),0,Configurations!$C$4*Configurations!$C$5*8760*(1-Configurations!$C$6)^C9*Configurations!$C$7*(1-Configurations!$C$8)) -> 429605.47 | E9: =IF(OR(A9<=Inputs!$B$21,A9>Inputs!$B$21+Configurations!$C$15),0,IF(A9<=Inputs!$B$21+Inputs!$B$5,0,D9*Inputs!$B$18/1000000)) -> 0 | F9: =IF(OR(A9<=Inputs!$B$21,A9>Inputs!$B$21+Configurations!$C$15),0,IF(A9<=Inputs!$B$21+Inputs!$B$5,Configurations!$C$13,Configurations!$C$12+Configurations!$C$13+Inputs!$B$20*E9)) -> 1.586 | G9: =E9-F9 -> -1.586 | H9: =IF(AND(A9>Inputs!$B$21,A9<=Inputs!$B$21+Inputs!$B$12),Capitalization!D$12,0) -> 14.791995 | I9: =G9-H9 -> -16.377995 | J9: =IF(A9<=Inputs!$B$21,"",IF(AND(A9<=Inputs!$B$22,Capitalization!D$18>0),Inputs!$B$25,Inputs!$B$26)) -> 0.7 | K9: =IF(A9=0,-Capitalization!D$19,IF(A9<=Inputs!$B$21,0,I9*J9-IF(AND(A9=Inputs!$B$22,Capitalization!D$18>0),Inputs!$B$23,0))) -> -11.464597 | L9: =IF(H9>0,G9/H9,"") -> -0.10722015 | M9: =IF(A9=0,-Capitalization!D$4,IF(A9<=Inputs!$B$21,0,G9)) -> -1.586
A10: 5 | B10: =IF(A10=0,"Equity",IF(A10<=Inputs!$B$21,"Construction",IF(A10<=Inputs!$B$21+Inputs!$B$5,"Queue wait",IF(A10<=Inputs!$B$21+Configurations!$C$15,"Grid ops","—")))) -> Queue wait | C10: =IF(A10<=Inputs!$B$21,"",A10-Inputs!$B$21-1) -> 2 | D10: =IF(OR(A10<=Inputs!$B$21,A10>Inputs!$B$21+Configurations!$C$15),0,Configurations!$C$4*Configurations!$C$5*8760*(1-Configurations!$C$6)^C10*Configurations!$C$7*(1-Configurations!$C$8)) -> 428746.26 | E10: =IF(OR(A10<=Inputs!$B$21,A10>Inputs!$B$21+Configurations!$C$15),0,IF(A10<=Inputs!$B$21+Inputs!$B$5,0,D10*Inputs!$B$18/1000000)) -> 0 | F10: =IF(OR(A10<=Inputs!$B$21,A10>Inputs!$B$21+Configurations!$C$15),0,IF(A10<=Inputs!$B$21+Inputs!$B$5,Configurations!$C$13,Configurations!$C$12+Configurations!$C$13+Inputs!$B$20*E10)) -> 1.586 | G10: =E10-F10 -> -1.586 | H10: =IF(AND(A10>Inputs!$B$21,A10<=Inputs!$B$21+Inputs!$B$12),Capitalization!D$12,0) -> 14.791995 | I10: =G10-H10 -> -16.377995 | J10: =IF(A10<=Inputs!$B$21,"",IF(AND(A10<=Inputs!$B$22,Capitalization!D$18>0),Inputs!$B$25,Inputs!$B$26)) -> 0.7 | K10: =IF(A10=0,-Capitalization!D$19,IF(A10<=Inputs!$B$21,0,I10*J10-IF(AND(A10=Inputs!$B$22,Capitalization!D$18>0),Inputs!$B$23,0))) -> -11.464597 | L10: =IF(H10>0,G10/H10,"") -> -0.10722015 | M10: =IF(A10=0,-Capitalization!D$4,IF(A10<=Inputs!$B$21,0,G10)) -> -1.586
A11: 6 | B11: =IF(A11=0,"Equity",IF(A11<=Inputs!$B$21,"Construction",IF(A11<=Inputs!$B$21+Inputs!$B$5,"Queue wait",IF(A11<=Inputs!$B$21+Configurations!$C$15,"Grid ops","—")))) -> Queue wait | C11: =IF(A11<=Inputs!$B$21,"",A11-Inputs!$B$21-1) -> 3 | D11: =IF(OR(A11<=Inputs!$B$21,A11>Inputs!$B$21+Configurations!$C$15),0,Configurations!$C$4*Configurations!$C$5*8760*(1-Configurations!$C$6)^C11*Configurations!$C$7*(1-Configurations!$C$8)) -> 427888.76 | E11: =IF(OR(A11<=Inputs!$B$21,A11>Inputs!$B$21+Configurations!$C$15),0,IF(A11<=Inputs!$B$21+Inputs!$B$5,0,D11*Inputs!$B$18/1000000)) -> 0 | F11: =IF(OR(A11<=Inputs!$B$21,A11>Inputs!$B$21+Configurations!$C$15),0,IF(A11<=Inputs!$B$21+Inputs!$B$5,Configurations!$C$13,Configurations!$C$12+Configurations!$C$13+Inputs!$B$20*E11)) -> 1.586 | G11: =E11-F11 -> -1.586 | H11: =IF(AND(A11>Inputs!$B$21,A11<=Inputs!$B$21+Inputs!$B$12),Capitalization!D$12,0) -> 14.791995 | I11: =G11-H11 -> -16.377995 | J11: =IF(A11<=Inputs!$B$21,"",IF(AND(A11<=Inputs!$B$22,Capitalization!D$18>0),Inputs!$B$25,Inputs!$B$26)) -> 0.7 | K11: =IF(A11=0,-Capitalization!D$19,IF(A11<=Inputs!$B$21,0,I11*J11-IF(AND(A11=Inputs!$B$22,Capitalization!D$18>0),Inputs!$B$23,0))) -> -12.464597 | L11: =IF(H11>0,G11/H11,"") -> -0.10722015 | M11: =IF(A11=0,-Capitalization!D$4,IF(A11<=Inputs!$B$21,0,G11)) -> -1.586
A12: 7 | B12: =IF(A12=0,"Equity",IF(A12<=Inputs!$B$21,"Construction",IF(A12<=Inputs!$B$21+Inputs!$B$5,"Queue wait",IF(A12<=Inputs!$B$21+Configurations!$C$15,"Grid ops","—")))) -> Grid ops | C12: =IF(A12<=Inputs!$B$21,"",A12-Inputs!$B$21-1) -> 4 | D12: =IF(OR(A12<=Inputs!$B$21,A12>Inputs!$B$21+Configurations!$C$15),0,Configurations!$C$4*Configurations!$C$5*8760*(1-Configurations!$C$6)^C12*Configurations!$C$7*(1-Configurations!$C$8)) -> 427032.99 | E12: =IF(OR(A12<=Inputs!$B$21,A12>Inputs!$B$21+Configurations!$C$15),0,IF(A12<=Inputs!$B$21+Inputs!$B$5,0,D12*Inputs!$B$18/1000000)) -> 30.746375 | F12: =IF(OR(A12<=Inputs!$B$21,A12>Inputs!$B$21+Configurations!$C$15),0,IF(A12<=Inputs!$B$21+Inputs!$B$5,Configurations!$C$13,Configurations!$C$12+Configurations!$C$13+Inputs!$B$20*E12)) -> 8.4221956 | G12: =E12-F12 -> 22.324179 | H12: =IF(AND(A12>Inputs!$B$21,A12<=Inputs!$B$21+Inputs!$B$12),Capitalization!D$12,0) -> 14.791995 | I12: =G12-H12 -> 7.5321842 | J12: =IF(A12<=Inputs!$B$21,"",IF(AND(A12<=Inputs!$B$22,Capitalization!D$18>0),Inputs!$B$25,Inputs!$B$26)) -> 0.975 | K12: =IF(A12=0,-Capitalization!D$19,IF(A12<=Inputs!$B$21,0,I12*J12-IF(AND(A12=Inputs!$B$22,Capitalization!D$18>0),Inputs!$B$23,0))) -> 7.3438796 | L12: =IF(H12>0,G12/H12,"") -> 1.5092068 | M12: =IF(A12=0,-Capitalization!D$4,IF(A12<=Inputs!$B$21,0,G12)) -> 22.324179
A13: 8 | B13: =IF(A13=0,"Equity",IF(A13<=Inputs!$B$21,"Construction",IF(A13<=Inputs!$B$21+Inputs!$B$5,"Queue wait",IF(A13<=Inputs!$B$21+Configurations!$C$15,"Grid ops","—")))) -> Grid ops | C13: =IF(A13<=Inputs!$B$21,"",A13-Inputs!$B$21-1) -> 5 | D13: =IF(OR(A13<=Inputs!$B$21,A13>Inputs!$B$21+Configurations!$C$15),0,Configurations!$C$4*Configurations!$C$5*8760*(1-Configurations!$C$6)^C13*Configurations!$C$7*(1-Configurations!$C$8)) -> 426178.92 | E13: =IF(OR(A13<=Inputs!$B$21,A13>Inputs!$B$21+Configurations!$C$15),0,IF(A13<=Inputs!$B$21+Inputs!$B$5,0,D13*Inputs!$B$18/1000000)) -> 30.684882 | F13: =IF(OR(A13<=Inputs!$B$21,A13>Inputs!$B$21+Configurations!$C$15),0,IF(A13<=Inputs!$B$21+Inputs!$B$5,Configurations!$C$13,Configurations!$C$12+Configurations!$C$13+Inputs!$B$20*E13)) -> 8.4212732 | G13: =E13-F13 -> 22.263609 | H13: =IF(AND(A13>Inputs!$B$21,A13<=Inputs!$B$21+Inputs!$B$12),Capitalization!D$12,0) -> 14.791995 | I13: =G13-H13 -> 7.4716139 | J13: =IF(A13<=Inputs!$B$21,"",IF(AND(A13<=Inputs!$B$22,Capitalization!D$18>0),Inputs!$B$25,Inputs!$B$26)) -> 0.975 | K13: =IF(A13=0,-Capitalization!D$19,IF(A13<=Inputs!$B$21,0,I13*J13-IF(AND(A13=Inputs!$B$22,Capitalization!D$18>0),Inputs!$B$23,0))) -> 7.2848235 | L13: =IF(H13>0,G13/H13,"") -> 1.505112 | M13: =IF(A13=0,-Capitalization!D$4,IF(A13<=Inputs!$B$21,0,G13)) -> 22.263609
A14: 9 | B14: =IF(A14=0,"Equity",IF(A14<=Inputs!$B$21,"Construction",IF(A14<=Inputs!$B$21+Inputs!$B$5,"Queue wait",IF(A14<=Inputs!$B$21+Configurations!$C$15,"Grid ops","—")))) -> Grid ops | C14: =IF(A14<=Inputs!$B$21,"",A14-Inputs!$B$21-1) -> 6 | D14: =IF(OR(A14<=Inputs!$B$21,A14>Inputs!$B$21+Configurations!$C$15),0,Configurations!$C$4*Configurations!$C$5*8760*(1-Configurations!$C$6)^C14*Configurations!$C$7*(1-Configurations!$C$8)) -> 425326.56 | E14: =IF(OR(A14<=Inputs!$B$21,A14>Inputs!$B$21+Configurations!$C$15),0,IF(A14<=Inputs!$B$21+Inputs!$B$5,0,D14*Inputs!$B$18/1000000)) -> 30.623512 | F14: =IF(OR(A14<=Inputs!$B$21,A14>Inputs!$B$21+Configurations!$C$15),0,IF(A14<=Inputs!$B$21+Inputs!$B$5,Configurations!$C$13,Configurations!$C$12+Configurations!$C$13+Inputs!$B$20*E14)) -> 8.4203527 | G14: =E14-F14 -> 22.20316 | H14: =IF(AND(A14>Inputs!$B$21,A14<=Inputs!$B$21+Inputs!$B$12),Capitalization!D$12,0) -> 14.791995 | I14: =G14-H14 -> 7.4111646 | J14: =IF(A14<=Inputs!$B$21,"",IF(AND(A14<=Inputs!$B$22,Capitalization!D$18>0),Inputs!$B$25,Inputs!$B$26)) -> 0.975 | K14: =IF(A14=0,-Capitalization!D$19,IF(A14<=Inputs!$B$21,0,I14*J14-IF(AND(A14=Inputs!$B$22,Capitalization!D$18>0),Inputs!$B$23,0))) -> 7.2258855 | L14: =IF(H14>0,G14/H14,"") -> 1.5010254 | M14: =IF(A14=0,-Capitalization!D$4,IF(A14<=Inputs!$B$21,0,G14)) -> 22.20316
A15: 10 | B15: =IF(A15=0,"Equity",IF(A15<=Inputs!$B$21,"Construction",IF(A15<=Inputs!$B$21+Inputs!$B$5,"Queue wait",IF(A15<=Inputs!$B$21+Configurations!$C$15,"Grid ops","—")))) -> Grid ops | C15: =IF(A15<=Inputs!$B$21,"",A15-Inputs!$B$21-1) -> 7 | D15: =IF(OR(A15<=Inputs!$B$21,A15>Inputs!$B$21+Configurations!$C$15),0,Configurations!$C$4*Configurations!$C$5*8760*(1-Configurations!$C$6)^C15*Configurations!$C$7*(1-Configurations!$C$8)) -> 424475.91 | E15: =IF(OR(A15<=Inputs!$B$21,A15>Inputs!$B$21+Configurations!$C$15),0,IF(A15<=Inputs!$B$21+Inputs!$B$5,0,D15*Inputs!$B$18/1000000)) -> 30.562265 | F15: =IF(OR(A15<=Inputs!$B$21,A15>Inputs!$B$21+Configurations!$C$15),0,IF(A15<=Inputs!$B$21+Inputs!$B$5,Configurations!$C$13,Configurations!$C$12+Configurations!$C$13+Inputs!$B$20*E15)) -> 8.419434 | G15: =E15-F15 -> 22.142831 | H15: =IF(AND(A15>Inputs!$B$21,A15<=Inputs!$B$21+Inputs!$B$12),Capitalization!D$12,0) -> 14.791995 | I15: =G15-H15 -> 7.3508363 | J15: =IF(A15<=Inputs!$B$21,"",IF(AND(A15<=Inputs!$B$22,Capitalization!D$18>0),Inputs!$B$25,Inputs!$B$26)) -> 0.975 | K15: =IF(A15=0,-Capitalization!D$19,IF(A15<=Inputs!$B$21,0,I15*J15-IF(AND(A15=Inputs!$B$22,Capitalization!D$18>0),Inputs!$B$23,0))) -> 7.1670654 | L15: =IF(H15>0,G15/H15,"") -> 1.4969469 | M15: =IF(A15=0,-Capitalization!D$4,IF(A15<=Inputs!$B$21,0,G15)) -> 22.142831
A16: 11 | B16: =IF(A16=0,"Equity",IF(A16<=Inputs!$B$21,"Construction",IF(A16<=Inputs!$B$21+Inputs!$B$5,"Queue wait",IF(A16<=Inputs!$B$21+Configurations!$C$15,"Grid ops","—")))) -> Grid ops | C16: =IF(A16<=Inputs!$B$21,"",A16-Inputs!$B$21-1) -> 8 | D16: =IF(OR(A16<=Inputs!$B$21,A16>Inputs!$B$21+Configurations!$C$15),0,Configurations!$C$4*Configurations!$C$5*8760*(1-Configurations!$C$6)^C16*Configurations!$C$7*(1-Configurations!$C$8)) -> 423626.96 | E16: =IF(OR(A16<=Inputs!$B$21,A16>Inputs!$B$21+Configurations!$C$15),0,IF(A16<=Inputs!$B$21+Inputs!$B$5,0,D16*Inputs!$B$18/1000000)) -> 30.501141 | F16: =IF(OR(A16<=Inputs!$B$21,A16>Inputs!$B$21+Configurations!$C$15),0,IF(A16<=Inputs!$B$21+Inputs!$B$5,Configurations!$C$13,Configurations!$C$12+Configurations!$C$13+Inputs!$B$20*E16)) -> 8.4185171 | G16: =E16-F16 -> 22.082624 | H16: =IF(AND(A16>Inputs!$B$21,A16<=Inputs!$B$21+Inputs!$B$12),Capitalization!D$12,0) -> 14.791995 | I16: =G16-H16 -> 7.2906287 | J16: =IF(A16<=Inputs!$B$21,"",IF(AND(A16<=Inputs!$B$22,Capitalization!D$18>0),Inputs!$B$25,Inputs!$B$26)) -> 0.975 | K16: =IF(A16=0,-Capitalization!D$19,IF(A16<=Inputs!$B$21,0,I16*J16-IF(AND(A16=Inputs!$B$22,Capitalization!D$18>0),Inputs!$B$23,0))) -> 7.1083629 | L16: =IF(H16>0,G16/H16,"") -> 1.4928766 | M16: =IF(A16=0,-Capitalization!D$4,IF(A16<=Inputs!$B$21,0,G16)) -> 22.082624
... A37: 32 | B37: =IF(A37=0,"Equity",IF(A37<=Inputs!$B$21,"Construction",IF(A37<=Inputs!$B$21+Inputs!$B$5,"Queue wait",IF(A37<=Inputs!$B$21+Configurations!$C$15,"Grid ops","—")))) -> — | C37: =IF(A37<=Inputs!$B$21,"",A37-Inputs!$B$21-1) -> 29 | D37: =IF(OR(A37<=Inputs!$B$21,A37>Inputs!$B$21+Configurations!$C$15),0,Configurations!$C$4*Configurations!$C$5*8760*(1-Configurations!$C$6)^C37*Configurations!$C$7*(1-Configurations!$C$8)) -> 0 | E37: =IF(OR(A37<=Inputs!$B$21,A37>Inputs!$B$21+Configurations!$C$15),0,IF(A37<=Inputs!$B$21+Inputs!$B$5,0,D37*Inputs!$B$18/1000000)) -> 0 | F37: =IF(OR(A37<=Inputs!$B$21,A37>Inputs!$B$21+Configurations!$C$15),0,IF(A37<=Inputs!$B$21+Inputs!$B$5,Configurations!$C$13,Configurations!$C$12+Configurations!$C$13+Inputs!$B$20*E37)) -> 0 | G37: =E37-F37 -> 0 | H37: =IF(AND(A37>Inputs!$B$21,A37<=Inputs!$B$21+Inputs!$B$12),Capitalization!D$12,0) -> 0 | I37: =G37-H37 -> 0 | J37: =IF(A37<=Inputs!$B$21,"",IF(AND(A37<=Inputs!$B$22,Capitalization!D$18>0),Inputs!$B$25,Inputs!$B$26)) -> 0.975 | K37: =IF(A37=0,-Capitalization!D$19,IF(A37<=Inputs!$B$21,0,I37*J37-IF(AND(A37=Inputs!$B$22,Capitalization!D$18>0),Inputs!$B$23,0))) -> 0 | L37: =IF(H37>0,G37/H37,"") | M37: =IF(A37=0,-Capitalization!D$4,IF(A37<=Inputs!$B$21,0,G37)) -> 0

Sheet WindColoc
A1: WindColoc — annual cash flow waterfall ($mm)
A2: Developer levered IRR: | B2: =IRR(K5:K37) -> 0.10059927 | C2: Unlevered (project) IRR: | D2: =IRR(M5:M37) -> 0.026329954 | E2: NPV of dev cash @ discount rate ($mm): | F2: =K5+NPV(Inputs!$B$24,K6:K37) -> 11.369007
A4: Year | B4: Phase | C4: Op yr | D4: Net energy (MWh) | E4: Revenue | F4: OPEX | G4: EBITDA | H4: Debt service | I4: Distributable cash | J4: Dev share | K4: Dev cash flow | L4: DSCR | M4: Project CF (unlevered)
A5: 0 | B5: =IF(A5=0,"Equity",IF(A5<=Inputs!$B$21,"Construction",IF(A5<=Inputs!$B$21+Inputs!$B$5,"Queue wait",IF(A5<=Inputs!$B$21+Configurations!$C$15,"Grid ops","—")))) -> Equity | C5: =IF(A5<=Inputs!$B$21,"",A5-Inputs!$B$21-1) | D5: =IF(OR(A5<=Inputs!$B$21,A5>Inputs!$B$21+Configurations!$C$15),0,Configurations!$C$4*Configurations!$C$5*8760*(1-Configurations!$C$6)^C5*Configurations!$C$7*(1-Configurations!$C$8)) -> 0 | E5: =IF(OR(A5<=Inputs!$B$21,A5>Inputs!$B$21+Configurations!$C$15),0,IF(A5<=Inputs!$B$21+Inputs!$B$5,D5*(1-Inputs!$B$10)*Inputs!$B$19/1000000,D5*Inputs!$B$18/1000000)) -> 0 | F5: =IF(OR(A5<=Inputs!$B$21,A5>Inputs!$B$21+Configurations!$C$15),0,Configurations!$C$12+Configurations!$C$13+Configurations!$C$14+Inputs!$B$20*E5) -> 0 | G5: =E5-F5 -> 0 | H5: =IF(AND(A5>Inputs!$B$21,A5<=Inputs!$B$21+Inputs!$B$12),Capitalization!E$12,0) -> 0 | I5: =G5-H5 -> 0 | J5: =IF(A5<=Inputs!$B$21,"",IF(AND(A5<=Inputs!$B$22,Capitalization!E$18>0),Inputs!$B$25,Inputs!$B$26)) | K5: =IF(A5=0,-Capitalization!E$19,IF(A5<=Inputs!$B$21,0,I5*J5-IF(AND(A5=Inputs!$B$22,Capitalization!E$18>0),Inputs!$B$23,0))) -> -31.643402 | L5: =IF(H5>0,G5/H5,"") | M5: =IF(A5=0,-Capitalization!E$4,IF(A5<=Inputs!$B$21,0,G5)) -> -339.4
A6: 1 | B6: =IF(A6=0,"Equity",IF(A6<=Inputs!$B$21,"Construction",IF(A6<=Inputs!$B$21+Inputs!$B$5,"Queue wait",IF(A6<=Inputs!$B$21+Configurations!$C$15,"Grid ops","—")))) -> Construction | C6: =IF(A6<=Inputs!$B$21,"",A6-Inputs!$B$21-1) | D6: =IF(OR(A6<=Inputs!$B$21,A6>Inputs!$B$21+Configurations!$C$15),0,Configurations!$C$4*Configurations!$C$5*8760*(1-Configurations!$C$6)^C6*Configurations!$C$7*(1-Configurations!$C$8)) -> 0 | E6: =IF(OR(A6<=Inputs!$B$21,A6>Inputs!$B$21+Configurations!$C$15),0,IF(A6<=Inputs!$B$21+Inputs!$B$5,D6*(1-Inputs!$B$10)*Inputs!$B$19/1000000,D6*Inputs!$B$18/1000000)) -> 0 | F6: =IF(OR(A6<=Inputs!$B$21,A6>Inputs!$B$21+Configurations!$C$15),0,Configurations!$C$12+Configurations!$C$13+Configurations!$C$14+Inputs!$B$20*E6) -> 0 | G6: =E6-F6 -> 0 | H6: =IF(AND(A6>Inputs!$B$21,A6<=Inputs!$B$21+Inputs!$B$12),Capitalization!E$12,0) -> 0 | I6: =G6-H6 -> 0 | J6: =IF(A6<=Inputs!$B$21,"",IF(AND(A6<=Inputs!$B$22,Capitalization!E$18>0),Inputs!$B$25,Inputs!$B$26)) | K6: =IF(A6=0,-Capitalization!E$19,IF(A6<=Inputs!$B$21,0,I6*J6-IF(AND(A6=Inputs!$B$22,Capitalization!E$18>0),Inputs!$B$23,0))) -> 0 | L6: =IF(H6>0,G6/H6,"") | M6: =IF(A6=0,-Capitalization!E$4,IF(A6<=Inputs!$B$21,0,G6)) -> 0
A7: 2 | B7: =IF(A7=0,"Equity",IF(A7<=Inputs!$B$21,"Construction",IF(A7<=Inputs!$B$21+Inputs!$B$5,"Queue wait",IF(A7<=Inputs!$B$21+Configurations!$C$15,"Grid ops","—")))) -> Construction | C7: =IF(A7<=Inputs!$B$21,"",A7-Inputs!$B$21-1) | D7: =IF(OR(A7<=Inputs!$B$21,A7>Inputs!$B$21+Configurations!$C$15),0,Configurations!$C$4*Configurations!$C$5*8760*(1-Configurations!$C$6)^C7*Configurations!$C$7*(1-Configurations!$C$8)) -> 0 | E7: =IF(OR(A7<=Inputs!$B$21,A7>Inputs!$B$21+Configurations!$C$15),0,IF(A7<=Inputs!$B$21+Inputs!$B$5,D7*(1-Inputs!$B$10)*Inputs!$B$19/1000000,D7*Inputs!$B$18/1000000)) -> 0 | F7: =IF(OR(A7<=Inputs!$B$21,A7>Inputs!$B$21+Configurations!$C$15),0,Configurations!$C$12+Configurations!$C$13+Configurations!$C$14+Inputs!$B$20*E7) -> 0 | G7: =E7-F7 -> 0 | H7: =IF(AND(A7>Inputs!$B$21,A7<=Inputs!$B$21+Inputs!$B$12),Capitalization!E$12,0) -> 0 | I7: =G7-H7 -> 0 | J7: =IF(A7<=Inputs!$B$21,"",IF(AND(A7<=Inputs!$B$22,Capitalization!E$18>0),Inputs!$B$25,Inputs!$B$26)) | K7: =IF(A7=0,-Capitalization!E$19,IF(A7<=Inputs!$B$21,0,I7*J7-IF(AND(A7=Inputs!$B$22,Capitalization!E$18>0),Inputs!$B$23,0))) -> 0 | L7: =IF(H7>0,G7/H7,"") | M7: =IF(A7=0,-Capitalization!E$4,IF(A7<=Inputs!$B$21,0,G7)) -> 0
A8: 3 | B8: =IF(A8=0,"Equity",IF(A8<=Inputs!$B$21,"Construction",IF(A8<=Inputs!$B$21+Inputs!$B$5,"Queue wait",IF(A8<=Inputs!$B$21+Configurations!$C$15,"Grid ops","—")))) -> Queue wait | C8: =IF(A8<=Inputs!$B$21,"",A8-Inputs!$B$21-1) -> 0 | D8: =IF(OR(A8<=Inputs!$B$21,A8>Inputs!$B$21+Configurations!$C$15),0,Configurations!$C$4*Configurations!$C$5*8760*(1-Configurations!$C$6)^C8*Configurations!$C$7*(1-Configurations!$C$8)) -> 430466.4 | E8: =IF(OR(A8<=Inputs!$B$21,A8>Inputs!$B$21+Configurations!$C$15),0,IF(A8<=Inputs!$B$21+Inputs!$B$5,D8*(1-Inputs!$B$10)*Inputs!$B$19/1000000,D8*Inputs!$B$18/1000000)) -> 25.569704 | F8: =IF(OR(A8<=Inputs!$B$21,A8>Inputs!$B$21+Configurations!$C$15),0,Configurations!$C$12+Configurations!$C$13+Configurations!$C$14+Inputs!$B$20*E8) -> 9.4695456 | G8: =E8-F8 -> 16.100159 | H8: =IF(AND(A8>Inputs!$B$21,A8<=Inputs!$B$21+Inputs!$B$12),Capitalization!E$12,0) -> 15.620421 | I8: =G8-H8 -> 0.47973806 | J8: =IF(A8<=Inputs!$B$21,"",IF(AND(A8<=Inputs!$B$22,Capitalization!E$18>0),Inputs!$B$25,Inputs!$B$26)) -> 0.7 | K8: =IF(A8=0,-Capitalization!E$19,IF(A8<=Inputs!$B$21,0,I8*J8-IF(AND(A8=Inputs!$B$22,Capitalization!E$18>0),Inputs!$B$23,0))) -> 0.33581664 | L8: =IF(H8>0,G8/H8,"") -> 1.0307122 | M8: =IF(A8=0,-Capitalization!E$4,IF(A8<=Inputs!$B$21,0,G8)) -> 16.100159
A9: 4 | B9: =IF(A9=0,"Equity",IF(A9<=Inputs!$B$21,"Construction",IF(A9<=Inputs!$B$21+Inputs!$B$5,"Queue wait",IF(A9<=Inputs!$B$21+Configurations!$C$15,"Grid ops","—")))) -> Queue wait | C9: =IF(A9<=Inputs!$B$21,"",A9-Inputs!$B$21-1) -> 1 | D9: =IF(OR(A9<=Inputs!$B$21,A9>Inputs!$B$21+Configurations!$C$15),0,Configurations!$C$4*Configurations!$C$5*8760*(1-Configurations!$C$6)^C9*Configurations!$C$7*(1-Configurations!$C$8)) -> 429605.47 | E9: =IF(OR(A9<=Inputs!$B$21,A9>Inputs!$B$21+Configurations!$C$15),0,IF(A9<=Inputs!$B$21+Inputs!$B$5,D9*(1-Inputs!$B$10)*Inputs!$B$19/1000000,D9*Inputs!$B$18/1000000)) -> 25.518565 | F9: =IF(OR(A9<=Inputs!$B$21,A9>Inputs!$B$21+Configurations!$C$15),0,Configurations!$C$12+Configurations!$C$13+Configurations!$C$14+Inputs!$B$20*E9) -> 9.4687785 | G9: =E9-F9 -> 16.049786 | H9: =IF(AND(A9>Inputs!$B$21,A9<=Inputs!$B$21+Inputs!$B$12),Capitalization!E$12,0) -> 15.620421 | I9: =G9-H9 -> 0.42936574 | J9: =IF(A9<=Inputs!$B$21,"",IF(AND(A9<=Inputs!$B$22,Capitalization!E$18>0),Inputs!$B$25,Inputs!$B$26)) -> 0.7 | K9: =IF(A9=0,-Capitalization!E$19,IF(A9<=Inputs!$B$21,0,I9*J9-IF(AND(A9=Inputs!$B$22,Capitalization!E$18>0),Inputs!$B$23,0))) -> 0.30055602 | L9: =IF(H9>0,G9/H9,"") -> 1.0274875 | M9: =IF(A9=0,-Capitalization!E$4,IF(A9<=Inputs!$B$21,0,G9)) -> 16.049786
A10: 5 | B10: =IF(A10=0,"Equity",IF(A10<=Inputs!$B$21,"Construction",IF(A10<=Inputs!$B$21+Inputs!$B$5,"Queue wait",IF(A10<=Inputs!$B$21+Configurations!$C$15,"Grid ops","—")))) -> Queue wait | C10: =IF(A10<=Inputs!$B$21,"",A10-Inputs!$B$21-1) -> 2 | D10: =IF(OR(A10<=Inputs!$B$21,A10>Inputs!$B$21+Configurations!$C$15),0,Configurations!$C$4*Configurations!$C$5*8760*(1-Configurations!$C$6)^C10*Configurations!$C$7*(1-Configurations!$C$8)) -> 428746.26 | E10: =IF(OR(A10<=Inputs!$B$21,A10>Inputs!$B$21+Configurations!$C$15),0,IF(A10<=Inputs!$B$21+Inputs!$B$5,D10*(1-Inputs!$B$10)*Inputs!$B$19/1000000,D10*Inputs!$B$18/1000000)) -> 25.467528 | F10: =IF(OR(A10<=Inputs!$B$21,A10>Inputs!$B$21+Configurations!$C$15),0,Configurations!$C$12+Configurations!$C$13+Configurations!$C$14+Inputs!$B$20*E10) -> 9.4680129 | G10: =E10-F10 -> 15.999515 | H10: =IF(AND(A10>Inputs!$B$21,A10<=Inputs!$B$21+Inputs!$B$12),Capitalization!E$12,0) -> 15.620421 | I10: =G10-H10 -> 0.37909417 | J10: =IF(A10<=Inputs!$B$21,"",IF(AND(A10<=Inputs!$B$22,Capitalization!E$18>0),Inputs!$B$25,Inputs!$B$26)) -> 0.7 | K10: =IF(A10=0,-Capitalization!E$19,IF(A10<=Inputs!$B$21,0,I10*J10-IF(AND(A10=Inputs!$B$22,Capitalization!E$18>0),Inputs!$B$23,0))) -> 0.26536592 | L10: =IF(H10>0,G10/H10,"") -> 1.0242691 | M10: =IF(A10=0,-Capitalization!E$4,IF(A10<=Inputs!$B$21,0,G10)) -> 15.999515
A11: 6 | B11: =IF(A11=0,"Equity",IF(A11<=Inputs!$B$21,"Construction",IF(A11<=Inputs!$B$21+Inputs!$B$5,"Queue wait",IF(A11<=Inputs!$B$21+Configurations!$C$15,"Grid ops","—")))) -> Queue wait | C11: =IF(A11<=Inputs!$B$21,"",A11-Inputs!$B$21-1) -> 3 | D11: =IF(OR(A11<=Inputs!$B$21,A11>Inputs!$B$21+Configurations!$C$15),0,Configurations!$C$4*Configurations!$C$5*8760*(1-Configurations!$C$6)^C11*Configurations!$C$7*(1-Configurations!$C$8)) -> 427888.76 | E11: =IF(OR(A11<=Inputs!$B$21,A11>Inputs!$B$21+Configurations!$C$15),0,IF(A11<=Inputs!$B$21+Inputs!$B$5,D11*(1-Inputs!$B$10)*Inputs!$B$19/1000000,D11*Inputs!$B$18/1000000)) -> 25.416593 | F11: =IF(OR(A11<=Inputs!$B$21,A11>Inputs!$B$21+Configurations!$C$15),0,Configurations!$C$12+Configurations!$C$13+Configurations!$C$14+Inputs!$B$20*E11) -> 9.4672489 | G11: =E11-F11 -> 15.949344 | H11: =IF(AND(A11>Inputs!$B$21,A11<=Inputs!$B$21+Inputs!$B$12),Capitalization!E$12,0) -> 15.620421 | I11: =G11-H11 -> 0.32892314 | J11: =IF(A11<=Inputs!$B$21,"",IF(AND(A11<=Inputs!$B$22,Capitalization!E$18>0),Inputs!$B$25,Inputs!$B$26)) -> 0.7 | K11: =IF(A11=0,-Capitalization!E$19,IF(A11<=Inputs!$B$21,0,I11*J11-IF(AND(A11=Inputs!$B$22,Capitalization!E$18>0),Inputs!$B$23,0))) -> -0.7697538 | L11: =IF(H11>0,G11/H11,"") -> 1.0210573 | M11: =IF(A11=0,-Capitalization!E$4,IF(A11<=Inputs!$B$21,0,G11)) -> 15.949344
A12: 7 | B12: =IF(A12=0,"Equity",IF(A12<=Inputs!$B$21,"Construction",IF(A12<=Inputs!$B$21+Inputs!$B$5,"Queue wait",IF(A12<=Inputs!$B$21+Configurations!$C$15,"Grid ops","—")))) -> Grid ops | C12: =IF(A12<=Inputs!$B$21,"",A12-Inputs!$B$21-1) -> 4 | D12: =IF(OR(A12<=Inputs!$B$21,A12>Inputs!$B$21+Configurations!$C$15),0,Configurations!$C$4*Configurations!$C$5*8760*(1-Configurations!$C$6)^C12*Configurations!$C$7*(1-Configurations!$C$8)) -> 427032.99 | E12: =IF(OR(A12<=Inputs!$B$21,A12>Inputs!$B$21+Configurations!$C$15),0,IF(A12<=Inputs!$B$21+Inputs!$B$5,D12*(1-Inputs!$B$10)*Inputs!$B$19/1000000,D12*Inputs!$B$18/1000000)) -> 30.746375 | F12: =IF(OR(A12<=Inputs!$B$21,A12>Inputs!$B$21+Configurations!$C$15),0,Configurations!$C$12+Configurations!$C$13+Configurations!$C$14+Inputs!$B$20*E12) -> 9.5471956 | G12: =E12-F12 -> 21.199179 | H12: =IF(AND(A12>Inputs!$B$21,A12<=Inputs!$B$21+Inputs!$B$12),Capitalization!E$12,0) -> 15.620421 | I12: =G12-H12 -> 5.5787588 | J12: =IF(A12<=Inputs!$B$21,"",IF(AND(A12<=Inputs!$B$22,Capitalization!E$18>0),Inputs!$B$25,Inputs!$B$26)) -> 0.975 | K12: =IF(A12=0,-Capitalization!E$19,IF(A12<=Inputs!$B$21,0,I12*J12-IF(AND(A12=Inputs!$B$22,Capitalization!E$18>0),Inputs!$B$23,0))) -> 5.4392899 | L12: =IF(H12>0,G12/H12,"") -> 1.3571452 | M12: =IF(A12=0,-Capitalization!E$4,IF(A12<=Inputs!$B$21,0,G12)) -> 21.199179
A13: 8 | B13: =IF(A13=0,"Equity",IF(A13<=Inputs!$B$21,"Construction",IF(A13<=Inputs!$B$21+Inputs!$B$5,"Queue wait",IF(A13<=Inputs!$B$21+Configurations!$C$15,"Grid ops","—")))) -> Grid ops | C13: =IF(A13<=Inputs!$B$21,"",A13-Inputs!$B$21-1) -> 5 | D13: =IF(OR(A13<=Inputs!$B$21,A13>Inputs!$B$21+Configurations!$C$15),0,Configurations!$C$4*Configurations!$C$5*8760*(1-Configurations!$C$6)^C13*Configurations!$C$7*(1-Configurations!$C$8)) -> 426178.92 | E13: =IF(OR(A13<=Inputs!$B$21,A13>Inputs!$B$21+Configurations!$C$15),0,IF(A13<=Inputs!$B$21+Inputs!$B$5,D13*(1-Inputs!$B$10)*Inputs!$B$19/1000000,D13*Inputs!$B$18/1000000)) -> 30.684882 | F13: =IF(OR(A13<=Inputs!$B$21,A13>Inputs!$B$21+Configurations!$C$15),0,Configurations!$C$12+Configurations!$C$13+Configurations!$C$14+Inputs!$B$20*E13) -> 9.5462732 | G13: =E13-F13 -> 21.138609 | H13: =IF(AND(A13>Inputs!$B$21,A13<=Inputs!$B$21+Inputs!$B$12),Capitalization!E$12,0) -> 15.620421 | I13: =G13-H13 -> 5.5181885 | J13: =IF(A13<=Inputs!$B$21,"",IF(AND(A13<=Inputs!$B$22,Capitalization!E$18>0),Inputs!$B$25,Inputs!$B$26)) -> 0.975 | K13: =IF(A13=0,-Capitalization!E$19,IF(A13<=Inputs!$B$21,0,I13*J13-IF(AND(A13=Inputs!$B$22,Capitalization!E$18>0),Inputs!$B$23,0))) -> 5.3802338 | L13: =IF(H13>0,G13/H13,"") -> 1.3532676 | M13: =IF(A13=0,-Capitalization!E$4,IF(A13<=Inputs!$B$21,0,G13)) -> 21.138609
A14: 9 | B14: =IF(A14=0,"Equity",IF(A14<=Inputs!$B$21,"Construction",IF(A14<=Inputs!$B$21+Inputs!$B$5,"Queue wait",IF(A14<=Inputs!$B$21+Configurations!$C$15,"Grid ops","—")))) -> Grid ops | C14: =IF(A14<=Inputs!$B$21,"",A14-Inputs!$B$21-1) -> 6 | D14: =IF(OR(A14<=Inputs!$B$21,A14>Inputs!$B$21+Configurations!$C$15),0,Configurations!$C$4*Configurations!$C$5*8760*(1-Configurations!$C$6)^C14*Configurations!$C$7*(1-Configurations!$C$8)) -> 425326.56 | E14: =IF(OR(A14<=Inputs!$B$21,A14>Inputs!$B$21+Configurations!$C$15),0,IF(A14<=Inputs!$B$21+Inputs!$B$5,D14*(1-Inputs!$B$10)*Inputs!$B$19/1000000,D14*Inputs!$B$18/1000000)) -> 30.623512 | F14: =IF(OR(A14<=Inputs!$B$21,A14>Inputs!$B$21+Configurations!$C$15),0,Configurations!$C$12+Configurations!$C$13+Configurations!$C$14+Inputs!$B$20*E14) -> 9.5453527 | G14: =E14-F14 -> 21.07816 | H14: =IF(AND(A14>Inputs!$B$21,A14<=Inputs!$B$21+Inputs!$B$12),Capitalization!E$12,0) -> 15.620421 | I14: =G14-H14 -> 5.4577393 | J14: =IF(A14<=Inputs!$B$21,"",IF(AND(A14<=Inputs!$B$22,Capitalization!E$18>0),Inputs!$B$25,Inputs!$B$26)) -> 0.975 | K14: =IF(A14=0,-Capitalization!E$19,IF(A14<=Inputs!$B$21,0,I14*J14-IF(AND(A14=Inputs!$B$22,Capitalization!E$18>0),Inputs!$B$23,0))) -> 5.3212958 | L14: =IF(H14>0,G14/H14,"") -> 1.3493977 | M14: =IF(A14=0,-Capitalization!E$4,IF(A14<=Inputs!$B$21,0,G14)) -> 21.07816
A15: 10 | B15: =IF(A15=0,"Equity",IF(A15<=Inputs!$B$21,"Construction",IF(A15<=Inputs!$B$21+Inputs!$B$5,"Queue wait",IF(A15<=Inputs!$B$21+Configurations!$C$15,"Grid ops","—")))) -> Grid ops | C15: =IF(A15<=Inputs!$B$21,"",A15-Inputs!$B$21-1) -> 7 | D15: =IF(OR(A15<=Inputs!$B$21,A15>Inputs!$B$21+Configurations!$C$15),0,Configurations!$C$4*Configurations!$C$5*8760*(1-Configurations!$C$6)^C15*Configurations!$C$7*(1-Configurations!$C$8)) -> 424475.91 | E15: =IF(OR(A15<=Inputs!$B$21,A15>Inputs!$B$21+Configurations!$C$15),0,IF(A15<=Inputs!$B$21+Inputs!$B$5,D15*(1-Inputs!$B$10)*Inputs!$B$19/1000000,D15*Inputs!$B$18/1000000)) -> 30.562265 | F15: =IF(OR(A15<=Inputs!$B$21,A15>Inputs!$B$21+Configurations!$C$15),0,Configurations!$C$12+Configurations!$C$13+Configurations!$C$14+Inputs!$B$20*E15) -> 9.544434 | G15: =E15-F15 -> 21.017831 | H15: =IF(AND(A15>Inputs!$B$21,A15<=Inputs!$B$21+Inputs!$B$12),Capitalization!E$12,0) -> 15.620421 | I15: =G15-H15 -> 5.3974109 | J15: =IF(A15<=Inputs!$B$21,"",IF(AND(A15<=Inputs!$B$22,Capitalization!E$18>0),Inputs!$B$25,Inputs!$B$26)) -> 0.975 | K15: =IF(A15=0,-Capitalization!E$19,IF(A15<=Inputs!$B$21,0,I15*J15-IF(AND(A15=Inputs!$B$22,Capitalization!E$18>0),Inputs!$B$23,0))) -> 5.2624757 | L15: =IF(H15>0,G15/H15,"") -> 1.3455356 | M15: =IF(A15=0,-Capitalization!E$4,IF(A15<=Inputs!$B$21,0,G15)) -> 21.017831
A16: 11 | B16: =IF(A16=0,"Equity",IF(A16<=Inputs!$B$21,"Construction",IF(A16<=Inputs!$B$21+Inputs!$B$5,"Queue wait",IF(A16<=Inputs!$B$21+Configurations!$C$15,"Grid ops","—")))) -> Grid ops | C16: =IF(A16<=Inputs!$B$21,"",A16-Inputs!$B$21-1) -> 8 | D16: =IF(OR(A16<=Inputs!$B$21,A16>Inputs!$B$21+Configurations!$C$15),0,Configurations!$C$4*Configurations!$C$5*8760*(1-Configurations!$C$6)^C16*Configurations!$C$7*(1-Configurations!$C$8)) -> 423626.96 | E16: =IF(OR(A16<=Inputs!$B$21,A16>Inputs!$B$21+Configurations!$C$15),0,IF(A16<=Inputs!$B$21+Inputs!$B$5,D16*(1-Inputs!$B$10)*Inputs!$B$19/1000000,D16*Inputs!$B$18/1000000)) -> 30.501141 | F16: =IF(OR(A16<=Inputs!$B$21,A16>Inputs!$B$21+Configurations!$C$15),0,Configurations!$C$12+Configurations!$C$13+Configurations!$C$14+Inputs!$B$20*E16) -> 9.5435171 | G16: =E16-F16 -> 20.957624 | H16: =IF(AND(A16>Inputs!$B$21,A16<=Inputs!$B$21+Inputs!$B$12),Capitalization!E$12,0) -> 15.620421 | I16: =G16-H16 -> 5.3372033 | J16: =IF(A16<=Inputs!$B$21,"",IF(AND(A16<=Inputs!$B$22,Capitalization!E$18>0),Inputs!$B$25,Inputs!$B$26)) -> 0.975 | K16: =IF(A16=0,-Capitalization!E$19,IF(A16<=Inputs!$B$21,0,I16*J16-IF(AND(A16=Inputs!$B$22,Capitalization!E$18>0),Inputs!$B$23,0))) -> 5.2037732 | L16: =IF(H16>0,G16/H16,"") -> 1.3416812 | M16: =IF(A16=0,-Capitalization!E$4,IF(A16<=Inputs!$B$21,0,G16)) -> 20.957624
... A37: 32 | B37: =IF(A37=0,"Equity",IF(A37<=Inputs!$B$21,"Construction",IF(A37<=Inputs!$B$21+Inputs!$B$5,"Queue wait",IF(A37<=Inputs!$B$21+Configurations!$C$15,"Grid ops","—")))) -> — | C37: =IF(A37<=Inputs!$B$21,"",A37-Inputs!$B$21-1) -> 29 | D37: =IF(OR(A37<=Inputs!$B$21,A37>Inputs!$B$21+Configurations!$C$15),0,Configurations!$C$4*Configurations!$C$5*8760*(1-Configurations!$C$6)^C37*Configurations!$C$7*(1-Configurations!$C$8)) -> 0 | E37: =IF(OR(A37<=Inputs!$B$21,A37>Inputs!$B$21+Configurations!$C$15),0,IF(A37<=Inputs!$B$21+Inputs!$B$5,D37*(1-Inputs!$B$10)*Inputs!$B$19/1000000,D37*Inputs!$B$18/1000000)) -> 0 | F37: =IF(OR(A37<=Inputs!$B$21,A37>Inputs!$B$21+Configurations!$C$15),0,Configurations!$C$12+Configurations!$C$13+Configurations!$C$14+Inputs!$B$20*E37) -> 0 | G37: =E37-F37 -> 0 | H37: =IF(AND(A37>Inputs!$B$21,A37<=Inputs!$B$21+Inputs!$B$12),Capitalization!E$12,0) -> 0 | I37: =G37-H37 -> 0 | J37: =IF(A37<=Inputs!$B$21,"",IF(AND(A37<=Inputs!$B$22,Capitalization!E$18>0),Inputs!$B$25,Inputs!$B$26)) -> 0.975 | K37: =IF(A37=0,-Capitalization!E$19,IF(A37<=Inputs!$B$21,0,I37*J37-IF(AND(A37=Inputs!$B$22,Capitalization!E$18>0),Inputs!$B$23,0))) -> 0 | L37: =IF(H37>0,G37/H37,"") | M37: =IF(A37=0,-Capitalization!E$4,IF(A37<=Inputs!$B$21,0,G37)) -> 0

Sheet GeoBase
A1: GeoBase — annual cash flow waterfall ($mm)
A2: Developer levered IRR: | B2: =IRR(K5:K37) -> 0.1161382 | C2: Unlevered (project) IRR: | D2: =IRR(M5:M37) -> 0.03856386 | E2: NPV of dev cash @ discount rate ($mm): | F2: =K5+NPV(Inputs!$B$24,K6:K37) -> 57.635835
A4: Year | B4: Phase | C4: Op yr | D4: Net energy (MWh) | E4: Revenue | F4: OPEX | G4: EBITDA | H4: Debt service | I4: Distributable cash | J4: Dev share | K4: Dev cash flow | L4: DSCR | M4: Project CF (unlevered)
A5: 0 | B5: =IF(A5=0,"Equity",IF(A5<=Inputs!$B$21,"Construction",IF(A5<=Inputs!$B$21+Inputs!$B$5,"Queue wait",IF(A5<=Inputs!$B$21+Configurations!$D$15,"Grid ops","—")))) -> Equity | C5: =IF(A5<=Inputs!$B$21,"",A5-Inputs!$B$21-1) | D5: =IF(OR(A5<=Inputs!$B$21,A5>Inputs!$B$21+Configurations!$D$15),0,Configurations!$D$4*Configurations!$D$5*8760*(1-Configurations!$D$6)^C5*Configurations!$D$7*(1-Configurations!$D$8)) -> 0 | E5: =IF(OR(A5<=Inputs!$B$21,A5>Inputs!$B$21+Configurations!$D$15),0,IF(A5<=Inputs!$B$21+Inputs!$B$5,0,D5*Inputs!$B$18/1000000)) -> 0 | F5: =IF(OR(A5<=Inputs!$B$21,A5>Inputs!$B$21+Configurations!$D$15),0,IF(A5<=Inputs!$B$21+Inputs!$B$5,Configurations!$D$13,Configurations!$D$12+Configurations!$D$13+Inputs!$B$20*E5)) -> 0 | G5: =E5-F5 -> 0 | H5: =IF(AND(A5>Inputs!$B$21,A5<=Inputs!$B$21+Inputs!$B$12),Capitalization!F$12,0) -> 0 | I5: =G5-H5 -> 0 | J5: =IF(A5<=Inputs!$B$21,"",IF(AND(A5<=Inputs!$B$22,Capitalization!F$18>0),Inputs!$B$25,Inputs!$B$26)) | K5: =IF(A5=0,-Capitalization!F$19,IF(A5<=Inputs!$B$21,0,I5*J5-IF(AND(A5=Inputs!$B$22,Capitalization!F$18>0),Inputs!$B$23,0))) -> -38.574086 | L5: =IF(H5>0,G5/H5,"") | M5: =IF(A5=0,-Capitalization!F$4,IF(A5<=Inputs!$B$21,0,G5)) -> -568.25
A6: 1 | B6: =IF(A6=0,"Equity",IF(A6<=Inputs!$B$21,"Construction",IF(A6<=Inputs!$B$21+Inputs!$B$5,"Queue wait",IF(A6<=Inputs!$B$21+Configurations!$D$15,"Grid ops","—")))) -> Construction | C6: =IF(A6<=Inputs!$B$21,"",A6-Inputs!$B$21-1) | D6: =IF(OR(A6<=Inputs!$B$21,A6>Inputs!$B$21+Configurations!$D$15),0,Configurations!$D$4*Configurations!$D$5*8760*(1-Configurations!$D$6)^C6*Configurations!$D$7*(1-Configurations!$D$8)) -> 0 | E6: =IF(OR(A6<=Inputs!$B$21,A6>Inputs!$B$21+Configurations!$D$15),0,IF(A6<=Inputs!$B$21+Inputs!$B$5,0,D6*Inputs!$B$18/1000000)) -> 0 | F6: =IF(OR(A6<=Inputs!$B$21,A6>Inputs!$B$21+Configurations!$D$15),0,IF(A6<=Inputs!$B$21+Inputs!$B$5,Configurations!$D$13,Configurations!$D$12+Configurations!$D$13+Inputs!$B$20*E6)) -> 0 | G6: =E6-F6 -> 0 | H6: =IF(AND(A6>Inputs!$B$21,A6<=Inputs!$B$21+Inputs!$B$12),Capitalization!F$12,0) -> 0 | I6: =G6-H6 -> 0 | J6: =IF(A6<=Inputs!$B$21,"",IF(AND(A6<=Inputs!$B$22,Capitalization!F$18>0),Inputs!$B$25,Inputs!$B$26)) | K6: =IF(A6=0,-Capitalization!F$19,IF(A6<=Inputs!$B$21,0,I6*J6-IF(AND(A6=Inputs!$B$22,Capitalization!F$18>0),Inputs!$B$23,0))) -> 0 | L6: =IF(H6>0,G6/H6,"") | M6: =IF(A6=0,-Capitalization!F$4,IF(A6<=Inputs!$B$21,0,G6)) -> 0
A7: 2 | B7: =IF(A7=0,"Equity",IF(A7<=Inputs!$B$21,"Construction",IF(A7<=Inputs!$B$21+Inputs!$B$5,"Queue wait",IF(A7<=Inputs!$B$21+Configurations!$D$15,"Grid ops","—")))) -> Construction | C7: =IF(A7<=Inputs!$B$21,"",A7-Inputs!$B$21-1) | D7: =IF(OR(A7<=Inputs!$B$21,A7>Inputs!$B$21+Configurations!$D$15),0,Configurations!$D$4*Configurations!$D$5*8760*(1-Configurations!$D$6)^C7*Configurations!$D$7*(1-Configurations!$D$8)) -> 0 | E7: =IF(OR(A7<=Inputs!$B$21,A7>Inputs!$B$21+Configurations!$D$15),0,IF(A7<=Inputs!$B$21+Inputs!$B$5,0,D7*Inputs!$B$18/1000000)) -> 0 | F7: =IF(OR(A7<=Inputs!$B$21,A7>Inputs!$B$21+Configurations!$D$15),0,IF(A7<=Inputs!$B$21+Inputs!$B$5,Configurations!$D$13,Configurations!$D$12+Configurations!$D$13+Inputs!$B$20*E7)) -> 0 | G7: =E7-F7 -> 0 | H7: =IF(AND(A7>Inputs!$B$21,A7<=Inputs!$B$21+Inputs!$B$12),Capitalization!F$12,0) -> 0 | I7: =G7-H7 -> 0 | J7: =IF(A7<=Inputs!$B$21,"",IF(AND(A7<=Inputs!$B$22,Capitalization!F$18>0),Inputs!$B$25,Inputs!$B$26)) | K7: =IF(A7=0,-Capitalization!F$19,IF(A7<=Inputs!$B$21,0,I7*J7-IF(AND(A7=Inputs!$B$22,Capitalization!F$18>0),Inputs!$B$23,0))) -> 0 | L7: =IF(H7>0,G7/H7,"") | M7: =IF(A7=0,-Capitalization!F$4,IF(A7<=Inputs!$B$21,0,G7)) -> 0
A8: 3 | B8: =IF(A8=0,"Equity",IF(A8<=Inputs!$B$21,"Construction",IF(A8<=Inputs!$B$21+Inputs!$B$5,"Queue wait",IF(A8<=Inputs!$B$21+Configurations!$D$15,"Grid ops","—")))) -> Queue wait | C8: =IF(A8<=Inputs!$B$21,"",A8-Inputs!$B$21-1) -> 0 | D8: =IF(OR(A8<=Inputs!$B$21,A8>Inputs!$B$21+Configurations!$D$15),0,Configurations!$D$4*Configurations!$D$5*8760*(1-Configurations!$D$6)^C8*Configurations!$D$7*(1-Configurations!$D$8)) -> 730255.5 | E8: =IF(OR(A8<=Inputs!$B$21,A8>Inputs!$B$21+Configurations!$D$15),0,IF(A8<=Inputs!$B$21+Inputs!$B$5,0,D8*Inputs!$B$18/1000000)) -> 0 | F8: =IF(OR(A8<=Inputs!$B$21,A8>Inputs!$B$21+Configurations!$D$15),0,IF(A8<=Inputs!$B$21+Inputs!$B$5,Configurations!$D$13,Configurations!$D$12+Configurations!$D$13+Inputs!$B$20*E8)) -> 2.573 | G8: =E8-F8 -> -2.573 | H8: =IF(AND(A8>Inputs!$B$21,A8<=Inputs!$B$21+Inputs!$B$12),Capitalization!F$12,0) -> 26.152929 | I8: =G8-H8 -> -28.725929 | J8: =IF(A8<=Inputs!$B$21,"",IF(AND(A8<=Inputs!$B$22,Capitalization!F$18>0),Inputs!$B$25,Inputs!$B$26)) -> 0.7 | K8: =IF(A8=0,-Capitalization!F$19,IF(A8<=Inputs!$B$21,0,I8*J8-IF(AND(A8=Inputs!$B$22,Capitalization!F$18>0),Inputs!$B$23,0))) -> -20.10815 | L8: =IF(H8>0,G8/H8,"") -> -0.098382863 | M8: =IF(A8=0,-Capitalization!F$4,IF(A8<=Inputs!$B$21,0,G8)) -> -2.573
A9: 4 | B9: =IF(A9=0,"Equity",IF(A9<=Inputs!$B$21,"Construction",IF(A9<=Inputs!$B$21+Inputs!$B$5,"Queue wait",IF(A9<=Inputs!$B$21+Configurations!$D$15,"Grid ops","—")))) -> Queue wait | C9: =IF(A9<=Inputs!$B$21,"",A9-Inputs!$B$21-1) -> 1 | D9: =IF(OR(A9<=Inputs!$B$21,A9>Inputs!$B$21+Configurations!$D$15),0,Configurations!$D$4*Configurations!$D$5*8760*(1-Configurations!$D$6)^C9*Configurations!$D$7*(1-Configurations!$D$8)) -> 730255.5 | E9: =IF(OR(A9<=Inputs!$B$21,A9>Inputs!$B$21+Configurations!$D$15),0,IF(A9<=Inputs!$B$21+Inputs!$B$5,0,D9*Inputs!$B$18/1000000)) -> 0 | F9: =IF(OR(A9<=Inputs!$B$21,A9>Inputs!$B$21+Configurations!$D$15),0,IF(A9<=Inputs!$B$21+Inputs!$B$5,Configurations!$D$13,Configurations!$D$12+Configurations!$D$13+Inputs!$B$20*E9)) -> 2.573 | G9: =E9-F9 -> -2.573 | H9: =IF(AND(A9>Inputs!$B$21,A9<=Inputs!$B$21+Inputs!$B$12),Capitalization!F$12,0) -> 26.152929 | I9: =G9-H9 -> -28.725929 | J9: =IF(A9<=Inputs!$B$21,"",IF(AND(A9<=Inputs!$B$22,Capitalization!F$18>0),Inputs!$B$25,Inputs!$B$26)) -> 0.7 | K9: =IF(A9=0,-Capitalization!F$19,IF(A9<=Inputs!$B$21,0,I9*J9-IF(AND(A9=Inputs!$B$22,Capitalization!F$18>0),Inputs!$B$23,0))) -> -20.10815 | L9: =IF(H9>0,G9/H9,"") -> -0.098382863 | M9: =IF(A9=0,-Capitalization!F$4,IF(A9<=Inputs!$B$21,0,G9)) -> -2.573
A10: 5 | B10: =IF(A10=0,"Equity",IF(A10<=Inputs!$B$21,"Construction",IF(A10<=Inputs!$B$21+Inputs!$B$5,"Queue wait",IF(A10<=Inputs!$B$21+Configurations!$D$15,"Grid ops","—")))) -> Queue wait | C10: =IF(A10<=Inputs!$B$21,"",A10-Inputs!$B$21-1) -> 2 | D10: =IF(OR(A10<=Inputs!$B$21,A10>Inputs!$B$21+Configurations!$D$15),0,Configurations!$D$4*Configurations!$D$5*8760*(1-Configurations!$D$6)^C10*Configurations!$D$7*(1-Configurations!$D$8)) -> 730255.5 | E10: =IF(OR(A10<=Inputs!$B$21,A10>Inputs!$B$21+Configurations!$D$15),0,IF(A10<=Inputs!$B$21+Inputs!$B$5,0,D10*Inputs!$B$18/1000000)) -> 0 | F10: =IF(OR(A10<=Inputs!$B$21,A10>Inputs!$B$21+Configurations!$D$15),0,IF(A10<=Inputs!$B$21+Inputs!$B$5,Configurations!$D$13,Configurations!$D$12+Configurations!$D$13+Inputs!$B$20*E10)) -> 2.573 | G10: =E10-F10 -> -2.573 | H10: =IF(AND(A10>Inputs!$B$21,A10<=Inputs!$B$21+Inputs!$B$12),Capitalization!F$12,0) -> 26.152929 | I10: =G10-H10 -> -28.725929 | J10: =IF(A10<=Inputs!$B$21,"",IF(AND(A10<=Inputs!$B$22,Capitalization!F$18>0),Inputs!$B$25,Inputs!$B$26)) -> 0.7 | K10: =IF(A10=0,-Capitalization!F$19,IF(A10<=Inputs!$B$21,0,I10*J10-IF(AND(A10=Inputs!$B$22,Capitalization!F$18>0),Inputs!$B$23,0))) -> -20.10815 | L10: =IF(H10>0,G10/H10,"") -> -0.098382863 | M10: =IF(A10=0,-Capitalization!F$4,IF(A10<=Inputs!$B$21,0,G10)) -> -2.573
A11: 6 | B11: =IF(A11=0,"Equity",IF(A11<=Inputs!$B$21,"Construction",IF(A11<=Inputs!$B$21+Inputs!$B$5,"Queue wait",IF(A11<=Inputs!$B$21+Configurations!$D$15,"Grid ops","—")))) -> Queue wait | C11: =IF(A11<=Inputs!$B$21,"",A11-Inputs!$B$21-1) -> 3 | D11: =IF(OR(A11<=Inputs!$B$21,A11>Inputs!$B$21+Configurations!$D$15),0,Configurations!$D$4*Configurations!$D$5*8760*(1-Configurations!$D$6)^C11*Configurations!$D$7*(1-Configurations!$D$8)) -> 730255.5 | E11: =IF(OR(A11<=Inputs!$B$21,A11>Inputs!$B$21+Configurations!$D$15),0,IF(A11<=Inputs!$B$21+Inputs!$B$5,0,D11*Inputs!$B$18/1000000)) -> 0 | F11: =IF(OR(A11<=Inputs!$B$21,A11>Inputs!$B$21+Configurations!$D$15),0,IF(A11<=Inputs!$B$21+Inputs!$B$5,Configurations!$D$13,Configurations!$D$12+Configurations!$D$13+Inputs!$B$20*E11)) -> 2.573 | G11: =E11-F11 -> -2.573 | H11: =IF(AND(A11>Inputs!$B$21,A11<=Inputs!$B$21+Inputs!$B$12),Capitalization!F$12,0) -> 26.152929 | I11: =G11-H11 -> -28.725929 | J11: =IF(A11<=Inputs!$B$21,"",IF(AND(A11<=Inputs!$B$22,Capitalization!F$18>0),Inputs!$B$25,Inputs!$B$26)) -> 0.7 | K11: =IF(A11=0,-Capitalization!F$19,IF(A11<=Inputs!$B$21,0,I11*J11-IF(AND(A11=Inputs!$B$22,Capitalization!F$18>0),Inputs!$B$23,0))) -> -21.10815 | L11: =IF(H11>0,G11/H11,"") -> -0.098382863 | M11: =IF(A11=0,-Capitalization!F$4,IF(A11<=Inputs!$B$21,0,G11)) -> -2.573
A12: 7 | B12: =IF(A12=0,"Equity",IF(A12<=Inputs!$B$21,"Construction",IF(A12<=Inputs!$B$21+Inputs!$B$5,"Queue wait",IF(A12<=Inputs!$B$21+Configurations!$D$15,"Grid ops","—")))) -> Grid ops | C12: =IF(A12<=Inputs!$B$21,"",A12-Inputs!$B$21-1) -> 4 | D12: =IF(OR(A12<=Inputs!$B$21,A12>Inputs!$B$21+Configurations!$D$15),0,Configurations!$D$4*Configurations!$D$5*8760*(1-Configurations!$D$6)^C12*Configurations!$D$7*(1-Configurations!$D$8)) -> 730255.5 | E12: =IF(OR(A12<=Inputs!$B$21,A12>Inputs!$B$21+Configurations!$D$15),0,IF(A12<=Inputs!$B$21+Inputs!$B$5,0,D12*Inputs!$B$18/1000000)) -> 52.578396 | F12: =IF(OR(A12<=Inputs!$B$21,A12>Inputs!$B$21+Configurations!$D$15),0,IF(A12<=Inputs!$B$21+Inputs!$B$5,Configurations!$D$13,Configurations!$D$12+Configurations!$D$13+Inputs!$B$20*E12)) -> 7.9866759 | G12: =E12-F12 -> 44.59172 | H12: =IF(AND(A12>Inputs!$B$21,A12<=Inputs!$B$21+Inputs!$B$12),Capitalization!F$12,0) -> 26.152929 | I12: =G12-H12 -> 18.438791 | J12: =IF(A12<=Inputs!$B$21,"",IF(AND(A12<=Inputs!$B$22,Capitalization!F$18>0),Inputs!$B$25,Inputs!$B$26)) -> 0.975 | K12: =IF(A12=0,-Capitalization!F$19,IF(A12<=Inputs!$B$21,0,I12*J12-IF(AND(A12=Inputs!$B$22,Capitalization!F$18>0),Inputs!$B$23,0))) -> 17.977822 | L12: =IF(H12>0,G12/H12,"") -> 1.7050373 | M12: =IF(A12=0,-Capitalization!F$4,IF(A12<=Inputs!$B$21,0,G12)) -> 44.59172
A13: 8 | B13: =IF(A13=0,"Equity",IF(A13<=Inputs!$B$21,"Construction",IF(A13<=Inputs!$B$21+Inputs!$B$5,"Queue wait",IF(A13<=Inputs!$B$21+Configurations!$D$15,"Grid ops","—")))) -> Grid ops | C13: =IF(A13<=Inputs!$B$21,"",A13-Inputs!$B$21-1) -> 5 | D13: =IF(OR(A13<=Inputs!$B$21,A13>Inputs!$B$21+Configurations!$D$15),0,Configurations!$D$4*Configurations!$D$5*8760*(1-Configurations!$D$6)^C13*Configurations!$D$7*(1-Configurations!$D$8)) -> 730255.5 | E13: =IF(OR(A13<=Inputs!$B$21,A13>Inputs!$B$21+Configurations!$D$15),0,IF(A13<=Inputs!$B$21+Inputs!$B$5,0,D13*Inputs!$B$18/1000000)) -> 52.578396 | F13: =IF(OR(A13<=Inputs!$B$21,A13>Inputs!$B$21+Configurations!$D$15),0,IF(A13<=Inputs!$B$21+Inputs!$B$5,Configurations!$D$13,Configurations!$D$12+Configurations!$D$13+Inputs!$B$20*E13)) -> 7.9866759 | G13: =E13-F13 -> 44.59172 | H13: =IF(AND(A13>Inputs!$B$21,A13<=Inputs!$B$21+Inputs!$B$12),Capitalization!F$12,0) -> 26.152929 | I13: =G13-H13 -> 18.438791 | J13: =IF(A13<=Inputs!$B$21,"",IF(AND(A13<=Inputs!$B$22,Capitalization!F$18>0),Inputs!$B$25,Inputs!$B$26)) -> 0.975 | K13: =IF(A13=0,-Capitalization!F$19,IF(A13<=Inputs!$B$21,0,I13*J13-IF(AND(A13=Inputs!$B$22,Capitalization!F$18>0),Inputs!$B$23,0))) -> 17.977822 | L13: =IF(H13>0,G13/H13,"") -> 1.7050373 | M13: =IF(A13=0,-Capitalization!F$4,IF(A13<=Inputs!$B$21,0,G13)) -> 44.59172
A14: 9 | B14: =IF(A14=0,"Equity",IF(A14<=Inputs!$B$21,"Construction",IF(A14<=Inputs!$B$21+Inputs!$B$5,"Queue wait",IF(A14<=Inputs!$B$21+Configurations!$D$15,"Grid ops","—")))) -> Grid ops | C14: =IF(A14<=Inputs!$B$21,"",A14-Inputs!$B$21-1) -> 6 | D14: =IF(OR(A14<=Inputs!$B$21,A14>Inputs!$B$21+Configurations!$D$15),0,Configurations!$D$4*Configurations!$D$5*8760*(1-Configurations!$D$6)^C14*Configurations!$D$7*(1-Configurations!$D$8)) -> 730255.5 | E14: =IF(OR(A14<=Inputs!$B$21,A14>Inputs!$B$21+Configurations!$D$15),0,IF(A14<=Inputs!$B$21+Inputs!$B$5,0,D14*Inputs!$B$18/1000000)) -> 52.578396 | F14: =IF(OR(A14<=Inputs!$B$21,A14>Inputs!$B$21+Configurations!$D$15),0,IF(A14<=Inputs!$B$21+Inputs!$B$5,Configurations!$D$13,Configurations!$D$12+Configurations!$D$13+Inputs!$B$20*E14)) -> 7.9866759 | G14: =E14-F14 -> 44.59172 | H14: =IF(AND(A14>Inputs!$B$21,A14<=Inputs!$B$21+Inputs!$B$12),Capitalization!F$12,0) -> 26.152929 | I14: =G14-H14 -> 18.438791 | J14: =IF(A14<=Inputs!$B$21,"",IF(AND(A14<=Inputs!$B$22,Capitalization!F$18>0),Inputs!$B$25,Inputs!$B$26)) -> 0.975 | K14: =IF(A14=0,-Capitalization!F$19,IF(A14<=Inputs!$B$21,0,I14*J14-IF(AND(A14=Inputs!$B$22,Capitalization!F$18>0),Inputs!$B$23,0))) -> 17.977822 | L14: =IF(H14>0,G14/H14,"") -> 1.7050373 | M14: =IF(A14=0,-Capitalization!F$4,IF(A14<=Inputs!$B$21,0,G14)) -> 44.59172
A15: 10 | B15: =IF(A15=0,"Equity",IF(A15<=Inputs!$B$21,"Construction",IF(A15<=Inputs!$B$21+Inputs!$B$5,"Queue wait",IF(A15<=Inputs!$B$21+Configurations!$D$15,"Grid ops","—")))) -> Grid ops | C15: =IF(A15<=Inputs!$B$21,"",A15-Inputs!$B$21-1) -> 7 | D15: =IF(OR(A15<=Inputs!$B$21,A15>Inputs!$B$21+Configurations!$D$15),0,Configurations!$D$4*Configurations!$D$5*8760*(1-Configurations!$D$6)^C15*Configurations!$D$7*(1-Configurations!$D$8)) -> 730255.5 | E15: =IF(OR(A15<=Inputs!$B$21,A15>Inputs!$B$21+Configurations!$D$15),0,IF(A15<=Inputs!$B$21+Inputs!$B$5,0,D15*Inputs!$B$18/1000000)) -> 52.578396 | F15: =IF(OR(A15<=Inputs!$B$21,A15>Inputs!$B$21+Configurations!$D$15),0,IF(A15<=Inputs!$B$21+Inputs!$B$5,Configurations!$D$13,Configurations!$D$12+Configurations!$D$13+Inputs!$B$20*E15)) -> 7.9866759 | G15: =E15-F15 -> 44.59172 | H15: =IF(AND(A15>Inputs!$B$21,A15<=Inputs!$B$21+Inputs!$B$12),Capitalization!F$12,0) -> 26.152929 | I15: =G15-H15 -> 18.438791 | J15: =IF(A15<=Inputs!$B$21,"",IF(AND(A15<=Inputs!$B$22,Capitalization!F$18>0),Inputs!$B$25,Inputs!$B$26)) -> 0.975 | K15: =IF(A15=0,-Capitalization!F$19,IF(A15<=Inputs!$B$21,0,I15*J15-IF(AND(A15=Inputs!$B$22,Capitalization!F$18>0),Inputs!$B$23,0))) -> 17.977822 | L15: =IF(H15>0,G15/H15,"") -> 1.7050373 | M15: =IF(A15=0,-Capitalization!F$4,IF(A15<=Inputs!$B$21,0,G15)) -> 44.59172
A16: 11 | B16: =IF(A16=0,"Equity",IF(A16<=Inputs!$B$21,"Construction",IF(A16<=Inputs!$B$21+Inputs!$B$5,"Queue wait",IF(A16<=Inputs!$B$21+Configurations!$D$15,"Grid ops","—")))) -> Grid ops | C16: =IF(A16<=Inputs!$B$21,"",A16-Inputs!$B$21-1) -> 8 | D16: =IF(OR(A16<=Inputs!$B$21,A16>Inputs!$B$21+Configurations!$D$15),0,Configurations!$D$4*Configurations!$D$5*8760*(1-Configurations!$D$6)^C16*Configurations!$D$7*(1-Configurations!$D$8)) -> 730255.5 | E16: =IF(OR(A16<=Inputs!$B$21,A16>Inputs!$B$21+Configurations!$D$15),0,IF(A16<=Inputs!$B$21+Inputs!$B$5,0,D16*Inputs!$B$18/1000000)) -> 52.578396 | F16: =IF(OR(A16<=Inputs!$B$21,A16>Inputs!$B$21+Configurations!$D$15),0,IF(A16<=Inputs!$B$21+Inputs!$B$5,Configurations!$D$13,Configurations!$D$12+Configurations!$D$13+Inputs!$B$20*E16)) -> 7.9866759 | G16: =E16-F16 -> 44.59172 | H16: =IF(AND(A16>Inputs!$B$21,A16<=Inputs!$B$21+Inputs!$B$12),Capitalization!F$12,0) -> 26.152929 | I16: =G16-H16 -> 18.438791 | J16: =IF(A16<=Inputs!$B$21,"",IF(AND(A16<=Inputs!$B$22,Capitalization!F$18>0),Inputs!$B$25,Inputs!$B$26)) -> 0.975 | K16: =IF(A16=0,-Capitalization!F$19,IF(A16<=Inputs!$B$21,0,I16*J16-IF(AND(A16=Inputs!$B$22,Capitalization!F$18>0),Inputs!$B$23,0))) -> 17.977822 | L16: =IF(H16>0,G16/H16,"") -> 1.7050373 | M16: =IF(A16=0,-Capitalization!F$4,IF(A16<=Inputs!$B$21,0,G16)) -> 44.59172
... A37: 32 | B37: =IF(A37=0,"Equity",IF(A37<=Inputs!$B$21,"Construction",IF(A37<=Inputs!$B$21+Inputs!$B$5,"Queue wait",IF(A37<=Inputs!$B$21+Configurations!$D$15,"Grid ops","—")))) -> Grid ops | C37: =IF(A37<=Inputs!$B$21,"",A37-Inputs!$B$21-1) -> 29 | D37: =IF(OR(A37<=Inputs!$B$21,A37>Inputs!$B$21+Configurations!$D$15),0,Configurations!$D$4*Configurations!$D$5*8760*(1-Configurations!$D$6)^C37*Configurations!$D$7*(1-Configurations!$D$8)) -> 730255.5 | E37: =IF(OR(A37<=Inputs!$B$21,A37>Inputs!$B$21+Configurations!$D$15),0,IF(A37<=Inputs!$B$21+Inputs!$B$5,0,D37*Inputs!$B$18/1000000)) -> 52.578396 | F37: =IF(OR(A37<=Inputs!$B$21,A37>Inputs!$B$21+Configurations!$D$15),0,IF(A37<=Inputs!$B$21+Inputs!$B$5,Configurations!$D$13,Configurations!$D$12+Configurations!$D$13+Inputs!$B$20*E37)) -> 7.9866759 | G37: =E37-F37 -> 44.59172 | H37: =IF(AND(A37>Inputs!$B$21,A37<=Inputs!$B$21+Inputs!$B$12),Capitalization!F$12,0) -> 0 | I37: =G37-H37 -> 44.59172 | J37: =IF(A37<=Inputs!$B$21,"",IF(AND(A37<=Inputs!$B$22,Capitalization!F$18>0),Inputs!$B$25,Inputs!$B$26)) -> 0.975 | K37: =IF(A37=0,-Capitalization!F$19,IF(A37<=Inputs!$B$21,0,I37*J37-IF(AND(A37=Inputs!$B$22,Capitalization!F$18>0),Inputs!$B$23,0))) -> 43.476927 | L37: =IF(H37>0,G37/H37,"") | M37: =IF(A37=0,-Capitalization!F$4,IF(A37<=Inputs!$B$21,0,G37)) -> 44.59172

Sheet GeoColoc
A1: GeoColoc — annual cash flow waterfall ($mm)
A2: Developer levered IRR: | B2: =IRR(K5:K37) -> 0.18824895 | C2: Unlevered (project) IRR: | D2: =IRR(M5:M37) -> 0.050237378 | E2: NPV of dev cash @ discount rate ($mm): | F2: =K5+NPV(Inputs!$B$24,K6:K37) -> 117.39788
A4: Year | B4: Phase | C4: Op yr | D4: Net energy (MWh) | E4: Revenue | F4: OPEX | G4: EBITDA | H4: Debt service | I4: Distributable cash | J4: Dev share | K4: Dev cash flow | L4: DSCR | M4: Project CF (unlevered)
A5: 0 | B5: =IF(A5=0,"Equity",IF(A5<=Inputs!$B$21,"Construction",IF(A5<=Inputs!$B$21+Inputs!$B$5,"Queue wait",IF(A5<=Inputs!$B$21+Configurations!$D$15,"Grid ops","—")))) -> Equity | C5: =IF(A5<=Inputs!$B$21,"",A5-Inputs!$B$21-1) | D5: =IF(OR(A5<=Inputs!$B$21,A5>Inputs!$B$21+Configurations!$D$15),0,Configurations!$D$4*Configurations!$D$5*8760*(1-Configurations!$D$6)^C5*Configurations!$D$7*(1-Configurations!$D$8)) -> 0 | E5: =IF(OR(A5<=Inputs!$B$21,A5>Inputs!$B$21+Configurations!$D$15),0,IF(A5<=Inputs!$B$21+Inputs!$B$5,D5*(1-Inputs!$B$10)*Inputs!$B$19/1000000,D5*Inputs!$B$18/1000000)) -> 0 | F5: =IF(OR(A5<=Inputs!$B$21,A5>Inputs!$B$21+Configurations!$D$15),0,Configurations!$D$12+Configurations!$D$13+Configurations!$D$14+Inputs!$B$20*E5) -> 0 | G5: =E5-F5 -> 0 | H5: =IF(AND(A5>Inputs!$B$21,A5<=Inputs!$B$21+Inputs!$B$12),Capitalization!G$12,0) -> 0 | I5: =G5-H5 -> 0 | J5: =IF(A5<=Inputs!$B$21,"",IF(AND(A5<=Inputs!$B$22,Capitalization!G$18>0),Inputs!$B$25,Inputs!$B$26)) | K5: =IF(A5=0,-Capitalization!G$19,IF(A5<=Inputs!$B$21,0,I5*J5-IF(AND(A5=Inputs!$B$22,Capitalization!G$18>0),Inputs!$B$23,0))) -> -43.974086 | L5: =IF(H5>0,G5/H5,"") | M5: =IF(A5=0,-Capitalization!G$4,IF(A5<=Inputs!$B$21,0,G5)) -> -580.25
A6: 1 | B6: =IF(A6=0,"Equity",IF(A6<=Inputs!$B$21,"Construction",IF(A6<=Inputs!$B$21+Inputs!$B$5,"Queue wait",IF(A6<=Inputs!$B$21+Configurations!$D$15,"Grid ops","—")))) -> Construction | C6: =IF(A6<=Inputs!$B$21,"",A6-Inputs!$B$21-1) | D6: =IF(OR(A6<=Inputs!$B$21,A6>Inputs!$B$21+Configurations!$D$15),0,Configurations!$D$4*Configurations!$D$5*8760*(1-Configurations!$D$6)^C6*Configurations!$D$7*(1-Configurations!$D$8)) -> 0 | E6: =IF(OR(A6<=Inputs!$B$21,A6>Inputs!$B$21+Configurations!$D$15),0,IF(A6<=Inputs!$B$21+Inputs!$B$5,D6*(1-Inputs!$B$10)*Inputs!$B$19/1000000,D6*Inputs!$B$18/1000000)) -> 0 | F6: =IF(OR(A6<=Inputs!$B$21,A6>Inputs!$B$21+Configurations!$D$15),0,Configurations!$D$12+Configurations!$D$13+Configurations!$D$14+Inputs!$B$20*E6) -> 0 | G6: =E6-F6 -> 0 | H6: =IF(AND(A6>Inputs!$B$21,A6<=Inputs!$B$21+Inputs!$B$12),Capitalization!G$12,0) -> 0 | I6: =G6-H6 -> 0 | J6: =IF(A6<=Inputs!$B$21,"",IF(AND(A6<=Inputs!$B$22,Capitalization!G$18>0),Inputs!$B$25,Inputs!$B$26)) | K6: =IF(A6=0,-Capitalization!G$19,IF(A6<=Inputs!$B$21,0,I6*J6-IF(AND(A6=Inputs!$B$22,Capitalization!G$18>0),Inputs!$B$23,0))) -> 0 | L6: =IF(H6>0,G6/H6,"") | M6: =IF(A6=0,-Capitalization!G$4,IF(A6<=Inputs!$B$21,0,G6)) -> 0
A7: 2 | B7: =IF(A7=0,"Equity",IF(A7<=Inputs!$B$21,"Construction",IF(A7<=Inputs!$B$21+Inputs!$B$5,"Queue wait",IF(A7<=Inputs!$B$21+Configurations!$D$15,"Grid ops","—")))) -> Construction | C7: =IF(A7<=Inputs!$B$21,"",A7-Inputs!$B$21-1) | D7: =IF(OR(A7<=Inputs!$B$21,A7>Inputs!$B$21+Configurations!$D$15),0,Configurations!$D$4*Configurations!$D$5*8760*(1-Configurations!$D$6)^C7*Configurations!$D$7*(1-Configurations!$D$8)) -> 0 | E7: =IF(OR(A7<=Inputs!$B$21,A7>Inputs!$B$21+Configurations!$D$15),0,IF(A7<=Inputs!$B$21+Inputs!$B$5,D7*(1-Inputs!$B$10)*Inputs!$B$19/1000000,D7*Inputs!$B$18/1000000)) -> 0 | F7: =IF(OR(A7<=Inputs!$B$21,A7>Inputs!$B$21+Configurations!$D$15),0,Configurations!$D$12+Configurations!$D$13+Configurations!$D$14+Inputs!$B$20*E7) -> 0 | G7: =E7-F7 -> 0 | H7: =IF(AND(A7>Inputs!$B$21,A7<=Inputs!$B$21+Inputs!$B$12),Capitalization!G$12,0) -> 0 | I7: =G7-H7 -> 0 | J7: =IF(A7<=Inputs!$B$21,"",IF(AND(A7<=Inputs!$B$22,Capitalization!G$18>0),Inputs!$B$25,Inputs!$B$26)) | K7: =IF(A7=0,-Capitalization!G$19,IF(A7<=Inputs!$B$21,0,I7*J7-IF(AND(A7=Inputs!$B$22,Capitalization!G$18>0),Inputs!$B$23,0))) -> 0 | L7: =IF(H7>0,G7/H7,"") | M7: =IF(A7=0,-Capitalization!G$4,IF(A7<=Inputs!$B$21,0,G7)) -> 0
A8: 3 | B8: =IF(A8=0,"Equity",IF(A8<=Inputs!$B$21,"Construction",IF(A8<=Inputs!$B$21+Inputs!$B$5,"Queue wait",IF(A8<=Inputs!$B$21+Configurations!$D$15,"Grid ops","—")))) -> Queue wait | C8: =IF(A8<=Inputs!$B$21,"",A8-Inputs!$B$21-1) -> 0 | D8: =IF(OR(A8<=Inputs!$B$21,A8>Inputs!$B$21+Configurations!$D$15),0,Configurations!$D$4*Configurations!$D$5*8760*(1-Configurations!$D$6)^C8*Configurations!$D$7*(1-Configurations!$D$8)) -> 730255.5 | E8: =IF(OR(A8<=Inputs!$B$21,A8>Inputs!$B$21+Configurations!$D$15),0,IF(A8<=Inputs!$B$21+Inputs!$B$5,D8*(1-Inputs!$B$10)*Inputs!$B$19/1000000,D8*Inputs!$B$18/1000000)) -> 43.377177 | F8: =IF(OR(A8<=Inputs!$B$21,A8>Inputs!$B$21+Configurations!$D$15),0,Configurations!$D$12+Configurations!$D$13+Configurations!$D$14+Inputs!$B$20*E8) -> 8.5986577 | G8: =E8-F8 -> 34.778519 | H8: =IF(AND(A8>Inputs!$B$21,A8<=Inputs!$B$21+Inputs!$B$12),Capitalization!G$12,0) -> 26.705212 | I8: =G8-H8 -> 8.0733069 | J8: =IF(A8<=Inputs!$B$21,"",IF(AND(A8<=Inputs!$B$22,Capitalization!G$18>0),Inputs!$B$25,Inputs!$B$26)) -> 0.7 | K8: =IF(A8=0,-Capitalization!G$19,IF(A8<=Inputs!$B$21,0,I8*J8-IF(AND(A8=Inputs!$B$22,Capitalization!G$18>0),Inputs!$B$23,0))) -> 5.6513148 | L8: =IF(H8>0,G8/H8,"") -> 1.302312 | M8: =IF(A8=0,-Capitalization!G$4,IF(A8<=Inputs!$B$21,0,G8)) -> 34.778519
A9: 4 | B9: =IF(A9=0,"Equity",IF(A9<=Inputs!$B$21,"Construction",IF(A9<=Inputs!$B$21+Inputs!$B$5,"Queue wait",IF(A9<=Inputs!$B$21+Configurations!$D$15,"Grid ops","—")))) -> Queue wait | C9: =IF(A9<=Inputs!$B$21,"",A9-Inputs!$B$21-1) -> 1 | D9: =IF(OR(A9<=Inputs!$B$21,A9>Inputs!$B$21+Configurations!$D$15),0,Configurations!$D$4*Configurations!$D$5*8760*(1-Configurations!$D$6)^C9*Configurations!$D$7*(1-Configurations!$D$8)) -> 730255.5 | E9: =IF(OR(A9<=Inputs!$B$21,A9>Inputs!$B$21+Configurations!$D$15),0,IF(A9<=Inputs!$B$21+Inputs!$B$5,D9*(1-Inputs!$B$10)*Inputs!$B$19/1000000,D9*Inputs!$B$18/1000000)) -> 43.377177 | F9: =IF(OR(A9<=Inputs!$B$21,A9>Inputs!$B$21+Configurations!$D$15),0,Configurations!$D$12+Configurations!$D$13+Configurations!$D$14+Inputs!$B$20*E9) -> 8.5986577 | G9: =E9-F9 -> 34.778519 | H9: =IF(AND(A9>Inputs!$B$21,A9<=Inputs!$B$21+Inputs!$B$12),Capitalization!G$12,0) -> 26.705212 | I9: =G9-H9 -> 8.0733069 | J9: =IF(A9<=Inputs!$B$21,"",IF(AND(A9<=Inputs!$B$22,Capitalization!G$18>0),Inputs!$B$25,Inputs!$B$26)) -> 0.7 | K9: =IF(A9=0,-Capitalization!G$19,IF(A9<=Inputs!$B$21,0,I9*J9-IF(AND(A9=Inputs!$B$22,Capitalization!G$18>0),Inputs!$B$23,0))) -> 5.6513148 | L9: =IF(H9>0,G9/H9,"") -> 1.302312 | M9: =IF(A9=0,-Capitalization!G$4,IF(A9<=Inputs!$B$21,0,G9)) -> 34.778519
A10: 5 | B10: =IF(A10=0,"Equity",IF(A10<=Inputs!$B$21,"Construction",IF(A10<=Inputs!$B$21+Inputs!$B$5,"Queue wait",IF(A10<=Inputs!$B$21+Configurations!$D$15,"Grid ops","—")))) -> Queue wait | C10: =IF(A10<=Inputs!$B$21,"",A10-Inputs!$B$21-1) -> 2 | D10: =IF(OR(A10<=Inputs!$B$21,A10>Inputs!$B$21+Configurations!$D$15),0,Configurations!$D$4*Configurations!$D$5*8760*(1-Configurations!$D$6)^C10*Configurations!$D$7*(1-Configurations!$D$8)) -> 730255.5 | E10: =IF(OR(A10<=Inputs!$B$21,A10>Inputs!$B$21+Configurations!$D$15),0,IF(A10<=Inputs!$B$21+Inputs!$B$5,D10*(1-Inputs!$B$10)*Inputs!$B$19/1000000,D10*Inputs!$B$18/1000000)) -> 43.377177 | F10: =IF(OR(A10<=Inputs!$B$21,A10>Inputs!$B$21+Configurations!$D$15),0,Configurations!$D$12+Configurations!$D$13+Configurations!$D$14+Inputs!$B$20*E10) -> 8.5986577 | G10: =E10-F10 -> 34.778519 | H10: =IF(AND(A10>Inputs!$B$21,A10<=Inputs!$B$21+Inputs!$B$12),Capitalization!G$12,0) -> 26.705212 | I10: =G10-H10 -> 8.0733069 | J10: =IF(A10<=Inputs!$B$21,"",IF(AND(A10<=Inputs!$B$22,Capitalization!G$18>0),Inputs!$B$25,Inputs!$B$26)) -> 0.7 | K10: =IF(A10=0,-Capitalization!G$19,IF(A10<=Inputs!$B$21,0,I10*J10-IF(AND(A10=Inputs!$B$22,Capitalization!G$18>0),Inputs!$B$23,0))) -> 5.6513148 | L10: =IF(H10>0,G10/H10,"") -> 1.302312 | M10: =IF(A10=0,-Capitalization!G$4,IF(A10<=Inputs!$B$21,0,G10)) -> 34.778519
A11: 6 | B11: =IF(A11=0,"Equity",IF(A11<=Inputs!$B$21,"Construction",IF(A11<=Inputs!$B$21+Inputs!$B$5,"Queue wait",IF(A11<=Inputs!$B$21+Configurations!$D$15,"Grid ops","—")))) -> Queue wait | C11: =IF(A11<=Inputs!$B$21,"",A11-Inputs!$B$21-1) -> 3 | D11: =IF(OR(A11<=Inputs!$B$21,A11>Inputs!$B$21+Configurations!$D$15),0,Configurations!$D$4*Configurations!$D$5*8760*(1-Configurations!$D$6)^C11*Configurations!$D$7*(1-Configurations!$D$8)) -> 730255.5 | E11: =IF(OR(A11<=Inputs!$B$21,A11>Inputs!$B$21+Configurations!$D$15),0,IF(A11<=Inputs!$B$21+Inputs!$B$5,D11*(1-Inputs!$B$10)*Inputs!$B$19/1000000,D11*Inputs!$B$18/1000000)) -> 43.377177 | F11: =IF(OR(A11<=Inputs!$B$21,A11>Inputs!$B$21+Configurations!$D$15),0,Configurations!$D$12+Configurations!$D$13+Configurations!$D$14+Inputs!$B$20*E11) -> 8.5986577 | G11: =E11-F11 -> 34.778519 | H11: =IF(AND(A11>Inputs!$B$21,A11<=Inputs!$B$21+Inputs!$B$12),Capitalization!G$12,0) -> 26.705212 | I11: =G11-H11 -> 8.0733069 | J11: =IF(A11<=Inputs!$B$21,"",IF(AND(A11<=Inputs!$B$22,Capitalization!G$18>0),Inputs!$B$25,Inputs!$B$26)) -> 0.7 | K11: =IF(A11=0,-Capitalization!G$19,IF(A11<=Inputs!$B$21,0,I11*J11-IF(AND(A11=Inputs!$B$22,Capitalization!G$18>0),Inputs!$B$23,0))) -> 4.6513148 | L11: =IF(H11>0,G11/H11,"") -> 1.302312 | M11: =IF(A11=0,-Capitalization!G$4,IF(A11<=Inputs!$B$21,0,G11)) -> 34.778519
A12: 7 | B12: =IF(A12=0,"Equity",IF(A12<=Inputs!$B$21,"Construction",IF(A12<=Inputs!$B$21+Inputs!$B$5,"Queue wait",IF(A12<=Inputs!$B$21+Configurations!$D$15,"Grid ops","—")))) -> Grid ops | C12: =IF(A12<=Inputs!$B$21,"",A12-Inputs!$B$21-1) -> 4 | D12: =IF(OR(A12<=Inputs!$B$21,A12>Inputs!$B$21+Configurations!$D$15),0,Configurations!$D$4*Configurations!$D$5*8760*(1-Configurations!$D$6)^C12*Configurations!$D$7*(1-Configurations!$D$8)) -> 730255.5 | E12: =IF(OR(A12<=Inputs!$B$21,A12>Inputs!$B$21+Configurations!$D$15),0,IF(A12<=Inputs!$B$21+Inputs!$B$5,D12*(1-Inputs!$B$10)*Inputs!$B$19/1000000,D12*Inputs!$B$18/1000000)) -> 52.578396 | F12: =IF(OR(A12<=Inputs!$B$21,A12>Inputs!$B$21+Configurations!$D$15),0,Configurations!$D$12+Configurations!$D$13+Configurations!$D$14+Inputs!$B$20*E12) -> 8.7366759 | G12: =E12-F12 -> 43.84172 | H12: =IF(AND(A12>Inputs!$B$21,A12<=Inputs!$B$21+Inputs!$B$12),Capitalization!G$12,0) -> 26.705212 | I12: =G12-H12 -> 17.136508 | J12: =IF(A12<=Inputs!$B$21,"",IF(AND(A12<=Inputs!$B$22,Capitalization!G$18>0),Inputs!$B$25,Inputs!$B$26)) -> 0.975 | K12: =IF(A12=0,-Capitalization!G$19,IF(A12<=Inputs!$B$21,0,I12*J12-IF(AND(A12=Inputs!$B$22,Capitalization!G$18>0),Inputs!$B$23,0))) -> 16.708095 | L12: =IF(H12>0,G12/H12,"") -> 1.6416915 | M12: =IF(A12=0,-Capitalization!G$4,IF(A12<=Inputs!$B$21,0,G12)) -> 43.84172
A13: 8 | B13: =IF(A13=0,"Equity",IF(A13<=Inputs!$B$21,"Construction",IF(A13<=Inputs!$B$21+Inputs!$B$5,"Queue wait",IF(A13<=Inputs!$B$21+Configurations!$D$15,"Grid ops","—")))) -> Grid ops | C13: =IF(A13<=Inputs!$B$21,"",A13-Inputs!$B$21-1) -> 5 | D13: =IF(OR(A13<=Inputs!$B$21,A13>Inputs!$B$21+Configurations!$D$15),0,Configurations!$D$4*Configurations!$D$5*8760*(1-Configurations!$D$6)^C13*Configurations!$D$7*(1-Configurations!$D$8)) -> 730255.5 | E13: =IF(OR(A13<=Inputs!$B$21,A13>Inputs!$B$21+Configurations!$D$15),0,IF(A13<=Inputs!$B$21+Inputs!$B$5,D13*(1-Inputs!$B$10)*Inputs!$B$19/1000000,D13*Inputs!$B$18/1000000)) -> 52.578396 | F13: =IF(OR(A13<=Inputs!$B$21,A13>Inputs!$B$21+Configurations!$D$15),0,Configurations!$D$12+Configurations!$D$13+Configurations!$D$14+Inputs!$B$20*E13) -> 8.7366759 | G13: =E13-F13 -> 43.84172 | H13: =IF(AND(A13>Inputs!$B$21,A13<=Inputs!$B$21+Inputs!$B$12),Capitalization!G$12,0) -> 26.705212 | I13: =G13-H13 -> 17.136508 | J13: =IF(A13<=Inputs!$B$21,"",IF(AND(A13<=Inputs!$B$22,Capitalization!G$18>0),Inputs!$B$25,Inputs!$B$26)) -> 0.975 | K13: =IF(A13=0,-Capitalization!G$19,IF(A13<=Inputs!$B$21,0,I13*J13-IF(AND(A13=Inputs!$B$22,Capitalization!G$18>0),Inputs!$B$23,0))) -> 16.708095 | L13: =IF(H13>0,G13/H13,"") -> 1.6416915 | M13: =IF(A13=0,-Capitalization!G$4,IF(A13<=Inputs!$B$21,0,G13)) -> 43.84172
A14: 9 | B14: =IF(A14=0,"Equity",IF(A14<=Inputs!$B$21,"Construction",IF(A14<=Inputs!$B$21+Inputs!$B$5,"Queue wait",IF(A14<=Inputs!$B$21+Configurations!$D$15,"Grid ops","—")))) -> Grid ops | C14: =IF(A14<=Inputs!$B$21,"",A14-Inputs!$B$21-1) -> 6 | D14: =IF(OR(A14<=Inputs!$B$21,A14>Inputs!$B$21+Configurations!$D$15),0,Configurations!$D$4*Configurations!$D$5*8760*(1-Configurations!$D$6)^C14*Configurations!$D$7*(1-Configurations!$D$8)) -> 730255.5 | E14: =IF(OR(A14<=Inputs!$B$21,A14>Inputs!$B$21+Configurations!$D$15),0,IF(A14<=Inputs!$B$21+Inputs!$B$5,D14*(1-Inputs!$B$10)*Inputs!$B$19/1000000,D14*Inputs!$B$18/1000000)) -> 52.578396 | F14: =IF(OR(A14<=Inputs!$B$21,A14>Inputs!$B$21+Configurations!$D$15),0,Configurations!$D$12+Configurations!$D$13+Configurations!$D$14+Inputs!$B$20*E14) -> 8.7366759 | G14: =E14-F14 -> 43.84172 | H14: =IF(AND(A14>Inputs!$B$21,A14<=Inputs!$B$21+Inputs!$B$12),Capitalization!G$12,0) -> 26.705212 | I14: =G14-H14 -> 17.136508 | J14: =IF(A14<=Inputs!$B$21,"",IF(AND(A14<=Inputs!$B$22,Capitalization!G$18>0),Inputs!$B$25,Inputs!$B$26)) -> 0.975 | K14: =IF(A14=0,-Capitalization!G$19,IF(A14<=Inputs!$B$21,0,I14*J14-IF(AND(A14=Inputs!$B$22,Capitalization!G$18>0),Inputs!$B$23,0))) -> 16.708095 | L14: =IF(H14>0,G14/H14,"") -> 1.6416915 | M14: =IF(A14=0,-Capitalization!G$4,IF(A14<=Inputs!$B$21,0,G14)) -> 43.84172
A15: 10 | B15: =IF(A15=0,"Equity",IF(A15<=Inputs!$B$21,"Construction",IF(A15<=Inputs!$B$21+Inputs!$B$5,"Queue wait",IF(A15<=Inputs!$B$21+Configurations!$D$15,"Grid ops","—")))) -> Grid ops | C15: =IF(A15<=Inputs!$B$21,"",A15-Inputs!$B$21-1) -> 7 | D15: =IF(OR(A15<=Inputs!$B$21,A15>Inputs!$B$21+Configurations!$D$15),0,Configurations!$D$4*Configurations!$D$5*8760*(1-Configurations!$D$6)^C15*Configurations!$D$7*(1-Configurations!$D$8)) -> 730255.5 | E15: =IF(OR(A15<=Inputs!$B$21,A15>Inputs!$B$21+Configurations!$D$15),0,IF(A15<=Inputs!$B$21+Inputs!$B$5,D15*(1-Inputs!$B$10)*Inputs!$B$19/1000000,D15*Inputs!$B$18/1000000)) -> 52.578396 | F15: =IF(OR(A15<=Inputs!$B$21,A15>Inputs!$B$21+Configurations!$D$15),0,Configurations!$D$12+Configurations!$D$13+Configurations!$D$14+Inputs!$B$20*E15) -> 8.7366759 | G15: =E15-F15 -> 43.84172 | H15: =IF(AND(A15>Inputs!$B$21,A15<=Inputs!$B$21+Inputs!$B$12),Capitalization!G$12,0) -> 26.705212 | I15: =G15-H15 -> 17.136508 | J15: =IF(A15<=Inputs!$B$21,"",IF(AND(A15<=Inputs!$B$22,Capitalization!G$18>0),Inputs!$B$25,Inputs!$B$26)) -> 0.975 | K15: =IF(A15=0,-Capitalization!G$19,IF(A15<=Inputs!$B$21,0,I15*J15-IF(AND(A15=Inputs!$B$22,Capitalization!G$18>0),Inputs!$B$23,0))) -> 16.708095 | L15: =IF(H15>0,G15/H15,"") -> 1.6416915 | M15: =IF(A15=0,-Capitalization!G$4,IF(A15<=Inputs!$B$21,0,G15)) -> 43.84172
A16: 11 | B16: =IF(A16=0,"Equity",IF(A16<=Inputs!$B$21,"Construction",IF(A16<=Inputs!$B$21+Inputs!$B$5,"Queue wait",IF(A16<=Inputs!$B$21+Configurations!$D$15,"Grid ops","—")))) -> Grid ops | C16: =IF(A16<=Inputs!$B$21,"",A16-Inputs!$B$21-1) -> 8 | D16: =IF(OR(A16<=Inputs!$B$21,A16>Inputs!$B$21+Configurations!$D$15),0,Configurations!$D$4*Configurations!$D$5*8760*(1-Configurations!$D$6)^C16*Configurations!$D$7*(1-Configurations!$D$8)) -> 730255.5 | E16: =IF(OR(A16<=Inputs!$B$21,A16>Inputs!$B$21+Configurations!$D$15),0,IF(A16<=Inputs!$B$21+Inputs!$B$5,D16*(1-Inputs!$B$10)*Inputs!$B$19/1000000,D16*Inputs!$B$18/1000000)) -> 52.578396 | F16: =IF(OR(A16<=Inputs!$B$21,A16>Inputs!$B$21+Configurations!$D$15),0,Configurations!$D$12+Configurations!$D$13+Configurations!$D$14+Inputs!$B$20*E16) -> 8.7366759 | G16: =E16-F16 -> 43.84172 | H16: =IF(AND(A16>Inputs!$B$21,A16<=Inputs!$B$21+Inputs!$B$12),Capitalization!G$12,0) -> 26.705212 | I16: =G16-H16 -> 17.136508 | J16: =IF(A16<=Inputs!$B$21,"",IF(AND(A16<=Inputs!$B$22,Capitalization!G$18>0),Inputs!$B$25,Inputs!$B$26)) -> 0.975 | K16: =IF(A16=0,-Capitalization!G$19,IF(A16<=Inputs!$B$21,0,I16*J16-IF(AND(A16=Inputs!$B$22,Capitalization!G$18>0),Inputs!$B$23,0))) -> 16.708095 | L16: =IF(H16>0,G16/H16,"") -> 1.6416915 | M16: =IF(A16=0,-Capitalization!G$4,IF(A16<=Inputs!$B$21,0,G16)) -> 43.84172
... A37: 32 | B37: =IF(A37=0,"Equity",IF(A37<=Inputs!$B$21,"Construction",IF(A37<=Inputs!$B$21+Inputs!$B$5,"Queue wait",IF(A37<=Inputs!$B$21+Configurations!$D$15,"Grid ops","—")))) -> Grid ops | C37: =IF(A37<=Inputs!$B$21,"",A37-Inputs!$B$21-1) -> 29 | D37: =IF(OR(A37<=Inputs!$B$21,A37>Inputs!$B$21+Configurations!$D$15),0,Configurations!$D$4*Configurations!$D$5*8760*(1-Configurations!$D$6)^C37*Configurations!$D$7*(1-Configurations!$D$8)) -> 730255.5 | E37: =IF(OR(A37<=Inputs!$B$21,A37>Inputs!$B$21+Configurations!$D$15),0,IF(A37<=Inputs!$B$21+Inputs!$B$5,D37*(1-Inputs!$B$10)*Inputs!$B$19/1000000,D37*Inputs!$B$18/1000000)) -> 52.578396 | F37: =IF(OR(A37<=Inputs!$B$21,A37>Inputs!$B$21+Configurations!$D$15),0,Configurations!$D$12+Configurations!$D$13+Configurations!$D$14+Inputs!$B$20*E37) -> 8.7366759 | G37: =E37-F37 -> 43.84172 | H37: =IF(AND(A37>Inputs!$B$21,A37<=Inputs!$B$21+Inputs!$B$12),Capitalization!G$12,0) -> 0 | I37: =G37-H37 -> 43.84172 | J37: =IF(A37<=Inputs!$B$21,"",IF(AND(A37<=Inputs!$B$22,Capitalization!G$18>0),Inputs!$B$25,Inputs!$B$26)) -> 0.975 | K37: =IF(A37=0,-Capitalization!G$19,IF(A37<=Inputs!$B$21,0,I37*J37-IF(AND(A37=Inputs!$B$22,Capitalization!G$18>0),Inputs!$B$23,0))) -> 42.745677 | L37: =IF(H37>0,G37/H37,"") | M37: =IF(A37=0,-Capitalization!G$4,IF(A37<=Inputs!$B$21,0,G37)) -> 43.84172

Sheet Results
A1: Results — all three configurations side by side (live; global levers on Inputs)
B3: Solar+BESS 100MW | C3: Wind+BESS 150MW | D3: Geothermal+BESS 100MW
A4: Baseline developer levered IRR | B4: =SolarBase!B2 -> 0.040713705 | C4: =WindBase!B2 -> 0.076471682 | D4: =GeoBase!B2 -> 0.1161382
A5: Co-location developer levered IRR | B5: =SolarColoc!B2 -> 0.044070577 | C5: =WindColoc!B2 -> 0.10059927 | D5: =GeoColoc!B2 -> 0.18824895
A6: Delta IRR (co-location - baseline), pp | B6: =(SolarColoc!B2-SolarBase!B2)*100 -> 0.33568718 | C6: =(WindColoc!B2-WindBase!B2)*100 -> 2.4127583 | D6: =(GeoColoc!B2-GeoBase!B2)*100 -> 7.2110754
A7: Baseline unlevered (project) IRR | B7: =SolarBase!D2 -> 0.0091238666 | C7: =WindBase!D2 -> 0.02031468 | D7: =GeoBase!D2 -> 0.03856386
A8: Co-location unlevered (project) IRR | B8: =SolarColoc!D2 -> 0.012821957 | C8: =WindColoc!D2 -> 0.026329954 | D8: =GeoColoc!D2 -> 0.050237378
A9: Baseline NPV of dev cash ($mm) | B9: =SolarBase!F2 -> -15.39658 | C9: =WindBase!F2 -> -2.4701198 | D9: =GeoBase!F2 -> 57.635835
A10: Co-location NPV of dev cash ($mm) | B10: =SolarColoc!F2 -> -15.39725 | C10: =WindColoc!F2 -> 11.369007 | D10: =GeoColoc!F2 -> 117.39788
A12: VALUE BRIDGE — dollar impact of co-location over the queue-wait window (live)
A13: Queue-wait revenue uplift, total ($mm) | B13: =SUMIFS(SolarColoc!E5:E37,SolarColoc!A5:A37,">"&Inputs!$B$21,SolarColoc!A5:A37,"<="&Inputs!$B$21+Inputs!$B$5)-SUMIFS(SolarBase!E5:E37,SolarBase!A5:A37,">"&Inputs!$B$21,SolarBase!A5:A37,"<="&Inputs!$B$21+Inputs!$B$5) -> 54.281941 | C13: =SUMIFS(WindColoc!E5:E37,WindColoc!A5:A37,">"&Inputs!$B$21,WindColoc!A5:A37,"<="&Inputs!$B$21+Inputs!$B$5)-SUMIFS(WindBase!E5:E37,WindBase!A5:A37,">"&Inputs!$B$21,WindBase!A5:A37,"<="&Inputs!$B$21+Inputs!$B$5) -> 101.97239 | D13: =SUMIFS(GeoColoc!E5:E37,GeoColoc!A5:A37,">"&Inputs!$B$21,GeoColoc!A5:A37,"<="&Inputs!$B$21+Inputs!$B$5)-SUMIFS(GeoBase!E5:E37,GeoBase!A5:A37,">"&Inputs!$B$21,GeoBase!A5:A37,"<="&Inputs!$B$21+Inputs!$B$5) -> 173.50871
A14: Queue-wait revenue uplift, per year ($mm/yr) | B14: =B13/Inputs!$B$5 -> 13.570485 | C14: =C13/Inputs!$B$5 -> 25.493097 | D14: =D13/Inputs!$B$5 -> 43.377177
A15: Queue-wait EBITDA uplift, total ($mm) | B15: =SUMIFS(SolarColoc!G5:G37,SolarColoc!A5:A37,">"&Inputs!$B$21,SolarColoc!A5:A37,"<="&Inputs!$B$21+Inputs!$B$5)-SUMIFS(SolarBase!G5:G37,SolarBase!A5:A37,">"&Inputs!$B$21,SolarBase!A5:A37,"<="&Inputs!$B$21+Inputs!$B$5) -> 38.467712 | C15: =SUMIFS(WindColoc!G5:G37,WindColoc!A5:A37,">"&Inputs!$B$21,WindColoc!A5:A37,"<="&Inputs!$B$21+Inputs!$B$5)-SUMIFS(WindBase!G5:G37,WindBase!A5:A37,">"&Inputs!$B$21,WindBase!A5:A37,"<="&Inputs!$B$21+Inputs!$B$5) -> 70.442803 | D15: =SUMIFS(GeoColoc!G5:G37,GeoColoc!A5:A37,">"&Inputs!$B$21,GeoColoc!A5:A37,"<="&Inputs!$B$21+Inputs!$B$5)-SUMIFS(GeoBase!G5:G37,GeoBase!A5:A37,">"&Inputs!$B$21,GeoBase!A5:A37,"<="&Inputs!$B$21+Inputs!$B$5) -> 149.40608
A16: Queue-wait developer cash uplift, total ($mm) | B16: =SUMIFS(SolarColoc!K5:K37,SolarColoc!A5:A37,">"&Inputs!$B$21,SolarColoc!A5:A37,"<="&Inputs!$B$21+Inputs!$B$5)-SUMIFS(SolarBase!K5:K37,SolarBase!A5:A37,">"&Inputs!$B$21,SolarBase!A5:A37,"<="&Inputs!$B$21+Inputs!$B$5) -> 28.482954 | C16: =SUMIFS(WindColoc!K5:K37,WindColoc!A5:A37,">"&Inputs!$B$21,WindColoc!A5:A37,"<="&Inputs!$B$21+Inputs!$B$5)-SUMIFS(WindBase!K5:K37,WindBase!A5:A37,">"&Inputs!$B$21,WindBase!A5:A37,"<="&Inputs!$B$21+Inputs!$B$5) -> 46.990371 | D16: =SUMIFS(GeoColoc!K5:K37,GeoColoc!A5:A37,">"&Inputs!$B$21,GeoColoc!A5:A37,"<="&Inputs!$B$21+Inputs!$B$5)-SUMIFS(GeoBase!K5:K37,GeoBase!A5:A37,">"&Inputs!$B$21,GeoBase!A5:A37,"<="&Inputs!$B$21+Inputs!$B$5) -> 103.03786
A17: vs. Microgrid CAPEX ($mm) | B17: =Configurations!$B$11 -> 12 | C17: =Configurations!$C$11 -> 18 | D17: =Configurations!$D$11 -> 12
A18: vs. Incremental developer equity ($mm) | B18: =Capitalization!C19-Capitalization!B19 -> 18.639101 | C18: =Capitalization!E19-Capitalization!D19 -> 8.1 | D18: =Capitalization!G19-Capitalization!F19 -> 5.4
A19: Delta NPV of developer cash ($mm) | B19: =SolarColoc!F2-SolarBase!F2 -> -0.00066990999 | C19: =WindColoc!F2-WindBase!F2 -> 13.839126 | D19: =GeoColoc!F2-GeoBase!F2 -> 59.762049
A21: Reading: revenue uplift = what the queue-wait window earns instead of $0; EBITDA uplift nets out the full O&M an operating plant
A22: incurs; developer cash uplift applies the pre-flip 70% share (debt service is identical, so it cancels). Delta NPV is the single-number summary.
A24: Scenario sweep — Solar+BESS 100MW (ITC pathway, flip yr 6; reproduce via Inputs levers)
A25: ITC | B25: Queue (yrs) | C25: Baseline IRR | D25: Co-location IRR | E25: Delta (pp)
A26: 0.3 | B26: 2 | C26: 0.0698 | D26: 0.0493 | E26: -2.05
A27: 0.3 | B27: 4 | C27: 0.0407 | D27: 0.0441 | E27: 0.34
A28: 0.3 | B28: 6 | C28: 0.014 | D28: 0.0377 | E28: 2.38
A29: 0.3 | B29: 8 | C29: -0.0061 | D29: 0.0321 | E29: 3.82
A30: 0 | B30: 2 | C30: -0.0084 | D30: -0.0114 | E30: -0.31
A31: 0 | B31: 4 | C31: -0.0201 | D31: -0.0141 | E31: 0.6
A32: 0 | B32: 6 | C32: -0.0305 | D32: -0.0167 | E32: 1.38
A33: 0 | B33: 8 | C33: -0.0405 | D33: -0.0193 | E33: 2.11
A35: Scenario sweep — Wind+BESS 150MW (ITC pathway, flip yr 6; reproduce via Inputs levers)
A36: ITC | B36: Queue (yrs) | C36: Baseline IRR | D36: Co-location IRR | E36: Delta (pp)
A37: 0.3 | B37: 2 | C37: 0.1133 | D37: 0.1107 | E37: -0.26
A38: 0.3 | B38: 4 | C38: 0.0765 | D38: 0.1006 | E38: 2.41
A39: 0.3 | B39: 6 | C39: 0.0443 | D39: 0.0898 | E39: 4.55
A40: 0.3 | B40: 8 | C40: 0.021 | D40: 0.0811 | E40: 6.01
A41: 0 | B41: 2 | C41: 0.0149 | D41: 0.0116 | E41: -0.33
A42: 0 | B42: 4 | C42: 0.0015 | D42: 0.0082 | E42: 0.68
A43: 0 | B43: 6 | C43: -0.0102 | D43: 0.005 | E43: 1.52
A44: 0 | B44: 8 | C44: -0.0209 | D44: 0.0019 | E44: 2.28
A46: Scenario sweep — Geothermal+BESS 100MW (ITC pathway, flip yr 6; reproduce via Inputs levers)
A47: ITC | B47: Queue (yrs) | C47: Baseline IRR | D47: Co-location IRR | E47: Delta (pp)
A48: 0.3 | B48: 2 | C48: 0.1572 | D48: 0.2006 | E48: 4.35
A49: 0.3 | B49: 4 | C49: 0.1161 | D49: 0.1882 | E49: 7.21
A50: 0.3 | B50: 6 | C50: 0.0832 | D50: 0.1764 | E50: 9.32
A51: 0.3 | B51: 8 | C51: 0.0612 | D51: 0.1679 | E51: 10.67
A52: 0 | B52: 2 | C52: 0.0469 | D52: 0.0557 | E52: 0.87
A53: 0 | B53: 4 | C53: 0.0342 | D53: 0.0526 | E53: 1.84
A54: 0 | B54: 6 | C54: 0.0238 | D54: 0.05 | E54: 2.61
A55: 0 | B55: 8 | C55: 0.0149 | D55: 0.0476 | E55: 3.27
A57: Takeaways: Q* ~3.5 yrs (solar), ~2.2 yrs (wind), <2 yrs (geothermal, 30% ITC). Delta IRR rises with capacity factor — geothermal shows the
A58: LARGEST improvement (+4.4 to +10.7pp), contradicting H1's expectation of the smallest: the delta is driven by energy monetized per queue
A59: year, not by baseline IRR level. ITC beats PTC for all three configs at these parameters (PTC inflation adjustment omitted — caveat).
