Workbook

Sheet _Index
A1: SPUR Combined Model (v7 + Model 3)
A3: MODEL 2: Project-Level DCF (Developer IRR)
A4: Inputs | B4: Global scenario levers (queue wait, ITC, credit type) + shared parameters
A5: Configurations | B5: Per-configuration CAPEX, CF, degradation, operating life (Solar/Wind/Geo)
A6: Capitalization | B6: Tax equity / debt / developer equity sizing: 6 columns (Base+Coloc × 3 configs)
A7: SolarBase | B7: Solar+BESS 100MW cash flow waterfall: project idle during queue wait
A8: SolarColoc | B8: Solar+BESS 100MW cash flow waterfall: BTM sales during queue wait
A9: WindBase | B9: Wind+BESS 150MW cash flow waterfall: project idle during queue wait
A10: WindColoc | B10: Wind+BESS 150MW cash flow waterfall: BTM sales during queue wait
A11: GeoBase | B11: Geothermal+BESS 100MW cash flow waterfall: project idle during queue wait
A12: GeoColoc | B12: Geothermal+BESS 100MW cash flow waterfall: BTM sales during queue wait
A13: Results | B13: Live IRR/NPV/Value Bridge + Queue×ITC sweep tables (all 3 configs)
A15: MODEL 3: Data Center Electricity Cost (H2 Test)
A16: M3_Inputs | B16: DC load, generation supply, sourced & placeholder prices
A17: M3_Coverage | B17: Energy-balance coverage ratio by configuration
A18: M3_StructA_B | B18: Structure A (utility tariff) & Structure B (sleeved grid PPA) all-in cost
A19: M3_StructC | B19: Structure C (BTM co-location) Phase 1 & Phase 2 all-in cost
A20: M3_Results | B20: Cost comparison + H2 savings test (20-35% threshold)
A22: MODEL 1: Electricity Price Benchmark (Stage 1)
A23: M1_Inputs | B23: All DMM-sourced data points (annual, quarterly, hourly, GHG) with URL citations
A24: M1_Benchmarks | B24: Derivation of P_low / P_avg / P_high from DMM hourly & annual statistics
A25: M1_Scenarios | B25: 3×3 matrix (load × carbon) = 9 price scenarios; spot-to-PPA bridge; solar capture caveat
A26: M1_Notes | B26: Methodology: why DMM instead of raw OASIS, binning proxy, limitations, replication path
A28: MODEL 4: Bilateral BTM PPA Pricing (Negotiation Zone)
A29: M4_LCOE | B29: LCOE per configuration (gross & net of tax equity): the developer's price floor
A30: M4_Bounds | B30: Floor vs three ceilings (all-in / energy-only / spot+wires); zone width; viability tests
A31: M4_Pricing | B31: Three price-setting methods; α lever; two-sided test; analytical mutually-acceptable range
A32: M4_Notes | B32: Methodology, findings (incl. $60 < LCOE for solar/wind), open loop-closure items
A34: FIGURES (native Excel charts; data + chart on each sheet)
A35: Fig2_Breakeven | B35: Levered IRR vs queue wait, 6 panels (lever × config); static sweep values
A36: Fig3_Zone | B36: Price floor / ceiling / acceptable range stacked bar; LIVE links to M4
A37: Fig4_Alpha | B37: IRR and DC saving vs bargaining share α, 3 panels; static sweep values

Sheet M1_Inputs
A1: Model 1: Electricity Price Benchmark: INPUTS (CAISO DMM Published Statistics)
A2: Blue = hardcoded from published DMM reports. Every value carries a source + URL in column E. See M1_Notes for methodology deviation from original Stage 1 spec.
A4: SEC 1: ANNUAL LOAD-WEIGHTED AVERAGE PRICES: California region
A5: Parameter | B5: Value | C5: Unit | D5: Year | E5: Source
A6: CA region day-ahead market avg price | B6: 41 | C6: $/MWh | D6: 2024 | E6: CAISO DMM 2024 Annual Report (Aug 7, 2025), Executive Summary p.3: 'day-ahead market prices averaged $41/MWh'. https://www.caiso.com/documents/2024-annual-report-on-market-issues-and-performance-aug-07-2025.pdf
A7: CA region 15-min market avg price | B7: 41.1 | C7: $/MWh | D7: 2024 | E7: CAISO DMM 2024 Annual Report, Figure E.2 table: California 41.1, -36% vs 2023. Same URL.
A8: CA region day-ahead market avg price | B8: 39 | C8: $/MWh | D8: 2025 | E8: CAISO DMM 2025 Annual Report (Jun 26, 2026), Executive Summary p.3: 'Day-ahead market prices averaged about $39/MWh'. https://www.caiso.com/documents/2025-annual-report-on-market-issues-and-performance.pdf
A9: CA region 15-min market avg price | B9: 38.32 | C9: $/MWh | D9: 2025 | E9: CAISO DMM 2025 Annual Report, Figure E.2 table: California $38.32, -7% vs 2024. Same URL.
A10: CAISO total wholesale cost per MWh of load | B10: 42 | C10: $/MWh | D10: 2025 | E10: CAISO DMM 2025 Annual Report, p.4: 'Total wholesale costs for the CAISO balancing area decreased by about 6 percent to $8.45 billion, or about $42/MWh'. Same URL.
A11: Implied 2023 CA DA avg (back-calc from -36% YoY) | B11: =B7/(1-0.36) -> 64.21875 | C11: $/MWh | D11: 2023 | E11: Calc: 2024 value / (1 - 0.36). DMM 2024 Annual Report states CA prices fell 36% from 2023. Use as high-gas-price sensitivity only.
A13: SEC 2: QUARTERLY PRICES: seasonal shape (CAISO balancing area)
A14: Parameter | B14: Value | C14: Unit | D14: Year | E14: Source
A15: Q1 2024 avg (DA/15-min/5-min blended) | B15: 43 | C15: $/MWh | D15: 2024 Q1 | E15: CAISO DMM Q1 2024 Report (Oct 11, 2024): 'average price of the three markets this quarter decreased to $43/MWh from $93/MWh in Q1 2023'. https://www.caiso.com/documents/2024-first-quarter-report-on-market-issues-and-performance-oct-11-2024.pdf
A16: Q2 2024 avg (15-min, WEIM-wide) | B16: 19 | C16: $/MWh | D16: 2024 Q2 | E16: CAISO DMM Q2 2024 Report (Nov 22, 2024): 'Prices in both the 15-minute and 5-minute markets averaged around $19/MWh, down 40% vs Q2 2023'. WEIM-wide figure; CA-specific likely ~$5-8 higher due to GHG. https://www.caiso.com/documents/2024-second-quarter-report-on-market-issues-and-performance-nov-22-2024.pdf
A17: Q3 2024 CAISO day-ahead avg | B17: 48 | C17: $/MWh | D17: 2024 Q3 | E17: CAISO DMM Q3 2024 Report (Dec 23, 2024), Sec 3.3 p.27: 'day-ahead prices averaged $48/MWh, 15-minute $47/MWh, 5-minute $40/MWh'. https://www.caiso.com/documents/2024-third-quarter-report-on-market-issues-and-performance-dec-23-2024.pdf
A18: Q3 2024 CA region 15-min avg | B18: 47.5 | C18: $/MWh | D18: 2024 Q3 | E18: CAISO DMM Q3 2024 Report, Figure E.1 table: California 47.5, -27% vs Q3 2023. Same URL.
A19: Q3 2024 July monthly DA peak-hours avg | B19: 58 | C19: $/MWh | D19: 2024 Jul | E19: CAISO DMM Q3 2024 Report, Figure 3.12 table: CAISO Jul $58 / Aug $42 / Sep $40 (peak hours HE7-22). Same URL.
A20: Q4 2025 WEIM 15-min avg | B20: 36 | C20: $/MWh | D20: 2025 Q4 | E20: CAISO DMM Q4 2025 Report (Mar 30, 2026): 'Overall 15-minute market prices across WEIM averaged $36/MWh, down 7% vs Q4 2024'. https://www.caiso.com/documents/2025-fourth-quarter-report-on-market-issues-and-performance.pdf
A22: SEC 3: HOURLY 15-MIN MARKET PRICES: Q3 2024 (Jul–Sep), CAISO DLAPs
A23: Source: CAISO DMM Q3 2024 Report, Table 3.3 'Hourly 15-minute market prices (July–September)', p.26. Values are load-weighted hourly averages at PG&E and SCE default load aggregation points. Same URL as SEC 2 Q3 row.
A24: Hour Ending | B24: PG&E DLAP ($/MWh) | C24: SCE DLAP ($/MWh) | D24: Blend ($/MWh) | E24: Net-load regime
A25: 1 | B25: 40 | C25: 40 | D25: =AVERAGE(B25,C25) -> 40 | E25: Overnight
A26: 2 | B26: 38 | C26: 38 | D26: =AVERAGE(B26,C26) -> 38 | E26: Overnight
A27: 3 | B27: 36 | C27: 36 | D27: =AVERAGE(B27,C27) -> 36 | E27: Overnight
A28: 4 | B28: 35 | C28: 35 | D28: =AVERAGE(B28,C28) -> 35 | E28: Overnight
A29: 5 | B29: 35 | C29: 35 | D29: =AVERAGE(B29,C29) -> 35 | E29: Overnight
A30: 6 | B30: 39 | C30: 38 | D30: =AVERAGE(B30,C30) -> 38.5 | E30: Overnight
A31: 7 | B31: 40 | C31: 40 | D31: =AVERAGE(B31,C31) -> 40 | E31: Overnight
A32: 8 | B32: 32 | C32: 30 | D32: =AVERAGE(B32,C32) -> 31 | E32: Morning ramp
A33: 9 | B33: 27 | C33: 21 | D33: =AVERAGE(B33,C33) -> 24 | E33: Mid-day solar
A34: 10 | B34: 26 | C34: 19 | D34: =AVERAGE(B34,C34) -> 22.5 | E34: Mid-day solar
A35: 11 | B35: 25 | C35: 20 | D35: =AVERAGE(B35,C35) -> 22.5 | E35: Mid-day solar
A36: 12 | B36: 27 | C36: 21 | D36: =AVERAGE(B36,C36) -> 24 | E36: Mid-day solar
... A48: 24 | B48: 42 | C48: 42 | D48: =AVERAGE(B48,C48) -> 42 | E48: Late evening
A50: SEC 4: GREENHOUSE GAS PRICE & IMPLIED MARGINAL EMISSION RATE
A51: Parameter | B51: Value | C51: Unit | D51: Year | E51: Source
A52: CA GHG allowance price (bilateral avg) | B52: 38.09 | C52: $/mtCO2e | D52: 2024 | E52: CAISO DMM 2024 Annual Report, p.2: 'California greenhouse gas allowances averaged $38.09/mtCO2e in bilateral markets in 2024'.
A53: GHG cost impact on efficient gas unit | B53: 16.19 | C53: $/MWh | D53: 2024 | E53: CAISO DMM 2024 Annual Report, p.2: 'This represented an additional cost of about $16.19/MWh for a relatively efficient gas unit'.
A54: CA GHG allowance price (bilateral avg) | B54: 29.89 | C54: $/mtCO2e | D54: 2025 | E54: CAISO DMM 2025 Annual Report, p.2: 'California greenhouse gas allowance prices averaged about $29.89/mtCO2e in 2025, down 22 percent from 2024'.
A55: GHG cost impact on efficient gas unit | B55: 12.7 | C55: $/MWh | D55: 2025 | E55: CAISO DMM 2025 Annual Report, p.2: 'representing an incremental cost of about $12.70/MWh for a relatively efficient gas unit'.
A56: Implied marginal emission rate (2024) | B56: =B53/B52 -> 0.42504594 | C56: tCO2e/MWh | D56: 2024 | E56: Calc: $/MWh ÷ $/mtCO2e. DMM-implied heat rate for 'relatively efficient gas unit' (CCGT). Cross-check: framework Sec 1.2 assumed 0.4–0.6 t/MWh.
A57: Implied marginal emission rate (2025) | B57: =B55/B54 -> 0.42489127 | C57: tCO2e/MWh | D57: 2025 | E57: Calc: same method. Consistency across years validates the DMM heat-rate assumption.
A58: Marginal emission rate: model input | B58: =AVERAGE(B56,B57) -> 0.42496861 | C58: tCO2e/MWh | D58: avg | E58: Calc: average of 2024 and 2025 implied rates. Used for carbon overlay in M1_Scenarios.
A60: SEC 5: PRICE DISTRIBUTION CONTEXT: tail behavior
A61: Parameter | B61: Value | C61: Unit | D61: Year | E61: Source
A62: Hours with negative DA price (SP15) | B62: 1180 | C62: hours/yr | D62: 2024 | E62: Resurety, 'Negative Prices in CAISO' (May 2025): '~1,180 hours in 2024 had below-zero prices (~13% of total hours)'. https://resurety.com/article-negative-prices-in-caiso/
A63: Share of hours negative | B63: =B62/8760 -> 0.1347032 | C63: frac | D63: 2024 | E63: Calc: hours / 8760
A64: Median negative price (SP15) | B64: -17 | C64: $/MWh | D64: 2024 | E64: Resurety (May 2025): 'median negative price in 2024 was ~-$17'. Same URL.
A65: Solar capture rate SP15 | B65: 0.3 | C65: frac of ATC | D65: 2024 | E65: Resurety (May 2025): 'annual solar capture rates to plummet to less than 30% in 2024' in SP15. Same URL. CRITICAL for solar config revenue assumption in Model 2.
A66: DA intervals with price > $250/MWh | B66: 0.006 | C66: frac | D66: 2024 Q3 | E66: CAISO DMM Q3 2024 Report, Sec 3.5 p.33: 'day-ahead market recorded 0.6 percent of intervals with average price exceeding $250/MWh'.
A67: Max DA (IFM) price observed | B67: 637 | C67: $/MWh | D67: 2024 Sep 5 | E67: CAISO Summer Market Performance Report Sep 2024 (Oct 31, 2024): 'IFM reached a maximum of $637/MWh on September 5'. https://www.caiso.com/documents/summer-market-performance-report-september-2024.pdf
A68: HE20 DA load-weighted avg (Q3 2024) | B68: 120 | C68: $/MWh | D68: 2024 Q3 | E68: CAISO DMM Q3 2024 Report, Sec 3.3 p.29: 'During hour-ending 20, the day-ahead load-weighted average energy price was $120/MWh'.

Sheet M1_Benchmarks
A1: Model 1: Three Load-Level Price Benchmarks (derived from DMM hourly & annual statistics)
A2: Green = pulled from M1_Inputs. Black = formula. Yellow = headline benchmark output feeding M1_Scenarios. Hour-bin definitions are a judgment call: see M1_Notes §3.
A4: SEC 1: HOUR-BIN DEFINITIONS (mapping framework load percentiles → DMM hourly regime)
A5: Benchmark | B5: Framework definition | C5: DMM proxy (Q3 2024 Table 3.3 hours) | D5: Hours in bin | E5: Rationale
A6: LOW | B6: Bottom 20th pctile system load; spring shoulder, mild weather, high solar | C6: HE10–HE13 (mid-day solar trough) | D6: 10,11,12,13 | E6: Framework text describes high-solar hours, i.e. low NET load. Mid-day trough is the empirical minimum in DMM Table 3.3 and the regime where solar/wind projects would actually be selling. Overnight hours (HE1-7, ~$35-40) are low GROSS load but not the framework's intent.
A7: AVERAGE | B7: 30th–70th pctile system load; typical demand, moderate weather | C7: Annual load-weighted DA average (2024 & 2025) | D7: all 8,760 | E7: Load-weighted annual mean already integrates the full distribution; DMM publishes this directly. Two-year average dampens single-year gas-price idiosyncrasy (2024 unusually low gas).
A8: HIGH | B8: Top 10th pctile system load; summer peak, extreme heat, evening ramp | C8: HE19–HE21 (evening net-load peak) | D8: 19,20,21 | E8: DMM Q3 2024 confirms 'prices peaked at HE20 when demand was still high but solar substantially below its peak'. Summer evening ramp is top-decile net load. Excludes extreme scarcity tail (>$250, only 0.6% of Q3 intervals).
A10: SEC 2: LOW BENCHMARK: mid-day solar trough
A11: PG&E DLAP, HE10–13 avg | B11: =AVERAGE(M1_Inputs!B34:B37) -> 26.25 | C11: $/MWh
A12: SCE DLAP, HE10–13 avg | B12: =AVERAGE(M1_Inputs!C34:C37) -> 20.75 | C12: $/MWh
A13: Blended (equal weight PG&E/SCE) | B13: =AVERAGE(B11,B12) -> 23.5 | C13: $/MWh
A14: Cross-check: Q2 2024 WEIM 15-min avg | B14: =M1_Inputs!B15 -> 43 | C14: $/MWh | D14: Spring-shoulder quarterly avg; WEIM-wide so ~$5–8 below CA. Consistent with mid-day blend.
A15: Cross-check: framework prior range | B15: 15 – 30 | C15: $/MWh | D15: Framework Sec 1.2 expected range. Blended value falls inside.
A16: LOW BENCHMARK (P_low) | B16: =ROUND(B13,0) -> 24 | C16: $/MWh | D16: Rounded to nearest $1. Mid-day Q3 blend; Q3 is the season where mid-day solar depression is strongest, so this is a conservative (low) value for annual mid-day.
A18: SEC 3: AVERAGE BENCHMARK: annual load-weighted DA
A19: 2024 CA DA avg | B19: =M1_Inputs!$B$6 -> 41 | C19: $/MWh
A20: 2025 CA DA avg | B20: =M1_Inputs!$B$8 -> 39 | C20: $/MWh
A21: 2-year average | B21: =AVERAGE(B19,B20) -> 40 | C21: $/MWh
A22: Cross-check: 2023 implied (high gas year) | B22: =M1_Inputs!$B$11 -> 64.21875 | C22: $/MWh | D22: Excluded from base benchmark: 2023 gas prices were anomalously high (SoCal Citygate $5.12 vs $2.14 in 2024). Available as upside sensitivity.
A23: Cross-check: framework prior range | B23: 35 – 55 | C23: $/MWh | D23: Framework Sec 1.2. 2-yr average falls inside.
A24: AVERAGE BENCHMARK (P_avg) | B24: =ROUND(B21,0) -> 40 | C24: $/MWh | D24: Rounded to nearest $1.
A26: SEC 4: HIGH BENCHMARK: summer evening net-load peak
A27: PG&E DLAP, HE19–21 avg | B27: =AVERAGE(M1_Inputs!B43:B45) -> 95 | C27: $/MWh
A28: SCE DLAP, HE19–21 avg | B28: =AVERAGE(M1_Inputs!C43:C45) -> 82 | C28: $/MWh
A29: Blended (equal weight PG&E/SCE) | B29: =AVERAGE(B27,B28) -> 88.5 | C29: $/MWh
A30: Cross-check: HE20 DA load-weighted (Q3 2024) | B30: =M1_Inputs!$B$68 -> 120 | C30: $/MWh | D30: Single peak hour; DA slightly above 15-min in this hour. Blend of HE19-21 is the fairer top-decile representation.
A31: Cross-check: framework prior range | B31: 60 – 120 | C31: $/MWh | D31: Framework Sec 1.2. Blended value falls inside.
A32: HIGH BENCHMARK (P_high) | B32: =ROUND(B29,0) -> 89 | C32: $/MWh | D32: Rounded to nearest $1. Q3-only; represents the summer regime where top-decile load occurs.
A34: SEC 5: SUMMARY: three base benchmarks (feed M1_Scenarios)
A35: Benchmark | B35: $/MWh | C35: vs. P_avg | D35: Framework range | E35: Inside range?
A36: P_low | B36: =B16 -> 24 | C36: =B36/$B$24-1 -> -0.4 | D36: $15–$30 | E36: =IF(AND(B36>=15,B36<=30),"YES","NO") -> YES
A37: P_avg | B37: =B24 -> 40 | C37: =B37/$B$24-1 -> 0 | D37: $35–$55 | E37: =IF(AND(B37>=35,B37<=55),"YES","NO") -> YES
A38: P_high | B38: =B32 -> 89 | C38: =B38/$B$24-1 -> 1.225 | D38: $60–$120 | E38: =IF(AND(B38>=60,B38<=120),"YES","NO") -> YES

Sheet M1_Scenarios
A1: Model 1: Nine Price Scenarios (3 load levels × 3 carbon prices) + PPA Bridge
A2: This is the Stage 1 output. Carbon adders are INCREMENTAL to the CA cap-and-trade cost already embedded in observed prices (framework Sec 1.2: '$0/ton = status quo').
A4: SEC 1: CARBON OVERLAY PARAMETERS
A5: Marginal emission rate (DMM-implied, efficient CCGT) | B5: =M1_Inputs!$B$58 -> 0.42496861 | C5: tCO2e/MWh | D5: From M1_Inputs SEC 4. Framework assumed 0.4–0.6; DMM data pins it at the low end (efficient CCGT sets the margin).
A6: Already-embedded CA carbon cost (2025 avg) | B6: =M1_Inputs!$B$54 -> 29.89 | C6: $/tCO2e | D6: Context only: observed prices already include this. Scenario adders stack on top.
A8: Carbon scenario | B8: Incremental $/tCO2e | C8: Adder $/MWh | D8: Framework rationale
A9: C0: status quo | B9: 0 | C9: =B9*$B$5 -> 0 | D9: Current CA cap-and-trade only (already in observed prices)
A10: C30: moderate | B10: 30 | C10: =B10*$B$5 -> 12.749058 | D10: Framework Sec 1.2: cap-and-trade escalation or federal carbon tax
A11: C60: aggressive | B11: 60 | C11: =B11*$B$5 -> 25.498116 | D11: Framework Sec 1.2: aggressive decarbonization / high SCC
A13: SEC 2: NINE-SCENARIO PRICE MATRIX ($/MWh): STAGE 1 OUTPUT
A14: Load level ↓ / Carbon → | B14: C0: status quo | C14: C30: moderate | D14: C60: aggressive
A15: LOW (mid-day solar trough) | B15: =M1_Benchmarks!$B$16+$C$9 -> 24 | C15: =M1_Benchmarks!$B$16+$C$10 -> 36.749058 | D15: =M1_Benchmarks!$B$16+$C$11 -> 49.498116
A16: AVERAGE (annual load-wtd) | B16: =M1_Benchmarks!$B$24+$C$9 -> 40 | C16: =M1_Benchmarks!$B$24+$C$10 -> 52.749058 | D16: =M1_Benchmarks!$B$24+$C$11 -> 65.498116
A17: HIGH (evening net-load peak) | B17: =M1_Benchmarks!$B$32+$C$9 -> 89 | C17: =M1_Benchmarks!$B$32+$C$10 -> 101.74906 | D17: =M1_Benchmarks!$B$32+$C$11 -> 114.49812
A19: Scenario naming for Model 2/3/4 runs: {L,A,H} × {C0,C30,C60} → e.g. 'A-C0' = average load, status-quo carbon = base case.
A21: SEC 3: SPOT-TO-PPA BRIDGE: how Model 1 connects to the $72/MWh already in Model 2
A22: Model 2 v7 uses a $72/MWh hybrid (solar+storage) PPA price sourced from LBNL Utility-Scale Solar. A PPA is a 15–20 yr fixed-price forward contract; spot DA prices are the annual realized average. The two are not the same quantity. This block reconciles them so the paper can state the relationship explicitly.
A23: Model 2 grid PPA price (LBNL hybrid PPA) | B23: =Inputs!B18 -> 72 | C23: $/MWh | D23: Cross-sheet link to Model 2 Inputs. LBNL Utility-Scale Solar 2024 Ed., solar+storage PPA levels. https://emp.lbl.gov/utility-scale-solar
A24: P_avg spot benchmark (this model) | B24: =M1_Benchmarks!$B$24 -> 40 | C24: $/MWh
A25: Implied PPA premium over spot | B25: =B23-B24 -> 32 | C25: $/MWh
A26: Implied PPA premium (%) | B26: =B23/B24-1 -> 0.8 | C26: frac | D26: Premium reflects: (a) 15-20yr price certainty, (b) storage capacity value in a hybrid PPA, (c) RA attributes bundled with energy, (d) counterparty credit. Not a contradiction: a PPA above spot is the normal market structure.
A28: Which price feeds Model 2 grid revenue?
A29: Option A: keep $72 PPA (current v7) | B29: =B23 -> 72 | C29: $/MWh | D29: Post-COD revenue assumes developer signs a contracted PPA. Consistent with how utility-scale projects are actually financed (lenders require contracted revenue). RECOMMENDED for base case.
A30: Option B: merchant at P_avg | B30: =M1_Benchmarks!$B$24 -> 40 | C30: $/MWh | D30: Post-COD revenue assumes merchant exposure to spot. Lower revenue, higher risk. Use as downside sensitivity: this is the 'no PPA available' case.
A31: Option C: merchant at P_high (peak-shaped) | B31: =M1_Benchmarks!$B$32 -> 89 | C31: $/MWh | D31: Only valid for dispatchable output (BESS discharge or geothermal) that can target evening peak. Not applicable to as-generated solar.
A33: SEC 4: SOLAR CAPTURE RATE: material caveat for Solar+BESS configuration
A34: SP15 solar capture rate (2024) | B34: =M1_Inputs!B65 -> 0.3 | C34: frac of ATC
A35: Solar-weighted realized spot (P_avg × capture) | B35: =M1_Benchmarks!$B$24*B34 -> 12 | C35: $/MWh | D35: If a solar project sold merchant with no storage, its generation-weighted price would be roughly this. This is why Model 2 solar baseline IRR is weak and why BESS is structurally required: it shifts output from P_low hours toward P_high hours.

Sheet M1_Notes
A1: Model 1: Methodology Notes and Deviation from Original Stage 1 Specification
A3: §1 What the proposal specified
A4: Revised Proposal (May 2026), Stage 1: download CAISO OASIS day-ahead hourly LMP for 2023–2025 at TH_SP15/TH_NP15, bin each hour by concurrent system load percentile (bottom 20% / 30–70% / top 10%), compute load-weighted average LMP per bin, then overlay three carbon prices. Output: 9 benchmark prices.
A6: §2 What was actually done, and why
A7: Benchmarks are constructed from CAISO Department of Market Monitoring (DMM) published statistics: the 2024 and 2025 Annual Reports and the 2024 Q1–Q3 and 2025 Q4 quarterly reports: rather than from raw OASIS hourly downloads. Reasons: (a) DMM figures are official, load-weighted, and independently computed by CAISO's market monitor, which is a stronger provenance for a citable benchmark than a student-processed OASIS extract; (b) DMM publishes exactly the aggregates the framework needs (annual load-weighted DA mean, hourly load-weighted 15-min profile, GHG cost per MWh); (c) raw OASIS processing was deferred to preserve time for Models 2–4, which are the analytical core. The raw-OASIS path remains available as a robustness check (see §6).
A9: §3 Binning: load percentile vs. hour-of-day proxy
A10: The framework bins by system-load percentile. DMM does not publish load-percentile-binned prices, so this model uses hour-of-day regimes from DMM Q3 2024 Table 3.3 as the proxy. The framework's own descriptions: LOW = 'spring shoulder, high solar output hours'; HIGH = 'summer peak, evening ramp': are net-load concepts, and net load in CAISO is a function of hour-of-day far more than of gross load. Mid-day solar trough (HE10–13) is the empirical minimum in the DMM table; evening ramp (HE19–21) is the empirical maximum. The mapping is therefore faithful to the framework's economic intent, but it is a judgment call and should be stated as such in the paper.
A12: §4 Known limitations
A13: (a) Hourly profile is Q3 2024 only. Q3 has the deepest mid-day depression and the highest evening peak, so P_low is a conservative low and P_high is a conservative high relative to a full-year hourly average. P_avg is unaffected (annual figure). (b) 15-minute market hourly averages are used for the hourly profile because DMM publishes that table; DA and 15-min converge on average (DMM Q3 2024 §3.3: 'typically tend to converge on average due to convergence bidding'), so the substitution is minor. (c) PG&E and SCE DLAPs are blended equally; a project-specific run should weight by actual node (Salton Sea geothermal and Tehachapi wind are SP15/SCE-side; solar 'various'). (d) 2023 is excluded from P_avg because DMM documents 2023 as a gas-price anomaly (SoCal Citygate $5.12 vs $2.14/MMBtu); it is retained as an explicit high-price sensitivity.
A15: §5 Carbon overlay
A16: Adders are computed as incremental $/tCO2e × marginal emission rate. The emission rate (0.425 tCO2e/MWh) is not assumed: it is back-calculated from DMM's own statement of the GHG cost impact on 'a relatively efficient gas unit' in both 2024 ($16.19/MWh ÷ $38.09/t) and 2025 ($12.70/MWh ÷ $29.89/t), which agree to three decimals. This pins the framework's 0.4–0.6 range to its lower bound. Adders are incremental to the CA cap-and-trade cost already embedded in observed prices; the C0 scenario is the observed price, not a carbon-free counterfactual.
A18: §6 Path to full OASIS replication (if time permits)
... A22: → Model 2 (DCF): the grid PPA price stays at $72/MWh (LBNL contracted hybrid PPA) for the base case; P_avg and P_high are sensitivity inputs for merchant-exposure cases. See M1_Scenarios SEC 3 for the reconciliation. → Model 3 (DC cost): Structure B 'PPA energy price' placeholder ($70) can be replaced by the Model 2 PPA link; P_avg is the VPPA settlement reference. → Model 4 (BTM pricing): P_avg + T&D stack (from Model 3 Structure B) forms the grid-alternative ceiling; the carbon scenarios shift the ceiling upward, widening the negotiation zone.

Sheet Inputs
A1: SPUR Preliminary Co-location Model v7: per-configuration tabs
A2: Three yellow levers apply to ALL configurations simultaneously (keeps cross-config comparison consistent). Blue = editable. $ in millions.
A4: SCENARIO LEVERS (GLOBAL)
A5: Queue wait (mech. completion -> COD), years | B5: 4 | C5: Test 2/4/6/8 (LBNL Queued Up 2025: https://emp.lbl.gov/queues)
A6: ITC rate | B6: 0.3 | C6: 0% = OBBBA Scenario D (zero credit under EITHER credit type); 30% = full rate w/ PWA
A7: Credit type (1=ITC, 2=PTC) | B7: 1 | C7: Framework 2.3.5: run both; PTC uses full depreciable basis
A8: SHARED PARAMETERS
A9: PTC rate ($/MWh, full rate w/ PWA) | B9: 15 | C9: $0.015/kWh, 10-yr duration (Framework 2.3.4; inflation adjustment omitted)
A10: BESS delivery loss (RTE approx.) | B10: 0.01 | C10: Annual approximation of round-trip losses
A11: Debt interest rate | B11: 0.055 | C11: Framework 2.3.1: 5-7% range
A12: Debt tenor (years) | B12: 20 | C12: Framework 2.3.1
A13: Target DSCR (debt sizing) | B13: 1.35 | C13: Framework 2.7
A14: Max leverage (% of total capital) | B14: 0.55 | C14: Framework 2.3.1: 50-55%; binds when DSCR-sized debt exceeds it (wind, geothermal)
A15: Combined tax rate (fed + CA) | B15: 0.2984 | C15: 21% federal + 8.84% CA
A16: Tax equity pay rate (per $ benefit PV) | B16: 0.8 | C16: TE pays ~80c per $1 PV of ITC + PTC + MACRS shield
A17: MACRS PV discount rate | B17: 0.07 | C17: Assumption
A18: Grid hybrid PPA price ($/MWh) | B18: 72 | C18: LBNL Utility-Scale Solar (hybrid PPA levels): https://emp.lbl.gov/utility-scale-solar
A19: BTM PPA price ($/MWh) | B19: 60 | C19: ~17% discount, within 10-20% industry range (Framework 4.3)
A20: Asset management (% of revenue) | B20: 0.015 | C20: Framework 2.6
... A27: BTM price source (1 = global B19, 2 = Model 4 per-config) | B27: 2 | C27: Set 1 to reproduce v7 results at flat $60. Set 2 to close the M4 to M2 loop.

Sheet Configurations
A1: Configuration library: each parameter feeds its configuration's tabs directly
A3: Parameter | B3: Solar+BESS 100MW | C3: Wind+BESS 150MW | D3: Geothermal+BESS 100MW | E3: Source / note
A4: Capacity (MW) | B4: 100 | C4: 150 | D4: 100 | E4: Solar/Geothermal: Framework 2.2.1. Wind: 150 MW scale variant (user-specified)
A5: Capacity factor | B5: 0.275 | C5: 0.35 | D5: 0.9 | E5: Solar: CA midpoint. Wind: upper Tehachapi 30-35%. Geothermal: 90%+ Salton Sea/Imperial Valley (NREL ATB 2024: https://atb.nrel.gov/electricity/2024/technologies)
A6: Annual degradation | B6: 0.005 | C6: 0.002 | D6: 0 | E6: Framework 2.5.2 (geothermal ~0%)
A7: Availability | B7: 0.98 | C7: 0.96 | D7: 0.95 | E7: Framework 2.5.2
A8: Electrical losses | B8: 0.025 | C8: 0.025 | D8: 0.025 | E8: Framework 2.5.2
A9: Total CAPEX ($mm) | B9: 197 | C9: 321.4 | D9: 568.25 | E9: Solar: Framework 2.2.3. Wind: $1,350/kW x150 + BESS 75MW/300MWh @$1,250/kW + dev 4% + land + intercon. Geothermal: $5,000/kW x100 + BESS 25MW/50MWh + dev 4% + land + intercon (NREL ATB 2024 midpoints)
A10: Qualified investment ($mm) | B10: 180 | C10: 296.25 | D10: 531.25 | E10: Generation + BESS only (Framework 2.2.4)
A11: Microgrid CAPEX ($mm) | B11: 12 | C11: 18 | D11: 12 | E11: $120/kW midpoint of $50-150/kW x capacity
A12: Fixed O&M, gen + BESS ($mm/yr) | B12: 3 | C12: 6.375 | D12: 4.625 | E12: Framework 2.6 midpoints per configuration
A13: Land lease + insurance ($mm/yr) | B13: 1.088 | C13: 1.586 | D13: 2.573 | E13: $0.3mm land + 0.4% of CAPEX insurance
A14: Microgrid O&M ($mm/yr) | B14: 0.75 | C14: 1.125 | D14: 0.75 | E14: $7.5/kW-yr x capacity
A15: Operating life (years) | B15: 25 | C15: 25 | D15: 30 | E15: Framework 2.1: 25 yrs solar/wind, 30 yrs geothermal
A16: BTM PPA price, effective ($/MWh) | B16: =IF(Inputs!$B$27=1,Inputs!$B$19,M4_Pricing!B19) -> 121.25624 | C16: =IF(Inputs!$B$27=1,Inputs!$B$19,M4_Pricing!C19) -> 116.35372 | D16: =IF(Inputs!$B$27=1,Inputs!$B$19,M4_Pricing!D19) -> 108.93487 | E16: Switch on Inputs!B27. Source 2 pulls the Model 4 selected price (M4_Pricing SEC 3), which depends on the method selector and alpha lever there. Feeds the queue-wait revenue in each Coloc tab.
A17: BTM PPA price at v7 default ($/MWh) | B17: =Inputs!$B$19 -> 60 | C17: =Inputs!$B$19 -> 60 | D17: =Inputs!$B$19 -> 60 | E17: Reference: the flat $60 the v7 sweep tables in Results were generated with.
A18: Notes: (1) Model finds ITC > PTC for all three configurations at these parameters: for geothermal this contradicts Framework 2.3.5's
A19: expectation; sensitive to the omitted PTC inflation adjustment and the 7% discount on the PTC stream. (2) Geothermal faces no near-term
A20: OBBBA deadline (phaseout from 2034), so the 0% ITC scenario is a stress test rather than a live policy risk for that configuration.

Sheet Capitalization
A1: Capitalization: debt = MIN(DSCR-sized, max leverage x capital); tax equity sized to ITC/PTC + MACRS shield
B3: Solar Base | C3: Solar Coloc | D3: Wind Base | E3: Wind Coloc | F3: Geo Base | G3: Geo Coloc
A4: Total capital required ($mm) | B4: =Configurations!$B$9 -> 197 | C4: =Configurations!$B$9+Configurations!$B$11 -> 209 | D4: =Configurations!$C$9 -> 321.4 | E4: =Configurations!$C$9+Configurations!$C$11 -> 339.4 | F4: =Configurations!$D$9 -> 568.25 | G4: =Configurations!$D$9+Configurations!$D$11 -> 580.25
A5: First grid-year net energy (MWh) | B5: =Configurations!$B$4*Configurations!$B$5*8760*Configurations!$B$7*(1-Configurations!$B$8) -> 230179.95 | C5: =Configurations!$B$4*Configurations!$B$5*8760*Configurations!$B$7*(1-Configurations!$B$8) -> 230179.95 | D5: =Configurations!$C$4*Configurations!$C$5*8760*Configurations!$C$7*(1-Configurations!$C$8) -> 430466.4 | E5: =Configurations!$C$4*Configurations!$C$5*8760*Configurations!$C$7*(1-Configurations!$C$8) -> 430466.4 | F5: =Configurations!$D$4*Configurations!$D$5*8760*Configurations!$D$7*(1-Configurations!$D$8) -> 730255.5 | G5: =Configurations!$D$4*Configurations!$D$5*8760*Configurations!$D$7*(1-Configurations!$D$8) -> 730255.5
A6: First grid-year revenue ($mm) | B6: =B5*Inputs!$B$18/1000000 -> 16.572956 | C6: =C5*Inputs!$B$18/1000000 -> 16.572956 | D6: =D5*Inputs!$B$18/1000000 -> 30.993581 | E6: =E5*Inputs!$B$18/1000000 -> 30.993581 | F6: =F5*Inputs!$B$18/1000000 -> 52.578396 | G6: =G5*Inputs!$B$18/1000000 -> 52.578396
A7: First grid-year OPEX ($mm) | B7: =Configurations!$B$12+Configurations!$B$13+Inputs!$B$20*B6 -> 4.3365943 | C7: =Configurations!$B$12+Configurations!$B$13+Configurations!$B$14+Inputs!$B$20*C6 -> 5.0865943 | D7: =Configurations!$C$12+Configurations!$C$13+Inputs!$B$20*D6 -> 8.4259037 | E7: =Configurations!$C$12+Configurations!$C$13+Configurations!$C$14+Inputs!$B$20*E6 -> 9.5509037 | F7: =Configurations!$D$12+Configurations!$D$13+Inputs!$B$20*F6 -> 7.9866759 | G7: =Configurations!$D$12+Configurations!$D$13+Configurations!$D$14+Inputs!$B$20*G6 -> 8.7366759
A8: First grid-year EBITDA ($mm) | B8: =B6-B7 -> 12.236362 | C8: =C6-C7 -> 11.486362 | D8: =D6-D7 -> 22.567677 | E8: =E6-E7 -> 21.442677 | F8: =F6-F7 -> 44.59172 | G8: =G6-G7 -> 43.84172
A9: Max debt service @ DSCR ($mm/yr) | B9: =B8/Inputs!$B$13 -> 9.0639719 | C9: =C8/Inputs!$B$13 -> 8.5084163 | D9: =D8/Inputs!$B$13 -> 16.716798 | E9: =E8/Inputs!$B$13 -> 15.883465 | F9: =F8/Inputs!$B$13 -> 33.030904 | G9: =G8/Inputs!$B$13 -> 32.475348
A10: DSCR-sized debt ($mm) | B10: =B9*(1-(1+Inputs!$B$11)^-Inputs!$B$12)/Inputs!$B$11 -> 108.31793 | C10: =C9*(1-(1+Inputs!$B$11)^-Inputs!$B$12)/Inputs!$B$11 -> 101.67883 | D10: =D9*(1-(1+Inputs!$B$11)^-Inputs!$B$12)/Inputs!$B$11 -> 199.77213 | E10: =E9*(1-(1+Inputs!$B$11)^-Inputs!$B$12)/Inputs!$B$11 -> 189.81348 | F10: =F9*(1-(1+Inputs!$B$11)^-Inputs!$B$12)/Inputs!$B$11 -> 394.73193 | G10: =G9*(1-(1+Inputs!$B$11)^-Inputs!$B$12)/Inputs!$B$11 -> 388.09283
A11: Senior debt after leverage cap ($mm) | B11: =MIN(B10,Inputs!$B$14*B4) -> 108.31793 | C11: =MIN(C10,Inputs!$B$14*C4) -> 101.67883 | D11: =MIN(D10,Inputs!$B$14*D4) -> 176.77 | E11: =MIN(E10,Inputs!$B$14*E4) -> 186.67 | F11: =MIN(F10,Inputs!$B$14*F4) -> 312.5375 | G11: =MIN(G10,Inputs!$B$14*G4) -> 319.1375
A12: Actual debt service ($mm/yr) | B12: =B11/((1-(1+Inputs!$B$11)^-Inputs!$B$12)/Inputs!$B$11) -> 9.0639719 | C12: =C11/((1-(1+Inputs!$B$11)^-Inputs!$B$12)/Inputs!$B$11) -> 8.5084163 | D12: =D11/((1-(1+Inputs!$B$11)^-Inputs!$B$12)/Inputs!$B$11) -> 14.791995 | E12: =E11/((1-(1+Inputs!$B$11)^-Inputs!$B$12)/Inputs!$B$11) -> 15.620421 | F12: =F11/((1-(1+Inputs!$B$11)^-Inputs!$B$12)/Inputs!$B$11) -> 26.152929 | G12: =G11/((1-(1+Inputs!$B$11)^-Inputs!$B$12)/Inputs!$B$11) -> 26.705212
A13: ITC amount ($mm) | B13: =IF(Inputs!$B$7=1,Configurations!$B$10*Inputs!$B$6,0) -> 54 | C13: =IF(Inputs!$B$7=1,Configurations!$B$10*Inputs!$B$6,0) -> 54 | D13: =IF(Inputs!$B$7=1,Configurations!$C$10*Inputs!$B$6,0) -> 88.875 | E13: =IF(Inputs!$B$7=1,Configurations!$C$10*Inputs!$B$6,0) -> 88.875 | F13: =IF(Inputs!$B$7=1,Configurations!$D$10*Inputs!$B$6,0) -> 159.375 | G13: =IF(Inputs!$B$7=1,Configurations!$D$10*Inputs!$B$6,0) -> 159.375
A14: PTC start year (calendar) | B14: =Inputs!$B$21+Inputs!$B$5+1 -> 7 | C14: =Inputs!$B$21+1 -> 3 | D14: =Inputs!$B$21+Inputs!$B$5+1 -> 7 | E14: =Inputs!$B$21+1 -> 3 | F14: =Inputs!$B$21+Inputs!$B$5+1 -> 7 | G14: =Inputs!$B$21+1 -> 3
A15: PTC stream PV ($mm) | B15: =IF(Inputs!$B$7=2,B5*Inputs!$B$9/1000000*(1-(1+Inputs!$B$17)^-10)/Inputs!$B$17/(1+Inputs!$B$17)^(B14-1),0) -> 0 | C15: =IF(Inputs!$B$7=2,C5*Inputs!$B$9/1000000*(1-(1+Inputs!$B$17)^-10)/Inputs!$B$17/(1+Inputs!$B$17)^(C14-1),0) -> 0 | D15: =IF(Inputs!$B$7=2,D5*Inputs!$B$9/1000000*(1-(1+Inputs!$B$17)^-10)/Inputs!$B$17/(1+Inputs!$B$17)^(D14-1),0) -> 0 | E15: =IF(Inputs!$B$7=2,E5*Inputs!$B$9/1000000*(1-(1+Inputs!$B$17)^-10)/Inputs!$B$17/(1+Inputs!$B$17)^(E14-1),0) -> 0 | F15: =IF(Inputs!$B$7=2,F5*Inputs!$B$9/1000000*(1-(1+Inputs!$B$17)^-10)/Inputs!$B$17/(1+Inputs!$B$17)^(F14-1),0) -> 0 | G15: =IF(Inputs!$B$7=2,G5*Inputs!$B$9/1000000*(1-(1+Inputs!$B$17)^-10)/Inputs!$B$17/(1+Inputs!$B$17)^(G14-1),0) -> 0
A16: Depreciable basis ($mm) | B16: =IF(Inputs!$B$7=1,Configurations!$B$10-0.5*B13,Configurations!$B$10) -> 153 | C16: =IF(Inputs!$B$7=1,Configurations!$B$10-0.5*C13,Configurations!$B$10) -> 153 | D16: =IF(Inputs!$B$7=1,Configurations!$C$10-0.5*D13,Configurations!$C$10) -> 251.8125 | E16: =IF(Inputs!$B$7=1,Configurations!$C$10-0.5*E13,Configurations!$C$10) -> 251.8125 | F16: =IF(Inputs!$B$7=1,Configurations!$D$10-0.5*F13,Configurations!$D$10) -> 451.5625 | G16: =IF(Inputs!$B$7=1,Configurations!$D$10-0.5*G13,Configurations!$D$10) -> 451.5625
A17: MACRS shield PV ($mm) | B17: =SUMPRODUCT($B$25:$B$30,B16*Inputs!$B$15/(1+Inputs!$B$17)^ROW(INDIRECT("1:6"))) -> 37.964505 | C17: =SUMPRODUCT($B$25:$B$30,C16*Inputs!$B$15/(1+Inputs!$B$17)^ROW(INDIRECT("1:6"))) -> 37.964505 | D17: =SUMPRODUCT($B$25:$B$30,D16*Inputs!$B$15/(1+Inputs!$B$17)^ROW(INDIRECT("1:6"))) -> 62.483248 | E17: =SUMPRODUCT($B$25:$B$30,E16*Inputs!$B$15/(1+Inputs!$B$17)^ROW(INDIRECT("1:6"))) -> 62.483248 | F17: =SUMPRODUCT($B$25:$B$30,F16*Inputs!$B$15/(1+Inputs!$B$17)^ROW(INDIRECT("1:6"))) -> 112.04802 | G17: =SUMPRODUCT($B$25:$B$30,G16*Inputs!$B$15/(1+Inputs!$B$17)^ROW(INDIRECT("1:6"))) -> 112.04802
A18: Tax equity contribution ($mm) | B18: =IF(Inputs!$B$6=0,0,Inputs!$B$16*(B13+B15+B17)) -> 73.571604 | C18: =IF(Inputs!$B$6=0,0,Inputs!$B$16*(C13+C15+C17)) -> 73.571604 | D18: =IF(Inputs!$B$6=0,0,Inputs!$B$16*(D13+D15+D17)) -> 121.0866 | E18: =IF(Inputs!$B$6=0,0,Inputs!$B$16*(E13+E15+E17)) -> 121.0866 | F18: =IF(Inputs!$B$6=0,0,Inputs!$B$16*(F13+F15+F17)) -> 217.13841 | G18: =IF(Inputs!$B$6=0,0,Inputs!$B$16*(G13+G15+G17)) -> 217.13841
A19: Developer equity ($mm) | B19: =B4-B11-B18 -> 15.110465 | C19: =C4-C11-C18 -> 33.749566 | D19: =D4-D11-D18 -> 23.543402 | E19: =E4-E11-E18 -> 31.643402 | F19: =F4-F11-F18 -> 38.574086 | G19: =G4-G11-G18 -> 43.974086
A21: PTC start assumption: baseline is not placed in service while idle (PTC begins at COD); co-location BTM operation is assumed
A22: to qualify as placed in service (PTC begins at mechanical completion). Open tax question: validate in practitioner interviews.
A24: MACRS 5-yr schedule (Framework 2.3.3)
A25: Year 1 | B25: 0.2
A26: Year 2 | B26: 0.32
A27: Year 3 | B27: 0.192
A28: Year 4 | B28: 0.1152
A29: Year 5 | B29: 0.1152
A30: Year 6 | B30: 0.0576

Sheet SolarBase
A1: SolarBase: annual cash flow waterfall ($mm)
A2: Developer levered IRR: | B2: =IRR(K5:K37) -> 0.040713705 | C2: Unlevered (project) IRR: | D2: =IRR(M5:M37) -> 0.0091238666 | E2: NPV of dev cash @ discount rate ($mm): | F2: =K5+NPV(Inputs!$B$24,K6:K37) -> -15.39658
A4: Year | B4: Phase | C4: Op yr | D4: Net energy (MWh) | E4: Revenue | F4: OPEX | G4: EBITDA | H4: Debt service | I4: Distributable cash | J4: Dev share | K4: Dev cash flow | L4: DSCR | M4: Project CF (unlevered)
A5: 0 | B5: =IF(A5=0,"Equity",IF(A5<=Inputs!$B$21,"Construction",IF(A5<=Inputs!$B$21+Inputs!$B$5,"Queue wait",IF(A5<=Inputs!$B$21+Configurations!$B$15,"Grid ops"," ")))) -> Equity | C5: =IF(A5<=Inputs!$B$21,"",A5-Inputs!$B$21-1) | D5: =IF(OR(A5<=Inputs!$B$21,A5>Inputs!$B$21+Configurations!$B$15),0,Configurations!$B$4*Configurations!$B$5*8760*(1-Configurations!$B$6)^C5*Configurations!$B$7*(1-Configurations!$B$8)) -> 0 | E5: =IF(OR(A5<=Inputs!$B$21,A5>Inputs!$B$21+Configurations!$B$15),0,IF(A5<=Inputs!$B$21+Inputs!$B$5,0,D5*Inputs!$B$18/1000000)) -> 0 | F5: =IF(OR(A5<=Inputs!$B$21,A5>Inputs!$B$21+Configurations!$B$15),0,IF(A5<=Inputs!$B$21+Inputs!$B$5,Configurations!$B$13,Configurations!$B$12+Configurations!$B$13+Inputs!$B$20*E5)) -> 0 | G5: =E5-F5 -> 0 | H5: =IF(AND(A5>Inputs!$B$21,A5<=Inputs!$B$21+Inputs!$B$12),Capitalization!B$12,0) -> 0 | I5: =G5-H5 -> 0 | J5: =IF(A5<=Inputs!$B$21,"",IF(AND(A5<=Inputs!$B$22,Capitalization!B$18>0),Inputs!$B$25,Inputs!$B$26)) | K5: =IF(A5=0,-Capitalization!B$19,IF(A5<=Inputs!$B$21,0,I5*J5-IF(AND(A5=Inputs!$B$22,Capitalization!B$18>0),Inputs!$B$23,0))) -> -15.110465 | L5: =IF(H5>0,G5/H5,"") | M5: =IF(A5=0,-Capitalization!B$4,IF(A5<=Inputs!$B$21,0,G5)) -> -197
A6: 1 | B6: =IF(A6=0,"Equity",IF(A6<=Inputs!$B$21,"Construction",IF(A6<=Inputs!$B$21+Inputs!$B$5,"Queue wait",IF(A6<=Inputs!$B$21+Configurations!$B$15,"Grid ops"," ")))) -> Construction | C6: =IF(A6<=Inputs!$B$21,"",A6-Inputs!$B$21-1) | D6: =IF(OR(A6<=Inputs!$B$21,A6>Inputs!$B$21+Configurations!$B$15),0,Configurations!$B$4*Configurations!$B$5*8760*(1-Configurations!$B$6)^C6*Configurations!$B$7*(1-Configurations!$B$8)) -> 0 | E6: =IF(OR(A6<=Inputs!$B$21,A6>Inputs!$B$21+Configurations!$B$15),0,IF(A6<=Inputs!$B$21+Inputs!$B$5,0,D6*Inputs!$B$18/1000000)) -> 0 | F6: =IF(OR(A6<=Inputs!$B$21,A6>Inputs!$B$21+Configurations!$B$15),0,IF(A6<=Inputs!$B$21+Inputs!$B$5,Configurations!$B$13,Configurations!$B$12+Configurations!$B$13+Inputs!$B$20*E6)) -> 0 | G6: =E6-F6 -> 0 | H6: =IF(AND(A6>Inputs!$B$21,A6<=Inputs!$B$21+Inputs!$B$12),Capitalization!B$12,0) -> 0 | I6: =G6-H6 -> 0 | J6: =IF(A6<=Inputs!$B$21,"",IF(AND(A6<=Inputs!$B$22,Capitalization!B$18>0),Inputs!$B$25,Inputs!$B$26)) | K6: =IF(A6=0,-Capitalization!B$19,IF(A6<=Inputs!$B$21,0,I6*J6-IF(AND(A6=Inputs!$B$22,Capitalization!B$18>0),Inputs!$B$23,0))) -> 0 | L6: =IF(H6>0,G6/H6,"") | M6: =IF(A6=0,-Capitalization!B$4,IF(A6<=Inputs!$B$21,0,G6)) -> 0
A7: 2 | B7: =IF(A7=0,"Equity",IF(A7<=Inputs!$B$21,"Construction",IF(A7<=Inputs!$B$21+Inputs!$B$5,"Queue wait",IF(A7<=Inputs!$B$21+Configurations!$B$15,"Grid ops"," ")))) -> Construction | C7: =IF(A7<=Inputs!$B$21,"",A7-Inputs!$B$21-1) | D7: =IF(OR(A7<=Inputs!$B$21,A7>Inputs!$B$21+Configurations!$B$15),0,Configurations!$B$4*Configurations!$B$5*8760*(1-Configurations!$B$6)^C7*Configurations!$B$7*(1-Configurations!$B$8)) -> 0 | E7: =IF(OR(A7<=Inputs!$B$21,A7>Inputs!$B$21+Configurations!$B$15),0,IF(A7<=Inputs!$B$21+Inputs!$B$5,0,D7*Inputs!$B$18/1000000)) -> 0 | F7: =IF(OR(A7<=Inputs!$B$21,A7>Inputs!$B$21+Configurations!$B$15),0,IF(A7<=Inputs!$B$21+Inputs!$B$5,Configurations!$B$13,Configurations!$B$12+Configurations!$B$13+Inputs!$B$20*E7)) -> 0 | G7: =E7-F7 -> 0 | H7: =IF(AND(A7>Inputs!$B$21,A7<=Inputs!$B$21+Inputs!$B$12),Capitalization!B$12,0) -> 0 | I7: =G7-H7 -> 0 | J7: =IF(A7<=Inputs!$B$21,"",IF(AND(A7<=Inputs!$B$22,Capitalization!B$18>0),Inputs!$B$25,Inputs!$B$26)) | K7: =IF(A7=0,-Capitalization!B$19,IF(A7<=Inputs!$B$21,0,I7*J7-IF(AND(A7=Inputs!$B$22,Capitalization!B$18>0),Inputs!$B$23,0))) -> 0 | L7: =IF(H7>0,G7/H7,"") | M7: =IF(A7=0,-Capitalization!B$4,IF(A7<=Inputs!$B$21,0,G7)) -> 0
A8: 3 | B8: =IF(A8=0,"Equity",IF(A8<=Inputs!$B$21,"Construction",IF(A8<=Inputs!$B$21+Inputs!$B$5,"Queue wait",IF(A8<=Inputs!$B$21+Configurations!$B$15,"Grid ops"," ")))) -> Queue wait | C8: =IF(A8<=Inputs!$B$21,"",A8-Inputs!$B$21-1) -> 0 | D8: =IF(OR(A8<=Inputs!$B$21,A8>Inputs!$B$21+Configurations!$B$15),0,Configurations!$B$4*Configurations!$B$5*8760*(1-Configurations!$B$6)^C8*Configurations!$B$7*(1-Configurations!$B$8)) -> 230179.95 | E8: =IF(OR(A8<=Inputs!$B$21,A8>Inputs!$B$21+Configurations!$B$15),0,IF(A8<=Inputs!$B$21+Inputs!$B$5,0,D8*Inputs!$B$18/1000000)) -> 0 | F8: =IF(OR(A8<=Inputs!$B$21,A8>Inputs!$B$21+Configurations!$B$15),0,IF(A8<=Inputs!$B$21+Inputs!$B$5,Configurations!$B$13,Configurations!$B$12+Configurations!$B$13+Inputs!$B$20*E8)) -> 1.088 | G8: =E8-F8 -> -1.088 | H8: =IF(AND(A8>Inputs!$B$21,A8<=Inputs!$B$21+Inputs!$B$12),Capitalization!B$12,0) -> 9.0639719 | I8: =G8-H8 -> -10.151972 | J8: =IF(A8<=Inputs!$B$21,"",IF(AND(A8<=Inputs!$B$22,Capitalization!B$18>0),Inputs!$B$25,Inputs!$B$26)) -> 0.7 | K8: =IF(A8=0,-Capitalization!B$19,IF(A8<=Inputs!$B$21,0,I8*J8-IF(AND(A8=Inputs!$B$22,Capitalization!B$18>0),Inputs!$B$23,0))) -> -7.1063803 | L8: =IF(H8>0,G8/H8,"") -> -0.12003568 | M8: =IF(A8=0,-Capitalization!B$4,IF(A8<=Inputs!$B$21,0,G8)) -> -1.088
A9: 4 | B9: =IF(A9=0,"Equity",IF(A9<=Inputs!$B$21,"Construction",IF(A9<=Inputs!$B$21+Inputs!$B$5,"Queue wait",IF(A9<=Inputs!$B$21+Configurations!$B$15,"Grid ops"," ")))) -> Queue wait | C9: =IF(A9<=Inputs!$B$21,"",A9-Inputs!$B$21-1) -> 1 | D9: =IF(OR(A9<=Inputs!$B$21,A9>Inputs!$B$21+Configurations!$B$15),0,Configurations!$B$4*Configurations!$B$5*8760*(1-Configurations!$B$6)^C9*Configurations!$B$7*(1-Configurations!$B$8)) -> 229029.05 | E9: =IF(OR(A9<=Inputs!$B$21,A9>Inputs!$B$21+Configurations!$B$15),0,IF(A9<=Inputs!$B$21+Inputs!$B$5,0,D9*Inputs!$B$18/1000000)) -> 0 | F9: =IF(OR(A9<=Inputs!$B$21,A9>Inputs!$B$21+Configurations!$B$15),0,IF(A9<=Inputs!$B$21+Inputs!$B$5,Configurations!$B$13,Configurations!$B$12+Configurations!$B$13+Inputs!$B$20*E9)) -> 1.088 | G9: =E9-F9 -> -1.088 | H9: =IF(AND(A9>Inputs!$B$21,A9<=Inputs!$B$21+Inputs!$B$12),Capitalization!B$12,0) -> 9.0639719 | I9: =G9-H9 -> -10.151972 | J9: =IF(A9<=Inputs!$B$21,"",IF(AND(A9<=Inputs!$B$22,Capitalization!B$18>0),Inputs!$B$25,Inputs!$B$26)) -> 0.7 | K9: =IF(A9=0,-Capitalization!B$19,IF(A9<=Inputs!$B$21,0,I9*J9-IF(AND(A9=Inputs!$B$22,Capitalization!B$18>0),Inputs!$B$23,0))) -> -7.1063803 | L9: =IF(H9>0,G9/H9,"") -> -0.12003568 | M9: =IF(A9=0,-Capitalization!B$4,IF(A9<=Inputs!$B$21,0,G9)) -> -1.088
A10: 5 | B10: =IF(A10=0,"Equity",IF(A10<=Inputs!$B$21,"Construction",IF(A10<=Inputs!$B$21+Inputs!$B$5,"Queue wait",IF(A10<=Inputs!$B$21+Configurations!$B$15,"Grid ops"," ")))) -> Queue wait | C10: =IF(A10<=Inputs!$B$21,"",A10-Inputs!$B$21-1) -> 2 | D10: =IF(OR(A10<=Inputs!$B$21,A10>Inputs!$B$21+Configurations!$B$15),0,Configurations!$B$4*Configurations!$B$5*8760*(1-Configurations!$B$6)^C10*Configurations!$B$7*(1-Configurations!$B$8)) -> 227883.9 | E10: =IF(OR(A10<=Inputs!$B$21,A10>Inputs!$B$21+Configurations!$B$15),0,IF(A10<=Inputs!$B$21+Inputs!$B$5,0,D10*Inputs!$B$18/1000000)) -> 0 | F10: =IF(OR(A10<=Inputs!$B$21,A10>Inputs!$B$21+Configurations!$B$15),0,IF(A10<=Inputs!$B$21+Inputs!$B$5,Configurations!$B$13,Configurations!$B$12+Configurations!$B$13+Inputs!$B$20*E10)) -> 1.088 | G10: =E10-F10 -> -1.088 | H10: =IF(AND(A10>Inputs!$B$21,A10<=Inputs!$B$21+Inputs!$B$12),Capitalization!B$12,0) -> 9.0639719 | I10: =G10-H10 -> -10.151972 | J10: =IF(A10<=Inputs!$B$21,"",IF(AND(A10<=Inputs!$B$22,Capitalization!B$18>0),Inputs!$B$25,Inputs!$B$26)) -> 0.7 | K10: =IF(A10=0,-Capitalization!B$19,IF(A10<=Inputs!$B$21,0,I10*J10-IF(AND(A10=Inputs!$B$22,Capitalization!B$18>0),Inputs!$B$23,0))) -> -7.1063803 | L10: =IF(H10>0,G10/H10,"") -> -0.12003568 | M10: =IF(A10=0,-Capitalization!B$4,IF(A10<=Inputs!$B$21,0,G10)) -> -1.088
A11: 6 | B11: =IF(A11=0,"Equity",IF(A11<=Inputs!$B$21,"Construction",IF(A11<=Inputs!$B$21+Inputs!$B$5,"Queue wait",IF(A11<=Inputs!$B$21+Configurations!$B$15,"Grid ops"," ")))) -> Queue wait | C11: =IF(A11<=Inputs!$B$21,"",A11-Inputs!$B$21-1) -> 3 | D11: =IF(OR(A11<=Inputs!$B$21,A11>Inputs!$B$21+Configurations!$B$15),0,Configurations!$B$4*Configurations!$B$5*8760*(1-Configurations!$B$6)^C11*Configurations!$B$7*(1-Configurations!$B$8)) -> 226744.49 | E11: =IF(OR(A11<=Inputs!$B$21,A11>Inputs!$B$21+Configurations!$B$15),0,IF(A11<=Inputs!$B$21+Inputs!$B$5,0,D11*Inputs!$B$18/1000000)) -> 0 | F11: =IF(OR(A11<=Inputs!$B$21,A11>Inputs!$B$21+Configurations!$B$15),0,IF(A11<=Inputs!$B$21+Inputs!$B$5,Configurations!$B$13,Configurations!$B$12+Configurations!$B$13+Inputs!$B$20*E11)) -> 1.088 | G11: =E11-F11 -> -1.088 | H11: =IF(AND(A11>Inputs!$B$21,A11<=Inputs!$B$21+Inputs!$B$12),Capitalization!B$12,0) -> 9.0639719 | I11: =G11-H11 -> -10.151972 | J11: =IF(A11<=Inputs!$B$21,"",IF(AND(A11<=Inputs!$B$22,Capitalization!B$18>0),Inputs!$B$25,Inputs!$B$26)) -> 0.7 | K11: =IF(A11=0,-Capitalization!B$19,IF(A11<=Inputs!$B$21,0,I11*J11-IF(AND(A11=Inputs!$B$22,Capitalization!B$18>0),Inputs!$B$23,0))) -> -8.1063803 | L11: =IF(H11>0,G11/H11,"") -> -0.12003568 | M11: =IF(A11=0,-Capitalization!B$4,IF(A11<=Inputs!$B$21,0,G11)) -> -1.088
A12: 7 | B12: =IF(A12=0,"Equity",IF(A12<=Inputs!$B$21,"Construction",IF(A12<=Inputs!$B$21+Inputs!$B$5,"Queue wait",IF(A12<=Inputs!$B$21+Configurations!$B$15,"Grid ops"," ")))) -> Grid ops | C12: =IF(A12<=Inputs!$B$21,"",A12-Inputs!$B$21-1) -> 4 | D12: =IF(OR(A12<=Inputs!$B$21,A12>Inputs!$B$21+Configurations!$B$15),0,Configurations!$B$4*Configurations!$B$5*8760*(1-Configurations!$B$6)^C12*Configurations!$B$7*(1-Configurations!$B$8)) -> 225610.76 | E12: =IF(OR(A12<=Inputs!$B$21,A12>Inputs!$B$21+Configurations!$B$15),0,IF(A12<=Inputs!$B$21+Inputs!$B$5,0,D12*Inputs!$B$18/1000000)) -> 16.243975 | F12: =IF(OR(A12<=Inputs!$B$21,A12>Inputs!$B$21+Configurations!$B$15),0,IF(A12<=Inputs!$B$21+Inputs!$B$5,Configurations!$B$13,Configurations!$B$12+Configurations!$B$13+Inputs!$B$20*E12)) -> 4.3316596 | G12: =E12-F12 -> 11.912315 | H12: =IF(AND(A12>Inputs!$B$21,A12<=Inputs!$B$21+Inputs!$B$12),Capitalization!B$12,0) -> 9.0639719 | I12: =G12-H12 -> 2.8483434 | J12: =IF(A12<=Inputs!$B$21,"",IF(AND(A12<=Inputs!$B$22,Capitalization!B$18>0),Inputs!$B$25,Inputs!$B$26)) -> 0.975 | K12: =IF(A12=0,-Capitalization!B$19,IF(A12<=Inputs!$B$21,0,I12*J12-IF(AND(A12=Inputs!$B$22,Capitalization!B$18>0),Inputs!$B$23,0))) -> 2.7771348 | L12: =IF(H12>0,G12/H12,"") -> 1.3142489 | M12: =IF(A12=0,-Capitalization!B$4,IF(A12<=Inputs!$B$21,0,G12)) -> 11.912315
A13: 8 | B13: =IF(A13=0,"Equity",IF(A13<=Inputs!$B$21,"Construction",IF(A13<=Inputs!$B$21+Inputs!$B$5,"Queue wait",IF(A13<=Inputs!$B$21+Configurations!$B$15,"Grid ops"," ")))) -> Grid ops | C13: =IF(A13<=Inputs!$B$21,"",A13-Inputs!$B$21-1) -> 5 | D13: =IF(OR(A13<=Inputs!$B$21,A13>Inputs!$B$21+Configurations!$B$15),0,Configurations!$B$4*Configurations!$B$5*8760*(1-Configurations!$B$6)^C13*Configurations!$B$7*(1-Configurations!$B$8)) -> 224482.71 | E13: =IF(OR(A13<=Inputs!$B$21,A13>Inputs!$B$21+Configurations!$B$15),0,IF(A13<=Inputs!$B$21+Inputs!$B$5,0,D13*Inputs!$B$18/1000000)) -> 16.162755 | F13: =IF(OR(A13<=Inputs!$B$21,A13>Inputs!$B$21+Configurations!$B$15),0,IF(A13<=Inputs!$B$21+Inputs!$B$5,Configurations!$B$13,Configurations!$B$12+Configurations!$B$13+Inputs!$B$20*E13)) -> 4.3304413 | G13: =E13-F13 -> 11.832314 | H13: =IF(AND(A13>Inputs!$B$21,A13<=Inputs!$B$21+Inputs!$B$12),Capitalization!B$12,0) -> 9.0639719 | I13: =G13-H13 -> 2.7683418 | J13: =IF(A13<=Inputs!$B$21,"",IF(AND(A13<=Inputs!$B$22,Capitalization!B$18>0),Inputs!$B$25,Inputs!$B$26)) -> 0.975 | K13: =IF(A13=0,-Capitalization!B$19,IF(A13<=Inputs!$B$21,0,I13*J13-IF(AND(A13=Inputs!$B$22,Capitalization!B$18>0),Inputs!$B$23,0))) -> 2.6991333 | L13: =IF(H13>0,G13/H13,"") -> 1.3054226 | M13: =IF(A13=0,-Capitalization!B$4,IF(A13<=Inputs!$B$21,0,G13)) -> 11.832314
A14: 9 | B14: =IF(A14=0,"Equity",IF(A14<=Inputs!$B$21,"Construction",IF(A14<=Inputs!$B$21+Inputs!$B$5,"Queue wait",IF(A14<=Inputs!$B$21+Configurations!$B$15,"Grid ops"," ")))) -> Grid ops | C14: =IF(A14<=Inputs!$B$21,"",A14-Inputs!$B$21-1) -> 6 | D14: =IF(OR(A14<=Inputs!$B$21,A14>Inputs!$B$21+Configurations!$B$15),0,Configurations!$B$4*Configurations!$B$5*8760*(1-Configurations!$B$6)^C14*Configurations!$B$7*(1-Configurations!$B$8)) -> 223360.3 | E14: =IF(OR(A14<=Inputs!$B$21,A14>Inputs!$B$21+Configurations!$B$15),0,IF(A14<=Inputs!$B$21+Inputs!$B$5,0,D14*Inputs!$B$18/1000000)) -> 16.081941 | F14: =IF(OR(A14<=Inputs!$B$21,A14>Inputs!$B$21+Configurations!$B$15),0,IF(A14<=Inputs!$B$21+Inputs!$B$5,Configurations!$B$13,Configurations!$B$12+Configurations!$B$13+Inputs!$B$20*E14)) -> 4.3292291 | G14: =E14-F14 -> 11.752712 | H14: =IF(AND(A14>Inputs!$B$21,A14<=Inputs!$B$21+Inputs!$B$12),Capitalization!B$12,0) -> 9.0639719 | I14: =G14-H14 -> 2.6887403 | J14: =IF(A14<=Inputs!$B$21,"",IF(AND(A14<=Inputs!$B$22,Capitalization!B$18>0),Inputs!$B$25,Inputs!$B$26)) -> 0.975 | K14: =IF(A14=0,-Capitalization!B$19,IF(A14<=Inputs!$B$21,0,I14*J14-IF(AND(A14=Inputs!$B$22,Capitalization!B$18>0),Inputs!$B$23,0))) -> 2.6215218 | L14: =IF(H14>0,G14/H14,"") -> 1.2966404 | M14: =IF(A14=0,-Capitalization!B$4,IF(A14<=Inputs!$B$21,0,G14)) -> 11.752712
A15: 10 | B15: =IF(A15=0,"Equity",IF(A15<=Inputs!$B$21,"Construction",IF(A15<=Inputs!$B$21+Inputs!$B$5,"Queue wait",IF(A15<=Inputs!$B$21+Configurations!$B$15,"Grid ops"," ")))) -> Grid ops | C15: =IF(A15<=Inputs!$B$21,"",A15-Inputs!$B$21-1) -> 7 | D15: =IF(OR(A15<=Inputs!$B$21,A15>Inputs!$B$21+Configurations!$B$15),0,Configurations!$B$4*Configurations!$B$5*8760*(1-Configurations!$B$6)^C15*Configurations!$B$7*(1-Configurations!$B$8)) -> 222243.49 | E15: =IF(OR(A15<=Inputs!$B$21,A15>Inputs!$B$21+Configurations!$B$15),0,IF(A15<=Inputs!$B$21+Inputs!$B$5,0,D15*Inputs!$B$18/1000000)) -> 16.001532 | F15: =IF(OR(A15<=Inputs!$B$21,A15>Inputs!$B$21+Configurations!$B$15),0,IF(A15<=Inputs!$B$21+Inputs!$B$5,Configurations!$B$13,Configurations!$B$12+Configurations!$B$13+Inputs!$B$20*E15)) -> 4.328023 | G15: =E15-F15 -> 11.673509 | H15: =IF(AND(A15>Inputs!$B$21,A15<=Inputs!$B$21+Inputs!$B$12),Capitalization!B$12,0) -> 9.0639719 | I15: =G15-H15 -> 2.6095367 | J15: =IF(A15<=Inputs!$B$21,"",IF(AND(A15<=Inputs!$B$22,Capitalization!B$18>0),Inputs!$B$25,Inputs!$B$26)) -> 0.975 | K15: =IF(A15=0,-Capitalization!B$19,IF(A15<=Inputs!$B$21,0,I15*J15-IF(AND(A15=Inputs!$B$22,Capitalization!B$18>0),Inputs!$B$23,0))) -> 2.5442983 | L15: =IF(H15>0,G15/H15,"") -> 1.2879021 | M15: =IF(A15=0,-Capitalization!B$4,IF(A15<=Inputs!$B$21,0,G15)) -> 11.673509
A16: 11 | B16: =IF(A16=0,"Equity",IF(A16<=Inputs!$B$21,"Construction",IF(A16<=Inputs!$B$21+Inputs!$B$5,"Queue wait",IF(A16<=Inputs!$B$21+Configurations!$B$15,"Grid ops"," ")))) -> Grid ops | C16: =IF(A16<=Inputs!$B$21,"",A16-Inputs!$B$21-1) -> 8 | D16: =IF(OR(A16<=Inputs!$B$21,A16>Inputs!$B$21+Configurations!$B$15),0,Configurations!$B$4*Configurations!$B$5*8760*(1-Configurations!$B$6)^C16*Configurations!$B$7*(1-Configurations!$B$8)) -> 221132.28 | E16: =IF(OR(A16<=Inputs!$B$21,A16>Inputs!$B$21+Configurations!$B$15),0,IF(A16<=Inputs!$B$21+Inputs!$B$5,0,D16*Inputs!$B$18/1000000)) -> 15.921524 | F16: =IF(OR(A16<=Inputs!$B$21,A16>Inputs!$B$21+Configurations!$B$15),0,IF(A16<=Inputs!$B$21+Inputs!$B$5,Configurations!$B$13,Configurations!$B$12+Configurations!$B$13+Inputs!$B$20*E16)) -> 4.3268229 | G16: =E16-F16 -> 11.594701 | H16: =IF(AND(A16>Inputs!$B$21,A16<=Inputs!$B$21+Inputs!$B$12),Capitalization!B$12,0) -> 9.0639719 | I16: =G16-H16 -> 2.5307292 | J16: =IF(A16<=Inputs!$B$21,"",IF(AND(A16<=Inputs!$B$22,Capitalization!B$18>0),Inputs!$B$25,Inputs!$B$26)) -> 0.975 | K16: =IF(A16=0,-Capitalization!B$19,IF(A16<=Inputs!$B$21,0,I16*J16-IF(AND(A16=Inputs!$B$22,Capitalization!B$18>0),Inputs!$B$23,0))) -> 2.4674609 | L16: =IF(H16>0,G16/H16,"") -> 1.2792075 | M16: =IF(A16=0,-Capitalization!B$4,IF(A16<=Inputs!$B$21,0,G16)) -> 11.594701
... A37: 32 | B37: =IF(A37=0,"Equity",IF(A37<=Inputs!$B$21,"Construction",IF(A37<=Inputs!$B$21+Inputs!$B$5,"Queue wait",IF(A37<=Inputs!$B$21+Configurations!$B$15,"Grid ops"," ")))) | C37: =IF(A37<=Inputs!$B$21,"",A37-Inputs!$B$21-1) -> 29 | D37: =IF(OR(A37<=Inputs!$B$21,A37>Inputs!$B$21+Configurations!$B$15),0,Configurations!$B$4*Configurations!$B$5*8760*(1-Configurations!$B$6)^C37*Configurations!$B$7*(1-Configurations!$B$8)) -> 0 | E37: =IF(OR(A37<=Inputs!$B$21,A37>Inputs!$B$21+Configurations!$B$15),0,IF(A37<=Inputs!$B$21+Inputs!$B$5,0,D37*Inputs!$B$18/1000000)) -> 0 | F37: =IF(OR(A37<=Inputs!$B$21,A37>Inputs!$B$21+Configurations!$B$15),0,IF(A37<=Inputs!$B$21+Inputs!$B$5,Configurations!$B$13,Configurations!$B$12+Configurations!$B$13+Inputs!$B$20*E37)) -> 0 | G37: =E37-F37 -> 0 | H37: =IF(AND(A37>Inputs!$B$21,A37<=Inputs!$B$21+Inputs!$B$12),Capitalization!B$12,0) -> 0 | I37: =G37-H37 -> 0 | J37: =IF(A37<=Inputs!$B$21,"",IF(AND(A37<=Inputs!$B$22,Capitalization!B$18>0),Inputs!$B$25,Inputs!$B$26)) -> 0.975 | K37: =IF(A37=0,-Capitalization!B$19,IF(A37<=Inputs!$B$21,0,I37*J37-IF(AND(A37=Inputs!$B$22,Capitalization!B$18>0),Inputs!$B$23,0))) -> 0 | L37: =IF(H37>0,G37/H37,"") | M37: =IF(A37=0,-Capitalization!B$4,IF(A37<=Inputs!$B$21,0,G37)) -> 0

Sheet SolarColoc
A1: SolarColoc: annual cash flow waterfall ($mm)
A2: Developer levered IRR: | B2: =IRR(K5:K37) -> 0.11794323 | C2: Unlevered (project) IRR: | D2: =IRR(M5:M37) -> 0.031641614 | E2: NPV of dev cash @ discount rate ($mm): | F2: =K5+NPV(Inputs!$B$24,K6:K37) -> 11.741962
A4: Year | B4: Phase | C4: Op yr | D4: Net energy (MWh) | E4: Revenue | F4: OPEX | G4: EBITDA | H4: Debt service | I4: Distributable cash | J4: Dev share | K4: Dev cash flow | L4: DSCR | M4: Project CF (unlevered)
A5: 0 | B5: =IF(A5=0,"Equity",IF(A5<=Inputs!$B$21,"Construction",IF(A5<=Inputs!$B$21+Inputs!$B$5,"Queue wait",IF(A5<=Inputs!$B$21+Configurations!$B$15,"Grid ops"," ")))) -> Equity | C5: =IF(A5<=Inputs!$B$21,"",A5-Inputs!$B$21-1) | D5: =IF(OR(A5<=Inputs!$B$21,A5>Inputs!$B$21+Configurations!$B$15),0,Configurations!$B$4*Configurations!$B$5*8760*(1-Configurations!$B$6)^C5*Configurations!$B$7*(1-Configurations!$B$8)) -> 0 | E5: =IF(OR(A5<=Inputs!$B$21,A5>Inputs!$B$21+Configurations!$B$15),0,IF(A5<=Inputs!$B$21+Inputs!$B$5,D5*(1-Inputs!$B$10)*Configurations!$B$16/1000000,D5*Inputs!$B$18/1000000)) -> 0 | F5: =IF(OR(A5<=Inputs!$B$21,A5>Inputs!$B$21+Configurations!$B$15),0,Configurations!$B$12+Configurations!$B$13+Configurations!$B$14+Inputs!$B$20*E5) -> 0 | G5: =E5-F5 -> 0 | H5: =IF(AND(A5>Inputs!$B$21,A5<=Inputs!$B$21+Inputs!$B$12),Capitalization!C$12,0) -> 0 | I5: =G5-H5 -> 0 | J5: =IF(A5<=Inputs!$B$21,"",IF(AND(A5<=Inputs!$B$22,Capitalization!C$18>0),Inputs!$B$25,Inputs!$B$26)) | K5: =IF(A5=0,-Capitalization!C$19,IF(A5<=Inputs!$B$21,0,I5*J5-IF(AND(A5=Inputs!$B$22,Capitalization!C$18>0),Inputs!$B$23,0))) -> -33.749566 | L5: =IF(H5>0,G5/H5,"") | M5: =IF(A5=0,-Capitalization!C$4,IF(A5<=Inputs!$B$21,0,G5)) -> -209
A6: 1 | B6: =IF(A6=0,"Equity",IF(A6<=Inputs!$B$21,"Construction",IF(A6<=Inputs!$B$21+Inputs!$B$5,"Queue wait",IF(A6<=Inputs!$B$21+Configurations!$B$15,"Grid ops"," ")))) -> Construction | C6: =IF(A6<=Inputs!$B$21,"",A6-Inputs!$B$21-1) | D6: =IF(OR(A6<=Inputs!$B$21,A6>Inputs!$B$21+Configurations!$B$15),0,Configurations!$B$4*Configurations!$B$5*8760*(1-Configurations!$B$6)^C6*Configurations!$B$7*(1-Configurations!$B$8)) -> 0 | E6: =IF(OR(A6<=Inputs!$B$21,A6>Inputs!$B$21+Configurations!$B$15),0,IF(A6<=Inputs!$B$21+Inputs!$B$5,D6*(1-Inputs!$B$10)*Configurations!$B$16/1000000,D6*Inputs!$B$18/1000000)) -> 0 | F6: =IF(OR(A6<=Inputs!$B$21,A6>Inputs!$B$21+Configurations!$B$15),0,Configurations!$B$12+Configurations!$B$13+Configurations!$B$14+Inputs!$B$20*E6) -> 0 | G6: =E6-F6 -> 0 | H6: =IF(AND(A6>Inputs!$B$21,A6<=Inputs!$B$21+Inputs!$B$12),Capitalization!C$12,0) -> 0 | I6: =G6-H6 -> 0 | J6: =IF(A6<=Inputs!$B$21,"",IF(AND(A6<=Inputs!$B$22,Capitalization!C$18>0),Inputs!$B$25,Inputs!$B$26)) | K6: =IF(A6=0,-Capitalization!C$19,IF(A6<=Inputs!$B$21,0,I6*J6-IF(AND(A6=Inputs!$B$22,Capitalization!C$18>0),Inputs!$B$23,0))) -> 0 | L6: =IF(H6>0,G6/H6,"") | M6: =IF(A6=0,-Capitalization!C$4,IF(A6<=Inputs!$B$21,0,G6)) -> 0
A7: 2 | B7: =IF(A7=0,"Equity",IF(A7<=Inputs!$B$21,"Construction",IF(A7<=Inputs!$B$21+Inputs!$B$5,"Queue wait",IF(A7<=Inputs!$B$21+Configurations!$B$15,"Grid ops"," ")))) -> Construction | C7: =IF(A7<=Inputs!$B$21,"",A7-Inputs!$B$21-1) | D7: =IF(OR(A7<=Inputs!$B$21,A7>Inputs!$B$21+Configurations!$B$15),0,Configurations!$B$4*Configurations!$B$5*8760*(1-Configurations!$B$6)^C7*Configurations!$B$7*(1-Configurations!$B$8)) -> 0 | E7: =IF(OR(A7<=Inputs!$B$21,A7>Inputs!$B$21+Configurations!$B$15),0,IF(A7<=Inputs!$B$21+Inputs!$B$5,D7*(1-Inputs!$B$10)*Configurations!$B$16/1000000,D7*Inputs!$B$18/1000000)) -> 0 | F7: =IF(OR(A7<=Inputs!$B$21,A7>Inputs!$B$21+Configurations!$B$15),0,Configurations!$B$12+Configurations!$B$13+Configurations!$B$14+Inputs!$B$20*E7) -> 0 | G7: =E7-F7 -> 0 | H7: =IF(AND(A7>Inputs!$B$21,A7<=Inputs!$B$21+Inputs!$B$12),Capitalization!C$12,0) -> 0 | I7: =G7-H7 -> 0 | J7: =IF(A7<=Inputs!$B$21,"",IF(AND(A7<=Inputs!$B$22,Capitalization!C$18>0),Inputs!$B$25,Inputs!$B$26)) | K7: =IF(A7=0,-Capitalization!C$19,IF(A7<=Inputs!$B$21,0,I7*J7-IF(AND(A7=Inputs!$B$22,Capitalization!C$18>0),Inputs!$B$23,0))) -> 0 | L7: =IF(H7>0,G7/H7,"") | M7: =IF(A7=0,-Capitalization!C$4,IF(A7<=Inputs!$B$21,0,G7)) -> 0
A8: 3 | B8: =IF(A8=0,"Equity",IF(A8<=Inputs!$B$21,"Construction",IF(A8<=Inputs!$B$21+Inputs!$B$5,"Queue wait",IF(A8<=Inputs!$B$21+Configurations!$B$15,"Grid ops"," ")))) -> Queue wait | C8: =IF(A8<=Inputs!$B$21,"",A8-Inputs!$B$21-1) -> 0 | D8: =IF(OR(A8<=Inputs!$B$21,A8>Inputs!$B$21+Configurations!$B$15),0,Configurations!$B$4*Configurations!$B$5*8760*(1-Configurations!$B$6)^C8*Configurations!$B$7*(1-Configurations!$B$8)) -> 230179.95 | E8: =IF(OR(A8<=Inputs!$B$21,A8>Inputs!$B$21+Configurations!$B$15),0,IF(A8<=Inputs!$B$21+Inputs!$B$5,D8*(1-Inputs!$B$10)*Configurations!$B$16/1000000,D8*Inputs!$B$18/1000000)) -> 27.631648 | F8: =IF(OR(A8<=Inputs!$B$21,A8>Inputs!$B$21+Configurations!$B$15),0,Configurations!$B$12+Configurations!$B$13+Configurations!$B$14+Inputs!$B$20*E8) -> 5.2524747 | G8: =E8-F8 -> 22.379173 | H8: =IF(AND(A8>Inputs!$B$21,A8<=Inputs!$B$21+Inputs!$B$12),Capitalization!C$12,0) -> 8.5084163 | I8: =G8-H8 -> 13.870757 | J8: =IF(A8<=Inputs!$B$21,"",IF(AND(A8<=Inputs!$B$22,Capitalization!C$18>0),Inputs!$B$25,Inputs!$B$26)) -> 0.7 | K8: =IF(A8=0,-Capitalization!C$19,IF(A8<=Inputs!$B$21,0,I8*J8-IF(AND(A8=Inputs!$B$22,Capitalization!C$18>0),Inputs!$B$23,0))) -> 9.70953 | L8: =IF(H8>0,G8/H8,"") -> 2.6302396 | M8: =IF(A8=0,-Capitalization!C$4,IF(A8<=Inputs!$B$21,0,G8)) -> 22.379173
A9: 4 | B9: =IF(A9=0,"Equity",IF(A9<=Inputs!$B$21,"Construction",IF(A9<=Inputs!$B$21+Inputs!$B$5,"Queue wait",IF(A9<=Inputs!$B$21+Configurations!$B$15,"Grid ops"," ")))) -> Queue wait | C9: =IF(A9<=Inputs!$B$21,"",A9-Inputs!$B$21-1) -> 1 | D9: =IF(OR(A9<=Inputs!$B$21,A9>Inputs!$B$21+Configurations!$B$15),0,Configurations!$B$4*Configurations!$B$5*8760*(1-Configurations!$B$6)^C9*Configurations!$B$7*(1-Configurations!$B$8)) -> 229029.05 | E9: =IF(OR(A9<=Inputs!$B$21,A9>Inputs!$B$21+Configurations!$B$15),0,IF(A9<=Inputs!$B$21+Inputs!$B$5,D9*(1-Inputs!$B$10)*Configurations!$B$16/1000000,D9*Inputs!$B$18/1000000)) -> 27.49349 | F9: =IF(OR(A9<=Inputs!$B$21,A9>Inputs!$B$21+Configurations!$B$15),0,Configurations!$B$12+Configurations!$B$13+Configurations!$B$14+Inputs!$B$20*E9) -> 5.2504023 | G9: =E9-F9 -> 22.243088 | H9: =IF(AND(A9>Inputs!$B$21,A9<=Inputs!$B$21+Inputs!$B$12),Capitalization!C$12,0) -> 8.5084163 | I9: =G9-H9 -> 13.734671 | J9: =IF(A9<=Inputs!$B$21,"",IF(AND(A9<=Inputs!$B$22,Capitalization!C$18>0),Inputs!$B$25,Inputs!$B$26)) -> 0.7 | K9: =IF(A9=0,-Capitalization!C$19,IF(A9<=Inputs!$B$21,0,I9*J9-IF(AND(A9=Inputs!$B$22,Capitalization!C$18>0),Inputs!$B$23,0))) -> 9.6142699 | L9: =IF(H9>0,G9/H9,"") -> 2.6142453 | M9: =IF(A9=0,-Capitalization!C$4,IF(A9<=Inputs!$B$21,0,G9)) -> 22.243088
A10: 5 | B10: =IF(A10=0,"Equity",IF(A10<=Inputs!$B$21,"Construction",IF(A10<=Inputs!$B$21+Inputs!$B$5,"Queue wait",IF(A10<=Inputs!$B$21+Configurations!$B$15,"Grid ops"," ")))) -> Queue wait | C10: =IF(A10<=Inputs!$B$21,"",A10-Inputs!$B$21-1) -> 2 | D10: =IF(OR(A10<=Inputs!$B$21,A10>Inputs!$B$21+Configurations!$B$15),0,Configurations!$B$4*Configurations!$B$5*8760*(1-Configurations!$B$6)^C10*Configurations!$B$7*(1-Configurations!$B$8)) -> 227883.9 | E10: =IF(OR(A10<=Inputs!$B$21,A10>Inputs!$B$21+Configurations!$B$15),0,IF(A10<=Inputs!$B$21+Inputs!$B$5,D10*(1-Inputs!$B$10)*Configurations!$B$16/1000000,D10*Inputs!$B$18/1000000)) -> 27.356022 | F10: =IF(OR(A10<=Inputs!$B$21,A10>Inputs!$B$21+Configurations!$B$15),0,Configurations!$B$12+Configurations!$B$13+Configurations!$B$14+Inputs!$B$20*E10) -> 5.2483403 | G10: =E10-F10 -> 22.107682 | H10: =IF(AND(A10>Inputs!$B$21,A10<=Inputs!$B$21+Inputs!$B$12),Capitalization!C$12,0) -> 8.5084163 | I10: =G10-H10 -> 13.599266 | J10: =IF(A10<=Inputs!$B$21,"",IF(AND(A10<=Inputs!$B$22,Capitalization!C$18>0),Inputs!$B$25,Inputs!$B$26)) -> 0.7 | K10: =IF(A10=0,-Capitalization!C$19,IF(A10<=Inputs!$B$21,0,I10*J10-IF(AND(A10=Inputs!$B$22,Capitalization!C$18>0),Inputs!$B$23,0))) -> 9.5194861 | L10: =IF(H10>0,G10/H10,"") -> 2.598331 | M10: =IF(A10=0,-Capitalization!C$4,IF(A10<=Inputs!$B$21,0,G10)) -> 22.107682
A11: 6 | B11: =IF(A11=0,"Equity",IF(A11<=Inputs!$B$21,"Construction",IF(A11<=Inputs!$B$21+Inputs!$B$5,"Queue wait",IF(A11<=Inputs!$B$21+Configurations!$B$15,"Grid ops"," ")))) -> Queue wait | C11: =IF(A11<=Inputs!$B$21,"",A11-Inputs!$B$21-1) -> 3 | D11: =IF(OR(A11<=Inputs!$B$21,A11>Inputs!$B$21+Configurations!$B$15),0,Configurations!$B$4*Configurations!$B$5*8760*(1-Configurations!$B$6)^C11*Configurations!$B$7*(1-Configurations!$B$8)) -> 226744.49 | E11: =IF(OR(A11<=Inputs!$B$21,A11>Inputs!$B$21+Configurations!$B$15),0,IF(A11<=Inputs!$B$21+Inputs!$B$5,D11*(1-Inputs!$B$10)*Configurations!$B$16/1000000,D11*Inputs!$B$18/1000000)) -> 27.219242 | F11: =IF(OR(A11<=Inputs!$B$21,A11>Inputs!$B$21+Configurations!$B$15),0,Configurations!$B$12+Configurations!$B$13+Configurations!$B$14+Inputs!$B$20*E11) -> 5.2462886 | G11: =E11-F11 -> 21.972954 | H11: =IF(AND(A11>Inputs!$B$21,A11<=Inputs!$B$21+Inputs!$B$12),Capitalization!C$12,0) -> 8.5084163 | I11: =G11-H11 -> 13.464537 | J11: =IF(A11<=Inputs!$B$21,"",IF(AND(A11<=Inputs!$B$22,Capitalization!C$18>0),Inputs!$B$25,Inputs!$B$26)) -> 0.7 | K11: =IF(A11=0,-Capitalization!C$19,IF(A11<=Inputs!$B$21,0,I11*J11-IF(AND(A11=Inputs!$B$22,Capitalization!C$18>0),Inputs!$B$23,0))) -> 8.4251762 | L11: =IF(H11>0,G11/H11,"") -> 2.5824963 | M11: =IF(A11=0,-Capitalization!C$4,IF(A11<=Inputs!$B$21,0,G11)) -> 21.972954
A12: 7 | B12: =IF(A12=0,"Equity",IF(A12<=Inputs!$B$21,"Construction",IF(A12<=Inputs!$B$21+Inputs!$B$5,"Queue wait",IF(A12<=Inputs!$B$21+Configurations!$B$15,"Grid ops"," ")))) -> Grid ops | C12: =IF(A12<=Inputs!$B$21,"",A12-Inputs!$B$21-1) -> 4 | D12: =IF(OR(A12<=Inputs!$B$21,A12>Inputs!$B$21+Configurations!$B$15),0,Configurations!$B$4*Configurations!$B$5*8760*(1-Configurations!$B$6)^C12*Configurations!$B$7*(1-Configurations!$B$8)) -> 225610.76 | E12: =IF(OR(A12<=Inputs!$B$21,A12>Inputs!$B$21+Configurations!$B$15),0,IF(A12<=Inputs!$B$21+Inputs!$B$5,D12*(1-Inputs!$B$10)*Configurations!$B$16/1000000,D12*Inputs!$B$18/1000000)) -> 16.243975 | F12: =IF(OR(A12<=Inputs!$B$21,A12>Inputs!$B$21+Configurations!$B$15),0,Configurations!$B$12+Configurations!$B$13+Configurations!$B$14+Inputs!$B$20*E12) -> 5.0816596 | G12: =E12-F12 -> 11.162315 | H12: =IF(AND(A12>Inputs!$B$21,A12<=Inputs!$B$21+Inputs!$B$12),Capitalization!C$12,0) -> 8.5084163 | I12: =G12-H12 -> 2.653899 | J12: =IF(A12<=Inputs!$B$21,"",IF(AND(A12<=Inputs!$B$22,Capitalization!C$18>0),Inputs!$B$25,Inputs!$B$26)) -> 0.975 | K12: =IF(A12=0,-Capitalization!C$19,IF(A12<=Inputs!$B$21,0,I12*J12-IF(AND(A12=Inputs!$B$22,Capitalization!C$18>0),Inputs!$B$23,0))) -> 2.5875515 | L12: =IF(H12>0,G12/H12,"") -> 1.3119146 | M12: =IF(A12=0,-Capitalization!C$4,IF(A12<=Inputs!$B$21,0,G12)) -> 11.162315
A13: 8 | B13: =IF(A13=0,"Equity",IF(A13<=Inputs!$B$21,"Construction",IF(A13<=Inputs!$B$21+Inputs!$B$5,"Queue wait",IF(A13<=Inputs!$B$21+Configurations!$B$15,"Grid ops"," ")))) -> Grid ops | C13: =IF(A13<=Inputs!$B$21,"",A13-Inputs!$B$21-1) -> 5 | D13: =IF(OR(A13<=Inputs!$B$21,A13>Inputs!$B$21+Configurations!$B$15),0,Configurations!$B$4*Configurations!$B$5*8760*(1-Configurations!$B$6)^C13*Configurations!$B$7*(1-Configurations!$B$8)) -> 224482.71 | E13: =IF(OR(A13<=Inputs!$B$21,A13>Inputs!$B$21+Configurations!$B$15),0,IF(A13<=Inputs!$B$21+Inputs!$B$5,D13*(1-Inputs!$B$10)*Configurations!$B$16/1000000,D13*Inputs!$B$18/1000000)) -> 16.162755 | F13: =IF(OR(A13<=Inputs!$B$21,A13>Inputs!$B$21+Configurations!$B$15),0,Configurations!$B$12+Configurations!$B$13+Configurations!$B$14+Inputs!$B$20*E13) -> 5.0804413 | G13: =E13-F13 -> 11.082314 | H13: =IF(AND(A13>Inputs!$B$21,A13<=Inputs!$B$21+Inputs!$B$12),Capitalization!C$12,0) -> 8.5084163 | I13: =G13-H13 -> 2.5738974 | J13: =IF(A13<=Inputs!$B$21,"",IF(AND(A13<=Inputs!$B$22,Capitalization!C$18>0),Inputs!$B$25,Inputs!$B$26)) -> 0.975 | K13: =IF(A13=0,-Capitalization!C$19,IF(A13<=Inputs!$B$21,0,I13*J13-IF(AND(A13=Inputs!$B$22,Capitalization!C$18>0),Inputs!$B$23,0))) -> 2.50955 | L13: =IF(H13>0,G13/H13,"") -> 1.3025119 | M13: =IF(A13=0,-Capitalization!C$4,IF(A13<=Inputs!$B$21,0,G13)) -> 11.082314
A14: 9 | B14: =IF(A14=0,"Equity",IF(A14<=Inputs!$B$21,"Construction",IF(A14<=Inputs!$B$21+Inputs!$B$5,"Queue wait",IF(A14<=Inputs!$B$21+Configurations!$B$15,"Grid ops"," ")))) -> Grid ops | C14: =IF(A14<=Inputs!$B$21,"",A14-Inputs!$B$21-1) -> 6 | D14: =IF(OR(A14<=Inputs!$B$21,A14>Inputs!$B$21+Configurations!$B$15),0,Configurations!$B$4*Configurations!$B$5*8760*(1-Configurations!$B$6)^C14*Configurations!$B$7*(1-Configurations!$B$8)) -> 223360.3 | E14: =IF(OR(A14<=Inputs!$B$21,A14>Inputs!$B$21+Configurations!$B$15),0,IF(A14<=Inputs!$B$21+Inputs!$B$5,D14*(1-Inputs!$B$10)*Configurations!$B$16/1000000,D14*Inputs!$B$18/1000000)) -> 16.081941 | F14: =IF(OR(A14<=Inputs!$B$21,A14>Inputs!$B$21+Configurations!$B$15),0,Configurations!$B$12+Configurations!$B$13+Configurations!$B$14+Inputs!$B$20*E14) -> 5.0792291 | G14: =E14-F14 -> 11.002712 | H14: =IF(AND(A14>Inputs!$B$21,A14<=Inputs!$B$21+Inputs!$B$12),Capitalization!C$12,0) -> 8.5084163 | I14: =G14-H14 -> 2.4942958 | J14: =IF(A14<=Inputs!$B$21,"",IF(AND(A14<=Inputs!$B$22,Capitalization!C$18>0),Inputs!$B$25,Inputs!$B$26)) -> 0.975 | K14: =IF(A14=0,-Capitalization!C$19,IF(A14<=Inputs!$B$21,0,I14*J14-IF(AND(A14=Inputs!$B$22,Capitalization!C$18>0),Inputs!$B$23,0))) -> 2.4319384 | L14: =IF(H14>0,G14/H14,"") -> 1.2931563 | M14: =IF(A14=0,-Capitalization!C$4,IF(A14<=Inputs!$B$21,0,G14)) -> 11.002712
A15: 10 | B15: =IF(A15=0,"Equity",IF(A15<=Inputs!$B$21,"Construction",IF(A15<=Inputs!$B$21+Inputs!$B$5,"Queue wait",IF(A15<=Inputs!$B$21+Configurations!$B$15,"Grid ops"," ")))) -> Grid ops | C15: =IF(A15<=Inputs!$B$21,"",A15-Inputs!$B$21-1) -> 7 | D15: =IF(OR(A15<=Inputs!$B$21,A15>Inputs!$B$21+Configurations!$B$15),0,Configurations!$B$4*Configurations!$B$5*8760*(1-Configurations!$B$6)^C15*Configurations!$B$7*(1-Configurations!$B$8)) -> 222243.49 | E15: =IF(OR(A15<=Inputs!$B$21,A15>Inputs!$B$21+Configurations!$B$15),0,IF(A15<=Inputs!$B$21+Inputs!$B$5,D15*(1-Inputs!$B$10)*Configurations!$B$16/1000000,D15*Inputs!$B$18/1000000)) -> 16.001532 | F15: =IF(OR(A15<=Inputs!$B$21,A15>Inputs!$B$21+Configurations!$B$15),0,Configurations!$B$12+Configurations!$B$13+Configurations!$B$14+Inputs!$B$20*E15) -> 5.078023 | G15: =E15-F15 -> 10.923509 | H15: =IF(AND(A15>Inputs!$B$21,A15<=Inputs!$B$21+Inputs!$B$12),Capitalization!C$12,0) -> 8.5084163 | I15: =G15-H15 -> 2.4150923 | J15: =IF(A15<=Inputs!$B$21,"",IF(AND(A15<=Inputs!$B$22,Capitalization!C$18>0),Inputs!$B$25,Inputs!$B$26)) -> 0.975 | K15: =IF(A15=0,-Capitalization!C$19,IF(A15<=Inputs!$B$21,0,I15*J15-IF(AND(A15=Inputs!$B$22,Capitalization!C$18>0),Inputs!$B$23,0))) -> 2.354715 | L15: =IF(H15>0,G15/H15,"") -> 1.2838474 | M15: =IF(A15=0,-Capitalization!C$4,IF(A15<=Inputs!$B$21,0,G15)) -> 10.923509
A16: 11 | B16: =IF(A16=0,"Equity",IF(A16<=Inputs!$B$21,"Construction",IF(A16<=Inputs!$B$21+Inputs!$B$5,"Queue wait",IF(A16<=Inputs!$B$21+Configurations!$B$15,"Grid ops"," ")))) -> Grid ops | C16: =IF(A16<=Inputs!$B$21,"",A16-Inputs!$B$21-1) -> 8 | D16: =IF(OR(A16<=Inputs!$B$21,A16>Inputs!$B$21+Configurations!$B$15),0,Configurations!$B$4*Configurations!$B$5*8760*(1-Configurations!$B$6)^C16*Configurations!$B$7*(1-Configurations!$B$8)) -> 221132.28 | E16: =IF(OR(A16<=Inputs!$B$21,A16>Inputs!$B$21+Configurations!$B$15),0,IF(A16<=Inputs!$B$21+Inputs!$B$5,D16*(1-Inputs!$B$10)*Configurations!$B$16/1000000,D16*Inputs!$B$18/1000000)) -> 15.921524 | F16: =IF(OR(A16<=Inputs!$B$21,A16>Inputs!$B$21+Configurations!$B$15),0,Configurations!$B$12+Configurations!$B$13+Configurations!$B$14+Inputs!$B$20*E16) -> 5.0768229 | G16: =E16-F16 -> 10.844701 | H16: =IF(AND(A16>Inputs!$B$21,A16<=Inputs!$B$21+Inputs!$B$12),Capitalization!C$12,0) -> 8.5084163 | I16: =G16-H16 -> 2.3362847 | J16: =IF(A16<=Inputs!$B$21,"",IF(AND(A16<=Inputs!$B$22,Capitalization!C$18>0),Inputs!$B$25,Inputs!$B$26)) -> 0.975 | K16: =IF(A16=0,-Capitalization!C$19,IF(A16<=Inputs!$B$21,0,I16*J16-IF(AND(A16=Inputs!$B$22,Capitalization!C$18>0),Inputs!$B$23,0))) -> 2.2778776 | L16: =IF(H16>0,G16/H16,"") -> 1.2745851 | M16: =IF(A16=0,-Capitalization!C$4,IF(A16<=Inputs!$B$21,0,G16)) -> 10.844701
... A37: 32 | B37: =IF(A37=0,"Equity",IF(A37<=Inputs!$B$21,"Construction",IF(A37<=Inputs!$B$21+Inputs!$B$5,"Queue wait",IF(A37<=Inputs!$B$21+Configurations!$B$15,"Grid ops"," ")))) | C37: =IF(A37<=Inputs!$B$21,"",A37-Inputs!$B$21-1) -> 29 | D37: =IF(OR(A37<=Inputs!$B$21,A37>Inputs!$B$21+Configurations!$B$15),0,Configurations!$B$4*Configurations!$B$5*8760*(1-Configurations!$B$6)^C37*Configurations!$B$7*(1-Configurations!$B$8)) -> 0 | E37: =IF(OR(A37<=Inputs!$B$21,A37>Inputs!$B$21+Configurations!$B$15),0,IF(A37<=Inputs!$B$21+Inputs!$B$5,D37*(1-Inputs!$B$10)*Configurations!$B$16/1000000,D37*Inputs!$B$18/1000000)) -> 0 | F37: =IF(OR(A37<=Inputs!$B$21,A37>Inputs!$B$21+Configurations!$B$15),0,Configurations!$B$12+Configurations!$B$13+Configurations!$B$14+Inputs!$B$20*E37) -> 0 | G37: =E37-F37 -> 0 | H37: =IF(AND(A37>Inputs!$B$21,A37<=Inputs!$B$21+Inputs!$B$12),Capitalization!C$12,0) -> 0 | I37: =G37-H37 -> 0 | J37: =IF(A37<=Inputs!$B$21,"",IF(AND(A37<=Inputs!$B$22,Capitalization!C$18>0),Inputs!$B$25,Inputs!$B$26)) -> 0.975 | K37: =IF(A37=0,-Capitalization!C$19,IF(A37<=Inputs!$B$21,0,I37*J37-IF(AND(A37=Inputs!$B$22,Capitalization!C$18>0),Inputs!$B$23,0))) -> 0 | L37: =IF(H37>0,G37/H37,"") | M37: =IF(A37=0,-Capitalization!C$4,IF(A37<=Inputs!$B$21,0,G37)) -> 0

Sheet WindBase
A1: WindBase: annual cash flow waterfall ($mm)
A2: Developer levered IRR: | B2: =IRR(K5:K37) -> 0.076471682 | C2: Unlevered (project) IRR: | D2: =IRR(M5:M37) -> 0.02031468 | E2: NPV of dev cash @ discount rate ($mm): | F2: =K5+NPV(Inputs!$B$24,K6:K37) -> -2.4701198
A4: Year | B4: Phase | C4: Op yr | D4: Net energy (MWh) | E4: Revenue | F4: OPEX | G4: EBITDA | H4: Debt service | I4: Distributable cash | J4: Dev share | K4: Dev cash flow | L4: DSCR | M4: Project CF (unlevered)
A5: 0 | B5: =IF(A5=0,"Equity",IF(A5<=Inputs!$B$21,"Construction",IF(A5<=Inputs!$B$21+Inputs!$B$5,"Queue wait",IF(A5<=Inputs!$B$21+Configurations!$C$15,"Grid ops"," ")))) -> Equity | C5: =IF(A5<=Inputs!$B$21,"",A5-Inputs!$B$21-1) | D5: =IF(OR(A5<=Inputs!$B$21,A5>Inputs!$B$21+Configurations!$C$15),0,Configurations!$C$4*Configurations!$C$5*8760*(1-Configurations!$C$6)^C5*Configurations!$C$7*(1-Configurations!$C$8)) -> 0 | E5: =IF(OR(A5<=Inputs!$B$21,A5>Inputs!$B$21+Configurations!$C$15),0,IF(A5<=Inputs!$B$21+Inputs!$B$5,0,D5*Inputs!$B$18/1000000)) -> 0 | F5: =IF(OR(A5<=Inputs!$B$21,A5>Inputs!$B$21+Configurations!$C$15),0,IF(A5<=Inputs!$B$21+Inputs!$B$5,Configurations!$C$13,Configurations!$C$12+Configurations!$C$13+Inputs!$B$20*E5)) -> 0 | G5: =E5-F5 -> 0 | H5: =IF(AND(A5>Inputs!$B$21,A5<=Inputs!$B$21+Inputs!$B$12),Capitalization!D$12,0) -> 0 | I5: =G5-H5 -> 0 | J5: =IF(A5<=Inputs!$B$21,"",IF(AND(A5<=Inputs!$B$22,Capitalization!D$18>0),Inputs!$B$25,Inputs!$B$26)) | K5: =IF(A5=0,-Capitalization!D$19,IF(A5<=Inputs!$B$21,0,I5*J5-IF(AND(A5=Inputs!$B$22,Capitalization!D$18>0),Inputs!$B$23,0))) -> -23.543402 | L5: =IF(H5>0,G5/H5,"") | M5: =IF(A5=0,-Capitalization!D$4,IF(A5<=Inputs!$B$21,0,G5)) -> -321.4
A6: 1 | B6: =IF(A6=0,"Equity",IF(A6<=Inputs!$B$21,"Construction",IF(A6<=Inputs!$B$21+Inputs!$B$5,"Queue wait",IF(A6<=Inputs!$B$21+Configurations!$C$15,"Grid ops"," ")))) -> Construction | C6: =IF(A6<=Inputs!$B$21,"",A6-Inputs!$B$21-1) | D6: =IF(OR(A6<=Inputs!$B$21,A6>Inputs!$B$21+Configurations!$C$15),0,Configurations!$C$4*Configurations!$C$5*8760*(1-Configurations!$C$6)^C6*Configurations!$C$7*(1-Configurations!$C$8)) -> 0 | E6: =IF(OR(A6<=Inputs!$B$21,A6>Inputs!$B$21+Configurations!$C$15),0,IF(A6<=Inputs!$B$21+Inputs!$B$5,0,D6*Inputs!$B$18/1000000)) -> 0 | F6: =IF(OR(A6<=Inputs!$B$21,A6>Inputs!$B$21+Configurations!$C$15),0,IF(A6<=Inputs!$B$21+Inputs!$B$5,Configurations!$C$13,Configurations!$C$12+Configurations!$C$13+Inputs!$B$20*E6)) -> 0 | G6: =E6-F6 -> 0 | H6: =IF(AND(A6>Inputs!$B$21,A6<=Inputs!$B$21+Inputs!$B$12),Capitalization!D$12,0) -> 0 | I6: =G6-H6 -> 0 | J6: =IF(A6<=Inputs!$B$21,"",IF(AND(A6<=Inputs!$B$22,Capitalization!D$18>0),Inputs!$B$25,Inputs!$B$26)) | K6: =IF(A6=0,-Capitalization!D$19,IF(A6<=Inputs!$B$21,0,I6*J6-IF(AND(A6=Inputs!$B$22,Capitalization!D$18>0),Inputs!$B$23,0))) -> 0 | L6: =IF(H6>0,G6/H6,"") | M6: =IF(A6=0,-Capitalization!D$4,IF(A6<=Inputs!$B$21,0,G6)) -> 0
A7: 2 | B7: =IF(A7=0,"Equity",IF(A7<=Inputs!$B$21,"Construction",IF(A7<=Inputs!$B$21+Inputs!$B$5,"Queue wait",IF(A7<=Inputs!$B$21+Configurations!$C$15,"Grid ops"," ")))) -> Construction | C7: =IF(A7<=Inputs!$B$21,"",A7-Inputs!$B$21-1) | D7: =IF(OR(A7<=Inputs!$B$21,A7>Inputs!$B$21+Configurations!$C$15),0,Configurations!$C$4*Configurations!$C$5*8760*(1-Configurations!$C$6)^C7*Configurations!$C$7*(1-Configurations!$C$8)) -> 0 | E7: =IF(OR(A7<=Inputs!$B$21,A7>Inputs!$B$21+Configurations!$C$15),0,IF(A7<=Inputs!$B$21+Inputs!$B$5,0,D7*Inputs!$B$18/1000000)) -> 0 | F7: =IF(OR(A7<=Inputs!$B$21,A7>Inputs!$B$21+Configurations!$C$15),0,IF(A7<=Inputs!$B$21+Inputs!$B$5,Configurations!$C$13,Configurations!$C$12+Configurations!$C$13+Inputs!$B$20*E7)) -> 0 | G7: =E7-F7 -> 0 | H7: =IF(AND(A7>Inputs!$B$21,A7<=Inputs!$B$21+Inputs!$B$12),Capitalization!D$12,0) -> 0 | I7: =G7-H7 -> 0 | J7: =IF(A7<=Inputs!$B$21,"",IF(AND(A7<=Inputs!$B$22,Capitalization!D$18>0),Inputs!$B$25,Inputs!$B$26)) | K7: =IF(A7=0,-Capitalization!D$19,IF(A7<=Inputs!$B$21,0,I7*J7-IF(AND(A7=Inputs!$B$22,Capitalization!D$18>0),Inputs!$B$23,0))) -> 0 | L7: =IF(H7>0,G7/H7,"") | M7: =IF(A7=0,-Capitalization!D$4,IF(A7<=Inputs!$B$21,0,G7)) -> 0
A8: 3 | B8: =IF(A8=0,"Equity",IF(A8<=Inputs!$B$21,"Construction",IF(A8<=Inputs!$B$21+Inputs!$B$5,"Queue wait",IF(A8<=Inputs!$B$21+Configurations!$C$15,"Grid ops"," ")))) -> Queue wait | C8: =IF(A8<=Inputs!$B$21,"",A8-Inputs!$B$21-1) -> 0 | D8: =IF(OR(A8<=Inputs!$B$21,A8>Inputs!$B$21+Configurations!$C$15),0,Configurations!$C$4*Configurations!$C$5*8760*(1-Configurations!$C$6)^C8*Configurations!$C$7*(1-Configurations!$C$8)) -> 430466.4 | E8: =IF(OR(A8<=Inputs!$B$21,A8>Inputs!$B$21+Configurations!$C$15),0,IF(A8<=Inputs!$B$21+Inputs!$B$5,0,D8*Inputs!$B$18/1000000)) -> 0 | F8: =IF(OR(A8<=Inputs!$B$21,A8>Inputs!$B$21+Configurations!$C$15),0,IF(A8<=Inputs!$B$21+Inputs!$B$5,Configurations!$C$13,Configurations!$C$12+Configurations!$C$13+Inputs!$B$20*E8)) -> 1.586 | G8: =E8-F8 -> -1.586 | H8: =IF(AND(A8>Inputs!$B$21,A8<=Inputs!$B$21+Inputs!$B$12),Capitalization!D$12,0) -> 14.791995 | I8: =G8-H8 -> -16.377995 | J8: =IF(A8<=Inputs!$B$21,"",IF(AND(A8<=Inputs!$B$22,Capitalization!D$18>0),Inputs!$B$25,Inputs!$B$26)) -> 0.7 | K8: =IF(A8=0,-Capitalization!D$19,IF(A8<=Inputs!$B$21,0,I8*J8-IF(AND(A8=Inputs!$B$22,Capitalization!D$18>0),Inputs!$B$23,0))) -> -11.464597 | L8: =IF(H8>0,G8/H8,"") -> -0.10722015 | M8: =IF(A8=0,-Capitalization!D$4,IF(A8<=Inputs!$B$21,0,G8)) -> -1.586
A9: 4 | B9: =IF(A9=0,"Equity",IF(A9<=Inputs!$B$21,"Construction",IF(A9<=Inputs!$B$21+Inputs!$B$5,"Queue wait",IF(A9<=Inputs!$B$21+Configurations!$C$15,"Grid ops"," ")))) -> Queue wait | C9: =IF(A9<=Inputs!$B$21,"",A9-Inputs!$B$21-1) -> 1 | D9: =IF(OR(A9<=Inputs!$B$21,A9>Inputs!$B$21+Configurations!$C$15),0,Configurations!$C$4*Configurations!$C$5*8760*(1-Configurations!$C$6)^C9*Configurations!$C$7*(1-Configurations!$C$8)) -> 429605.47 | E9: =IF(OR(A9<=Inputs!$B$21,A9>Inputs!$B$21+Configurations!$C$15),0,IF(A9<=Inputs!$B$21+Inputs!$B$5,0,D9*Inputs!$B$18/1000000)) -> 0 | F9: =IF(OR(A9<=Inputs!$B$21,A9>Inputs!$B$21+Configurations!$C$15),0,IF(A9<=Inputs!$B$21+Inputs!$B$5,Configurations!$C$13,Configurations!$C$12+Configurations!$C$13+Inputs!$B$20*E9)) -> 1.586 | G9: =E9-F9 -> -1.586 | H9: =IF(AND(A9>Inputs!$B$21,A9<=Inputs!$B$21+Inputs!$B$12),Capitalization!D$12,0) -> 14.791995 | I9: =G9-H9 -> -16.377995 | J9: =IF(A9<=Inputs!$B$21,"",IF(AND(A9<=Inputs!$B$22,Capitalization!D$18>0),Inputs!$B$25,Inputs!$B$26)) -> 0.7 | K9: =IF(A9=0,-Capitalization!D$19,IF(A9<=Inputs!$B$21,0,I9*J9-IF(AND(A9=Inputs!$B$22,Capitalization!D$18>0),Inputs!$B$23,0))) -> -11.464597 | L9: =IF(H9>0,G9/H9,"") -> -0.10722015 | M9: =IF(A9=0,-Capitalization!D$4,IF(A9<=Inputs!$B$21,0,G9)) -> -1.586
A10: 5 | B10: =IF(A10=0,"Equity",IF(A10<=Inputs!$B$21,"Construction",IF(A10<=Inputs!$B$21+Inputs!$B$5,"Queue wait",IF(A10<=Inputs!$B$21+Configurations!$C$15,"Grid ops"," ")))) -> Queue wait | C10: =IF(A10<=Inputs!$B$21,"",A10-Inputs!$B$21-1) -> 2 | D10: =IF(OR(A10<=Inputs!$B$21,A10>Inputs!$B$21+Configurations!$C$15),0,Configurations!$C$4*Configurations!$C$5*8760*(1-Configurations!$C$6)^C10*Configurations!$C$7*(1-Configurations!$C$8)) -> 428746.26 | E10: =IF(OR(A10<=Inputs!$B$21,A10>Inputs!$B$21+Configurations!$C$15),0,IF(A10<=Inputs!$B$21+Inputs!$B$5,0,D10*Inputs!$B$18/1000000)) -> 0 | F10: =IF(OR(A10<=Inputs!$B$21,A10>Inputs!$B$21+Configurations!$C$15),0,IF(A10<=Inputs!$B$21+Inputs!$B$5,Configurations!$C$13,Configurations!$C$12+Configurations!$C$13+Inputs!$B$20*E10)) -> 1.586 | G10: =E10-F10 -> -1.586 | H10: =IF(AND(A10>Inputs!$B$21,A10<=Inputs!$B$21+Inputs!$B$12),Capitalization!D$12,0) -> 14.791995 | I10: =G10-H10 -> -16.377995 | J10: =IF(A10<=Inputs!$B$21,"",IF(AND(A10<=Inputs!$B$22,Capitalization!D$18>0),Inputs!$B$25,Inputs!$B$26)) -> 0.7 | K10: =IF(A10=0,-Capitalization!D$19,IF(A10<=Inputs!$B$21,0,I10*J10-IF(AND(A10=Inputs!$B$22,Capitalization!D$18>0),Inputs!$B$23,0))) -> -11.464597 | L10: =IF(H10>0,G10/H10,"") -> -0.10722015 | M10: =IF(A10=0,-Capitalization!D$4,IF(A10<=Inputs!$B$21,0,G10)) -> -1.586
A11: 6 | B11: =IF(A11=0,"Equity",IF(A11<=Inputs!$B$21,"Construction",IF(A11<=Inputs!$B$21+Inputs!$B$5,"Queue wait",IF(A11<=Inputs!$B$21+Configurations!$C$15,"Grid ops"," ")))) -> Queue wait | C11: =IF(A11<=Inputs!$B$21,"",A11-Inputs!$B$21-1) -> 3 | D11: =IF(OR(A11<=Inputs!$B$21,A11>Inputs!$B$21+Configurations!$C$15),0,Configurations!$C$4*Configurations!$C$5*8760*(1-Configurations!$C$6)^C11*Configurations!$C$7*(1-Configurations!$C$8)) -> 427888.76 | E11: =IF(OR(A11<=Inputs!$B$21,A11>Inputs!$B$21+Configurations!$C$15),0,IF(A11<=Inputs!$B$21+Inputs!$B$5,0,D11*Inputs!$B$18/1000000)) -> 0 | F11: =IF(OR(A11<=Inputs!$B$21,A11>Inputs!$B$21+Configurations!$C$15),0,IF(A11<=Inputs!$B$21+Inputs!$B$5,Configurations!$C$13,Configurations!$C$12+Configurations!$C$13+Inputs!$B$20*E11)) -> 1.586 | G11: =E11-F11 -> -1.586 | H11: =IF(AND(A11>Inputs!$B$21,A11<=Inputs!$B$21+Inputs!$B$12),Capitalization!D$12,0) -> 14.791995 | I11: =G11-H11 -> -16.377995 | J11: =IF(A11<=Inputs!$B$21,"",IF(AND(A11<=Inputs!$B$22,Capitalization!D$18>0),Inputs!$B$25,Inputs!$B$26)) -> 0.7 | K11: =IF(A11=0,-Capitalization!D$19,IF(A11<=Inputs!$B$21,0,I11*J11-IF(AND(A11=Inputs!$B$22,Capitalization!D$18>0),Inputs!$B$23,0))) -> -12.464597 | L11: =IF(H11>0,G11/H11,"") -> -0.10722015 | M11: =IF(A11=0,-Capitalization!D$4,IF(A11<=Inputs!$B$21,0,G11)) -> -1.586
A12: 7 | B12: =IF(A12=0,"Equity",IF(A12<=Inputs!$B$21,"Construction",IF(A12<=Inputs!$B$21+Inputs!$B$5,"Queue wait",IF(A12<=Inputs!$B$21+Configurations!$C$15,"Grid ops"," ")))) -> Grid ops | C12: =IF(A12<=Inputs!$B$21,"",A12-Inputs!$B$21-1) -> 4 | D12: =IF(OR(A12<=Inputs!$B$21,A12>Inputs!$B$21+Configurations!$C$15),0,Configurations!$C$4*Configurations!$C$5*8760*(1-Configurations!$C$6)^C12*Configurations!$C$7*(1-Configurations!$C$8)) -> 427032.99 | E12: =IF(OR(A12<=Inputs!$B$21,A12>Inputs!$B$21+Configurations!$C$15),0,IF(A12<=Inputs!$B$21+Inputs!$B$5,0,D12*Inputs!$B$18/1000000)) -> 30.746375 | F12: =IF(OR(A12<=Inputs!$B$21,A12>Inputs!$B$21+Configurations!$C$15),0,IF(A12<=Inputs!$B$21+Inputs!$B$5,Configurations!$C$13,Configurations!$C$12+Configurations!$C$13+Inputs!$B$20*E12)) -> 8.4221956 | G12: =E12-F12 -> 22.324179 | H12: =IF(AND(A12>Inputs!$B$21,A12<=Inputs!$B$21+Inputs!$B$12),Capitalization!D$12,0) -> 14.791995 | I12: =G12-H12 -> 7.5321842 | J12: =IF(A12<=Inputs!$B$21,"",IF(AND(A12<=Inputs!$B$22,Capitalization!D$18>0),Inputs!$B$25,Inputs!$B$26)) -> 0.975 | K12: =IF(A12=0,-Capitalization!D$19,IF(A12<=Inputs!$B$21,0,I12*J12-IF(AND(A12=Inputs!$B$22,Capitalization!D$18>0),Inputs!$B$23,0))) -> 7.3438796 | L12: =IF(H12>0,G12/H12,"") -> 1.5092068 | M12: =IF(A12=0,-Capitalization!D$4,IF(A12<=Inputs!$B$21,0,G12)) -> 22.324179
A13: 8 | B13: =IF(A13=0,"Equity",IF(A13<=Inputs!$B$21,"Construction",IF(A13<=Inputs!$B$21+Inputs!$B$5,"Queue wait",IF(A13<=Inputs!$B$21+Configurations!$C$15,"Grid ops"," ")))) -> Grid ops | C13: =IF(A13<=Inputs!$B$21,"",A13-Inputs!$B$21-1) -> 5 | D13: =IF(OR(A13<=Inputs!$B$21,A13>Inputs!$B$21+Configurations!$C$15),0,Configurations!$C$4*Configurations!$C$5*8760*(1-Configurations!$C$6)^C13*Configurations!$C$7*(1-Configurations!$C$8)) -> 426178.92 | E13: =IF(OR(A13<=Inputs!$B$21,A13>Inputs!$B$21+Configurations!$C$15),0,IF(A13<=Inputs!$B$21+Inputs!$B$5,0,D13*Inputs!$B$18/1000000)) -> 30.684882 | F13: =IF(OR(A13<=Inputs!$B$21,A13>Inputs!$B$21+Configurations!$C$15),0,IF(A13<=Inputs!$B$21+Inputs!$B$5,Configurations!$C$13,Configurations!$C$12+Configurations!$C$13+Inputs!$B$20*E13)) -> 8.4212732 | G13: =E13-F13 -> 22.263609 | H13: =IF(AND(A13>Inputs!$B$21,A13<=Inputs!$B$21+Inputs!$B$12),Capitalization!D$12,0) -> 14.791995 | I13: =G13-H13 -> 7.4716139 | J13: =IF(A13<=Inputs!$B$21,"",IF(AND(A13<=Inputs!$B$22,Capitalization!D$18>0),Inputs!$B$25,Inputs!$B$26)) -> 0.975 | K13: =IF(A13=0,-Capitalization!D$19,IF(A13<=Inputs!$B$21,0,I13*J13-IF(AND(A13=Inputs!$B$22,Capitalization!D$18>0),Inputs!$B$23,0))) -> 7.2848235 | L13: =IF(H13>0,G13/H13,"") -> 1.505112 | M13: =IF(A13=0,-Capitalization!D$4,IF(A13<=Inputs!$B$21,0,G13)) -> 22.263609
A14: 9 | B14: =IF(A14=0,"Equity",IF(A14<=Inputs!$B$21,"Construction",IF(A14<=Inputs!$B$21+Inputs!$B$5,"Queue wait",IF(A14<=Inputs!$B$21+Configurations!$C$15,"Grid ops"," ")))) -> Grid ops | C14: =IF(A14<=Inputs!$B$21,"",A14-Inputs!$B$21-1) -> 6 | D14: =IF(OR(A14<=Inputs!$B$21,A14>Inputs!$B$21+Configurations!$C$15),0,Configurations!$C$4*Configurations!$C$5*8760*(1-Configurations!$C$6)^C14*Configurations!$C$7*(1-Configurations!$C$8)) -> 425326.56 | E14: =IF(OR(A14<=Inputs!$B$21,A14>Inputs!$B$21+Configurations!$C$15),0,IF(A14<=Inputs!$B$21+Inputs!$B$5,0,D14*Inputs!$B$18/1000000)) -> 30.623512 | F14: =IF(OR(A14<=Inputs!$B$21,A14>Inputs!$B$21+Configurations!$C$15),0,IF(A14<=Inputs!$B$21+Inputs!$B$5,Configurations!$C$13,Configurations!$C$12+Configurations!$C$13+Inputs!$B$20*E14)) -> 8.4203527 | G14: =E14-F14 -> 22.20316 | H14: =IF(AND(A14>Inputs!$B$21,A14<=Inputs!$B$21+Inputs!$B$12),Capitalization!D$12,0) -> 14.791995 | I14: =G14-H14 -> 7.4111646 | J14: =IF(A14<=Inputs!$B$21,"",IF(AND(A14<=Inputs!$B$22,Capitalization!D$18>0),Inputs!$B$25,Inputs!$B$26)) -> 0.975 | K14: =IF(A14=0,-Capitalization!D$19,IF(A14<=Inputs!$B$21,0,I14*J14-IF(AND(A14=Inputs!$B$22,Capitalization!D$18>0),Inputs!$B$23,0))) -> 7.2258855 | L14: =IF(H14>0,G14/H14,"") -> 1.5010254 | M14: =IF(A14=0,-Capitalization!D$4,IF(A14<=Inputs!$B$21,0,G14)) -> 22.20316
A15: 10 | B15: =IF(A15=0,"Equity",IF(A15<=Inputs!$B$21,"Construction",IF(A15<=Inputs!$B$21+Inputs!$B$5,"Queue wait",IF(A15<=Inputs!$B$21+Configurations!$C$15,"Grid ops"," ")))) -> Grid ops | C15: =IF(A15<=Inputs!$B$21,"",A15-Inputs!$B$21-1) -> 7 | D15: =IF(OR(A15<=Inputs!$B$21,A15>Inputs!$B$21+Configurations!$C$15),0,Configurations!$C$4*Configurations!$C$5*8760*(1-Configurations!$C$6)^C15*Configurations!$C$7*(1-Configurations!$C$8)) -> 424475.91 | E15: =IF(OR(A15<=Inputs!$B$21,A15>Inputs!$B$21+Configurations!$C$15),0,IF(A15<=Inputs!$B$21+Inputs!$B$5,0,D15*Inputs!$B$18/1000000)) -> 30.562265 | F15: =IF(OR(A15<=Inputs!$B$21,A15>Inputs!$B$21+Configurations!$C$15),0,IF(A15<=Inputs!$B$21+Inputs!$B$5,Configurations!$C$13,Configurations!$C$12+Configurations!$C$13+Inputs!$B$20*E15)) -> 8.419434 | G15: =E15-F15 -> 22.142831 | H15: =IF(AND(A15>Inputs!$B$21,A15<=Inputs!$B$21+Inputs!$B$12),Capitalization!D$12,0) -> 14.791995 | I15: =G15-H15 -> 7.3508363 | J15: =IF(A15<=Inputs!$B$21,"",IF(AND(A15<=Inputs!$B$22,Capitalization!D$18>0),Inputs!$B$25,Inputs!$B$26)) -> 0.975 | K15: =IF(A15=0,-Capitalization!D$19,IF(A15<=Inputs!$B$21,0,I15*J15-IF(AND(A15=Inputs!$B$22,Capitalization!D$18>0),Inputs!$B$23,0))) -> 7.1670654 | L15: =IF(H15>0,G15/H15,"") -> 1.4969469 | M15: =IF(A15=0,-Capitalization!D$4,IF(A15<=Inputs!$B$21,0,G15)) -> 22.142831
A16: 11 | B16: =IF(A16=0,"Equity",IF(A16<=Inputs!$B$21,"Construction",IF(A16<=Inputs!$B$21+Inputs!$B$5,"Queue wait",IF(A16<=Inputs!$B$21+Configurations!$C$15,"Grid ops"," ")))) -> Grid ops | C16: =IF(A16<=Inputs!$B$21,"",A16-Inputs!$B$21-1) -> 8 | D16: =IF(OR(A16<=Inputs!$B$21,A16>Inputs!$B$21+Configurations!$C$15),0,Configurations!$C$4*Configurations!$C$5*8760*(1-Configurations!$C$6)^C16*Configurations!$C$7*(1-Configurations!$C$8)) -> 423626.96 | E16: =IF(OR(A16<=Inputs!$B$21,A16>Inputs!$B$21+Configurations!$C$15),0,IF(A16<=Inputs!$B$21+Inputs!$B$5,0,D16*Inputs!$B$18/1000000)) -> 30.501141 | F16: =IF(OR(A16<=Inputs!$B$21,A16>Inputs!$B$21+Configurations!$C$15),0,IF(A16<=Inputs!$B$21+Inputs!$B$5,Configurations!$C$13,Configurations!$C$12+Configurations!$C$13+Inputs!$B$20*E16)) -> 8.4185171 | G16: =E16-F16 -> 22.082624 | H16: =IF(AND(A16>Inputs!$B$21,A16<=Inputs!$B$21+Inputs!$B$12),Capitalization!D$12,0) -> 14.791995 | I16: =G16-H16 -> 7.2906287 | J16: =IF(A16<=Inputs!$B$21,"",IF(AND(A16<=Inputs!$B$22,Capitalization!D$18>0),Inputs!$B$25,Inputs!$B$26)) -> 0.975 | K16: =IF(A16=0,-Capitalization!D$19,IF(A16<=Inputs!$B$21,0,I16*J16-IF(AND(A16=Inputs!$B$22,Capitalization!D$18>0),Inputs!$B$23,0))) -> 7.1083629 | L16: =IF(H16>0,G16/H16,"") -> 1.4928766 | M16: =IF(A16=0,-Capitalization!D$4,IF(A16<=Inputs!$B$21,0,G16)) -> 22.082624
... A37: 32 | B37: =IF(A37=0,"Equity",IF(A37<=Inputs!$B$21,"Construction",IF(A37<=Inputs!$B$21+Inputs!$B$5,"Queue wait",IF(A37<=Inputs!$B$21+Configurations!$C$15,"Grid ops"," ")))) | C37: =IF(A37<=Inputs!$B$21,"",A37-Inputs!$B$21-1) -> 29 | D37: =IF(OR(A37<=Inputs!$B$21,A37>Inputs!$B$21+Configurations!$C$15),0,Configurations!$C$4*Configurations!$C$5*8760*(1-Configurations!$C$6)^C37*Configurations!$C$7*(1-Configurations!$C$8)) -> 0 | E37: =IF(OR(A37<=Inputs!$B$21,A37>Inputs!$B$21+Configurations!$C$15),0,IF(A37<=Inputs!$B$21+Inputs!$B$5,0,D37*Inputs!$B$18/1000000)) -> 0 | F37: =IF(OR(A37<=Inputs!$B$21,A37>Inputs!$B$21+Configurations!$C$15),0,IF(A37<=Inputs!$B$21+Inputs!$B$5,Configurations!$C$13,Configurations!$C$12+Configurations!$C$13+Inputs!$B$20*E37)) -> 0 | G37: =E37-F37 -> 0 | H37: =IF(AND(A37>Inputs!$B$21,A37<=Inputs!$B$21+Inputs!$B$12),Capitalization!D$12,0) -> 0 | I37: =G37-H37 -> 0 | J37: =IF(A37<=Inputs!$B$21,"",IF(AND(A37<=Inputs!$B$22,Capitalization!D$18>0),Inputs!$B$25,Inputs!$B$26)) -> 0.975 | K37: =IF(A37=0,-Capitalization!D$19,IF(A37<=Inputs!$B$21,0,I37*J37-IF(AND(A37=Inputs!$B$22,Capitalization!D$18>0),Inputs!$B$23,0))) -> 0 | L37: =IF(H37>0,G37/H37,"") | M37: =IF(A37=0,-Capitalization!D$4,IF(A37<=Inputs!$B$21,0,G37)) -> 0

Sheet WindColoc
A1: WindColoc: annual cash flow waterfall ($mm)
A2: Developer levered IRR: | B2: =IRR(K5:K37) -> 0.24443198 | C2: Unlevered (project) IRR: | D2: =IRR(M5:M37) -> 0.04603537 | E2: NPV of dev cash @ discount rate ($mm): | F2: =K5+NPV(Inputs!$B$24,K6:K37) -> 58.258031
A4: Year | B4: Phase | C4: Op yr | D4: Net energy (MWh) | E4: Revenue | F4: OPEX | G4: EBITDA | H4: Debt service | I4: Distributable cash | J4: Dev share | K4: Dev cash flow | L4: DSCR | M4: Project CF (unlevered)
A5: 0 | B5: =IF(A5=0,"Equity",IF(A5<=Inputs!$B$21,"Construction",IF(A5<=Inputs!$B$21+Inputs!$B$5,"Queue wait",IF(A5<=Inputs!$B$21+Configurations!$C$15,"Grid ops"," ")))) -> Equity | C5: =IF(A5<=Inputs!$B$21,"",A5-Inputs!$B$21-1) | D5: =IF(OR(A5<=Inputs!$B$21,A5>Inputs!$B$21+Configurations!$C$15),0,Configurations!$C$4*Configurations!$C$5*8760*(1-Configurations!$C$6)^C5*Configurations!$C$7*(1-Configurations!$C$8)) -> 0 | E5: =IF(OR(A5<=Inputs!$B$21,A5>Inputs!$B$21+Configurations!$C$15),0,IF(A5<=Inputs!$B$21+Inputs!$B$5,D5*(1-Inputs!$B$10)*Configurations!$C$16/1000000,D5*Inputs!$B$18/1000000)) -> 0 | F5: =IF(OR(A5<=Inputs!$B$21,A5>Inputs!$B$21+Configurations!$C$15),0,Configurations!$C$12+Configurations!$C$13+Configurations!$C$14+Inputs!$B$20*E5) -> 0 | G5: =E5-F5 -> 0 | H5: =IF(AND(A5>Inputs!$B$21,A5<=Inputs!$B$21+Inputs!$B$12),Capitalization!E$12,0) -> 0 | I5: =G5-H5 -> 0 | J5: =IF(A5<=Inputs!$B$21,"",IF(AND(A5<=Inputs!$B$22,Capitalization!E$18>0),Inputs!$B$25,Inputs!$B$26)) | K5: =IF(A5=0,-Capitalization!E$19,IF(A5<=Inputs!$B$21,0,I5*J5-IF(AND(A5=Inputs!$B$22,Capitalization!E$18>0),Inputs!$B$23,0))) -> -31.643402 | L5: =IF(H5>0,G5/H5,"") | M5: =IF(A5=0,-Capitalization!E$4,IF(A5<=Inputs!$B$21,0,G5)) -> -339.4
A6: 1 | B6: =IF(A6=0,"Equity",IF(A6<=Inputs!$B$21,"Construction",IF(A6<=Inputs!$B$21+Inputs!$B$5,"Queue wait",IF(A6<=Inputs!$B$21+Configurations!$C$15,"Grid ops"," ")))) -> Construction | C6: =IF(A6<=Inputs!$B$21,"",A6-Inputs!$B$21-1) | D6: =IF(OR(A6<=Inputs!$B$21,A6>Inputs!$B$21+Configurations!$C$15),0,Configurations!$C$4*Configurations!$C$5*8760*(1-Configurations!$C$6)^C6*Configurations!$C$7*(1-Configurations!$C$8)) -> 0 | E6: =IF(OR(A6<=Inputs!$B$21,A6>Inputs!$B$21+Configurations!$C$15),0,IF(A6<=Inputs!$B$21+Inputs!$B$5,D6*(1-Inputs!$B$10)*Configurations!$C$16/1000000,D6*Inputs!$B$18/1000000)) -> 0 | F6: =IF(OR(A6<=Inputs!$B$21,A6>Inputs!$B$21+Configurations!$C$15),0,Configurations!$C$12+Configurations!$C$13+Configurations!$C$14+Inputs!$B$20*E6) -> 0 | G6: =E6-F6 -> 0 | H6: =IF(AND(A6>Inputs!$B$21,A6<=Inputs!$B$21+Inputs!$B$12),Capitalization!E$12,0) -> 0 | I6: =G6-H6 -> 0 | J6: =IF(A6<=Inputs!$B$21,"",IF(AND(A6<=Inputs!$B$22,Capitalization!E$18>0),Inputs!$B$25,Inputs!$B$26)) | K6: =IF(A6=0,-Capitalization!E$19,IF(A6<=Inputs!$B$21,0,I6*J6-IF(AND(A6=Inputs!$B$22,Capitalization!E$18>0),Inputs!$B$23,0))) -> 0 | L6: =IF(H6>0,G6/H6,"") | M6: =IF(A6=0,-Capitalization!E$4,IF(A6<=Inputs!$B$21,0,G6)) -> 0
A7: 2 | B7: =IF(A7=0,"Equity",IF(A7<=Inputs!$B$21,"Construction",IF(A7<=Inputs!$B$21+Inputs!$B$5,"Queue wait",IF(A7<=Inputs!$B$21+Configurations!$C$15,"Grid ops"," ")))) -> Construction | C7: =IF(A7<=Inputs!$B$21,"",A7-Inputs!$B$21-1) | D7: =IF(OR(A7<=Inputs!$B$21,A7>Inputs!$B$21+Configurations!$C$15),0,Configurations!$C$4*Configurations!$C$5*8760*(1-Configurations!$C$6)^C7*Configurations!$C$7*(1-Configurations!$C$8)) -> 0 | E7: =IF(OR(A7<=Inputs!$B$21,A7>Inputs!$B$21+Configurations!$C$15),0,IF(A7<=Inputs!$B$21+Inputs!$B$5,D7*(1-Inputs!$B$10)*Configurations!$C$16/1000000,D7*Inputs!$B$18/1000000)) -> 0 | F7: =IF(OR(A7<=Inputs!$B$21,A7>Inputs!$B$21+Configurations!$C$15),0,Configurations!$C$12+Configurations!$C$13+Configurations!$C$14+Inputs!$B$20*E7) -> 0 | G7: =E7-F7 -> 0 | H7: =IF(AND(A7>Inputs!$B$21,A7<=Inputs!$B$21+Inputs!$B$12),Capitalization!E$12,0) -> 0 | I7: =G7-H7 -> 0 | J7: =IF(A7<=Inputs!$B$21,"",IF(AND(A7<=Inputs!$B$22,Capitalization!E$18>0),Inputs!$B$25,Inputs!$B$26)) | K7: =IF(A7=0,-Capitalization!E$19,IF(A7<=Inputs!$B$21,0,I7*J7-IF(AND(A7=Inputs!$B$22,Capitalization!E$18>0),Inputs!$B$23,0))) -> 0 | L7: =IF(H7>0,G7/H7,"") | M7: =IF(A7=0,-Capitalization!E$4,IF(A7<=Inputs!$B$21,0,G7)) -> 0
A8: 3 | B8: =IF(A8=0,"Equity",IF(A8<=Inputs!$B$21,"Construction",IF(A8<=Inputs!$B$21+Inputs!$B$5,"Queue wait",IF(A8<=Inputs!$B$21+Configurations!$C$15,"Grid ops"," ")))) -> Queue wait | C8: =IF(A8<=Inputs!$B$21,"",A8-Inputs!$B$21-1) -> 0 | D8: =IF(OR(A8<=Inputs!$B$21,A8>Inputs!$B$21+Configurations!$C$15),0,Configurations!$C$4*Configurations!$C$5*8760*(1-Configurations!$C$6)^C8*Configurations!$C$7*(1-Configurations!$C$8)) -> 430466.4 | E8: =IF(OR(A8<=Inputs!$B$21,A8>Inputs!$B$21+Configurations!$C$15),0,IF(A8<=Inputs!$B$21+Inputs!$B$5,D8*(1-Inputs!$B$10)*Configurations!$C$16/1000000,D8*Inputs!$B$18/1000000)) -> 49.585505 | F8: =IF(OR(A8<=Inputs!$B$21,A8>Inputs!$B$21+Configurations!$C$15),0,Configurations!$C$12+Configurations!$C$13+Configurations!$C$14+Inputs!$B$20*E8) -> 9.8297826 | G8: =E8-F8 -> 39.755723 | H8: =IF(AND(A8>Inputs!$B$21,A8<=Inputs!$B$21+Inputs!$B$12),Capitalization!E$12,0) -> 15.620421 | I8: =G8-H8 -> 24.135302 | J8: =IF(A8<=Inputs!$B$21,"",IF(AND(A8<=Inputs!$B$22,Capitalization!E$18>0),Inputs!$B$25,Inputs!$B$26)) -> 0.7 | K8: =IF(A8=0,-Capitalization!E$19,IF(A8<=Inputs!$B$21,0,I8*J8-IF(AND(A8=Inputs!$B$22,Capitalization!E$18>0),Inputs!$B$23,0))) -> 16.894711 | L8: =IF(H8>0,G8/H8,"") -> 2.5451122 | M8: =IF(A8=0,-Capitalization!E$4,IF(A8<=Inputs!$B$21,0,G8)) -> 39.755723
A9: 4 | B9: =IF(A9=0,"Equity",IF(A9<=Inputs!$B$21,"Construction",IF(A9<=Inputs!$B$21+Inputs!$B$5,"Queue wait",IF(A9<=Inputs!$B$21+Configurations!$C$15,"Grid ops"," ")))) -> Queue wait | C9: =IF(A9<=Inputs!$B$21,"",A9-Inputs!$B$21-1) -> 1 | D9: =IF(OR(A9<=Inputs!$B$21,A9>Inputs!$B$21+Configurations!$C$15),0,Configurations!$C$4*Configurations!$C$5*8760*(1-Configurations!$C$6)^C9*Configurations!$C$7*(1-Configurations!$C$8)) -> 429605.47 | E9: =IF(OR(A9<=Inputs!$B$21,A9>Inputs!$B$21+Configurations!$C$15),0,IF(A9<=Inputs!$B$21+Inputs!$B$5,D9*(1-Inputs!$B$10)*Configurations!$C$16/1000000,D9*Inputs!$B$18/1000000)) -> 49.486334 | F9: =IF(OR(A9<=Inputs!$B$21,A9>Inputs!$B$21+Configurations!$C$15),0,Configurations!$C$12+Configurations!$C$13+Configurations!$C$14+Inputs!$B$20*E9) -> 9.828295 | G9: =E9-F9 -> 39.658039 | H9: =IF(AND(A9>Inputs!$B$21,A9<=Inputs!$B$21+Inputs!$B$12),Capitalization!E$12,0) -> 15.620421 | I9: =G9-H9 -> 24.037619 | J9: =IF(A9<=Inputs!$B$21,"",IF(AND(A9<=Inputs!$B$22,Capitalization!E$18>0),Inputs!$B$25,Inputs!$B$26)) -> 0.7 | K9: =IF(A9=0,-Capitalization!E$19,IF(A9<=Inputs!$B$21,0,I9*J9-IF(AND(A9=Inputs!$B$22,Capitalization!E$18>0),Inputs!$B$23,0))) -> 16.826333 | L9: =IF(H9>0,G9/H9,"") -> 2.5388586 | M9: =IF(A9=0,-Capitalization!E$4,IF(A9<=Inputs!$B$21,0,G9)) -> 39.658039
A10: 5 | B10: =IF(A10=0,"Equity",IF(A10<=Inputs!$B$21,"Construction",IF(A10<=Inputs!$B$21+Inputs!$B$5,"Queue wait",IF(A10<=Inputs!$B$21+Configurations!$C$15,"Grid ops"," ")))) -> Queue wait | C10: =IF(A10<=Inputs!$B$21,"",A10-Inputs!$B$21-1) -> 2 | D10: =IF(OR(A10<=Inputs!$B$21,A10>Inputs!$B$21+Configurations!$C$15),0,Configurations!$C$4*Configurations!$C$5*8760*(1-Configurations!$C$6)^C10*Configurations!$C$7*(1-Configurations!$C$8)) -> 428746.26 | E10: =IF(OR(A10<=Inputs!$B$21,A10>Inputs!$B$21+Configurations!$C$15),0,IF(A10<=Inputs!$B$21+Inputs!$B$5,D10*(1-Inputs!$B$10)*Configurations!$C$16/1000000,D10*Inputs!$B$18/1000000)) -> 49.387362 | F10: =IF(OR(A10<=Inputs!$B$21,A10>Inputs!$B$21+Configurations!$C$15),0,Configurations!$C$12+Configurations!$C$13+Configurations!$C$14+Inputs!$B$20*E10) -> 9.8268104 | G10: =E10-F10 -> 39.560551 | H10: =IF(AND(A10>Inputs!$B$21,A10<=Inputs!$B$21+Inputs!$B$12),Capitalization!E$12,0) -> 15.620421 | I10: =G10-H10 -> 23.940131 | J10: =IF(A10<=Inputs!$B$21,"",IF(AND(A10<=Inputs!$B$22,Capitalization!E$18>0),Inputs!$B$25,Inputs!$B$26)) -> 0.7 | K10: =IF(A10=0,-Capitalization!E$19,IF(A10<=Inputs!$B$21,0,I10*J10-IF(AND(A10=Inputs!$B$22,Capitalization!E$18>0),Inputs!$B$23,0))) -> 16.758091 | L10: =IF(H10>0,G10/H10,"") -> 2.5326175 | M10: =IF(A10=0,-Capitalization!E$4,IF(A10<=Inputs!$B$21,0,G10)) -> 39.560551
A11: 6 | B11: =IF(A11=0,"Equity",IF(A11<=Inputs!$B$21,"Construction",IF(A11<=Inputs!$B$21+Inputs!$B$5,"Queue wait",IF(A11<=Inputs!$B$21+Configurations!$C$15,"Grid ops"," ")))) -> Queue wait | C11: =IF(A11<=Inputs!$B$21,"",A11-Inputs!$B$21-1) -> 3 | D11: =IF(OR(A11<=Inputs!$B$21,A11>Inputs!$B$21+Configurations!$C$15),0,Configurations!$C$4*Configurations!$C$5*8760*(1-Configurations!$C$6)^C11*Configurations!$C$7*(1-Configurations!$C$8)) -> 427888.76 | E11: =IF(OR(A11<=Inputs!$B$21,A11>Inputs!$B$21+Configurations!$C$15),0,IF(A11<=Inputs!$B$21+Inputs!$B$5,D11*(1-Inputs!$B$10)*Configurations!$C$16/1000000,D11*Inputs!$B$18/1000000)) -> 49.288587 | F11: =IF(OR(A11<=Inputs!$B$21,A11>Inputs!$B$21+Configurations!$C$15),0,Configurations!$C$12+Configurations!$C$13+Configurations!$C$14+Inputs!$B$20*E11) -> 9.8253288 | G11: =E11-F11 -> 39.463258 | H11: =IF(AND(A11>Inputs!$B$21,A11<=Inputs!$B$21+Inputs!$B$12),Capitalization!E$12,0) -> 15.620421 | I11: =G11-H11 -> 23.842838 | J11: =IF(A11<=Inputs!$B$21,"",IF(AND(A11<=Inputs!$B$22,Capitalization!E$18>0),Inputs!$B$25,Inputs!$B$26)) -> 0.7 | K11: =IF(A11=0,-Capitalization!E$19,IF(A11<=Inputs!$B$21,0,I11*J11-IF(AND(A11=Inputs!$B$22,Capitalization!E$18>0),Inputs!$B$23,0))) -> 15.689986 | L11: =IF(H11>0,G11/H11,"") -> 2.526389 | M11: =IF(A11=0,-Capitalization!E$4,IF(A11<=Inputs!$B$21,0,G11)) -> 39.463258
A12: 7 | B12: =IF(A12=0,"Equity",IF(A12<=Inputs!$B$21,"Construction",IF(A12<=Inputs!$B$21+Inputs!$B$5,"Queue wait",IF(A12<=Inputs!$B$21+Configurations!$C$15,"Grid ops"," ")))) -> Grid ops | C12: =IF(A12<=Inputs!$B$21,"",A12-Inputs!$B$21-1) -> 4 | D12: =IF(OR(A12<=Inputs!$B$21,A12>Inputs!$B$21+Configurations!$C$15),0,Configurations!$C$4*Configurations!$C$5*8760*(1-Configurations!$C$6)^C12*Configurations!$C$7*(1-Configurations!$C$8)) -> 427032.99 | E12: =IF(OR(A12<=Inputs!$B$21,A12>Inputs!$B$21+Configurations!$C$15),0,IF(A12<=Inputs!$B$21+Inputs!$B$5,D12*(1-Inputs!$B$10)*Configurations!$C$16/1000000,D12*Inputs!$B$18/1000000)) -> 30.746375 | F12: =IF(OR(A12<=Inputs!$B$21,A12>Inputs!$B$21+Configurations!$C$15),0,Configurations!$C$12+Configurations!$C$13+Configurations!$C$14+Inputs!$B$20*E12) -> 9.5471956 | G12: =E12-F12 -> 21.199179 | H12: =IF(AND(A12>Inputs!$B$21,A12<=Inputs!$B$21+Inputs!$B$12),Capitalization!E$12,0) -> 15.620421 | I12: =G12-H12 -> 5.5787588 | J12: =IF(A12<=Inputs!$B$21,"",IF(AND(A12<=Inputs!$B$22,Capitalization!E$18>0),Inputs!$B$25,Inputs!$B$26)) -> 0.975 | K12: =IF(A12=0,-Capitalization!E$19,IF(A12<=Inputs!$B$21,0,I12*J12-IF(AND(A12=Inputs!$B$22,Capitalization!E$18>0),Inputs!$B$23,0))) -> 5.4392899 | L12: =IF(H12>0,G12/H12,"") -> 1.3571452 | M12: =IF(A12=0,-Capitalization!E$4,IF(A12<=Inputs!$B$21,0,G12)) -> 21.199179
A13: 8 | B13: =IF(A13=0,"Equity",IF(A13<=Inputs!$B$21,"Construction",IF(A13<=Inputs!$B$21+Inputs!$B$5,"Queue wait",IF(A13<=Inputs!$B$21+Configurations!$C$15,"Grid ops"," ")))) -> Grid ops | C13: =IF(A13<=Inputs!$B$21,"",A13-Inputs!$B$21-1) -> 5 | D13: =IF(OR(A13<=Inputs!$B$21,A13>Inputs!$B$21+Configurations!$C$15),0,Configurations!$C$4*Configurations!$C$5*8760*(1-Configurations!$C$6)^C13*Configurations!$C$7*(1-Configurations!$C$8)) -> 426178.92 | E13: =IF(OR(A13<=Inputs!$B$21,A13>Inputs!$B$21+Configurations!$C$15),0,IF(A13<=Inputs!$B$21+Inputs!$B$5,D13*(1-Inputs!$B$10)*Configurations!$C$16/1000000,D13*Inputs!$B$18/1000000)) -> 30.684882 | F13: =IF(OR(A13<=Inputs!$B$21,A13>Inputs!$B$21+Configurations!$C$15),0,Configurations!$C$12+Configurations!$C$13+Configurations!$C$14+Inputs!$B$20*E13) -> 9.5462732 | G13: =E13-F13 -> 21.138609 | H13: =IF(AND(A13>Inputs!$B$21,A13<=Inputs!$B$21+Inputs!$B$12),Capitalization!E$12,0) -> 15.620421 | I13: =G13-H13 -> 5.5181885 | J13: =IF(A13<=Inputs!$B$21,"",IF(AND(A13<=Inputs!$B$22,Capitalization!E$18>0),Inputs!$B$25,Inputs!$B$26)) -> 0.975 | K13: =IF(A13=0,-Capitalization!E$19,IF(A13<=Inputs!$B$21,0,I13*J13-IF(AND(A13=Inputs!$B$22,Capitalization!E$18>0),Inputs!$B$23,0))) -> 5.3802338 | L13: =IF(H13>0,G13/H13,"") -> 1.3532676 | M13: =IF(A13=0,-Capitalization!E$4,IF(A13<=Inputs!$B$21,0,G13)) -> 21.138609
A14: 9 | B14: =IF(A14=0,"Equity",IF(A14<=Inputs!$B$21,"Construction",IF(A14<=Inputs!$B$21+Inputs!$B$5,"Queue wait",IF(A14<=Inputs!$B$21+Configurations!$C$15,"Grid ops"," ")))) -> Grid ops | C14: =IF(A14<=Inputs!$B$21,"",A14-Inputs!$B$21-1) -> 6 | D14: =IF(OR(A14<=Inputs!$B$21,A14>Inputs!$B$21+Configurations!$C$15),0,Configurations!$C$4*Configurations!$C$5*8760*(1-Configurations!$C$6)^C14*Configurations!$C$7*(1-Configurations!$C$8)) -> 425326.56 | E14: =IF(OR(A14<=Inputs!$B$21,A14>Inputs!$B$21+Configurations!$C$15),0,IF(A14<=Inputs!$B$21+Inputs!$B$5,D14*(1-Inputs!$B$10)*Configurations!$C$16/1000000,D14*Inputs!$B$18/1000000)) -> 30.623512 | F14: =IF(OR(A14<=Inputs!$B$21,A14>Inputs!$B$21+Configurations!$C$15),0,Configurations!$C$12+Configurations!$C$13+Configurations!$C$14+Inputs!$B$20*E14) -> 9.5453527 | G14: =E14-F14 -> 21.07816 | H14: =IF(AND(A14>Inputs!$B$21,A14<=Inputs!$B$21+Inputs!$B$12),Capitalization!E$12,0) -> 15.620421 | I14: =G14-H14 -> 5.4577393 | J14: =IF(A14<=Inputs!$B$21,"",IF(AND(A14<=Inputs!$B$22,Capitalization!E$18>0),Inputs!$B$25,Inputs!$B$26)) -> 0.975 | K14: =IF(A14=0,-Capitalization!E$19,IF(A14<=Inputs!$B$21,0,I14*J14-IF(AND(A14=Inputs!$B$22,Capitalization!E$18>0),Inputs!$B$23,0))) -> 5.3212958 | L14: =IF(H14>0,G14/H14,"") -> 1.3493977 | M14: =IF(A14=0,-Capitalization!E$4,IF(A14<=Inputs!$B$21,0,G14)) -> 21.07816
A15: 10 | B15: =IF(A15=0,"Equity",IF(A15<=Inputs!$B$21,"Construction",IF(A15<=Inputs!$B$21+Inputs!$B$5,"Queue wait",IF(A15<=Inputs!$B$21+Configurations!$C$15,"Grid ops"," ")))) -> Grid ops | C15: =IF(A15<=Inputs!$B$21,"",A15-Inputs!$B$21-1) -> 7 | D15: =IF(OR(A15<=Inputs!$B$21,A15>Inputs!$B$21+Configurations!$C$15),0,Configurations!$C$4*Configurations!$C$5*8760*(1-Configurations!$C$6)^C15*Configurations!$C$7*(1-Configurations!$C$8)) -> 424475.91 | E15: =IF(OR(A15<=Inputs!$B$21,A15>Inputs!$B$21+Configurations!$C$15),0,IF(A15<=Inputs!$B$21+Inputs!$B$5,D15*(1-Inputs!$B$10)*Configurations!$C$16/1000000,D15*Inputs!$B$18/1000000)) -> 30.562265 | F15: =IF(OR(A15<=Inputs!$B$21,A15>Inputs!$B$21+Configurations!$C$15),0,Configurations!$C$12+Configurations!$C$13+Configurations!$C$14+Inputs!$B$20*E15) -> 9.544434 | G15: =E15-F15 -> 21.017831 | H15: =IF(AND(A15>Inputs!$B$21,A15<=Inputs!$B$21+Inputs!$B$12),Capitalization!E$12,0) -> 15.620421 | I15: =G15-H15 -> 5.3974109 | J15: =IF(A15<=Inputs!$B$21,"",IF(AND(A15<=Inputs!$B$22,Capitalization!E$18>0),Inputs!$B$25,Inputs!$B$26)) -> 0.975 | K15: =IF(A15=0,-Capitalization!E$19,IF(A15<=Inputs!$B$21,0,I15*J15-IF(AND(A15=Inputs!$B$22,Capitalization!E$18>0),Inputs!$B$23,0))) -> 5.2624757 | L15: =IF(H15>0,G15/H15,"") -> 1.3455356 | M15: =IF(A15=0,-Capitalization!E$4,IF(A15<=Inputs!$B$21,0,G15)) -> 21.017831
A16: 11 | B16: =IF(A16=0,"Equity",IF(A16<=Inputs!$B$21,"Construction",IF(A16<=Inputs!$B$21+Inputs!$B$5,"Queue wait",IF(A16<=Inputs!$B$21+Configurations!$C$15,"Grid ops"," ")))) -> Grid ops | C16: =IF(A16<=Inputs!$B$21,"",A16-Inputs!$B$21-1) -> 8 | D16: =IF(OR(A16<=Inputs!$B$21,A16>Inputs!$B$21+Configurations!$C$15),0,Configurations!$C$4*Configurations!$C$5*8760*(1-Configurations!$C$6)^C16*Configurations!$C$7*(1-Configurations!$C$8)) -> 423626.96 | E16: =IF(OR(A16<=Inputs!$B$21,A16>Inputs!$B$21+Configurations!$C$15),0,IF(A16<=Inputs!$B$21+Inputs!$B$5,D16*(1-Inputs!$B$10)*Configurations!$C$16/1000000,D16*Inputs!$B$18/1000000)) -> 30.501141 | F16: =IF(OR(A16<=Inputs!$B$21,A16>Inputs!$B$21+Configurations!$C$15),0,Configurations!$C$12+Configurations!$C$13+Configurations!$C$14+Inputs!$B$20*E16) -> 9.5435171 | G16: =E16-F16 -> 20.957624 | H16: =IF(AND(A16>Inputs!$B$21,A16<=Inputs!$B$21+Inputs!$B$12),Capitalization!E$12,0) -> 15.620421 | I16: =G16-H16 -> 5.3372033 | J16: =IF(A16<=Inputs!$B$21,"",IF(AND(A16<=Inputs!$B$22,Capitalization!E$18>0),Inputs!$B$25,Inputs!$B$26)) -> 0.975 | K16: =IF(A16=0,-Capitalization!E$19,IF(A16<=Inputs!$B$21,0,I16*J16-IF(AND(A16=Inputs!$B$22,Capitalization!E$18>0),Inputs!$B$23,0))) -> 5.2037732 | L16: =IF(H16>0,G16/H16,"") -> 1.3416812 | M16: =IF(A16=0,-Capitalization!E$4,IF(A16<=Inputs!$B$21,0,G16)) -> 20.957624
... A37: 32 | B37: =IF(A37=0,"Equity",IF(A37<=Inputs!$B$21,"Construction",IF(A37<=Inputs!$B$21+Inputs!$B$5,"Queue wait",IF(A37<=Inputs!$B$21+Configurations!$C$15,"Grid ops"," ")))) | C37: =IF(A37<=Inputs!$B$21,"",A37-Inputs!$B$21-1) -> 29 | D37: =IF(OR(A37<=Inputs!$B$21,A37>Inputs!$B$21+Configurations!$C$15),0,Configurations!$C$4*Configurations!$C$5*8760*(1-Configurations!$C$6)^C37*Configurations!$C$7*(1-Configurations!$C$8)) -> 0 | E37: =IF(OR(A37<=Inputs!$B$21,A37>Inputs!$B$21+Configurations!$C$15),0,IF(A37<=Inputs!$B$21+Inputs!$B$5,D37*(1-Inputs!$B$10)*Configurations!$C$16/1000000,D37*Inputs!$B$18/1000000)) -> 0 | F37: =IF(OR(A37<=Inputs!$B$21,A37>Inputs!$B$21+Configurations!$C$15),0,Configurations!$C$12+Configurations!$C$13+Configurations!$C$14+Inputs!$B$20*E37) -> 0 | G37: =E37-F37 -> 0 | H37: =IF(AND(A37>Inputs!$B$21,A37<=Inputs!$B$21+Inputs!$B$12),Capitalization!E$12,0) -> 0 | I37: =G37-H37 -> 0 | J37: =IF(A37<=Inputs!$B$21,"",IF(AND(A37<=Inputs!$B$22,Capitalization!E$18>0),Inputs!$B$25,Inputs!$B$26)) -> 0.975 | K37: =IF(A37=0,-Capitalization!E$19,IF(A37<=Inputs!$B$21,0,I37*J37-IF(AND(A37=Inputs!$B$22,Capitalization!E$18>0),Inputs!$B$23,0))) -> 0 | L37: =IF(H37>0,G37/H37,"") | M37: =IF(A37=0,-Capitalization!E$4,IF(A37<=Inputs!$B$21,0,G37)) -> 0

Sheet GeoBase
A1: GeoBase: annual cash flow waterfall ($mm)
A2: Developer levered IRR: | B2: =IRR(K5:K37) -> 0.1161382 | C2: Unlevered (project) IRR: | D2: =IRR(M5:M37) -> 0.03856386 | E2: NPV of dev cash @ discount rate ($mm): | F2: =K5+NPV(Inputs!$B$24,K6:K37) -> 57.635835
A4: Year | B4: Phase | C4: Op yr | D4: Net energy (MWh) | E4: Revenue | F4: OPEX | G4: EBITDA | H4: Debt service | I4: Distributable cash | J4: Dev share | K4: Dev cash flow | L4: DSCR | M4: Project CF (unlevered)
A5: 0 | B5: =IF(A5=0,"Equity",IF(A5<=Inputs!$B$21,"Construction",IF(A5<=Inputs!$B$21+Inputs!$B$5,"Queue wait",IF(A5<=Inputs!$B$21+Configurations!$D$15,"Grid ops"," ")))) -> Equity | C5: =IF(A5<=Inputs!$B$21,"",A5-Inputs!$B$21-1) | D5: =IF(OR(A5<=Inputs!$B$21,A5>Inputs!$B$21+Configurations!$D$15),0,Configurations!$D$4*Configurations!$D$5*8760*(1-Configurations!$D$6)^C5*Configurations!$D$7*(1-Configurations!$D$8)) -> 0 | E5: =IF(OR(A5<=Inputs!$B$21,A5>Inputs!$B$21+Configurations!$D$15),0,IF(A5<=Inputs!$B$21+Inputs!$B$5,0,D5*Inputs!$B$18/1000000)) -> 0 | F5: =IF(OR(A5<=Inputs!$B$21,A5>Inputs!$B$21+Configurations!$D$15),0,IF(A5<=Inputs!$B$21+Inputs!$B$5,Configurations!$D$13,Configurations!$D$12+Configurations!$D$13+Inputs!$B$20*E5)) -> 0 | G5: =E5-F5 -> 0 | H5: =IF(AND(A5>Inputs!$B$21,A5<=Inputs!$B$21+Inputs!$B$12),Capitalization!F$12,0) -> 0 | I5: =G5-H5 -> 0 | J5: =IF(A5<=Inputs!$B$21,"",IF(AND(A5<=Inputs!$B$22,Capitalization!F$18>0),Inputs!$B$25,Inputs!$B$26)) | K5: =IF(A5=0,-Capitalization!F$19,IF(A5<=Inputs!$B$21,0,I5*J5-IF(AND(A5=Inputs!$B$22,Capitalization!F$18>0),Inputs!$B$23,0))) -> -38.574086 | L5: =IF(H5>0,G5/H5,"") | M5: =IF(A5=0,-Capitalization!F$4,IF(A5<=Inputs!$B$21,0,G5)) -> -568.25
A6: 1 | B6: =IF(A6=0,"Equity",IF(A6<=Inputs!$B$21,"Construction",IF(A6<=Inputs!$B$21+Inputs!$B$5,"Queue wait",IF(A6<=Inputs!$B$21+Configurations!$D$15,"Grid ops"," ")))) -> Construction | C6: =IF(A6<=Inputs!$B$21,"",A6-Inputs!$B$21-1) | D6: =IF(OR(A6<=Inputs!$B$21,A6>Inputs!$B$21+Configurations!$D$15),0,Configurations!$D$4*Configurations!$D$5*8760*(1-Configurations!$D$6)^C6*Configurations!$D$7*(1-Configurations!$D$8)) -> 0 | E6: =IF(OR(A6<=Inputs!$B$21,A6>Inputs!$B$21+Configurations!$D$15),0,IF(A6<=Inputs!$B$21+Inputs!$B$5,0,D6*Inputs!$B$18/1000000)) -> 0 | F6: =IF(OR(A6<=Inputs!$B$21,A6>Inputs!$B$21+Configurations!$D$15),0,IF(A6<=Inputs!$B$21+Inputs!$B$5,Configurations!$D$13,Configurations!$D$12+Configurations!$D$13+Inputs!$B$20*E6)) -> 0 | G6: =E6-F6 -> 0 | H6: =IF(AND(A6>Inputs!$B$21,A6<=Inputs!$B$21+Inputs!$B$12),Capitalization!F$12,0) -> 0 | I6: =G6-H6 -> 0 | J6: =IF(A6<=Inputs!$B$21,"",IF(AND(A6<=Inputs!$B$22,Capitalization!F$18>0),Inputs!$B$25,Inputs!$B$26)) | K6: =IF(A6=0,-Capitalization!F$19,IF(A6<=Inputs!$B$21,0,I6*J6-IF(AND(A6=Inputs!$B$22,Capitalization!F$18>0),Inputs!$B$23,0))) -> 0 | L6: =IF(H6>0,G6/H6,"") | M6: =IF(A6=0,-Capitalization!F$4,IF(A6<=Inputs!$B$21,0,G6)) -> 0
A7: 2 | B7: =IF(A7=0,"Equity",IF(A7<=Inputs!$B$21,"Construction",IF(A7<=Inputs!$B$21+Inputs!$B$5,"Queue wait",IF(A7<=Inputs!$B$21+Configurations!$D$15,"Grid ops"," ")))) -> Construction | C7: =IF(A7<=Inputs!$B$21,"",A7-Inputs!$B$21-1) | D7: =IF(OR(A7<=Inputs!$B$21,A7>Inputs!$B$21+Configurations!$D$15),0,Configurations!$D$4*Configurations!$D$5*8760*(1-Configurations!$D$6)^C7*Configurations!$D$7*(1-Configurations!$D$8)) -> 0 | E7: =IF(OR(A7<=Inputs!$B$21,A7>Inputs!$B$21+Configurations!$D$15),0,IF(A7<=Inputs!$B$21+Inputs!$B$5,0,D7*Inputs!$B$18/1000000)) -> 0 | F7: =IF(OR(A7<=Inputs!$B$21,A7>Inputs!$B$21+Configurations!$D$15),0,IF(A7<=Inputs!$B$21+Inputs!$B$5,Configurations!$D$13,Configurations!$D$12+Configurations!$D$13+Inputs!$B$20*E7)) -> 0 | G7: =E7-F7 -> 0 | H7: =IF(AND(A7>Inputs!$B$21,A7<=Inputs!$B$21+Inputs!$B$12),Capitalization!F$12,0) -> 0 | I7: =G7-H7 -> 0 | J7: =IF(A7<=Inputs!$B$21,"",IF(AND(A7<=Inputs!$B$22,Capitalization!F$18>0),Inputs!$B$25,Inputs!$B$26)) | K7: =IF(A7=0,-Capitalization!F$19,IF(A7<=Inputs!$B$21,0,I7*J7-IF(AND(A7=Inputs!$B$22,Capitalization!F$18>0),Inputs!$B$23,0))) -> 0 | L7: =IF(H7>0,G7/H7,"") | M7: =IF(A7=0,-Capitalization!F$4,IF(A7<=Inputs!$B$21,0,G7)) -> 0
A8: 3 | B8: =IF(A8=0,"Equity",IF(A8<=Inputs!$B$21,"Construction",IF(A8<=Inputs!$B$21+Inputs!$B$5,"Queue wait",IF(A8<=Inputs!$B$21+Configurations!$D$15,"Grid ops"," ")))) -> Queue wait | C8: =IF(A8<=Inputs!$B$21,"",A8-Inputs!$B$21-1) -> 0 | D8: =IF(OR(A8<=Inputs!$B$21,A8>Inputs!$B$21+Configurations!$D$15),0,Configurations!$D$4*Configurations!$D$5*8760*(1-Configurations!$D$6)^C8*Configurations!$D$7*(1-Configurations!$D$8)) -> 730255.5 | E8: =IF(OR(A8<=Inputs!$B$21,A8>Inputs!$B$21+Configurations!$D$15),0,IF(A8<=Inputs!$B$21+Inputs!$B$5,0,D8*Inputs!$B$18/1000000)) -> 0 | F8: =IF(OR(A8<=Inputs!$B$21,A8>Inputs!$B$21+Configurations!$D$15),0,IF(A8<=Inputs!$B$21+Inputs!$B$5,Configurations!$D$13,Configurations!$D$12+Configurations!$D$13+Inputs!$B$20*E8)) -> 2.573 | G8: =E8-F8 -> -2.573 | H8: =IF(AND(A8>Inputs!$B$21,A8<=Inputs!$B$21+Inputs!$B$12),Capitalization!F$12,0) -> 26.152929 | I8: =G8-H8 -> -28.725929 | J8: =IF(A8<=Inputs!$B$21,"",IF(AND(A8<=Inputs!$B$22,Capitalization!F$18>0),Inputs!$B$25,Inputs!$B$26)) -> 0.7 | K8: =IF(A8=0,-Capitalization!F$19,IF(A8<=Inputs!$B$21,0,I8*J8-IF(AND(A8=Inputs!$B$22,Capitalization!F$18>0),Inputs!$B$23,0))) -> -20.10815 | L8: =IF(H8>0,G8/H8,"") -> -0.098382863 | M8: =IF(A8=0,-Capitalization!F$4,IF(A8<=Inputs!$B$21,0,G8)) -> -2.573
A9: 4 | B9: =IF(A9=0,"Equity",IF(A9<=Inputs!$B$21,"Construction",IF(A9<=Inputs!$B$21+Inputs!$B$5,"Queue wait",IF(A9<=Inputs!$B$21+Configurations!$D$15,"Grid ops"," ")))) -> Queue wait | C9: =IF(A9<=Inputs!$B$21,"",A9-Inputs!$B$21-1) -> 1 | D9: =IF(OR(A9<=Inputs!$B$21,A9>Inputs!$B$21+Configurations!$D$15),0,Configurations!$D$4*Configurations!$D$5*8760*(1-Configurations!$D$6)^C9*Configurations!$D$7*(1-Configurations!$D$8)) -> 730255.5 | E9: =IF(OR(A9<=Inputs!$B$21,A9>Inputs!$B$21+Configurations!$D$15),0,IF(A9<=Inputs!$B$21+Inputs!$B$5,0,D9*Inputs!$B$18/1000000)) -> 0 | F9: =IF(OR(A9<=Inputs!$B$21,A9>Inputs!$B$21+Configurations!$D$15),0,IF(A9<=Inputs!$B$21+Inputs!$B$5,Configurations!$D$13,Configurations!$D$12+Configurations!$D$13+Inputs!$B$20*E9)) -> 2.573 | G9: =E9-F9 -> -2.573 | H9: =IF(AND(A9>Inputs!$B$21,A9<=Inputs!$B$21+Inputs!$B$12),Capitalization!F$12,0) -> 26.152929 | I9: =G9-H9 -> -28.725929 | J9: =IF(A9<=Inputs!$B$21,"",IF(AND(A9<=Inputs!$B$22,Capitalization!F$18>0),Inputs!$B$25,Inputs!$B$26)) -> 0.7 | K9: =IF(A9=0,-Capitalization!F$19,IF(A9<=Inputs!$B$21,0,I9*J9-IF(AND(A9=Inputs!$B$22,Capitalization!F$18>0),Inputs!$B$23,0))) -> -20.10815 | L9: =IF(H9>0,G9/H9,"") -> -0.098382863 | M9: =IF(A9=0,-Capitalization!F$4,IF(A9<=Inputs!$B$21,0,G9)) -> -2.573
A10: 5 | B10: =IF(A10=0,"Equity",IF(A10<=Inputs!$B$21,"Construction",IF(A10<=Inputs!$B$21+Inputs!$B$5,"Queue wait",IF(A10<=Inputs!$B$21+Configurations!$D$15,"Grid ops"," ")))) -> Queue wait | C10: =IF(A10<=Inputs!$B$21,"",A10-Inputs!$B$21-1) -> 2 | D10: =IF(OR(A10<=Inputs!$B$21,A10>Inputs!$B$21+Configurations!$D$15),0,Configurations!$D$4*Configurations!$D$5*8760*(1-Configurations!$D$6)^C10*Configurations!$D$7*(1-Configurations!$D$8)) -> 730255.5 | E10: =IF(OR(A10<=Inputs!$B$21,A10>Inputs!$B$21+Configurations!$D$15),0,IF(A10<=Inputs!$B$21+Inputs!$B$5,0,D10*Inputs!$B$18/1000000)) -> 0 | F10: =IF(OR(A10<=Inputs!$B$21,A10>Inputs!$B$21+Configurations!$D$15),0,IF(A10<=Inputs!$B$21+Inputs!$B$5,Configurations!$D$13,Configurations!$D$12+Configurations!$D$13+Inputs!$B$20*E10)) -> 2.573 | G10: =E10-F10 -> -2.573 | H10: =IF(AND(A10>Inputs!$B$21,A10<=Inputs!$B$21+Inputs!$B$12),Capitalization!F$12,0) -> 26.152929 | I10: =G10-H10 -> -28.725929 | J10: =IF(A10<=Inputs!$B$21,"",IF(AND(A10<=Inputs!$B$22,Capitalization!F$18>0),Inputs!$B$25,Inputs!$B$26)) -> 0.7 | K10: =IF(A10=0,-Capitalization!F$19,IF(A10<=Inputs!$B$21,0,I10*J10-IF(AND(A10=Inputs!$B$22,Capitalization!F$18>0),Inputs!$B$23,0))) -> -20.10815 | L10: =IF(H10>0,G10/H10,"") -> -0.098382863 | M10: =IF(A10=0,-Capitalization!F$4,IF(A10<=Inputs!$B$21,0,G10)) -> -2.573
A11: 6 | B11: =IF(A11=0,"Equity",IF(A11<=Inputs!$B$21,"Construction",IF(A11<=Inputs!$B$21+Inputs!$B$5,"Queue wait",IF(A11<=Inputs!$B$21+Configurations!$D$15,"Grid ops"," ")))) -> Queue wait | C11: =IF(A11<=Inputs!$B$21,"",A11-Inputs!$B$21-1) -> 3 | D11: =IF(OR(A11<=Inputs!$B$21,A11>Inputs!$B$21+Configurations!$D$15),0,Configurations!$D$4*Configurations!$D$5*8760*(1-Configurations!$D$6)^C11*Configurations!$D$7*(1-Configurations!$D$8)) -> 730255.5 | E11: =IF(OR(A11<=Inputs!$B$21,A11>Inputs!$B$21+Configurations!$D$15),0,IF(A11<=Inputs!$B$21+Inputs!$B$5,0,D11*Inputs!$B$18/1000000)) -> 0 | F11: =IF(OR(A11<=Inputs!$B$21,A11>Inputs!$B$21+Configurations!$D$15),0,IF(A11<=Inputs!$B$21+Inputs!$B$5,Configurations!$D$13,Configurations!$D$12+Configurations!$D$13+Inputs!$B$20*E11)) -> 2.573 | G11: =E11-F11 -> -2.573 | H11: =IF(AND(A11>Inputs!$B$21,A11<=Inputs!$B$21+Inputs!$B$12),Capitalization!F$12,0) -> 26.152929 | I11: =G11-H11 -> -28.725929 | J11: =IF(A11<=Inputs!$B$21,"",IF(AND(A11<=Inputs!$B$22,Capitalization!F$18>0),Inputs!$B$25,Inputs!$B$26)) -> 0.7 | K11: =IF(A11=0,-Capitalization!F$19,IF(A11<=Inputs!$B$21,0,I11*J11-IF(AND(A11=Inputs!$B$22,Capitalization!F$18>0),Inputs!$B$23,0))) -> -21.10815 | L11: =IF(H11>0,G11/H11,"") -> -0.098382863 | M11: =IF(A11=0,-Capitalization!F$4,IF(A11<=Inputs!$B$21,0,G11)) -> -2.573
A12: 7 | B12: =IF(A12=0,"Equity",IF(A12<=Inputs!$B$21,"Construction",IF(A12<=Inputs!$B$21+Inputs!$B$5,"Queue wait",IF(A12<=Inputs!$B$21+Configurations!$D$15,"Grid ops"," ")))) -> Grid ops | C12: =IF(A12<=Inputs!$B$21,"",A12-Inputs!$B$21-1) -> 4 | D12: =IF(OR(A12<=Inputs!$B$21,A12>Inputs!$B$21+Configurations!$D$15),0,Configurations!$D$4*Configurations!$D$5*8760*(1-Configurations!$D$6)^C12*Configurations!$D$7*(1-Configurations!$D$8)) -> 730255.5 | E12: =IF(OR(A12<=Inputs!$B$21,A12>Inputs!$B$21+Configurations!$D$15),0,IF(A12<=Inputs!$B$21+Inputs!$B$5,0,D12*Inputs!$B$18/1000000)) -> 52.578396 | F12: =IF(OR(A12<=Inputs!$B$21,A12>Inputs!$B$21+Configurations!$D$15),0,IF(A12<=Inputs!$B$21+Inputs!$B$5,Configurations!$D$13,Configurations!$D$12+Configurations!$D$13+Inputs!$B$20*E12)) -> 7.9866759 | G12: =E12-F12 -> 44.59172 | H12: =IF(AND(A12>Inputs!$B$21,A12<=Inputs!$B$21+Inputs!$B$12),Capitalization!F$12,0) -> 26.152929 | I12: =G12-H12 -> 18.438791 | J12: =IF(A12<=Inputs!$B$21,"",IF(AND(A12<=Inputs!$B$22,Capitalization!F$18>0),Inputs!$B$25,Inputs!$B$26)) -> 0.975 | K12: =IF(A12=0,-Capitalization!F$19,IF(A12<=Inputs!$B$21,0,I12*J12-IF(AND(A12=Inputs!$B$22,Capitalization!F$18>0),Inputs!$B$23,0))) -> 17.977822 | L12: =IF(H12>0,G12/H12,"") -> 1.7050373 | M12: =IF(A12=0,-Capitalization!F$4,IF(A12<=Inputs!$B$21,0,G12)) -> 44.59172
A13: 8 | B13: =IF(A13=0,"Equity",IF(A13<=Inputs!$B$21,"Construction",IF(A13<=Inputs!$B$21+Inputs!$B$5,"Queue wait",IF(A13<=Inputs!$B$21+Configurations!$D$15,"Grid ops"," ")))) -> Grid ops | C13: =IF(A13<=Inputs!$B$21,"",A13-Inputs!$B$21-1) -> 5 | D13: =IF(OR(A13<=Inputs!$B$21,A13>Inputs!$B$21+Configurations!$D$15),0,Configurations!$D$4*Configurations!$D$5*8760*(1-Configurations!$D$6)^C13*Configurations!$D$7*(1-Configurations!$D$8)) -> 730255.5 | E13: =IF(OR(A13<=Inputs!$B$21,A13>Inputs!$B$21+Configurations!$D$15),0,IF(A13<=Inputs!$B$21+Inputs!$B$5,0,D13*Inputs!$B$18/1000000)) -> 52.578396 | F13: =IF(OR(A13<=Inputs!$B$21,A13>Inputs!$B$21+Configurations!$D$15),0,IF(A13<=Inputs!$B$21+Inputs!$B$5,Configurations!$D$13,Configurations!$D$12+Configurations!$D$13+Inputs!$B$20*E13)) -> 7.9866759 | G13: =E13-F13 -> 44.59172 | H13: =IF(AND(A13>Inputs!$B$21,A13<=Inputs!$B$21+Inputs!$B$12),Capitalization!F$12,0) -> 26.152929 | I13: =G13-H13 -> 18.438791 | J13: =IF(A13<=Inputs!$B$21,"",IF(AND(A13<=Inputs!$B$22,Capitalization!F$18>0),Inputs!$B$25,Inputs!$B$26)) -> 0.975 | K13: =IF(A13=0,-Capitalization!F$19,IF(A13<=Inputs!$B$21,0,I13*J13-IF(AND(A13=Inputs!$B$22,Capitalization!F$18>0),Inputs!$B$23,0))) -> 17.977822 | L13: =IF(H13>0,G13/H13,"") -> 1.7050373 | M13: =IF(A13=0,-Capitalization!F$4,IF(A13<=Inputs!$B$21,0,G13)) -> 44.59172
A14: 9 | B14: =IF(A14=0,"Equity",IF(A14<=Inputs!$B$21,"Construction",IF(A14<=Inputs!$B$21+Inputs!$B$5,"Queue wait",IF(A14<=Inputs!$B$21+Configurations!$D$15,"Grid ops"," ")))) -> Grid ops | C14: =IF(A14<=Inputs!$B$21,"",A14-Inputs!$B$21-1) -> 6 | D14: =IF(OR(A14<=Inputs!$B$21,A14>Inputs!$B$21+Configurations!$D$15),0,Configurations!$D$4*Configurations!$D$5*8760*(1-Configurations!$D$6)^C14*Configurations!$D$7*(1-Configurations!$D$8)) -> 730255.5 | E14: =IF(OR(A14<=Inputs!$B$21,A14>Inputs!$B$21+Configurations!$D$15),0,IF(A14<=Inputs!$B$21+Inputs!$B$5,0,D14*Inputs!$B$18/1000000)) -> 52.578396 | F14: =IF(OR(A14<=Inputs!$B$21,A14>Inputs!$B$21+Configurations!$D$15),0,IF(A14<=Inputs!$B$21+Inputs!$B$5,Configurations!$D$13,Configurations!$D$12+Configurations!$D$13+Inputs!$B$20*E14)) -> 7.9866759 | G14: =E14-F14 -> 44.59172 | H14: =IF(AND(A14>Inputs!$B$21,A14<=Inputs!$B$21+Inputs!$B$12),Capitalization!F$12,0) -> 26.152929 | I14: =G14-H14 -> 18.438791 | J14: =IF(A14<=Inputs!$B$21,"",IF(AND(A14<=Inputs!$B$22,Capitalization!F$18>0),Inputs!$B$25,Inputs!$B$26)) -> 0.975 | K14: =IF(A14=0,-Capitalization!F$19,IF(A14<=Inputs!$B$21,0,I14*J14-IF(AND(A14=Inputs!$B$22,Capitalization!F$18>0),Inputs!$B$23,0))) -> 17.977822 | L14: =IF(H14>0,G14/H14,"") -> 1.7050373 | M14: =IF(A14=0,-Capitalization!F$4,IF(A14<=Inputs!$B$21,0,G14)) -> 44.59172
A15: 10 | B15: =IF(A15=0,"Equity",IF(A15<=Inputs!$B$21,"Construction",IF(A15<=Inputs!$B$21+Inputs!$B$5,"Queue wait",IF(A15<=Inputs!$B$21+Configurations!$D$15,"Grid ops"," ")))) -> Grid ops | C15: =IF(A15<=Inputs!$B$21,"",A15-Inputs!$B$21-1) -> 7 | D15: =IF(OR(A15<=Inputs!$B$21,A15>Inputs!$B$21+Configurations!$D$15),0,Configurations!$D$4*Configurations!$D$5*8760*(1-Configurations!$D$6)^C15*Configurations!$D$7*(1-Configurations!$D$8)) -> 730255.5 | E15: =IF(OR(A15<=Inputs!$B$21,A15>Inputs!$B$21+Configurations!$D$15),0,IF(A15<=Inputs!$B$21+Inputs!$B$5,0,D15*Inputs!$B$18/1000000)) -> 52.578396 | F15: =IF(OR(A15<=Inputs!$B$21,A15>Inputs!$B$21+Configurations!$D$15),0,IF(A15<=Inputs!$B$21+Inputs!$B$5,Configurations!$D$13,Configurations!$D$12+Configurations!$D$13+Inputs!$B$20*E15)) -> 7.9866759 | G15: =E15-F15 -> 44.59172 | H15: =IF(AND(A15>Inputs!$B$21,A15<=Inputs!$B$21+Inputs!$B$12),Capitalization!F$12,0) -> 26.152929 | I15: =G15-H15 -> 18.438791 | J15: =IF(A15<=Inputs!$B$21,"",IF(AND(A15<=Inputs!$B$22,Capitalization!F$18>0),Inputs!$B$25,Inputs!$B$26)) -> 0.975 | K15: =IF(A15=0,-Capitalization!F$19,IF(A15<=Inputs!$B$21,0,I15*J15-IF(AND(A15=Inputs!$B$22,Capitalization!F$18>0),Inputs!$B$23,0))) -> 17.977822 | L15: =IF(H15>0,G15/H15,"") -> 1.7050373 | M15: =IF(A15=0,-Capitalization!F$4,IF(A15<=Inputs!$B$21,0,G15)) -> 44.59172
A16: 11 | B16: =IF(A16=0,"Equity",IF(A16<=Inputs!$B$21,"Construction",IF(A16<=Inputs!$B$21+Inputs!$B$5,"Queue wait",IF(A16<=Inputs!$B$21+Configurations!$D$15,"Grid ops"," ")))) -> Grid ops | C16: =IF(A16<=Inputs!$B$21,"",A16-Inputs!$B$21-1) -> 8 | D16: =IF(OR(A16<=Inputs!$B$21,A16>Inputs!$B$21+Configurations!$D$15),0,Configurations!$D$4*Configurations!$D$5*8760*(1-Configurations!$D$6)^C16*Configurations!$D$7*(1-Configurations!$D$8)) -> 730255.5 | E16: =IF(OR(A16<=Inputs!$B$21,A16>Inputs!$B$21+Configurations!$D$15),0,IF(A16<=Inputs!$B$21+Inputs!$B$5,0,D16*Inputs!$B$18/1000000)) -> 52.578396 | F16: =IF(OR(A16<=Inputs!$B$21,A16>Inputs!$B$21+Configurations!$D$15),0,IF(A16<=Inputs!$B$21+Inputs!$B$5,Configurations!$D$13,Configurations!$D$12+Configurations!$D$13+Inputs!$B$20*E16)) -> 7.9866759 | G16: =E16-F16 -> 44.59172 | H16: =IF(AND(A16>Inputs!$B$21,A16<=Inputs!$B$21+Inputs!$B$12),Capitalization!F$12,0) -> 26.152929 | I16: =G16-H16 -> 18.438791 | J16: =IF(A16<=Inputs!$B$21,"",IF(AND(A16<=Inputs!$B$22,Capitalization!F$18>0),Inputs!$B$25,Inputs!$B$26)) -> 0.975 | K16: =IF(A16=0,-Capitalization!F$19,IF(A16<=Inputs!$B$21,0,I16*J16-IF(AND(A16=Inputs!$B$22,Capitalization!F$18>0),Inputs!$B$23,0))) -> 17.977822 | L16: =IF(H16>0,G16/H16,"") -> 1.7050373 | M16: =IF(A16=0,-Capitalization!F$4,IF(A16<=Inputs!$B$21,0,G16)) -> 44.59172
... A37: 32 | B37: =IF(A37=0,"Equity",IF(A37<=Inputs!$B$21,"Construction",IF(A37<=Inputs!$B$21+Inputs!$B$5,"Queue wait",IF(A37<=Inputs!$B$21+Configurations!$D$15,"Grid ops"," ")))) -> Grid ops | C37: =IF(A37<=Inputs!$B$21,"",A37-Inputs!$B$21-1) -> 29 | D37: =IF(OR(A37<=Inputs!$B$21,A37>Inputs!$B$21+Configurations!$D$15),0,Configurations!$D$4*Configurations!$D$5*8760*(1-Configurations!$D$6)^C37*Configurations!$D$7*(1-Configurations!$D$8)) -> 730255.5 | E37: =IF(OR(A37<=Inputs!$B$21,A37>Inputs!$B$21+Configurations!$D$15),0,IF(A37<=Inputs!$B$21+Inputs!$B$5,0,D37*Inputs!$B$18/1000000)) -> 52.578396 | F37: =IF(OR(A37<=Inputs!$B$21,A37>Inputs!$B$21+Configurations!$D$15),0,IF(A37<=Inputs!$B$21+Inputs!$B$5,Configurations!$D$13,Configurations!$D$12+Configurations!$D$13+Inputs!$B$20*E37)) -> 7.9866759 | G37: =E37-F37 -> 44.59172 | H37: =IF(AND(A37>Inputs!$B$21,A37<=Inputs!$B$21+Inputs!$B$12),Capitalization!F$12,0) -> 0 | I37: =G37-H37 -> 44.59172 | J37: =IF(A37<=Inputs!$B$21,"",IF(AND(A37<=Inputs!$B$22,Capitalization!F$18>0),Inputs!$B$25,Inputs!$B$26)) -> 0.975 | K37: =IF(A37=0,-Capitalization!F$19,IF(A37<=Inputs!$B$21,0,I37*J37-IF(AND(A37=Inputs!$B$22,Capitalization!F$18>0),Inputs!$B$23,0))) -> 43.476927 | L37: =IF(H37>0,G37/H37,"") | M37: =IF(A37=0,-Capitalization!F$4,IF(A37<=Inputs!$B$21,0,G37)) -> 44.59172

Sheet GeoColoc
A1: GeoColoc: annual cash flow waterfall ($mm)
A2: Developer levered IRR: | B2: =IRR(K5:K37) -> 0.33081969 | C2: Unlevered (project) IRR: | D2: =IRR(M5:M37) -> 0.065368596 | E2: NPV of dev cash @ discount rate ($mm): | F2: =K5+NPV(Inputs!$B$24,K6:K37) -> 186.66422
A4: Year | B4: Phase | C4: Op yr | D4: Net energy (MWh) | E4: Revenue | F4: OPEX | G4: EBITDA | H4: Debt service | I4: Distributable cash | J4: Dev share | K4: Dev cash flow | L4: DSCR | M4: Project CF (unlevered)
A5: 0 | B5: =IF(A5=0,"Equity",IF(A5<=Inputs!$B$21,"Construction",IF(A5<=Inputs!$B$21+Inputs!$B$5,"Queue wait",IF(A5<=Inputs!$B$21+Configurations!$D$15,"Grid ops"," ")))) -> Equity | C5: =IF(A5<=Inputs!$B$21,"",A5-Inputs!$B$21-1) | D5: =IF(OR(A5<=Inputs!$B$21,A5>Inputs!$B$21+Configurations!$D$15),0,Configurations!$D$4*Configurations!$D$5*8760*(1-Configurations!$D$6)^C5*Configurations!$D$7*(1-Configurations!$D$8)) -> 0 | E5: =IF(OR(A5<=Inputs!$B$21,A5>Inputs!$B$21+Configurations!$D$15),0,IF(A5<=Inputs!$B$21+Inputs!$B$5,D5*(1-Inputs!$B$10)*Configurations!$D$16/1000000,D5*Inputs!$B$18/1000000)) -> 0 | F5: =IF(OR(A5<=Inputs!$B$21,A5>Inputs!$B$21+Configurations!$D$15),0,Configurations!$D$12+Configurations!$D$13+Configurations!$D$14+Inputs!$B$20*E5) -> 0 | G5: =E5-F5 -> 0 | H5: =IF(AND(A5>Inputs!$B$21,A5<=Inputs!$B$21+Inputs!$B$12),Capitalization!G$12,0) -> 0 | I5: =G5-H5 -> 0 | J5: =IF(A5<=Inputs!$B$21,"",IF(AND(A5<=Inputs!$B$22,Capitalization!G$18>0),Inputs!$B$25,Inputs!$B$26)) | K5: =IF(A5=0,-Capitalization!G$19,IF(A5<=Inputs!$B$21,0,I5*J5-IF(AND(A5=Inputs!$B$22,Capitalization!G$18>0),Inputs!$B$23,0))) -> -43.974086 | L5: =IF(H5>0,G5/H5,"") | M5: =IF(A5=0,-Capitalization!G$4,IF(A5<=Inputs!$B$21,0,G5)) -> -580.25
A6: 1 | B6: =IF(A6=0,"Equity",IF(A6<=Inputs!$B$21,"Construction",IF(A6<=Inputs!$B$21+Inputs!$B$5,"Queue wait",IF(A6<=Inputs!$B$21+Configurations!$D$15,"Grid ops"," ")))) -> Construction | C6: =IF(A6<=Inputs!$B$21,"",A6-Inputs!$B$21-1) | D6: =IF(OR(A6<=Inputs!$B$21,A6>Inputs!$B$21+Configurations!$D$15),0,Configurations!$D$4*Configurations!$D$5*8760*(1-Configurations!$D$6)^C6*Configurations!$D$7*(1-Configurations!$D$8)) -> 0 | E6: =IF(OR(A6<=Inputs!$B$21,A6>Inputs!$B$21+Configurations!$D$15),0,IF(A6<=Inputs!$B$21+Inputs!$B$5,D6*(1-Inputs!$B$10)*Configurations!$D$16/1000000,D6*Inputs!$B$18/1000000)) -> 0 | F6: =IF(OR(A6<=Inputs!$B$21,A6>Inputs!$B$21+Configurations!$D$15),0,Configurations!$D$12+Configurations!$D$13+Configurations!$D$14+Inputs!$B$20*E6) -> 0 | G6: =E6-F6 -> 0 | H6: =IF(AND(A6>Inputs!$B$21,A6<=Inputs!$B$21+Inputs!$B$12),Capitalization!G$12,0) -> 0 | I6: =G6-H6 -> 0 | J6: =IF(A6<=Inputs!$B$21,"",IF(AND(A6<=Inputs!$B$22,Capitalization!G$18>0),Inputs!$B$25,Inputs!$B$26)) | K6: =IF(A6=0,-Capitalization!G$19,IF(A6<=Inputs!$B$21,0,I6*J6-IF(AND(A6=Inputs!$B$22,Capitalization!G$18>0),Inputs!$B$23,0))) -> 0 | L6: =IF(H6>0,G6/H6,"") | M6: =IF(A6=0,-Capitalization!G$4,IF(A6<=Inputs!$B$21,0,G6)) -> 0
A7: 2 | B7: =IF(A7=0,"Equity",IF(A7<=Inputs!$B$21,"Construction",IF(A7<=Inputs!$B$21+Inputs!$B$5,"Queue wait",IF(A7<=Inputs!$B$21+Configurations!$D$15,"Grid ops"," ")))) -> Construction | C7: =IF(A7<=Inputs!$B$21,"",A7-Inputs!$B$21-1) | D7: =IF(OR(A7<=Inputs!$B$21,A7>Inputs!$B$21+Configurations!$D$15),0,Configurations!$D$4*Configurations!$D$5*8760*(1-Configurations!$D$6)^C7*Configurations!$D$7*(1-Configurations!$D$8)) -> 0 | E7: =IF(OR(A7<=Inputs!$B$21,A7>Inputs!$B$21+Configurations!$D$15),0,IF(A7<=Inputs!$B$21+Inputs!$B$5,D7*(1-Inputs!$B$10)*Configurations!$D$16/1000000,D7*Inputs!$B$18/1000000)) -> 0 | F7: =IF(OR(A7<=Inputs!$B$21,A7>Inputs!$B$21+Configurations!$D$15),0,Configurations!$D$12+Configurations!$D$13+Configurations!$D$14+Inputs!$B$20*E7) -> 0 | G7: =E7-F7 -> 0 | H7: =IF(AND(A7>Inputs!$B$21,A7<=Inputs!$B$21+Inputs!$B$12),Capitalization!G$12,0) -> 0 | I7: =G7-H7 -> 0 | J7: =IF(A7<=Inputs!$B$21,"",IF(AND(A7<=Inputs!$B$22,Capitalization!G$18>0),Inputs!$B$25,Inputs!$B$26)) | K7: =IF(A7=0,-Capitalization!G$19,IF(A7<=Inputs!$B$21,0,I7*J7-IF(AND(A7=Inputs!$B$22,Capitalization!G$18>0),Inputs!$B$23,0))) -> 0 | L7: =IF(H7>0,G7/H7,"") | M7: =IF(A7=0,-Capitalization!G$4,IF(A7<=Inputs!$B$21,0,G7)) -> 0
A8: 3 | B8: =IF(A8=0,"Equity",IF(A8<=Inputs!$B$21,"Construction",IF(A8<=Inputs!$B$21+Inputs!$B$5,"Queue wait",IF(A8<=Inputs!$B$21+Configurations!$D$15,"Grid ops"," ")))) -> Queue wait | C8: =IF(A8<=Inputs!$B$21,"",A8-Inputs!$B$21-1) -> 0 | D8: =IF(OR(A8<=Inputs!$B$21,A8>Inputs!$B$21+Configurations!$D$15),0,Configurations!$D$4*Configurations!$D$5*8760*(1-Configurations!$D$6)^C8*Configurations!$D$7*(1-Configurations!$D$8)) -> 730255.5 | E8: =IF(OR(A8<=Inputs!$B$21,A8>Inputs!$B$21+Configurations!$D$15),0,IF(A8<=Inputs!$B$21+Inputs!$B$5,D8*(1-Inputs!$B$10)*Configurations!$D$16/1000000,D8*Inputs!$B$18/1000000)) -> 78.754788 | F8: =IF(OR(A8<=Inputs!$B$21,A8>Inputs!$B$21+Configurations!$D$15),0,Configurations!$D$12+Configurations!$D$13+Configurations!$D$14+Inputs!$B$20*E8) -> 9.1293218 | G8: =E8-F8 -> 69.625466 | H8: =IF(AND(A8>Inputs!$B$21,A8<=Inputs!$B$21+Inputs!$B$12),Capitalization!G$12,0) -> 26.705212 | I8: =G8-H8 -> 42.920254 | J8: =IF(A8<=Inputs!$B$21,"",IF(AND(A8<=Inputs!$B$22,Capitalization!G$18>0),Inputs!$B$25,Inputs!$B$26)) -> 0.7 | K8: =IF(A8=0,-Capitalization!G$19,IF(A8<=Inputs!$B$21,0,I8*J8-IF(AND(A8=Inputs!$B$22,Capitalization!G$18>0),Inputs!$B$23,0))) -> 30.044178 | L8: =IF(H8>0,G8/H8,"") -> 2.6071864 | M8: =IF(A8=0,-Capitalization!G$4,IF(A8<=Inputs!$B$21,0,G8)) -> 69.625466
A9: 4 | B9: =IF(A9=0,"Equity",IF(A9<=Inputs!$B$21,"Construction",IF(A9<=Inputs!$B$21+Inputs!$B$5,"Queue wait",IF(A9<=Inputs!$B$21+Configurations!$D$15,"Grid ops"," ")))) -> Queue wait | C9: =IF(A9<=Inputs!$B$21,"",A9-Inputs!$B$21-1) -> 1 | D9: =IF(OR(A9<=Inputs!$B$21,A9>Inputs!$B$21+Configurations!$D$15),0,Configurations!$D$4*Configurations!$D$5*8760*(1-Configurations!$D$6)^C9*Configurations!$D$7*(1-Configurations!$D$8)) -> 730255.5 | E9: =IF(OR(A9<=Inputs!$B$21,A9>Inputs!$B$21+Configurations!$D$15),0,IF(A9<=Inputs!$B$21+Inputs!$B$5,D9*(1-Inputs!$B$10)*Configurations!$D$16/1000000,D9*Inputs!$B$18/1000000)) -> 78.754788 | F9: =IF(OR(A9<=Inputs!$B$21,A9>Inputs!$B$21+Configurations!$D$15),0,Configurations!$D$12+Configurations!$D$13+Configurations!$D$14+Inputs!$B$20*E9) -> 9.1293218 | G9: =E9-F9 -> 69.625466 | H9: =IF(AND(A9>Inputs!$B$21,A9<=Inputs!$B$21+Inputs!$B$12),Capitalization!G$12,0) -> 26.705212 | I9: =G9-H9 -> 42.920254 | J9: =IF(A9<=Inputs!$B$21,"",IF(AND(A9<=Inputs!$B$22,Capitalization!G$18>0),Inputs!$B$25,Inputs!$B$26)) -> 0.7 | K9: =IF(A9=0,-Capitalization!G$19,IF(A9<=Inputs!$B$21,0,I9*J9-IF(AND(A9=Inputs!$B$22,Capitalization!G$18>0),Inputs!$B$23,0))) -> 30.044178 | L9: =IF(H9>0,G9/H9,"") -> 2.6071864 | M9: =IF(A9=0,-Capitalization!G$4,IF(A9<=Inputs!$B$21,0,G9)) -> 69.625466
A10: 5 | B10: =IF(A10=0,"Equity",IF(A10<=Inputs!$B$21,"Construction",IF(A10<=Inputs!$B$21+Inputs!$B$5,"Queue wait",IF(A10<=Inputs!$B$21+Configurations!$D$15,"Grid ops"," ")))) -> Queue wait | C10: =IF(A10<=Inputs!$B$21,"",A10-Inputs!$B$21-1) -> 2 | D10: =IF(OR(A10<=Inputs!$B$21,A10>Inputs!$B$21+Configurations!$D$15),0,Configurations!$D$4*Configurations!$D$5*8760*(1-Configurations!$D$6)^C10*Configurations!$D$7*(1-Configurations!$D$8)) -> 730255.5 | E10: =IF(OR(A10<=Inputs!$B$21,A10>Inputs!$B$21+Configurations!$D$15),0,IF(A10<=Inputs!$B$21+Inputs!$B$5,D10*(1-Inputs!$B$10)*Configurations!$D$16/1000000,D10*Inputs!$B$18/1000000)) -> 78.754788 | F10: =IF(OR(A10<=Inputs!$B$21,A10>Inputs!$B$21+Configurations!$D$15),0,Configurations!$D$12+Configurations!$D$13+Configurations!$D$14+Inputs!$B$20*E10) -> 9.1293218 | G10: =E10-F10 -> 69.625466 | H10: =IF(AND(A10>Inputs!$B$21,A10<=Inputs!$B$21+Inputs!$B$12),Capitalization!G$12,0) -> 26.705212 | I10: =G10-H10 -> 42.920254 | J10: =IF(A10<=Inputs!$B$21,"",IF(AND(A10<=Inputs!$B$22,Capitalization!G$18>0),Inputs!$B$25,Inputs!$B$26)) -> 0.7 | K10: =IF(A10=0,-Capitalization!G$19,IF(A10<=Inputs!$B$21,0,I10*J10-IF(AND(A10=Inputs!$B$22,Capitalization!G$18>0),Inputs!$B$23,0))) -> 30.044178 | L10: =IF(H10>0,G10/H10,"") -> 2.6071864 | M10: =IF(A10=0,-Capitalization!G$4,IF(A10<=Inputs!$B$21,0,G10)) -> 69.625466
A11: 6 | B11: =IF(A11=0,"Equity",IF(A11<=Inputs!$B$21,"Construction",IF(A11<=Inputs!$B$21+Inputs!$B$5,"Queue wait",IF(A11<=Inputs!$B$21+Configurations!$D$15,"Grid ops"," ")))) -> Queue wait | C11: =IF(A11<=Inputs!$B$21,"",A11-Inputs!$B$21-1) -> 3 | D11: =IF(OR(A11<=Inputs!$B$21,A11>Inputs!$B$21+Configurations!$D$15),0,Configurations!$D$4*Configurations!$D$5*8760*(1-Configurations!$D$6)^C11*Configurations!$D$7*(1-Configurations!$D$8)) -> 730255.5 | E11: =IF(OR(A11<=Inputs!$B$21,A11>Inputs!$B$21+Configurations!$D$15),0,IF(A11<=Inputs!$B$21+Inputs!$B$5,D11*(1-Inputs!$B$10)*Configurations!$D$16/1000000,D11*Inputs!$B$18/1000000)) -> 78.754788 | F11: =IF(OR(A11<=Inputs!$B$21,A11>Inputs!$B$21+Configurations!$D$15),0,Configurations!$D$12+Configurations!$D$13+Configurations!$D$14+Inputs!$B$20*E11) -> 9.1293218 | G11: =E11-F11 -> 69.625466 | H11: =IF(AND(A11>Inputs!$B$21,A11<=Inputs!$B$21+Inputs!$B$12),Capitalization!G$12,0) -> 26.705212 | I11: =G11-H11 -> 42.920254 | J11: =IF(A11<=Inputs!$B$21,"",IF(AND(A11<=Inputs!$B$22,Capitalization!G$18>0),Inputs!$B$25,Inputs!$B$26)) -> 0.7 | K11: =IF(A11=0,-Capitalization!G$19,IF(A11<=Inputs!$B$21,0,I11*J11-IF(AND(A11=Inputs!$B$22,Capitalization!G$18>0),Inputs!$B$23,0))) -> 29.044178 | L11: =IF(H11>0,G11/H11,"") -> 2.6071864 | M11: =IF(A11=0,-Capitalization!G$4,IF(A11<=Inputs!$B$21,0,G11)) -> 69.625466
A12: 7 | B12: =IF(A12=0,"Equity",IF(A12<=Inputs!$B$21,"Construction",IF(A12<=Inputs!$B$21+Inputs!$B$5,"Queue wait",IF(A12<=Inputs!$B$21+Configurations!$D$15,"Grid ops"," ")))) -> Grid ops | C12: =IF(A12<=Inputs!$B$21,"",A12-Inputs!$B$21-1) -> 4 | D12: =IF(OR(A12<=Inputs!$B$21,A12>Inputs!$B$21+Configurations!$D$15),0,Configurations!$D$4*Configurations!$D$5*8760*(1-Configurations!$D$6)^C12*Configurations!$D$7*(1-Configurations!$D$8)) -> 730255.5 | E12: =IF(OR(A12<=Inputs!$B$21,A12>Inputs!$B$21+Configurations!$D$15),0,IF(A12<=Inputs!$B$21+Inputs!$B$5,D12*(1-Inputs!$B$10)*Configurations!$D$16/1000000,D12*Inputs!$B$18/1000000)) -> 52.578396 | F12: =IF(OR(A12<=Inputs!$B$21,A12>Inputs!$B$21+Configurations!$D$15),0,Configurations!$D$12+Configurations!$D$13+Configurations!$D$14+Inputs!$B$20*E12) -> 8.7366759 | G12: =E12-F12 -> 43.84172 | H12: =IF(AND(A12>Inputs!$B$21,A12<=Inputs!$B$21+Inputs!$B$12),Capitalization!G$12,0) -> 26.705212 | I12: =G12-H12 -> 17.136508 | J12: =IF(A12<=Inputs!$B$21,"",IF(AND(A12<=Inputs!$B$22,Capitalization!G$18>0),Inputs!$B$25,Inputs!$B$26)) -> 0.975 | K12: =IF(A12=0,-Capitalization!G$19,IF(A12<=Inputs!$B$21,0,I12*J12-IF(AND(A12=Inputs!$B$22,Capitalization!G$18>0),Inputs!$B$23,0))) -> 16.708095 | L12: =IF(H12>0,G12/H12,"") -> 1.6416915 | M12: =IF(A12=0,-Capitalization!G$4,IF(A12<=Inputs!$B$21,0,G12)) -> 43.84172
A13: 8 | B13: =IF(A13=0,"Equity",IF(A13<=Inputs!$B$21,"Construction",IF(A13<=Inputs!$B$21+Inputs!$B$5,"Queue wait",IF(A13<=Inputs!$B$21+Configurations!$D$15,"Grid ops"," ")))) -> Grid ops | C13: =IF(A13<=Inputs!$B$21,"",A13-Inputs!$B$21-1) -> 5 | D13: =IF(OR(A13<=Inputs!$B$21,A13>Inputs!$B$21+Configurations!$D$15),0,Configurations!$D$4*Configurations!$D$5*8760*(1-Configurations!$D$6)^C13*Configurations!$D$7*(1-Configurations!$D$8)) -> 730255.5 | E13: =IF(OR(A13<=Inputs!$B$21,A13>Inputs!$B$21+Configurations!$D$15),0,IF(A13<=Inputs!$B$21+Inputs!$B$5,D13*(1-Inputs!$B$10)*Configurations!$D$16/1000000,D13*Inputs!$B$18/1000000)) -> 52.578396 | F13: =IF(OR(A13<=Inputs!$B$21,A13>Inputs!$B$21+Configurations!$D$15),0,Configurations!$D$12+Configurations!$D$13+Configurations!$D$14+Inputs!$B$20*E13) -> 8.7366759 | G13: =E13-F13 -> 43.84172 | H13: =IF(AND(A13>Inputs!$B$21,A13<=Inputs!$B$21+Inputs!$B$12),Capitalization!G$12,0) -> 26.705212 | I13: =G13-H13 -> 17.136508 | J13: =IF(A13<=Inputs!$B$21,"",IF(AND(A13<=Inputs!$B$22,Capitalization!G$18>0),Inputs!$B$25,Inputs!$B$26)) -> 0.975 | K13: =IF(A13=0,-Capitalization!G$19,IF(A13<=Inputs!$B$21,0,I13*J13-IF(AND(A13=Inputs!$B$22,Capitalization!G$18>0),Inputs!$B$23,0))) -> 16.708095 | L13: =IF(H13>0,G13/H13,"") -> 1.6416915 | M13: =IF(A13=0,-Capitalization!G$4,IF(A13<=Inputs!$B$21,0,G13)) -> 43.84172
A14: 9 | B14: =IF(A14=0,"Equity",IF(A14<=Inputs!$B$21,"Construction",IF(A14<=Inputs!$B$21+Inputs!$B$5,"Queue wait",IF(A14<=Inputs!$B$21+Configurations!$D$15,"Grid ops"," ")))) -> Grid ops | C14: =IF(A14<=Inputs!$B$21,"",A14-Inputs!$B$21-1) -> 6 | D14: =IF(OR(A14<=Inputs!$B$21,A14>Inputs!$B$21+Configurations!$D$15),0,Configurations!$D$4*Configurations!$D$5*8760*(1-Configurations!$D$6)^C14*Configurations!$D$7*(1-Configurations!$D$8)) -> 730255.5 | E14: =IF(OR(A14<=Inputs!$B$21,A14>Inputs!$B$21+Configurations!$D$15),0,IF(A14<=Inputs!$B$21+Inputs!$B$5,D14*(1-Inputs!$B$10)*Configurations!$D$16/1000000,D14*Inputs!$B$18/1000000)) -> 52.578396 | F14: =IF(OR(A14<=Inputs!$B$21,A14>Inputs!$B$21+Configurations!$D$15),0,Configurations!$D$12+Configurations!$D$13+Configurations!$D$14+Inputs!$B$20*E14) -> 8.7366759 | G14: =E14-F14 -> 43.84172 | H14: =IF(AND(A14>Inputs!$B$21,A14<=Inputs!$B$21+Inputs!$B$12),Capitalization!G$12,0) -> 26.705212 | I14: =G14-H14 -> 17.136508 | J14: =IF(A14<=Inputs!$B$21,"",IF(AND(A14<=Inputs!$B$22,Capitalization!G$18>0),Inputs!$B$25,Inputs!$B$26)) -> 0.975 | K14: =IF(A14=0,-Capitalization!G$19,IF(A14<=Inputs!$B$21,0,I14*J14-IF(AND(A14=Inputs!$B$22,Capitalization!G$18>0),Inputs!$B$23,0))) -> 16.708095 | L14: =IF(H14>0,G14/H14,"") -> 1.6416915 | M14: =IF(A14=0,-Capitalization!G$4,IF(A14<=Inputs!$B$21,0,G14)) -> 43.84172
A15: 10 | B15: =IF(A15=0,"Equity",IF(A15<=Inputs!$B$21,"Construction",IF(A15<=Inputs!$B$21+Inputs!$B$5,"Queue wait",IF(A15<=Inputs!$B$21+Configurations!$D$15,"Grid ops"," ")))) -> Grid ops | C15: =IF(A15<=Inputs!$B$21,"",A15-Inputs!$B$21-1) -> 7 | D15: =IF(OR(A15<=Inputs!$B$21,A15>Inputs!$B$21+Configurations!$D$15),0,Configurations!$D$4*Configurations!$D$5*8760*(1-Configurations!$D$6)^C15*Configurations!$D$7*(1-Configurations!$D$8)) -> 730255.5 | E15: =IF(OR(A15<=Inputs!$B$21,A15>Inputs!$B$21+Configurations!$D$15),0,IF(A15<=Inputs!$B$21+Inputs!$B$5,D15*(1-Inputs!$B$10)*Configurations!$D$16/1000000,D15*Inputs!$B$18/1000000)) -> 52.578396 | F15: =IF(OR(A15<=Inputs!$B$21,A15>Inputs!$B$21+Configurations!$D$15),0,Configurations!$D$12+Configurations!$D$13+Configurations!$D$14+Inputs!$B$20*E15) -> 8.7366759 | G15: =E15-F15 -> 43.84172 | H15: =IF(AND(A15>Inputs!$B$21,A15<=Inputs!$B$21+Inputs!$B$12),Capitalization!G$12,0) -> 26.705212 | I15: =G15-H15 -> 17.136508 | J15: =IF(A15<=Inputs!$B$21,"",IF(AND(A15<=Inputs!$B$22,Capitalization!G$18>0),Inputs!$B$25,Inputs!$B$26)) -> 0.975 | K15: =IF(A15=0,-Capitalization!G$19,IF(A15<=Inputs!$B$21,0,I15*J15-IF(AND(A15=Inputs!$B$22,Capitalization!G$18>0),Inputs!$B$23,0))) -> 16.708095 | L15: =IF(H15>0,G15/H15,"") -> 1.6416915 | M15: =IF(A15=0,-Capitalization!G$4,IF(A15<=Inputs!$B$21,0,G15)) -> 43.84172
A16: 11 | B16: =IF(A16=0,"Equity",IF(A16<=Inputs!$B$21,"Construction",IF(A16<=Inputs!$B$21+Inputs!$B$5,"Queue wait",IF(A16<=Inputs!$B$21+Configurations!$D$15,"Grid ops"," ")))) -> Grid ops | C16: =IF(A16<=Inputs!$B$21,"",A16-Inputs!$B$21-1) -> 8 | D16: =IF(OR(A16<=Inputs!$B$21,A16>Inputs!$B$21+Configurations!$D$15),0,Configurations!$D$4*Configurations!$D$5*8760*(1-Configurations!$D$6)^C16*Configurations!$D$7*(1-Configurations!$D$8)) -> 730255.5 | E16: =IF(OR(A16<=Inputs!$B$21,A16>Inputs!$B$21+Configurations!$D$15),0,IF(A16<=Inputs!$B$21+Inputs!$B$5,D16*(1-Inputs!$B$10)*Configurations!$D$16/1000000,D16*Inputs!$B$18/1000000)) -> 52.578396 | F16: =IF(OR(A16<=Inputs!$B$21,A16>Inputs!$B$21+Configurations!$D$15),0,Configurations!$D$12+Configurations!$D$13+Configurations!$D$14+Inputs!$B$20*E16) -> 8.7366759 | G16: =E16-F16 -> 43.84172 | H16: =IF(AND(A16>Inputs!$B$21,A16<=Inputs!$B$21+Inputs!$B$12),Capitalization!G$12,0) -> 26.705212 | I16: =G16-H16 -> 17.136508 | J16: =IF(A16<=Inputs!$B$21,"",IF(AND(A16<=Inputs!$B$22,Capitalization!G$18>0),Inputs!$B$25,Inputs!$B$26)) -> 0.975 | K16: =IF(A16=0,-Capitalization!G$19,IF(A16<=Inputs!$B$21,0,I16*J16-IF(AND(A16=Inputs!$B$22,Capitalization!G$18>0),Inputs!$B$23,0))) -> 16.708095 | L16: =IF(H16>0,G16/H16,"") -> 1.6416915 | M16: =IF(A16=0,-Capitalization!G$4,IF(A16<=Inputs!$B$21,0,G16)) -> 43.84172
... A37: 32 | B37: =IF(A37=0,"Equity",IF(A37<=Inputs!$B$21,"Construction",IF(A37<=Inputs!$B$21+Inputs!$B$5,"Queue wait",IF(A37<=Inputs!$B$21+Configurations!$D$15,"Grid ops"," ")))) -> Grid ops | C37: =IF(A37<=Inputs!$B$21,"",A37-Inputs!$B$21-1) -> 29 | D37: =IF(OR(A37<=Inputs!$B$21,A37>Inputs!$B$21+Configurations!$D$15),0,Configurations!$D$4*Configurations!$D$5*8760*(1-Configurations!$D$6)^C37*Configurations!$D$7*(1-Configurations!$D$8)) -> 730255.5 | E37: =IF(OR(A37<=Inputs!$B$21,A37>Inputs!$B$21+Configurations!$D$15),0,IF(A37<=Inputs!$B$21+Inputs!$B$5,D37*(1-Inputs!$B$10)*Configurations!$D$16/1000000,D37*Inputs!$B$18/1000000)) -> 52.578396 | F37: =IF(OR(A37<=Inputs!$B$21,A37>Inputs!$B$21+Configurations!$D$15),0,Configurations!$D$12+Configurations!$D$13+Configurations!$D$14+Inputs!$B$20*E37) -> 8.7366759 | G37: =E37-F37 -> 43.84172 | H37: =IF(AND(A37>Inputs!$B$21,A37<=Inputs!$B$21+Inputs!$B$12),Capitalization!G$12,0) -> 0 | I37: =G37-H37 -> 43.84172 | J37: =IF(A37<=Inputs!$B$21,"",IF(AND(A37<=Inputs!$B$22,Capitalization!G$18>0),Inputs!$B$25,Inputs!$B$26)) -> 0.975 | K37: =IF(A37=0,-Capitalization!G$19,IF(A37<=Inputs!$B$21,0,I37*J37-IF(AND(A37=Inputs!$B$22,Capitalization!G$18>0),Inputs!$B$23,0))) -> 42.745677 | L37: =IF(H37>0,G37/H37,"") | M37: =IF(A37=0,-Capitalization!G$4,IF(A37<=Inputs!$B$21,0,G37)) -> 43.84172

Sheet Results
A1: Results: all three configurations side by side (live; global levers on Inputs)
B3: Solar+BESS 100MW | C3: Wind+BESS 150MW | D3: Geothermal+BESS 100MW
A4: Baseline developer levered IRR | B4: =SolarBase!B2 -> 0.040713705 | C4: =WindBase!B2 -> 0.076471682 | D4: =GeoBase!B2 -> 0.1161382
A5: Co-location developer levered IRR | B5: =SolarColoc!B2 -> 0.11794323 | C5: =WindColoc!B2 -> 0.24443198 | D5: =GeoColoc!B2 -> 0.33081969
A6: Delta IRR (co-location - baseline), pp | B6: =(SolarColoc!B2-SolarBase!B2)*100 -> 7.7229525 | C6: =(WindColoc!B2-WindBase!B2)*100 -> 16.79603 | D6: =(GeoColoc!B2-GeoBase!B2)*100 -> 21.468149
A7: Baseline unlevered (project) IRR | B7: =SolarBase!D2 -> 0.0091238666 | C7: =WindBase!D2 -> 0.02031468 | D7: =GeoBase!D2 -> 0.03856386
A8: Co-location unlevered (project) IRR | B8: =SolarColoc!D2 -> 0.031641614 | C8: =WindColoc!D2 -> 0.04603537 | D8: =GeoColoc!D2 -> 0.065368596
A9: Baseline NPV of dev cash ($mm) | B9: =SolarBase!F2 -> -15.39658 | C9: =WindBase!F2 -> -2.4701198 | D9: =GeoBase!F2 -> 57.635835
A10: Co-location NPV of dev cash ($mm) | B10: =SolarColoc!F2 -> 11.741962 | C10: =WindColoc!F2 -> 58.258031 | D10: =GeoColoc!F2 -> 186.66422
A12: VALUE BRIDGE: dollar impact of co-location over the queue-wait window (live)
A13: Queue-wait revenue uplift, total ($mm) | B13: =SUMIFS(SolarColoc!E5:E37,SolarColoc!A5:A37,">"&Inputs!$B$21,SolarColoc!A5:A37,"<="&Inputs!$B$21+Inputs!$B$5)-SUMIFS(SolarBase!E5:E37,SolarBase!A5:A37,">"&Inputs!$B$21,SolarBase!A5:A37,"<="&Inputs!$B$21+Inputs!$B$5) -> 109.7004 | C13: =SUMIFS(WindColoc!E5:E37,WindColoc!A5:A37,">"&Inputs!$B$21,WindColoc!A5:A37,"<="&Inputs!$B$21+Inputs!$B$5)-SUMIFS(WindBase!E5:E37,WindBase!A5:A37,">"&Inputs!$B$21,WindBase!A5:A37,"<="&Inputs!$B$21+Inputs!$B$5) -> 197.74779 | D13: =SUMIFS(GeoColoc!E5:E37,GeoColoc!A5:A37,">"&Inputs!$B$21,GeoColoc!A5:A37,"<="&Inputs!$B$21+Inputs!$B$5)-SUMIFS(GeoBase!E5:E37,GeoBase!A5:A37,">"&Inputs!$B$21,GeoBase!A5:A37,"<="&Inputs!$B$21+Inputs!$B$5) -> 315.01915
A14: Queue-wait revenue uplift, per year ($mm/yr) | B14: =B13/Inputs!$B$5 -> 27.425101 | C14: =C13/Inputs!$B$5 -> 49.436947 | D14: =D13/Inputs!$B$5 -> 78.754788
A15: Queue-wait EBITDA uplift, total ($mm) | B15: =SUMIFS(SolarColoc!G5:G37,SolarColoc!A5:A37,">"&Inputs!$B$21,SolarColoc!A5:A37,"<="&Inputs!$B$21+Inputs!$B$5)-SUMIFS(SolarBase!G5:G37,SolarBase!A5:A37,">"&Inputs!$B$21,SolarBase!A5:A37,"<="&Inputs!$B$21+Inputs!$B$5) -> 93.054897 | C15: =SUMIFS(WindColoc!G5:G37,WindColoc!A5:A37,">"&Inputs!$B$21,WindColoc!A5:A37,"<="&Inputs!$B$21+Inputs!$B$5)-SUMIFS(WindBase!G5:G37,WindBase!A5:A37,">"&Inputs!$B$21,WindBase!A5:A37,"<="&Inputs!$B$21+Inputs!$B$5) -> 164.78157 | D15: =SUMIFS(GeoColoc!G5:G37,GeoColoc!A5:A37,">"&Inputs!$B$21,GeoColoc!A5:A37,"<="&Inputs!$B$21+Inputs!$B$5)-SUMIFS(GeoBase!G5:G37,GeoBase!A5:A37,">"&Inputs!$B$21,GeoBase!A5:A37,"<="&Inputs!$B$21+Inputs!$B$5) -> 288.79386
A16: Queue-wait developer cash uplift, total ($mm) | B16: =SUMIFS(SolarColoc!K5:K37,SolarColoc!A5:A37,">"&Inputs!$B$21,SolarColoc!A5:A37,"<="&Inputs!$B$21+Inputs!$B$5)-SUMIFS(SolarBase!K5:K37,SolarBase!A5:A37,">"&Inputs!$B$21,SolarBase!A5:A37,"<="&Inputs!$B$21+Inputs!$B$5) -> 66.693983 | C16: =SUMIFS(WindColoc!K5:K37,WindColoc!A5:A37,">"&Inputs!$B$21,WindColoc!A5:A37,"<="&Inputs!$B$21+Inputs!$B$5)-SUMIFS(WindBase!K5:K37,WindBase!A5:A37,">"&Inputs!$B$21,WindBase!A5:A37,"<="&Inputs!$B$21+Inputs!$B$5) -> 113.02751 | D16: =SUMIFS(GeoColoc!K5:K37,GeoColoc!A5:A37,">"&Inputs!$B$21,GeoColoc!A5:A37,"<="&Inputs!$B$21+Inputs!$B$5)-SUMIFS(GeoBase!K5:K37,GeoBase!A5:A37,">"&Inputs!$B$21,GeoBase!A5:A37,"<="&Inputs!$B$21+Inputs!$B$5) -> 200.60931
A17: vs. Microgrid CAPEX ($mm) | B17: =Configurations!$B$11 -> 12 | C17: =Configurations!$C$11 -> 18 | D17: =Configurations!$D$11 -> 12
A18: vs. Incremental developer equity ($mm) | B18: =Capitalization!C19-Capitalization!B19 -> 18.639101 | C18: =Capitalization!E19-Capitalization!D19 -> 8.1 | D18: =Capitalization!G19-Capitalization!F19 -> 5.4
A19: Delta NPV of developer cash ($mm) | B19: =SolarColoc!F2-SolarBase!F2 -> 27.138542 | C19: =WindColoc!F2-WindBase!F2 -> 60.728151 | D19: =GeoColoc!F2-GeoBase!F2 -> 129.02839
A24: Scenario sweep: Solar+BESS 100MW (ITC pathway, flip yr 6; reproduce via Inputs levers)
A25: ITC | B25: Queue (yrs) | C25: Baseline IRR | D25: Co-location IRR | E25: Delta (pp)
A26: 0.3 | B26: 2 | C26: 0.0698 | D26: 0.0493 | E26: -2.05
A27: 0.3 | B27: 4 | C27: 0.0407 | D27: 0.0441 | E27: 0.34
A28: 0.3 | B28: 6 | C28: 0.014 | D28: 0.0377 | E28: 2.38
A29: 0.3 | B29: 8 | C29: -0.0061 | D29: 0.0321 | E29: 3.82
A30: 0 | B30: 2 | C30: -0.0084 | D30: -0.0114 | E30: -0.31
A31: 0 | B31: 4 | C31: -0.0201 | D31: -0.0141 | E31: 0.6
A32: 0 | B32: 6 | C32: -0.0305 | D32: -0.0167 | E32: 1.38
A33: 0 | B33: 8 | C33: -0.0405 | D33: -0.0193 | E33: 2.11
A35: Scenario sweep: Wind+BESS 150MW (ITC pathway, flip yr 6; reproduce via Inputs levers)
A36: ITC | B36: Queue (yrs) | C36: Baseline IRR | D36: Co-location IRR | E36: Delta (pp)
A37: 0.3 | B37: 2 | C37: 0.1133 | D37: 0.1107 | E37: -0.26
A38: 0.3 | B38: 4 | C38: 0.0765 | D38: 0.1006 | E38: 2.41
A39: 0.3 | B39: 6 | C39: 0.0443 | D39: 0.0898 | E39: 4.55
A40: 0.3 | B40: 8 | C40: 0.021 | D40: 0.0811 | E40: 6.01
A41: 0 | B41: 2 | C41: 0.0149 | D41: 0.0116 | E41: -0.33
A42: 0 | B42: 4 | C42: 0.0015 | D42: 0.0082 | E42: 0.68
A43: 0 | B43: 6 | C43: -0.0102 | D43: 0.005 | E43: 1.52
A44: 0 | B44: 8 | C44: -0.0209 | D44: 0.0019 | E44: 2.28
A46: Scenario sweep: Geothermal+BESS 100MW (ITC pathway, flip yr 6; reproduce via Inputs levers)
A47: ITC | B47: Queue (yrs) | C47: Baseline IRR | D47: Co-location IRR | E47: Delta (pp)
A48: 0.3 | B48: 2 | C48: 0.1572 | D48: 0.2006 | E48: 4.35
A49: 0.3 | B49: 4 | C49: 0.1161 | D49: 0.1882 | E49: 7.21
A50: 0.3 | B50: 6 | C50: 0.0832 | D50: 0.1764 | E50: 9.32
A51: 0.3 | B51: 8 | C51: 0.0612 | D51: 0.1679 | E51: 10.67
A52: 0 | B52: 2 | C52: 0.0469 | D52: 0.0557 | E52: 0.87
A53: 0 | B53: 4 | C53: 0.0342 | D53: 0.0526 | E53: 1.84
A54: 0 | B54: 6 | C54: 0.0238 | D54: 0.05 | E54: 2.61
A55: 0 | B55: 8 | C55: 0.0149 | D55: 0.0476 | E55: 3.27
A57: Takeaways: Q* ~3.5 yrs (solar), ~2.2 yrs (wind), <2 yrs (geothermal, 30% ITC). Delta IRR rises with capacity factor: geothermal shows the
A58: LARGEST improvement (+4.4 to +10.7pp), contradicting H1's expectation of the smallest: the delta is driven by energy monetized per queue
A59: year, not by baseline IRR level. ITC beats PTC for all three configs at these parameters (PTC inflation adjustment omitted: caveat).
A62: M4 LOOP CLOSURE: co-location IRR at flat $60 (v7 sweep) vs at Model 4 per-config BTM
A63: Effective BTM price now in use ($/MWh) | B63: =Configurations!B16 -> 121.25624 | C63: =Configurations!C16 -> 116.35372 | D63: =Configurations!D16 -> 108.93487
A64: Co-location levered IRR at flat $60 (from v7 sweep, 4yr/30%) | B64: =D27 -> 0.0441 | C64: =D38 -> 0.1006 | D64: =D49 -> 0.1882
A65: Co-location levered IRR, live at effective BTM | B65: =B5 -> 0.11794323 | C65: =C5 -> 0.24443198 | D65: =D5 -> 0.33081969
A66: IRR change from closing the loop, pp | B66: =(B65-B64)*100 -> 7.3843231 | C66: =(C65-C64)*100 -> 14.383198 | D66: =(D65-D64)*100 -> 14.261969
A67: Comparison valid only when Inputs!B5 = 4 and B6 = 0.30 (the sweep cell used). Baseline IRR is unaffected by BTM price.

Sheet M3_Inputs
A1: Model 3 - Data Center Electricity Cost Model - INPUTS
A2: Blue = hardcoded input. Yellow = PLACEHOLDER pending sourced data. Column D = source.
A3: SEC 1: DATA CENTER LOAD
A4: DC nameplate load | B4: 100 | C4: MW | D4: Scenario setting (user; central case of 50/100/200 MW matrix)
A5: DC load factor | B5: 0.9 | C5: frac | D5: PLACEHOLDER - AI DC annualized utilization; to be sourced (lit. / Chien interview). Typical claim 85-95%.
A6: Hours per year | B6: 8760 | C6: hrs | D6: Constant
A7: Annual DC demand | B7: =B4*B5*B6 -> 788400 | C7: MWh/yr | D7: Calc: nameplate x LF x 8760
A8: SEC 2: GENERATION SUPPLY (from Model 2 configs)
A9: Solar net capacity factor | B9: 0.26 | C9: frac | D9: PLACEHOLDER - Model 2 SolarBase net of degradation/availability/losses (gross CF 25-30%, NREL ATB 2024, https://atb.nrel.gov/electricity/2024/technologies)
A10: Wind net capacity factor | B10: 0.33 | C10: frac | D10: PLACEHOLDER - Model 2 WindBase net (gross 30-35%, NREL ATB 2024)
A11: Geothermal net capacity factor | B11: 0.87 | C11: frac | D11: PLACEHOLDER - Model 2 GeoBase net (gross 90%+, NREL ATB 2024)
A12: Solar capacity | B12: 100 | C12: MW | D12: Model 2 configuration
A13: Wind capacity | B13: 150 | C13: MW | D13: Model 2 configuration
A14: Geothermal capacity | B14: 100 | C14: MW | D14: Model 2 configuration
A15: BESS round-trip efficiency | B15: 0.875 | C15: frac | D15: Framework Sec 2.5.3 (85-90%); applied to shifted energy share - simplified: coverage treated as energy-balance bound, hourly dispatch pending
A16: SEC 3: PRICES - SOURCED
A17: CAISO HV Transmission Access Charge (TAC) | B17: 15.5751 | C17: $/MWh | D17: CAISO, High Voltage Access Charge Rates effective Jan 1 2026, https://www.caiso.com/documents/high-voltage-access-charge-rates-effective-jan-01-2026.pdf
A18: RA capacity price (system, wtd avg) | B18: 25.19 | C18: $/kW-mo | D18: CPUC, 2025 LCR-RCM calculation (Q1-Q4 2024 contracts, 2025-26 delivery), https://www.cpuc.ca.gov/-/media/cpuc-website/divisions/energy-division/documents/resource-adequacy-homepage/resource-adequacy-compliance-materials/lcr-rcm-2025.pdf
A19: Planning reserve margin (PRM) | B19: 0.18 | C19: frac | D19: CPUC D.25-06-048 (June 2025), Slice-of-Day framework, https://www.cpuc.ca.gov/-/media/cpuc-website/divisions/energy-division/documents/resource-adequacy-homepage/oga-fact-sheet-on-track-3-decision-final.pdf
A20: Utility bundled all-in rate (Structure A) | B20: 236.91 | C20: $/MWh | D20: PG&E Schedule B-20 Primary, total electricity cost $0.23691/kWh, rates as of Mar 1 2026, PG&E-3CE Joint Rate Comparison, https://www.pge.com/assets/pge/docs/account/alternate-energy-providers/3ce-rcc.pdf. Note: transmission-voltage (B-20 T) would be somewhat lower; treat as upper reference.
A21: EIA-861 CA industrial avg (cross-check) | B21: 215.3 | C21: $/MWh | D21: EIA-861 2024, California industrial average retail price (prior extraction; re-verify at https://www.eia.gov/electricity/data/eia861/)
A22: Non-bypassable charges (NBC: PCIA/PPP/ND/wildfire) | B22: 23 | C22: $/MWh | D22: PLACEHOLDER - anchored to PG&E PCIA/FF line ~$0.023/kWh in PG&E joint rate comparisons (see B-20 rows, same PG&E PDFs); decompose properly from PG&E/SCE tariff sheets
A23: SEC 4: PRICES - PLACEHOLDERS (pending Model 1 / Model 4)
A24: Grid PPA energy price (Structure B) | B24: 70 | C24: $/MWh | D24: PLACEHOLDER - market comparable needed (LevelTen CAISO index or similar); do NOT reuse project LCOE (circularity)
A25: BTM PPA price (Structure C) | B25: 62 | C25: $/MWh | D25: PLACEHOLDER - Model 4 output pending; currently midpoint assumption from Model 2
A26: Ancillary services + CAISO GMC | B26: 1.5 | C26: $/MWh | D26: PLACEHOLDER - CAISO GMC ~$0.4-0.5 + AS; source from CAISO market charges schedule
A27: Scheduling coordinator fee | B27: 0.5 | C27: $/MWh | D27: PLACEHOLDER
A28: Shaping / imbalance cost | B28: 7 | C28: $/MWh | D28: PLACEHOLDER - as-generated renewable vs flat load mismatch; source from hourly dispatch model when built
A29: Microgrid service fee (paid by DC) | B29: 3.5 | C29: $/MWh | D29: Framework Sec 3.2 range $2-5/MWh. ALLOCATION ASSUMPTION: microgrid CAPEX sits in Model 2 project CAPEX; DC pays service fee only - no double count
A30: Backup power cost (diesel, Phase 1) | B30: 300 | C30: $/MWh | D30: PLACEHOLDER - CA diesel gen fuel+O&M+permits; source needed (e.g., Lazard LCOE+ gas peaking as proxy, CARB permit constraints)
A31: Standby charge (Phase 2, grid backup) | B31: 5 | C31: $/MWh | D31: PLACEHOLDER - CPUC standby/departing-load tariff (e.g., PG&E Schedule S); convert $/kW-mo to $/MWh once sourced

Sheet M3_Coverage
A1: Energy-Balance Coverage by Configuration
A2: Coverage = min(1, annual net generation / annual DC demand). Energy-balance upper bound: BESS shifts timing but cannot create energy. Hourly dispatch (pending) will only lower these.
B4: Solar+BESS | C4: Wind+BESS | D4: Geo+BESS
A5: Capacity (MW) | B5: =M3_Inputs!B12 -> 100 | C5: =M3_Inputs!B13 -> 150 | D5: =M3_Inputs!B14 -> 100
A6: Net capacity factor | B6: =M3_Inputs!B9 -> 0.26 | C6: =M3_Inputs!B10 -> 0.33 | D6: =M3_Inputs!B11 -> 0.87
A7: Annual net generation (MWh) | B7: =B5*B6*M3_Inputs!$B$6 -> 227760 | C7: =C5*C6*M3_Inputs!$B$6 -> 433620 | D7: =D5*D6*M3_Inputs!$B$6 -> 762120
A8: Annual DC demand (MWh) | B8: =M3_Inputs!$B$7 -> 788400 | C8: =M3_Inputs!$B$7 -> 788400 | D8: =M3_Inputs!$B$7 -> 788400
A9: Coverage ratio (capped at 100%) | B9: =MIN(1,B7/B8) -> 0.28888889 | C9: =MIN(1,C7/C8) -> 0.55 | D9: =MIN(1,D7/D8) -> 0.96666667
A10: Uncovered share (backup/grid) | B10: =1-B9 -> 0.71111111 | C10: =1-C9 -> 0.45 | D10: =1-D9 -> 0.033333333

Sheet M3_StructA_B
A1: Structure A: Utility Tariff (bundled, all-in)
A3: All-in delivered cost ($/MWh) | B3: =M3_Inputs!B20 -> 236.91 | C3: PG&E B-20 Primary, Mar 2026. Upper reference; transmission voltage would be lower.
A4: Cross-check: EIA-861 CA industrial avg | B4: =M3_Inputs!B21 -> 215.3
A7: Structure B: Sleeved Grid PPA (all-in delivered)
A8: VPPA treated as sensitivity (see note row 20). Sleeved = physical delivery via grid at transmission voltage.
A10: PPA energy price | B10: =M3_Inputs!B24 -> 70 | C10: Placeholder pending market comp
A11: CAISO TAC (HV) | B11: =M3_Inputs!B17 -> 15.5751 | C11: Sourced - CAISO Jan 2026
A12: Non-bypassable charges | B12: =M3_Inputs!B22 -> 23 | C12: Placeholder range
A13: Resource Adequacy | B13: =M3_Inputs!B4*1000*(1+M3_Inputs!B19)*M3_Inputs!B18*12/M3_Inputs!B7 -> 45.242314 | C13: Calc: nameplate kW x (1+PRM) x $/kW-mo x 12 / annual MWh. Price and PRM sourced.
A14: Ancillary + GMC | B14: =M3_Inputs!B26 -> 1.5 | C14: Placeholder
A15: Scheduling coordinator | B15: =M3_Inputs!B27 -> 0.5 | C15: Placeholder
A16: Shaping / imbalance | B16: =M3_Inputs!B28 -> 7 | C16: Placeholder
A17: Structure B all-in ($/MWh) | B17: =SUM(B10:B16) -> 162.81741
A19: KEY FINDING
A20: RA capacity cost alone adds ~$45/MWh to a flat 100 MW load. Structure B all-in far exceeds the framework's $60-90/MWh estimate, resolving the Model 3 internal inconsistency in the direction of a WIDER negotiation zone.
A22: VPPA sensitivity: VPPA cost = Structure A retail cost + (PPA price - hub LMP settlement). Requires Model 1 LMP; deferred.

Sheet M3_StructC
A1: Structure C: BTM Co-location (all-in $/MWh to the DC)
A2: Phase 1 = islanded (queue wait): backup fills uncovered share. Phase 2 = grid-connected: grid supply fills uncovered share.
B4: Solar+BESS | C4: Wind+BESS | D4: Geo+BESS
A5: Coverage ratio | B5: =M3_Coverage!B9 -> 0.28888889 | C5: =M3_Coverage!C9 -> 0.55 | D5: =M3_Coverage!D9 -> 0.96666667
A7: PHASE 1 (islanded, queue-wait window)
A8: BTM energy component | B8: =B5*M3_Inputs!$B$25 -> 17.911111 | C8: =C5*M3_Inputs!$B$25 -> 34.1 | D8: =D5*M3_Inputs!$B$25 -> 59.933333
A9: Backup component (uncovered x diesel) | B9: =(1-B5)*M3_Inputs!$B$30 -> 213.33333 | C9: =(1-C5)*M3_Inputs!$B$30 -> 135 | D9: =(1-D5)*M3_Inputs!$B$30 -> 10
A10: Microgrid service fee | B10: =M3_Inputs!$B$29 -> 3.5 | C10: =M3_Inputs!$B$29 -> 3.5 | D10: =M3_Inputs!$B$29 -> 3.5
A11: Phase 1 all-in ($/MWh) | B11: =SUM(B8:B10) -> 234.74444 | C11: =SUM(C8:C10) -> 172.6 | D11: =SUM(D8:D10) -> 73.433333
A13: PHASE 2 (grid-connected, post-COD)
A14: BTM energy component | B14: =B5*M3_Inputs!$B$25 -> 17.911111 | C14: =C5*M3_Inputs!$B$25 -> 34.1 | D14: =D5*M3_Inputs!$B$25 -> 59.933333
A15: Grid supplemental (uncovered x [PPA+TAC+NBC]) | B15: =(1-B5)*(M3_Inputs!$B$24+M3_Inputs!$B$17+M3_Inputs!$B$22) -> 77.20896 | C15: =(1-C5)*(M3_Inputs!$B$24+M3_Inputs!$B$17+M3_Inputs!$B$22) -> 48.858795 | D15: =(1-D5)*(M3_Inputs!$B$24+M3_Inputs!$B$17+M3_Inputs!$B$22) -> 3.61917
A16: Standby charge | B16: =M3_Inputs!$B$31 -> 5 | C16: =M3_Inputs!$B$31 -> 5 | D16: =M3_Inputs!$B$31 -> 5
A17: Microgrid service fee | B17: =M3_Inputs!$B$29 -> 3.5 | C17: =M3_Inputs!$B$29 -> 3.5 | D17: =M3_Inputs!$B$29 -> 3.5
A18: Phase 2 all-in ($/MWh) | B18: =SUM(B14:B17) -> 103.62007 | C18: =SUM(C14:C17) -> 91.458795 | D18: =SUM(D14:D17) -> 72.052503
A20: Note: Phase 2 grid supplemental assumes RA embedded in supplemental supply price is NOT separately charged (conservative low); alternative adds pro-rata RA - test in sensitivity.

Sheet M3_Results
A1: Model 3 Results - Effective Delivered Cost and H2 Test
B3: Solar+BESS | C3: Wind+BESS | D3: Geo+BESS
A4: Structure A - utility tariff ($/MWh) | B4: =M3_StructA_B!$B$3 -> 236.91 | C4: =M3_StructA_B!$B$3 -> 236.91 | D4: =M3_StructA_B!$B$3 -> 236.91
A5: Structure B - sleeved grid PPA all-in ($/MWh) | B5: =M3_StructA_B!$B$17 -> 162.81741 | C5: =M3_StructA_B!$B$17 -> 162.81741 | D5: =M3_StructA_B!$B$17 -> 162.81741
A6: Structure C - Phase 1 islanded ($/MWh) | B6: =M3_StructC!B11 -> 234.74444 | C6: =M3_StructC!C11 -> 172.6 | D6: =M3_StructC!D11 -> 73.433333
A7: Structure C - Phase 2 grid-connected ($/MWh) | B7: =M3_StructC!B18 -> 103.62007 | C7: =M3_StructC!C18 -> 91.458795 | D7: =M3_StructC!D18 -> 72.052503
A9: H2 TEST - dual denominator
A10: Savings, P1 vs B all-in: (B-C1)/B | B10: =(B5-B6)/B5 -> -0.44176498 | C10: =(C5-C6)/C5 -> -0.060083171 | D10: =(D5-D6)/D5 -> 0.54898354
A11: Savings, P2 vs B all-in: (B-C2)/B | B11: =(B5-B7)/B5 -> 0.36358115 | C11: =(C5-C7)/C5 -> 0.43827387 | D11: =(D5-D7)/D5 -> 0.55746439
A12: Savings, P1 vs B PPA price only | B12: =(M3_Inputs!$B$24-B6)/M3_Inputs!$B$24 -> -2.3534921 | C12: =(M3_Inputs!$B$24-C6)/M3_Inputs!$B$24 -> -1.4657143 | D12: =(M3_Inputs!$B$24-D6)/M3_Inputs!$B$24 -> -0.049047619
A13: Savings, P2 vs B PPA price only | B13: =(M3_Inputs!$B$24-B7)/M3_Inputs!$B$24 -> -0.48028673 | C13: =(M3_Inputs!$B$24-C7)/M3_Inputs!$B$24 -> -0.30655421 | D13: =(M3_Inputs!$B$24-D7)/M3_Inputs!$B$24 -> -0.029321476
A14: H2 (20-35%) met on all-in basis, Phase 1? | B14: =IF(B10>=0.2,"YES","NO") -> NO | C14: =IF(C10>=0.2,"YES","NO") -> NO | D14: =IF(D10>=0.2,"YES","NO") -> YES
A16: READING
A17: The vs-PPA-price-only rows will show negative 'savings' for low-coverage configs (solar) because backup cost dominates - this is why the all-in denominator is the meaningful H2 test.

Sheet M4_LCOE
A1: Model 4: Levelized Cost of Energy (price FLOOR for BTM negotiation)
A2: LCOE = [CAPEX + PV(OPEX)] / PV(Energy). Green = linked from Configurations / Capitalization (Model 2). Yellow = headline floor. Closed-form annuity formulas; all live.
A4: SEC 1: SHARED PARAMETERS
A5: Discount rate (WACC proxy) | B5: =Inputs!B24 -> 0.08 | C5: frac | D5: Linked to Model 2 NPV discount rate (8%). Framework 2.4: WACC ~7-9%.
A6: Hours per year | B6: 8760 | C6: hrs
A8: SEC 2: LCOE BUILD-UP BY CONFIGURATION
B9: Solar+BESS 100MW | C9: Wind+BESS 150MW | D9: Geo+BESS 100MW | E9: Source / formula
A10: Capacity (MW) | B10: =Configurations!B4 -> 100 | C10: =Configurations!C4 -> 150 | D10: =Configurations!D4 -> 100 | E10: Configurations R4
A11: Capacity factor | B11: =Configurations!B5 -> 0.275 | C11: =Configurations!C5 -> 0.35 | D11: =Configurations!D5 -> 0.9 | E11: Configurations R5
A12: Availability | B12: =Configurations!B7 -> 0.98 | C12: =Configurations!C7 -> 0.96 | D12: =Configurations!D7 -> 0.95 | E12: Configurations R7
A13: Electrical losses | B13: =Configurations!B8 -> 0.025 | C13: =Configurations!C8 -> 0.025 | D13: =Configurations!D8 -> 0.025 | E13: Configurations R8
A14: Annual degradation | B14: =Configurations!B6 -> 0.005 | C14: =Configurations!C6 -> 0.002 | D14: =Configurations!D6 -> 0 | E14: Configurations R6
A15: Operating life (yrs) | B15: =Configurations!B15 -> 25 | C15: =Configurations!C15 -> 25 | D15: =Configurations!D15 -> 30 | E15: Configurations R15
A16: Year-1 net energy (MWh) | B16: =B10*B11*$B$6*B12*(1-B13) -> 230179.95 | C16: =C10*C11*$B$6*C12*(1-C13) -> 430466.4 | D16: =D10*D11*$B$6*D12*(1-D13) -> 730255.5 | E16: Formula: mw × CF × 8760 × avail × (1−loss)
A17: Total CAPEX, baseline ($mm) | B17: =Configurations!B9 -> 197 | C17: =Configurations!C9 -> 321.4 | D17: =Configurations!D9 -> 568.25 | E17: Configurations R9: excludes microgrid
A18: Microgrid CAPEX ($mm) | B18: =Configurations!B11 -> 12 | C18: =Configurations!C11 -> 18 | D18: =Configurations!D11 -> 12 | E18: Configurations R11
A19: Total CAPEX, co-location ($mm) | B19: =B17+B18 -> 209 | C19: =C17+C18 -> 339.4 | D19: =D17+D18 -> 580.25 | E19: Formula: baseline + microgrid
A20: Fixed O&M gen+BESS ($mm/yr) | B20: =Configurations!B12 -> 3 | C20: =Configurations!C12 -> 6.375 | D20: =Configurations!D12 -> 4.625 | E20: Configurations R12
A21: Land + insurance ($mm/yr) | B21: =Configurations!B13 -> 1.088 | C21: =Configurations!C13 -> 1.586 | D21: =Configurations!D13 -> 2.573 | E21: Configurations R13
A22: Microgrid O&M ($mm/yr) | B22: =Configurations!B14 -> 0.75 | C22: =Configurations!C14 -> 1.125 | D22: =Configurations!D14 -> 0.75 | E22: Configurations R14
A23: Annual OPEX, baseline ($mm/yr) | B23: =B20+B21 -> 4.088 | C23: =C20+C21 -> 7.961 | D23: =D20+D21 -> 7.198 | E23: Formula: o&m + land/ins (no microgrid)
A24: Annual OPEX, co-location ($mm/yr) | B24: =B23+B22 -> 4.838 | C24: =C23+C22 -> 9.086 | D24: =D23+D22 -> 7.948 | E24: Formula: o&m + land/ins + microgrid o&m
A25: ITC amount @ lever rate ($mm) | B25: =Capitalization!B13 -> 54 | C25: =Capitalization!D13 -> 88.875 | D25: =Capitalization!F13 -> 159.375 | E25: Capitalization R13 (base col)
A26: Tax equity contribution ($mm) | B26: =Capitalization!B18 -> 73.571604 | C26: =Capitalization!D18 -> 121.0866 | D26: =Capitalization!F18 -> 217.13841 | E26: Capitalization R18 (base col): what TE actually pays for the credits
A28: SEC 3: PRESENT-VALUE FACTORS
A29: PV annuity factor for level OPEX | B29: =(1-(1+$B$5)^-B15)/$B$5 -> 10.674776 | C29: =(1-(1+$B$5)^-C15)/$B$5 -> 10.674776 | D29: =(1-(1+$B$5)^-D15)/$B$5 -> 11.257783 | E29: Formula: [1 − (1+r)^−N] / r
A30: Degradation-adjusted growth q = (1−d)/(1+r) | B30: =(1-B14)/(1+$B$5) -> 0.9212963 | C30: =(1-C14)/(1+$B$5) -> 0.92407407 | D30: =(1-D14)/(1+$B$5) -> 0.92592593
A31: PV energy factor (yrs of Y1-equivalent) | B31: =B30*(1-B30^B15)/(1-B30) -> 10.197931 | C31: =C30*(1-C30^C15)/(1-C30) -> 10.480344 | D31: =D30*(1-D30^D15)/(1-D30) -> 11.257783 | E31: Formula: q(1−q^N)/(1−q); geometric series of degrading output discounted at r)
A32: PV of lifetime energy (MWh) | B32: =B16*B31 -> 2347359.3 | C32: =C16*C31 -> 4511435.9 | D32: =D16*D31 -> 8221058.2
A34: SEC 4: LCOE OUTPUTS ($/MWh)
B35: Solar+BESS 100MW | C35: Wind+BESS 150MW | D35: Geo+BESS 100MW | E35: Interpretation
A36: LCOE: baseline, no credit (gross) | B36: =((B17)+B23*B29)*1000000/B32 -> 102.51455 | C36: =((C17)+C23*C29)*1000000/C32 -> 90.07817 | D36: =((D17)+D23*D29)*1000000/D32 -> 78.978096 | E36: Full project cost with no tax-credit offset. OBBBA Scenario D floor.
A37: LCOE: co-location, no credit (gross) | B37: =((B19)+B24*B29)*1000000/B32 -> 111.03736 | C37: =((C19)+C24*C29)*1000000/C32 -> 96.72996 | D37: =((D19)+D24*D29)*1000000/D32 -> 81.4648 | E37: Adds microgrid CAPEX + O&M. This is the physical floor for a BTM sale with zero credits.
A38: LCOE: baseline, net of tax equity | B38: =((B17-B26)+B23*B29)*1000000/B32 -> 71.172267 | C38: =((C17-C26)+C23*C29)*1000000/C32 -> 63.238246 | D38: =((D17-D26)+D23*D29)*1000000/D32 -> 52.565631 | E38: CAPEX reduced by tax-equity contribution (Capitalization R18). Developer's effective cost floor at current ITC lever.
A39: LCOE: co-location, net of tax equity | B39: =((B19-B26)+B24*B29)*1000000/B32 -> 79.69507 | C39: =((C19-C26)+C24*C29)*1000000/C32 -> 69.890036 | D39: =((D19-D26)+D24*D29)*1000000/D32 -> 55.052335 | E39: BASE-CASE FLOOR. Co-location CAPEX net of tax equity. Feeds M4_Bounds.
A41: Cross-check vs NREL ATB 2024 generation-only LCOE ranges
A42: NREL ATB 2024 (moderate, R&D+Market) | B42: Solar PV $24–42 | C42: Wind $25–50 | D42: Geothermal $55–80 | E42: Framework Sec 2.4 table. Model values are HIGHER because they include BESS ($113–159 LCOS), microgrid, land, interconnection: ATB is bare generation. https://atb.nrel.gov/electricity/2024/technologies

Sheet M4_Bounds
A1: Model 4: Price Floor, Ceiling, and Negotiation Zone
A2: Floor = developer's LCOE (M4_LCOE). Ceiling = data center's grid alternative (M3 Structure B). Zone = Ceiling − Floor. Framework Sec 4.2: 'If LCOE > Grid PPA Cost, co-location is not viable at any price.'
A4: SEC 1: CEILING: data center's grid alternative (config-independent)
A5: Ceiling A: Structure B all-in delivered | B5: =M3_StructA_B!B17 -> 162.81741 | C5: $/MWh | D5: PRIMARY CEILING per framework Sec 4.2. Sleeved PPA energy + TAC + NBC + RA + AS + SC + shaping. What the DC actually avoids by going BTM.
A6: Ceiling B: energy-only market PPA | B6: =Inputs!B18 -> 72 | C6: $/MWh | D6: LBNL hybrid PPA ($72). Reference point for the 'industry 10-20% discount' convention (framework 4.3). NOT the true ceiling: DC also avoids T&D.
A7: Ceiling C: spot + wires (Phase-2 supplemental) | B7: =M1_Benchmarks!$B$24+M3_Inputs!B17+M3_Inputs!B22 -> 78.5751 | C7: $/MWh | D7: P_avg (M1) + CAISO TAC + NBC. Lower-bound ceiling: merchant grid supply with no RA. Used in M3 Phase 2 supplemental.
A8: T&D + capacity savings pool (A − B) | B8: =B5-B6 -> 90.817414 | C8: $/MWh | D8: The non-energy charges avoided by BTM. Framework 4.3: 'allocating the T&D savings roughly 50/50 between the parties'.
A10: SEC 2: FLOOR & ZONE BY CONFIGURATION
B11: Solar+BESS | C11: Wind+BESS | D11: Geo+BESS | E11: Note
A12: Floor: LCOE gross (no credit) | B12: =M4_LCOE!B37 -> 111.03736 | C12: =M4_LCOE!C37 -> 96.72996 | D12: =M4_LCOE!D37 -> 81.4648 | E12: OBBBA Scenario D / FEOC-fail floor
A13: Floor: LCOE net of tax equity (BASE) | B13: =M4_LCOE!B39 -> 79.69507 | C13: =M4_LCOE!C39 -> 69.890036 | D13: =M4_LCOE!D39 -> 55.052335 | E13: Base-case floor at current ITC lever (Inputs!B6)
A15: Zone vs Ceiling A (all-in): base floor | B15: =$B$5-B13 -> 83.122343 | C15: =$B$5-C13 -> 92.927378 | D15: =$B$5-D13 -> 107.76508 | E15: Primary negotiation zone width
A16: Zone vs Ceiling B (energy-only): base floor | B16: =$B$6-B13 -> -7.6950704 | C16: =$B$6-C13 -> 2.1099644 | D16: =$B$6-D13 -> 16.947665 | E16: Zone if DC ignores its T&D savings (narrow-frame negotiation)
A17: Zone vs Ceiling A: gross floor (no credit) | B17: =$B$5-B12 -> 51.780058 | C17: =$B$5-C12 -> 66.087454 | D17: =$B$5-D12 -> 81.352614 | E17: Stress: zone survives loss of tax credits?
A19: SEC 3: VIABILITY TESTS
B20: Solar+BESS | C20: Wind+BESS | D20: Geo+BESS | E20: Reading
A21: Viable vs all-in ceiling (base floor)? | B21: =IF(B15>0,"YES","NO") -> YES | C21: =IF(C15>0,"YES","NO") -> YES | D21: =IF(D15>0,"YES","NO") -> YES | E21: Framework 4.2 test
A22: Viable vs energy-only ceiling (base floor)? | B22: =IF(B16>0,"YES","NO") -> NO | C22: =IF(C16>0,"YES","NO") -> YES | D22: =IF(D16>0,"YES","NO") -> YES | E22: If NO: developer's cost exceeds market PPA: only viable if DC shares its T&D savings
A23: Viable vs all-in ceiling (zero credit)? | B23: =IF(B17>0,"YES","NO") -> YES | C23: =IF(C17>0,"YES","NO") -> YES | D23: =IF(D17>0,"YES","NO") -> YES | E23: Survives OBBBA Scenario D?
A24: Model 2 BTM input ($60) above base floor? | B24: =IF(Inputs!$B$19>=B13,"YES","NO: below LCOE") -> NO: below LCOE | C24: =IF(Inputs!$B$19>=C13,"YES","NO: below LCOE") -> NO: below LCOE | D24: =IF(Inputs!$B$19>=D13,"YES","NO: below LCOE") -> YES | E24: Consistency check: Model 2's $60 BTM assumption vs this model's floor. NO means Model 2 is pricing that config below cost.

Sheet M4_Pricing
A1: Model 4: BTM Price Setting and Two-Sided Viability Test
A2: Three methods from framework Sec 4.3. Yellow lever = bargaining share α. Output feeds back to Model 2 (BTM revenue) and Model 3 (Structure C cost).
A4: SEC 1: LEVERS
A5: Bargaining share α (0 = DC has all power → floor; 1 = developer → ceiling) | B5: 0.5 | C5: frac | D5: Framework 4.3: geothermal/unique site → α higher; DC with multiple site options → α lower. 0.5 = symmetric.
A6: Industry discount to energy-only PPA | B6: 0.15 | C6: frac | D6: Framework 4.3: 'BTM PPA typically set at 10-20% discount to grid PPA'. Midpoint 15%.
A7: Developer levered IRR hurdle | B7: 0.1 | C7: frac | D7: Framework 2.9.3: 'Developer equity hurdle rate: 10-15%'. Low end used.
A8: DC minimum savings vs grid (H2 lower bound) | B8: 0.2 | C8: frac | D8: H2 hypothesis: 20-35% savings. Lower bound as acceptance threshold.
A10: SEC 2: THREE PRICE-SETTING METHODS ($/MWh)
B11: Solar+BESS | C11: Wind+BESS | D11: Geo+BESS | E11: Method
A12: Method 1: Midpoint (floor, all-in ceiling) | B12: =(M4_Bounds!B13+M4_Bounds!$B$5)/2 -> 121.25624 | C12: =(M4_Bounds!C13+M4_Bounds!$B$5)/2 -> 116.35372 | D12: =(M4_Bounds!D13+M4_Bounds!$B$5)/2 -> 108.93487 | E12: Framework 4.5 Step 1: 'initial BTM price as midpoint of LCOE and Grid PPA'. Splits the full surplus 50/50.
A13: Method 2: Industry discount to energy PPA | B13: =M4_Bounds!$B$6*(1-$B$6) -> 61.2 | C13: =M4_Bounds!$B$6*(1-$B$6) -> 61.2 | D13: =M4_Bounds!$B$6*(1-$B$6) -> 61.2 | E13: Framework 4.3 convention. Config-independent: ignores developer's cost. Matches Model 2's $60 at 17% discount.
A14: Method 3: Bargaining share α on zone | B14: =M4_Bounds!B13+$B$5*(M4_Bounds!$B$5-M4_Bounds!B13) -> 121.25624 | C14: =M4_Bounds!C13+$B$5*(M4_Bounds!$B$5-M4_Bounds!C13) -> 116.35372 | D14: =M4_Bounds!D13+$B$5*(M4_Bounds!$B$5-M4_Bounds!D13) -> 108.93487 | E14: General form; Method 1 is α=0.5. Lever above.
A15: Method 2 vs floor: is discount price above LCOE? | B15: =IF(B13>=M4_Bounds!B13,"YES","NO: below cost") -> NO: below cost | C15: =IF(C13>=M4_Bounds!C13,"YES","NO: below cost") -> NO: below cost | D15: =IF(D13>=M4_Bounds!D13,"YES","NO: below cost") -> YES | E15: If NO, the industry convention would price this config below its own LCOE. Developer would not sign.
A17: SEC 3: SELECTED BTM PRICE (feeds Model 2 / Model 3)
A18: Method selector (1/2/3) | B18: 3 | D18: Default = 3 (bargaining share). Change to 1 or 2 to switch.
A19: BTM PPA price: selected ($/MWh) | B19: =CHOOSE($B$18,B12,B13,B14) -> 121.25624 | C19: =CHOOSE($B$18,C12,C13,C14) -> 116.35372 | D19: =CHOOSE($B$18,D12,D13,D14) -> 108.93487 | E19: → Replace Inputs!B19 ($60 flat) with these per-config values to close the M4→M2 loop. Not auto-linked: Model 2 v7 has a single global BTM cell.
A20: vs Model 2 current input ($60) | B20: =B19-Inputs!$B$19 -> 61.256242 | C20: =C19-Inputs!$B$19 -> 56.353725 | D20: =D19-Inputs!$B$19 -> 48.934874 | E20: Positive = Model 4 says price should be higher than Model 2 assumes.
A22: SEC 4: TWO-SIDED VIABILITY AT SELECTED PRICE
B23: Solar+BESS | C23: Wind+BESS | D23: Geo+BESS | E23: Test
A24: Developer side: price − LCOE floor ($/MWh) | B24: =B19-M4_Bounds!B13 -> 41.561172 | C24: =C19-M4_Bounds!C13 -> 46.463689 | D24: =D19-M4_Bounds!D13 -> 53.882539 | E24: Margin over cost at 8% WACC. Positive = earns above WACC unlevered.
A25: Developer side: Model 2 co-loc levered IRR (live, at effective BTM) | B25: =SolarColoc!B2 -> 0.11794323 | C25: =WindColoc!B2 -> 0.24443198 | D25: =GeoColoc!B2 -> 0.33081969 | E25: Live from Model 2 at the effective BTM price (Configurations R16). With Inputs!B27 = 2 this IS the test at the Model 4 price; loop closed.
A26: Developer side: meets hurdle at effective BTM? | B26: =IF(B25>=$B$7,"YES","NO") -> YES | C26: =IF(C25>=$B$7,"YES","NO") -> YES | D26: =IF(D25>=$B$7,"YES","NO") -> YES
A27: DC side: all-in BTM cost, Phase 2 ($/MWh) | B27: =M3_Coverage!B9*B19+(1-M3_Coverage!B9)*(M3_Inputs!$B$24+M3_Inputs!$B$17+M3_Inputs!$B$22)+M3_Inputs!$B$31+M3_Inputs!$B$29 -> 120.73854 | C27: =M3_Coverage!C9*C19+(1-M3_Coverage!C9)*(M3_Inputs!$B$24+M3_Inputs!$B$17+M3_Inputs!$B$22)+M3_Inputs!$B$31+M3_Inputs!$B$29 -> 121.35334 | D27: =M3_Coverage!D9*D19+(1-M3_Coverage!D9)*(M3_Inputs!$B$24+M3_Inputs!$B$17+M3_Inputs!$B$22)+M3_Inputs!$B$31+M3_Inputs!$B$29 -> 117.42288 | E27: Recomputes M3_StructC Phase 2 formula at the selected BTM price instead of M3's $62 placeholder.
A28: DC side: savings vs Structure B all-in | B28: =(M4_Bounds!$B$5-B27)/M4_Bounds!$B$5 -> 0.25844209 | C28: =(M4_Bounds!$B$5-C27)/M4_Bounds!$B$5 -> 0.25466607 | D28: =(M4_Bounds!$B$5-D27)/M4_Bounds!$B$5 -> 0.27880637
A29: DC side: meets minimum savings? | B29: =IF(B28>=$B$8,"YES","NO") -> YES | C29: =IF(C28>=$B$8,"YES","NO") -> YES | D29: =IF(D28>=$B$8,"YES","NO") -> YES
A30: BOTH PARTIES VIABLE (Phase 2, at effective BTM)? | B30: =IF(AND(B25>=$B$7,B28>=$B$8,B24>=0),"YES","NO") -> YES | C30: =IF(AND(C25>=$B$7,C28>=$B$8,C24>=0),"YES","NO") -> YES | D30: =IF(AND(D25>=$B$7,D28>=$B$8,D24>=0),"YES","NO") -> YES | E30: Framework 4.5 Step 4: 'range of BTM prices that simultaneously satisfy both parties'. Requires: IRR ≥ hurdle AND DC savings ≥ min AND price ≥ LCOE.
A32: SEC 5: PRICE RANGE SATISFYING BOTH (analytical)
A33: Max price DC accepts (savings = min) | B33: =(M4_Bounds!$B$5*(1-$B$8)-(1-M3_Coverage!B9)*(M3_Inputs!$B$24+M3_Inputs!$B$17+M3_Inputs!$B$22)-M3_Inputs!$B$31-M3_Inputs!$B$29)/M3_Coverage!B9 -> 154.19413 | C33: =(M4_Bounds!$B$5*(1-$B$8)-(1-M3_Coverage!C9)*(M3_Inputs!$B$24+M3_Inputs!$B$17+M3_Inputs!$B$22)-M3_Inputs!$B$31-M3_Inputs!$B$29)/M3_Coverage!C9 -> 132.53661 | D33: =(M4_Bounds!$B$5*(1-$B$8)-(1-M3_Coverage!D9)*(M3_Inputs!$B$24+M3_Inputs!$B$17+M3_Inputs!$B$22)-M3_Inputs!$B$31-M3_Inputs!$B$29)/M3_Coverage!D9 -> 122.20837 | E33: Solves Phase-2 cost equation for P such that DC savings exactly equal the minimum threshold.
A34: Min price developer accepts (LCOE floor) | B34: =M4_Bounds!B13 -> 79.69507 | C34: =M4_Bounds!C13 -> 69.890036 | D34: =M4_Bounds!D13 -> 55.052335
A35: Mutually acceptable range width ($/MWh) | B35: =B33-B34 -> 74.499059 | C35: =C33-C34 -> 62.646575 | D35: =D33-D34 -> 67.156039 | E35: Negative = no price satisfies both at these thresholds. This is the headline Model 4 output.
A36: Deal exists? | B36: =IF(B33>=B34,"YES","NO") -> YES | C36: =IF(C33>=C34,"YES","NO") -> YES | D36: =IF(D33>=D34,"YES","NO") -> YES

Sheet M4_Notes
A1: Model 4: Methodology Notes and Findings
A3: §1 What Model 4 does
A4: Determines the price range within which a behind-the-meter PPA is acceptable to both the renewable developer and the co-located data center (framework Sec 4). Floor = developer's LCOE (M4_LCOE, computed from Model 2 Configurations at the Model 2 discount rate). Ceiling = data center's grid alternative (M3 Structure B all-in delivered cost). Zone = ceiling − floor. Three price-setting methods (framework 4.3/4.5), a two-sided viability test, and an analytical solve for the mutually acceptable range.
A6: §2 LCOE construction
A7: Closed-form: LCOE = [CAPEX + OPEX × PVA(r,N)] / [E₁ × q(1−q^N)/(1−q)] with q = (1−d)/(1+r). CAPEX and OPEX pulled live from Configurations (NREL ATB 2024 midpoints). Discount rate linked to Model 2's 8% NPV rate (framework 2.4: WACC 7–9%). Two variants: gross (no credits, OBBBA Scenario D) and net of tax equity (CAPEX reduced by the Capitalization R18 contribution). Net LCOE is the base floor because tax equity is real capital the developer does not have to raise. Model LCOEs are above NREL ATB generation-only ranges because they include BESS (LCOS $113–159), microgrid, land, and interconnection: this is by design; the floor must cover the whole project.
A9: §3 FINDING: Model 2's $60/MWh BTM price is below LCOE for solar and wind
A10: Base-case co-location LCOE net of tax equity: Solar $79.70, Wind $69.89, Geothermal $55.05. Model 2 v7 uses a flat $60 BTM input for all three. At $60, solar is selling ~$20 below cost and wind ~$10 below cost at 8% WACC; only geothermal clears its floor. This is consistent with Model 2's own unlevered IRRs (solar 1.3%, wind 2.6%, geo 5.0% co-loc: all below 8%) and with the earlier finding that solar cannot be rescued by co-location. The $60 figure came from the 'industry 10–20% discount to energy PPA' convention, which is benchmarked to the $72 energy-only PPA and is blind to the developer's cost.
A12: §4 FINDING: the true negotiation zone is much wider than the framework expected, because the ceiling is higher
A13: Framework Sec 3 estimated Structure B (sleeved grid PPA) at $60–90/MWh. Model 3 found $162.82 once RA ($45), TAC ($16), NBC ($23), and shaping are stacked. That $91 gap between energy-only PPA and all-in delivered cost is the 'T&D + capacity savings pool' the two parties are actually dividing. With the all-in ceiling, the zone is $83 (solar) / $93 (wind) / $108 (geo) wide, and the midpoint price is ~$109–121 rather than ~$60. At the midpoint the developer earns $42–54/MWh over LCOE and the DC still saves 26–28% vs grid: both parties clear their thresholds for all three configurations. Framework 4.2's warning that 'if LCOE > Grid PPA Cost, co-location is not viable' does NOT bind for any configuration once the correct ceiling is used, even in the zero-credit stress case.
A15: §5 FINDING: Method 2 (industry convention) and Methods 1/3 (surplus-splitting) give very different prices; the paper must choose and justify
A16: Method 2 gives $61 for all configs (config-blind). Methods 1/3 at α=0.5 give $109–121 (config-specific). The $50–60 gap is the T&D savings pool split. Recommended framing for the paper: Method 2 is what a DC would open with if it frames the deal as 'a cheaper PPA'; Methods 1/3 are what the deal is worth once the DC's avoided wires and capacity costs are priced in. The bargaining lever α lets the paper show the full range. A defensible base case is α = 0.5 (framework 4.3: 'allocating the T&D savings roughly 50/50'), which is Method 1.
A18: §6 Analytical mutually-acceptable range (SEC 5)
... A25: H1 (developer IRR +3–6 pp) was tested in Model 2 at $60 BTM. At Model-4-consistent prices, the co-location uplift is larger for all configs and solar likely crosses the 10% hurdle. H2 (DC saves 20–35%) holds at the midpoint price for all configs in Phase 2 (26–28%). The restated hypothesis should be joint: 'there exists a BTM price at which the developer clears WACC and the DC saves ≥20%, for all three configurations, with the geothermal zone widest on the developer side and the solar zone widest on the DC side.'

Sheet Fig2_Breakeven
A1: Figure 2 data: developer levered IRR vs post-completion queue wait
A2: STATIC VALUES. Each row is one full model run (Inputs!B5 = queue years, B6 = ITC, B27 = BTM lever), IRR recomputed from the developer cash-flow column (K5:K37) with numpy_financial because LibreOffice IRR() does not converge for negative returns. Regenerate with the sweep script if any upstream input changes. Levers: 1 = flat $60 BTM (Inputs!B19), 2 = Model 4 per-config price. Columns J-L record the effective BTM price for each row; under lever 2 it rises when ITC = 0 because the LCOE floor loses its tax-equity offset.
A4: BTM lever | B4: ITC | C4: Queue (yr) | D4: Solar base | E4: Solar coloc | F4: Wind base | G4: Wind coloc | H4: Geo base | I4: Geo coloc | J4: Solar BTM $/MWh | K4: Wind BTM $/MWh | L4: Geo BTM $/MWh
A5: 1 | B5: 0.3 | C5: 1 | D5: 0.092040598 | E5: 0.052337812 | F5: 0.14262314 | G5: 0.11696155 | H5: 0.19217083 | I5: 0.20913406 | J5: 60 | K5: 60 | L5: 60
A6: 1 | B6: 0.3 | C6: 2 | D6: 0.069820429 | E6: 0.049346081 | F6: 0.11328635 | G6: 0.11065833 | H6: 0.15717651 | I6: 0.20063726 | J6: 60 | K6: 60 | L6: 60
A7: 1 | B7: 0.3 | C7: 3 | D7: 0.053561747 | E7: 0.046605392 | F7: 0.092469993 | G7: 0.10527767 | H7: 0.13352394 | I7: 0.19382367 | J7: 60 | K7: 60 | L7: 60
A8: 1 | B8: 0.3 | C8: 4 | D8: 0.040713705 | E8: 0.044070577 | F8: 0.076471682 | G8: 0.10059927 | H8: 0.1161382 | I8: 0.18824895 | J8: 60 | K8: 60 | L8: 60
A9: 1 | B9: 0.3 | C9: 5 | D9: 0.026138602 | E9: 0.040790138 | F9: 0.058749789 | G9: 0.094874732 | H9: 0.097673895 | I9: 0.18181078 | J9: 60 | K9: 60 | L9: 60
A10: 1 | B10: 0.3 | C10: 6 | D10: 0.013974172 | E10: 0.037726166 | F10: 0.044269679 | G10: 0.089795055 | H10: 0.083195996 | I10: 0.1764084 | J10: 60 | K10: 60 | L10: 60
A11: 1 | B11: 0.3 | C11: 7 | D11: 0.0033881237 | E11: 0.034838778 | F11: 0.031912461 | G11: 0.085225856 | H11: 0.071317754 | I11: 0.17182054 | J11: 60 | K11: 60 | L11: 60
A12: 1 | B12: 0.3 | C12: 8 | D12: -0.0061327494 | E12: 0.032095808 | F12: 0.020995619 | G12: 0.081067712 | H12: 0.061220659 | I12: 0.1678871 | J12: 60 | K12: 60 | L12: 60
A13: 1 | B13: 0 | C13: 1 | D13: -0.0017275321 | E13: -0.010083413 | F13: 0.022755932 | G13: 0.013396892 | H13: 0.054789404 | I13: 0.057348897 | J13: 60 | K13: 60 | L13: 60
A14: 1 | B14: 0 | C14: 2 | D14: -0.0083739762 | E14: -0.011432201 | F14: 0.014883522 | G14: 0.011611445 | H14: 0.046933154 | I14: 0.055660282 | J14: 60 | K14: 60 | L14: 60
A15: 1 | B15: 0 | C15: 3 | D15: -0.014426261 | E15: -0.012763465 | F15: 0.0078681943 | G15: 0.0098906467 | H15: 0.040168875 | I15: 0.05409445 | J15: 60 | K15: 60 | L15: 60
A16: 1 | B16: 0 | C16: 4 | D16: -0.020056428 | E16: -0.014082723 | F16: 0.0014622448 | G16: 0.0082230453 | H16: 0.034190215 | I16: 0.052634432 | J16: 60 | K16: 60 | L16: 60
... A36: 2 | B36: 0 | C36: 8 | D36: -0.040466795 | E36: 0.064344699 | F36: -0.020924905 | G36: 0.096340738 | H36: 0.014859652 | I36: 0.1171452 | J36: 136.93 | K36: 129.77 | L36: 122.14

Sheet Fig3_Zone
A1: Figure 3 data: BTM price bounds and mutually acceptable range
A2: LIVE. All values link to M4_Bounds / M4_Pricing. Stacked bar: segment 1 (no fill) = floor offset; segment 2 (green) = mutually acceptable range; segment 3 (grey) = remainder of zone to ceiling.
A4: Configuration | B4: Net LCOE floor | C4: Gross LCOE | D4: DC 20% limit (P_max) | E4: Ceiling (Structure B) | F4: Midpoint | G4: Seg1: floor | H4: Seg2: acceptable | I4: Seg3: rest of zone | J4: $60 marker
A5: Solar+BESS 100 MW | B5: =M4_Bounds!B13 -> 79.69507 | C5: =M4_Bounds!B12 -> 111.03736 | D5: =M4_Pricing!B33 -> 154.19413 | E5: =M4_Bounds!$B$5 -> 162.81741 | F5: =(B5+E5)/2 -> 121.25624 | G5: =B5 -> 79.69507 | H5: =D5-B5 -> 74.499059 | I5: =E5-D5 -> 8.6232837 | J5: =Inputs!$B$19 -> 60
A6: Wind+BESS 150 MW | B6: =M4_Bounds!C13 -> 69.890036 | C6: =M4_Bounds!C12 -> 96.72996 | D6: =M4_Pricing!C33 -> 132.53661 | E6: =M4_Bounds!$B$5 -> 162.81741 | F6: =(B6+E6)/2 -> 116.35372 | G6: =B6 -> 69.890036 | H6: =D6-B6 -> 62.646575 | I6: =E6-D6 -> 30.280803 | J6: =Inputs!$B$19 -> 60
A7: Geothermal+BESS 100 MW | B7: =M4_Bounds!D13 -> 55.052335 | C7: =M4_Bounds!D12 -> 81.4648 | D7: =M4_Pricing!D33 -> 122.20837 | E7: =M4_Bounds!$B$5 -> 162.81741 | F7: =(B7+E7)/2 -> 108.93487 | G7: =B7 -> 55.052335 | H7: =D7-B7 -> 67.156039 | I7: =E7-D7 -> 40.60904 | J7: =Inputs!$B$19 -> 60

Sheet Fig4_Alpha
A1: Figure 4 data: two-sided viability across the bargaining share
A2: STATIC VALUES from 7 closed-loop runs varying M4_Pricing!B5 (α). IRR = Results!B5:D5 (live Model 2 at that price); DC saving = M4_Pricing DC-side savings row. Regenerate if upstream inputs change. Hurdle 10% and min saving 20% are the M4_Pricing lever values.
A4: α | B4: Solar IRR | C4: Solar DC saving | D4: Wind IRR | E4: Wind DC saving | F4: Geo IRR | G4: Geo DC saving | H4: Hurdle | I4: Min saving
A5: 0 | B5: 0.062704805 | C5: 0.33218457 | D5: 0.11874048 | E5: 0.4116212 | F5: 0.17731194 | G5: 0.59871352 | H5: =M4_Pricing!$B$7 -> 0.1 | I5: =M4_Pricing!$B$8 -> 0.2
A6: 0.1 | B6: 0.071890822 | C6: 0.31743608 | D6: 0.13870144 | E6: 0.38023017 | F6: 0.20215961 | G6: 0.53473209 | H6: =M4_Pricing!$B$7 -> 0.1 | I6: =M4_Pricing!$B$8 -> 0.2
A7: 0.2 | B7: 0.081970424 | C7: 0.30268758 | D7: 0.16164931 | E7: 0.34883915 | F7: 0.23069493 | G7: 0.47075066 | H7: =M4_Pricing!$B$7 -> 0.1 | I7: =M4_Pricing!$B$8 -> 0.2
A8: 0.35 | B8: 0.098876141 | C8: 0.28056483 | D8: 0.20109878 | E8: 0.30175261 | F8: 0.27903097 | G8: 0.37477851 | H8: =M4_Pricing!$B$7 -> 0.1 | I8: =M4_Pricing!$B$8 -> 0.2
A9: 0.5 | B9: 0.11794323 | C9: 0.25844209 | D9: 0.24443198 | E9: 0.25466607 | F9: 0.33081969 | G9: 0.27880637 | H9: =M4_Pricing!$B$7 -> 0.1 | I9: =M4_Pricing!$B$8 -> 0.2
A10: 0.65 | B10: 0.1389621 | C10: 0.23631934 | D10: 0.28879563 | E10: 0.20757952 | F10: 0.38276249 | G10: 0.18283422 | H10: =M4_Pricing!$B$7 -> 0.1 | I10: =M4_Pricing!$B$8 -> 0.2
A11: 0.8 | B11: 0.16147569 | C11: 0.2141966 | D11: 0.33218361 | E11: 0.16049298 | F11: 0.43293066 | G11: 0.086862079 | H11: =M4_Pricing!$B$7 -> 0.1 | I11: =M4_Pricing!$B$8 -> 0.2
